Workbook

Sheet Summary
A1: GoKesari - test results tracker
A2: As of 14 Oct 2026, 15:00 UTC. Every recorded test run from 22 Sep to 14 Oct 2026: test site (test.gokesari.com), production (gokesari.com) checks, CI / local automated suites and the database-split verifications.
A3: 'Results (detail)' holds each recorded step or check, read from the TEST_RESULTS files and the UI test workbook. Outcome 'OK (recorded)' = the step was recorded as working but the source did not write PASS.
A4: Counts on this sheet are formulas. To add a run: add a row in 'Test Runs' and its checks in 'Results (detail)'.
A5: Save in /Users/agtci/Documents/Doc_GoKesari/Test_Cases_Tracking.
A7: 1. Test runs by overall result
A8: Overall result | B8: Runs
A9: PASS | B9: =COUNTIF('Test Runs'!$Q$2:$Q$23,A9)
A10: PASS with open items | B10: =COUNTIF('Test Runs'!$Q$2:$Q$23,A10)
A11: FAIL | B11: =COUNTIF('Test Runs'!$Q$2:$Q$23,A11)
A12: BLOCKED | B12: =COUNTIF('Test Runs'!$Q$2:$Q$23,A12)
A13: NOT RUN | B13: =COUNTIF('Test Runs'!$Q$2:$Q$23,A13)
A14: Total runs | B14: =SUM(B9:B13)
A16: 2. Recorded steps and checks by outcome
A17: Outcome | B17: Checks | C17: % of total
A18: PASS | B18: =COUNTIF('Results (detail)'!$I$2:$I$311,A18) | C18: =IF($B$24=0,0,B18/$B$24)
A19: OK (recorded) | B19: =COUNTIF('Results (detail)'!$I$2:$I$311,A19) | C19: =IF($B$24=0,0,B19/$B$24)
A20: FAIL | B20: =COUNTIF('Results (detail)'!$I$2:$I$311,A20) | C20: =IF($B$24=0,0,B20/$B$24)
A21: BLOCKED | B21: =COUNTIF('Results (detail)'!$I$2:$I$311,A21) | C21: =IF($B$24=0,0,B21/$B$24)
A22: NOT RUN | B22: =COUNTIF('Results (detail)'!$I$2:$I$311,A22) | C22: =IF($B$24=0,0,B22/$B$24)
A23: ISSUE | B23: =COUNTIF('Results (detail)'!$I$2:$I$311,A23) | C23: =IF($B$24=0,0,B23/$B$24)
A24: Total recorded checks | B24: =SUM(B18:B23) | C24: =SUM(C18:C23)
A26: 3. Defects found in testing
A27: Status | B27: Defects
A28: Fixed | B28: =COUNTIF(Defects!$E$2:$E$24,A28)
A29: Open | B29: =COUNTIF(Defects!$E$2:$E$24,A29)
A30: Owner action | B30: =COUNTIF(Defects!$E$2:$E$24,A30)
A31: To confirm | B31: =COUNTIF(Defects!$E$2:$E$24,A31)
A32: Accepted | B32: =COUNTIF(Defects!$E$2:$E$24,A32)
A33: Total | B33: =SUM(B28:B32)
A35: 4. Per run (declared totals from the run's own report; recorded = rows in 'Results (detail)')
A36: Run | B36: Date | C36: Declared run | D36: Declared pass | E36: Declared fail | F36: Recorded checks | G36: Fail (recorded) | H36: Overall
A37: ='Test Runs'!A2&" "&'Test Runs'!D2 | B37: ='Test Runs'!B2 | C37: =IF('Test Runs'!H2="","-",'Test Runs'!H2) | D37: =IF('Test Runs'!I2="","-",'Test Runs'!I2) | E37: =IF('Test Runs'!J2="","-",'Test Runs'!J2) | F37: ='Test Runs'!L2 | G37: ='Test Runs'!O2 | H37: ='Test Runs'!Q2
A38: ='Test Runs'!A3&" "&'Test Runs'!D3 | B38: ='Test Runs'!B3 | C38: =IF('Test Runs'!H3="","-",'Test Runs'!H3) | D38: =IF('Test Runs'!I3="","-",'Test Runs'!I3) | E38: =IF('Test Runs'!J3="","-",'Test Runs'!J3) | F38: ='Test Runs'!L3 | G38: ='Test Runs'!O3 | H38: ='Test Runs'!Q3
A39: ='Test Runs'!A4&" "&'Test Runs'!D4 | B39: ='Test Runs'!B4 | C39: =IF('Test Runs'!H4="","-",'Test Runs'!H4) | D39: =IF('Test Runs'!I4="","-",'Test Runs'!I4) | E39: =IF('Test Runs'!J4="","-",'Test Runs'!J4) | F39: ='Test Runs'!L4 | G39: ='Test Runs'!O4 | H39: ='Test Runs'!Q4
A40: ='Test Runs'!A5&" "&'Test Runs'!D5 | B40: ='Test Runs'!B5 | C40: =IF('Test Runs'!H5="","-",'Test Runs'!H5) | D40: =IF('Test Runs'!I5="","-",'Test Runs'!I5) | E40: =IF('Test Runs'!J5="","-",'Test Runs'!J5) | F40: ='Test Runs'!L5 | G40: ='Test Runs'!O5 | H40: ='Test Runs'!Q5
A41: ='Test Runs'!A6&" "&'Test Runs'!D6 | B41: ='Test Runs'!B6 | C41: =IF('Test Runs'!H6="","-",'Test Runs'!H6) | D41: =IF('Test Runs'!I6="","-",'Test Runs'!I6) | E41: =IF('Test Runs'!J6="","-",'Test Runs'!J6) | F41: ='Test Runs'!L6 | G41: ='Test Runs'!O6 | H41: ='Test Runs'!Q6
A42: ='Test Runs'!A7&" "&'Test Runs'!D7 | B42: ='Test Runs'!B7 | C42: =IF('Test Runs'!H7="","-",'Test Runs'!H7) | D42: =IF('Test Runs'!I7="","-",'Test Runs'!I7) | E42: =IF('Test Runs'!J7="","-",'Test Runs'!J7) | F42: ='Test Runs'!L7 | G42: ='Test Runs'!O7 | H42: ='Test Runs'!Q7
A43: ='Test Runs'!A8&" "&'Test Runs'!D8 | B43: ='Test Runs'!B8 | C43: =IF('Test Runs'!H8="","-",'Test Runs'!H8) | D43: =IF('Test Runs'!I8="","-",'Test Runs'!I8) | E43: =IF('Test Runs'!J8="","-",'Test Runs'!J8) | F43: ='Test Runs'!L8 | G43: ='Test Runs'!O8 | H43: ='Test Runs'!Q8
A44: ='Test Runs'!A9&" "&'Test Runs'!D9 | B44: ='Test Runs'!B9 | C44: =IF('Test Runs'!H9="","-",'Test Runs'!H9) | D44: =IF('Test Runs'!I9="","-",'Test Runs'!I9) | E44: =IF('Test Runs'!J9="","-",'Test Runs'!J9) | F44: ='Test Runs'!L9 | G44: ='Test Runs'!O9 | H44: ='Test Runs'!Q9
A45: ='Test Runs'!A10&" "&'Test Runs'!D10 | B45: ='Test Runs'!B10 | C45: =IF('Test Runs'!H10="","-",'Test Runs'!H10) | D45: =IF('Test Runs'!I10="","-",'Test Runs'!I10) | E45: =IF('Test Runs'!J10="","-",'Test Runs'!J10) | F45: ='Test Runs'!L10 | G45: ='Test Runs'!O10 | H45: ='Test Runs'!Q10
A46: ='Test Runs'!A11&" "&'Test Runs'!D11 | B46: ='Test Runs'!B11 | C46: =IF('Test Runs'!H11="","-",'Test Runs'!H11) | D46: =IF('Test Runs'!I11="","-",'Test Runs'!I11) | E46: =IF('Test Runs'!J11="","-",'Test Runs'!J11) | F46: ='Test Runs'!L11 | G46: ='Test Runs'!O11 | H46: ='Test Runs'!Q11
A47: ='Test Runs'!A12&" "&'Test Runs'!D12 | B47: ='Test Runs'!B12 | C47: =IF('Test Runs'!H12="","-",'Test Runs'!H12) | D47: =IF('Test Runs'!I12="","-",'Test Runs'!I12) | E47: =IF('Test Runs'!J12="","-",'Test Runs'!J12) | F47: ='Test Runs'!L12 | G47: ='Test Runs'!O12 | H47: ='Test Runs'!Q12
A48: ='Test Runs'!A13&" "&'Test Runs'!D13 | B48: ='Test Runs'!B13 | C48: =IF('Test Runs'!H13="","-",'Test Runs'!H13) | D48: =IF('Test Runs'!I13="","-",'Test Runs'!I13) | E48: =IF('Test Runs'!J13="","-",'Test Runs'!J13) | F48: ='Test Runs'!L13 | G48: ='Test Runs'!O13 | H48: ='Test Runs'!Q13
... A58: ='Test Runs'!A23&" "&'Test Runs'!D23 | B58: ='Test Runs'!B23 | C58: =IF('Test Runs'!H23="","-",'Test Runs'!H23) | D58: =IF('Test Runs'!I23="","-",'Test Runs'!I23) | E58: =IF('Test Runs'!J23="","-",'Test Runs'!J23) | F58: ='Test Runs'!L23 | G58: ='Test Runs'!O23 | H58: ='Test Runs'!Q23
A60: 5. Headlines (14 Oct 2026)
A61: 1. 22 test runs recorded (310 individual checks). Most features released 8-14 Oct were tested on test.gokesari.com and spot-checked on gokesari.com after release; Seller Central has local checks only and the saffron wordmark change has no recorded run.
A62: 2. Latest: the seller / customer database split verified PASS on production (14 Oct, run 19: 190 tables, 486 rows, every checksum equal) after the test split (13 Oct). Please confirm the production split databases' names.
A63: 3. Open defects: OCR auto-read does not start on Hostinger (D-18); mail host hourly cap (D-04); hydration error on /wallet and /admin/orders (D-13); same subquery bug in 3 queries (D-15); stale lifecycle E2E steps (D-20); slow 4G pages (D-07).
A64: 4. Owner actions found by testing: Maps server key restriction (D-05, D-10); Verification Suite keys (D-23); SMS provider for test (D-11).
A65: 5. Not run yet: the 791-case plan (0 of 791 executed) and the order-lifecycle run on staging (local 21/21 only).

Sheet Test Runs
A1: Run ID | B1: Date | C1: Environment | D1: Scope | E1: Feature IDs | F1: PRs | G1: Method | H1: Declared run | I1: Declared pass | J1: Declared fail | K1: Declared not run | L1: Recorded checks | M1: Pass | N1: OK (recorded) | O1: Fail | P1: Blocked / not run / issue | Q1: Overall result | R1: Open items / notes | S1: Evidence
A2: TR-01 | B2: 2026-09-22 | C2: Local (Windows 11, PostgreSQL 16) | D2: Baseline automated suite before the marketplace work | E2: All modules | F2: - | G2: Automated (vitest) | H2: 628 | I2: 626 | J2: 2 | K2: 0 | L2: =COUNTIF('Results (detail)'!$B$2:$B$311,A2) | M2: =COUNTIFS('Results (detail)'!$B$2:$B$311,A2,'Results (detail)'!$I$2:$I$311,"PASS") | N2: =COUNTIFS('Results (detail)'!$B$2:$B$311,A2,'Results (detail)'!$I$2:$I$311,"OK (recorded)") | O2: =COUNTIFS('Results (detail)'!$B$2:$B$311,A2,'Results (detail)'!$I$2:$I$311,"FAIL") | P2: =COUNTIFS('Results (detail)'!$B$2:$B$311,A2,'Results (detail)'!$I$2:$I$311,"BLOCKED")+COUNTIFS('Results (detail)'!$B$2:$B$311,A2,'Results (detail)'!$I$2:$I$311,"NOT RUN")+COUNTIFS('Results (detail)'!$B$2:$B$311,A2,'Results (detail)'!$I$2:$I$311,"ISSUE") | Q2: PASS | R2: The 2 failures are Windows line-ending artefacts in generated docs (0 functional failures) | S2: docs/gokesari-audit/GOKESARI_BASELINE_TEST_REPORT.xlsx
A3: TR-02 | B3: 2026-10-08 | C3: test.gokesari.com | D3: Four features: delivery options, legal documents, bank accounts (Rs 1), referral code + regression | E3: NEW-039, NEW-040, NEW-041, NEW-042 | F3: #102 | G3: Browser (Chromium, phone + desktop), real emailed codes, Cashfree sandbox | L3: =COUNTIF('Results (detail)'!$B$2:$B$311,A3) | M3: =COUNTIFS('Results (detail)'!$B$2:$B$311,A3,'Results (detail)'!$I$2:$I$311,"PASS") | N3: =COUNTIFS('Results (detail)'!$B$2:$B$311,A3,'Results (detail)'!$I$2:$I$311,"OK (recorded)") | O3: =COUNTIFS('Results (detail)'!$B$2:$B$311,A3,'Results (detail)'!$I$2:$I$311,"FAIL") | P3: =COUNTIFS('Results (detail)'!$B$2:$B$311,A3,'Results (detail)'!$I$2:$I$311,"BLOCKED")+COUNTIFS('Results (detail)'!$B$2:$B$311,A3,'Results (detail)'!$I$2:$I$311,"NOT RUN")+COUNTIFS('Results (detail)'!$B$2:$B$311,A3,'Results (detail)'!$I$2:$I$311,"ISSUE") | Q3: PASS with open items | R3: 3 bugs found (fixed in #103); payout gate not runnable on test; mail host hourly cap (S-5) | S3: docs/four-features-2026-10/TEST_RESULTS.md §1-3
A4: TR-03 | B4: 2026-10-08 | C4: test.gokesari.com | D4: Four features: re-check of the #103 fixes | E4: NEW-039, NEW-041, NEW-042 | F4: #103 | G4: Browser + database evidence | L4: =COUNTIF('Results (detail)'!$B$2:$B$311,A4) | M4: =COUNTIFS('Results (detail)'!$B$2:$B$311,A4,'Results (detail)'!$I$2:$I$311,"PASS") | N4: =COUNTIFS('Results (detail)'!$B$2:$B$311,A4,'Results (detail)'!$I$2:$I$311,"OK (recorded)") | O4: =COUNTIFS('Results (detail)'!$B$2:$B$311,A4,'Results (detail)'!$I$2:$I$311,"FAIL") | P4: =COUNTIFS('Results (detail)'!$B$2:$B$311,A4,'Results (detail)'!$I$2:$I$311,"BLOCKED")+COUNTIFS('Results (detail)'!$B$2:$B$311,A4,'Results (detail)'!$I$2:$I$311,"NOT RUN")+COUNTIFS('Results (detail)'!$B$2:$B$311,A4,'Results (detail)'!$I$2:$I$311,"ISSUE") | Q4: PASS | R4: - | S4: docs/four-features-2026-10/TEST_RESULTS.md §4
A5: TR-04 | B5: 2026-10-09 | C5: test.gokesari.com | D5: Four features: owner's decisions (round 1) - bank refunds, customer sign-up referral | E5: NEW-048, NEW-049 | F5: #106 | G5: Browser | L5: =COUNTIF('Results (detail)'!$B$2:$B$311,A5) | M5: =COUNTIFS('Results (detail)'!$B$2:$B$311,A5,'Results (detail)'!$I$2:$I$311,"PASS") | N5: =COUNTIFS('Results (detail)'!$B$2:$B$311,A5,'Results (detail)'!$I$2:$I$311,"OK (recorded)") | O5: =COUNTIFS('Results (detail)'!$B$2:$B$311,A5,'Results (detail)'!$I$2:$I$311,"FAIL") | P5: =COUNTIFS('Results (detail)'!$B$2:$B$311,A5,'Results (detail)'!$I$2:$I$311,"BLOCKED")+COUNTIFS('Results (detail)'!$B$2:$B$311,A5,'Results (detail)'!$I$2:$I$311,"NOT RUN")+COUNTIFS('Results (detail)'!$B$2:$B$311,A5,'Results (detail)'!$I$2:$I$311,"ISSUE") | Q5: PASS | R5: - | S5: docs/four-features-2026-10/TEST_RESULTS.md §5
A6: TR-05 | B6: 2026-10-09 | C6: test.gokesari.com | D6: Four features: owner's decisions (round 2) - mandatory customer referral from a date | E6: NEW-048 | F6: #109 | G6: Browser | L6: =COUNTIF('Results (detail)'!$B$2:$B$311,A6) | M6: =COUNTIFS('Results (detail)'!$B$2:$B$311,A6,'Results (detail)'!$I$2:$I$311,"PASS") | N6: =COUNTIFS('Results (detail)'!$B$2:$B$311,A6,'Results (detail)'!$I$2:$I$311,"OK (recorded)") | O6: =COUNTIFS('Results (detail)'!$B$2:$B$311,A6,'Results (detail)'!$I$2:$I$311,"FAIL") | P6: =COUNTIFS('Results (detail)'!$B$2:$B$311,A6,'Results (detail)'!$I$2:$I$311,"BLOCKED")+COUNTIFS('Results (detail)'!$B$2:$B$311,A6,'Results (detail)'!$I$2:$I$311,"NOT RUN")+COUNTIFS('Results (detail)'!$B$2:$B$311,A6,'Results (detail)'!$I$2:$I$311,"ISSUE") | Q6: PASS | R6: - | S6: docs/four-features-2026-10/TEST_RESULTS.md §6
A7: TR-06 | B7: 2026-10-09 | C7: test.gokesari.com | D7: Bank check with Cashfree Verification Suite (O-7) | E7: NEW-050 | F7: #115, #117 | G7: Browser | L7: =COUNTIF('Results (detail)'!$B$2:$B$311,A7) | M7: =COUNTIFS('Results (detail)'!$B$2:$B$311,A7,'Results (detail)'!$I$2:$I$311,"PASS") | N7: =COUNTIFS('Results (detail)'!$B$2:$B$311,A7,'Results (detail)'!$I$2:$I$311,"OK (recorded)") | O7: =COUNTIFS('Results (detail)'!$B$2:$B$311,A7,'Results (detail)'!$I$2:$I$311,"FAIL") | P7: =COUNTIFS('Results (detail)'!$B$2:$B$311,A7,'Results (detail)'!$I$2:$I$311,"BLOCKED")+COUNTIFS('Results (detail)'!$B$2:$B$311,A7,'Results (detail)'!$I$2:$I$311,"NOT RUN")+COUNTIFS('Results (detail)'!$B$2:$B$311,A7,'Results (detail)'!$I$2:$I$311,"ISSUE") | Q7: BLOCKED | R7: Test site does not see the Verification Suite keys (they must be in the Hostinger environment, not only GitHub); O7.2-O7.5 not run | S7: docs/four-features-2026-10/TEST_RESULTS.md §7
A8: TR-07 | B8: 2026-10-09 | C8: Local + test.gokesari.com + preview app | D8: Tile Board home screens | E8: NEW-046, NEW-047 | F8: #112 | G8: Unit (29) + browser (Playwright) | L8: =COUNTIF('Results (detail)'!$B$2:$B$311,A8) | M8: =COUNTIFS('Results (detail)'!$B$2:$B$311,A8,'Results (detail)'!$I$2:$I$311,"PASS") | N8: =COUNTIFS('Results (detail)'!$B$2:$B$311,A8,'Results (detail)'!$I$2:$I$311,"OK (recorded)") | O8: =COUNTIFS('Results (detail)'!$B$2:$B$311,A8,'Results (detail)'!$I$2:$I$311,"FAIL") | P8: =COUNTIFS('Results (detail)'!$B$2:$B$311,A8,'Results (detail)'!$I$2:$I$311,"BLOCKED")+COUNTIFS('Results (detail)'!$B$2:$B$311,A8,'Results (detail)'!$I$2:$I$311,"NOT RUN")+COUNTIFS('Results (detail)'!$B$2:$B$311,A8,'Results (detail)'!$I$2:$I$311,"ISSUE") | Q8: PASS | R8: Signed-in roles checked locally only | S8: docs/tile-board-2026-10/TEST_RESULTS.md
A9: TR-08 | B9: 2026-10-09 | C9: test.gokesari.com | D9: Tile Board UI pass: navigation, access, end-to-end, Lighthouse, fit (all roles, 7 sizes x 3 languages) | E9: NEW-051 to NEW-055 | F9: #122, #124 | G9: Browser + Lighthouse | H9: 1038 | I9: 1026 | J9: 8 | K9: 4 | L9: =COUNTIF('Results (detail)'!$B$2:$B$311,A9) | M9: =COUNTIFS('Results (detail)'!$B$2:$B$311,A9,'Results (detail)'!$I$2:$I$311,"PASS") | N9: =COUNTIFS('Results (detail)'!$B$2:$B$311,A9,'Results (detail)'!$I$2:$I$311,"OK (recorded)") | O9: =COUNTIFS('Results (detail)'!$B$2:$B$311,A9,'Results (detail)'!$I$2:$I$311,"FAIL") | P9: =COUNTIFS('Results (detail)'!$B$2:$B$311,A9,'Results (detail)'!$I$2:$I$311,"BLOCKED")+COUNTIFS('Results (detail)'!$B$2:$B$311,A9,'Results (detail)'!$I$2:$I$311,"NOT RUN")+COUNTIFS('Results (detail)'!$B$2:$B$311,A9,'Results (detail)'!$I$2:$I$311,"ISSUE") | Q9: PASS with open items | R9: 8 fail: 5 pages over 3 s on slow 4G, shop owner board 2 px over at 320x640, 1 link blocked, 1 Lighthouse; 4 not run (2 sandbox payments - Actions billing, rider return pickup, KYC-pending approval) | S9: docs/tile-board-2026-10/TEST_RESULTS_UI_PASS.md; GoKesari_UI_Test_Report_2026-10-09.xlsx
A10: TR-09 | B10: 2026-10-09 | C10: gokesari.com + test.gokesari.com | D10: Production checks after release #126; PR #127 on test | E10: NEW-051 to NEW-055, PLT-014 | F10: #126, #127 | G10: HTTP + Lighthouse | L10: =COUNTIF('Results (detail)'!$B$2:$B$311,A10) | M10: =COUNTIFS('Results (detail)'!$B$2:$B$311,A10,'Results (detail)'!$I$2:$I$311,"PASS") | N10: =COUNTIFS('Results (detail)'!$B$2:$B$311,A10,'Results (detail)'!$I$2:$I$311,"OK (recorded)") | O10: =COUNTIFS('Results (detail)'!$B$2:$B$311,A10,'Results (detail)'!$I$2:$I$311,"FAIL") | P10: =COUNTIFS('Results (detail)'!$B$2:$B$311,A10,'Results (detail)'!$I$2:$I$311,"BLOCKED")+COUNTIFS('Results (detail)'!$B$2:$B$311,A10,'Results (detail)'!$I$2:$I$311,"NOT RUN")+COUNTIFS('Results (detail)'!$B$2:$B$311,A10,'Results (detail)'!$I$2:$I$311,"ISSUE") | Q10: PASS | R10: - | S10: docs/tile-board-2026-10/TEST_RESULTS_UI_PASS.md (Production)
A11: TR-10 | B11: 2026-10-10 | C11: test.gokesari.com | D11: Nearby shops + referral Mandatory/Optional settings + regression | E11: NEW-057, NEW-058, NEW-059 | F11: #133, #136 | G11: Browser (Android, iPhone, desktop emulation), Cashfree sandbox | L11: =COUNTIF('Results (detail)'!$B$2:$B$311,A11) | M11: =COUNTIFS('Results (detail)'!$B$2:$B$311,A11,'Results (detail)'!$I$2:$I$311,"PASS") | N11: =COUNTIFS('Results (detail)'!$B$2:$B$311,A11,'Results (detail)'!$I$2:$I$311,"OK (recorded)") | O11: =COUNTIFS('Results (detail)'!$B$2:$B$311,A11,'Results (detail)'!$I$2:$I$311,"FAIL") | P11: =COUNTIFS('Results (detail)'!$B$2:$B$311,A11,'Results (detail)'!$I$2:$I$311,"BLOCKED")+COUNTIFS('Results (detail)'!$B$2:$B$311,A11,'Results (detail)'!$I$2:$I$311,"NOT RUN")+COUNTIFS('Results (detail)'!$B$2:$B$311,A11,'Results (detail)'!$I$2:$I$311,"ISSUE") | Q11: PASS with open items | R11: Backfill blocked by the Maps server key (N-1); paid self-registration not run (no SMS provider, N-2) | S11: docs/nearby-referral-2026-10/TEST_RESULTS.md §1-5
A12: TR-11 | B12: 2026-10-10 | C12: gokesari.com + mobile apps | D12: Nearby + referral settings: production checks after release #135; Android APK | E12: NEW-057, NEW-058 | F12: #135, #137 | G12: HTTP + browser, read-only | L12: =COUNTIF('Results (detail)'!$B$2:$B$311,A12) | M12: =COUNTIFS('Results (detail)'!$B$2:$B$311,A12,'Results (detail)'!$I$2:$I$311,"PASS") | N12: =COUNTIFS('Results (detail)'!$B$2:$B$311,A12,'Results (detail)'!$I$2:$I$311,"OK (recorded)") | O12: =COUNTIFS('Results (detail)'!$B$2:$B$311,A12,'Results (detail)'!$I$2:$I$311,"FAIL") | P12: =COUNTIFS('Results (detail)'!$B$2:$B$311,A12,'Results (detail)'!$I$2:$I$311,"BLOCKED")+COUNTIFS('Results (detail)'!$B$2:$B$311,A12,'Results (detail)'!$I$2:$I$311,"NOT RUN")+COUNTIFS('Results (detail)'!$B$2:$B$311,A12,'Results (detail)'!$I$2:$I$311,"ISSUE") | Q12: PASS | R12: Admin page on production needs an admin sign-in | S12: docs/nearby-referral-2026-10/TEST_RESULTS.md §6-7
A13: TR-12 | B13: 2026-10-11 | C13: test.gokesari.com + gokesari.com | D13: Fix: referral codes / societies counted 0 | E13: NEW-065 | F13: #138, #139 | G13: Integration tests + API + smoke | L13: =COUNTIF('Results (detail)'!$B$2:$B$311,A13) | M13: =COUNTIFS('Results (detail)'!$B$2:$B$311,A13,'Results (detail)'!$I$2:$I$311,"PASS") | N13: =COUNTIFS('Results (detail)'!$B$2:$B$311,A13,'Results (detail)'!$I$2:$I$311,"OK (recorded)") | O13: =COUNTIFS('Results (detail)'!$B$2:$B$311,A13,'Results (detail)'!$I$2:$I$311,"FAIL") | P13: =COUNTIFS('Results (detail)'!$B$2:$B$311,A13,'Results (detail)'!$I$2:$I$311,"BLOCKED")+COUNTIFS('Results (detail)'!$B$2:$B$311,A13,'Results (detail)'!$I$2:$I$311,"NOT RUN")+COUNTIFS('Results (detail)'!$B$2:$B$311,A13,'Results (detail)'!$I$2:$I$311,"ISSUE") | Q13: PASS | R13: Same bug pattern in 3 other queries (GAP-016) | S13: docs/nearby-referral-2026-10/TEST_RESULTS.md §8
A14: TR-13 | B14: 2026-10-12 | C14: Local (cloud session, PostgreSQL 16) | D14: Seller Central and /sell | E14: NEW-060 | F14: #142 | G14: Automated (1,702 tests) + manual on a dev server | L14: =COUNTIF('Results (detail)'!$B$2:$B$311,A14) | M14: =COUNTIFS('Results (detail)'!$B$2:$B$311,A14,'Results (detail)'!$I$2:$I$311,"PASS") | N14: =COUNTIFS('Results (detail)'!$B$2:$B$311,A14,'Results (detail)'!$I$2:$I$311,"OK (recorded)") | O14: =COUNTIFS('Results (detail)'!$B$2:$B$311,A14,'Results (detail)'!$I$2:$I$311,"FAIL") | P14: =COUNTIFS('Results (detail)'!$B$2:$B$311,A14,'Results (detail)'!$I$2:$I$311,"BLOCKED")+COUNTIFS('Results (detail)'!$B$2:$B$311,A14,'Results (detail)'!$I$2:$I$311,"NOT RUN")+COUNTIFS('Results (detail)'!$B$2:$B$311,A14,'Results (detail)'!$I$2:$I$311,"ISSUE") | Q14: PASS | R14: No staging or production run recorded | S14: docs/seller-central-2026-10/TEST_RESULTS.md
A15: TR-14 | B15: 2026-10-13 | C15: CI + local production build | D15: 13 Oct release: automated suites and local browser flow | E15: NEW-062, NEW-063, NEW-064, PLT-015 | F15: #146-#148 | G15: Automated (1,743 unit/integration), E2E lifecycle 21/21, branding 16/16 | L15: =COUNTIF('Results (detail)'!$B$2:$B$311,A15) | M15: =COUNTIFS('Results (detail)'!$B$2:$B$311,A15,'Results (detail)'!$I$2:$I$311,"PASS") | N15: =COUNTIFS('Results (detail)'!$B$2:$B$311,A15,'Results (detail)'!$I$2:$I$311,"OK (recorded)") | O15: =COUNTIFS('Results (detail)'!$B$2:$B$311,A15,'Results (detail)'!$I$2:$I$311,"FAIL") | P15: =COUNTIFS('Results (detail)'!$B$2:$B$311,A15,'Results (detail)'!$I$2:$I$311,"BLOCKED")+COUNTIFS('Results (detail)'!$B$2:$B$311,A15,'Results (detail)'!$I$2:$I$311,"NOT RUN")+COUNTIFS('Results (detail)'!$B$2:$B$311,A15,'Results (detail)'!$I$2:$I$311,"ISSUE") | Q15: PASS | R15: Two stale lifecycle E2E steps left out | S15: docs/document-upload-2026-10/TEST_RESULTS.md (Automated)
A16: TR-15 | B16: 2026-10-13 | C16: test.gokesari.com | D16: 13 Oct release on staging (first pass) | E16: NEW-062, NEW-063, NEW-064 | F16: #146 | G16: Browser + API | L16: =COUNTIF('Results (detail)'!$B$2:$B$311,A16) | M16: =COUNTIFS('Results (detail)'!$B$2:$B$311,A16,'Results (detail)'!$I$2:$I$311,"PASS") | N16: =COUNTIFS('Results (detail)'!$B$2:$B$311,A16,'Results (detail)'!$I$2:$I$311,"OK (recorded)") | O16: =COUNTIFS('Results (detail)'!$B$2:$B$311,A16,'Results (detail)'!$I$2:$I$311,"FAIL") | P16: =COUNTIFS('Results (detail)'!$B$2:$B$311,A16,'Results (detail)'!$I$2:$I$311,"BLOCKED")+COUNTIFS('Results (detail)'!$B$2:$B$311,A16,'Results (detail)'!$I$2:$I$311,"NOT RUN")+COUNTIFS('Results (detail)'!$B$2:$B$311,A16,'Results (detail)'!$I$2:$I$311,"ISSUE") | Q16: FAIL | R16: Document read 504 at 60 s (fixed in #147) | S16: docs/document-upload-2026-10/TEST_RESULTS.md (Staging)
A17: TR-16 | B17: 2026-10-13 | C17: test.gokesari.com | D17: 13 Oct release: staging re-check after #147 and #148 | E17: NEW-062 | F17: #147, #148 | G17: Browser + API | L17: =COUNTIF('Results (detail)'!$B$2:$B$311,A17) | M17: =COUNTIFS('Results (detail)'!$B$2:$B$311,A17,'Results (detail)'!$I$2:$I$311,"PASS") | N17: =COUNTIFS('Results (detail)'!$B$2:$B$311,A17,'Results (detail)'!$I$2:$I$311,"OK (recorded)") | O17: =COUNTIFS('Results (detail)'!$B$2:$B$311,A17,'Results (detail)'!$I$2:$I$311,"FAIL") | P17: =COUNTIFS('Results (detail)'!$B$2:$B$311,A17,'Results (detail)'!$I$2:$I$311,"BLOCKED")+COUNTIFS('Results (detail)'!$B$2:$B$311,A17,'Results (detail)'!$I$2:$I$311,"NOT RUN")+COUNTIFS('Results (detail)'!$B$2:$B$311,A17,'Results (detail)'!$I$2:$I$311,"ISSUE") | Q17: PASS with open items | R17: OCR worker does not start on Hostinger - owners type the details | S17: docs/document-upload-2026-10/TEST_RESULTS.md (Staging re-check)
A18: TR-17 | B18: 2026-10-13 | C18: gokesari.com | D18: 13 Oct release on production (#149) | E18: NEW-062, NEW-063, NEW-064 | F18: #149, #150, #151 | G18: HTTP, screenshots, branding E2E | L18: =COUNTIF('Results (detail)'!$B$2:$B$311,A18) | M18: =COUNTIFS('Results (detail)'!$B$2:$B$311,A18,'Results (detail)'!$I$2:$I$311,"PASS") | N18: =COUNTIFS('Results (detail)'!$B$2:$B$311,A18,'Results (detail)'!$I$2:$I$311,"OK (recorded)") | O18: =COUNTIFS('Results (detail)'!$B$2:$B$311,A18,'Results (detail)'!$I$2:$I$311,"FAIL") | P18: =COUNTIFS('Results (detail)'!$B$2:$B$311,A18,'Results (detail)'!$I$2:$I$311,"BLOCKED")+COUNTIFS('Results (detail)'!$B$2:$B$311,A18,'Results (detail)'!$I$2:$I$311,"NOT RUN")+COUNTIFS('Results (detail)'!$B$2:$B$311,A18,'Results (detail)'!$I$2:$I$311,"ISSUE") | Q18: PASS with open items | R18: Stray '·' in the footer on a 412 px phone - fixed in #150/#151 (E2E 16/16 on gokesari.com) | S18: docs/document-upload-2026-10/TEST_RESULTS.md (Production)
A19: TR-18 | B19: 2026-10-13 | C19: Test databases (Neon us-east-2) | D19: Seller / customer database split - test verification (run #5) | E19: PLT-015 | F19: #146, #152, #154 | G19: Database split workflow: migrate + verify | H19: 190 | I19: 190 | J19: 0 | K19: 0 | L19: =COUNTIF('Results (detail)'!$B$2:$B$311,A19) | M19: =COUNTIFS('Results (detail)'!$B$2:$B$311,A19,'Results (detail)'!$I$2:$I$311,"PASS") | N19: =COUNTIFS('Results (detail)'!$B$2:$B$311,A19,'Results (detail)'!$I$2:$I$311,"OK (recorded)") | O19: =COUNTIFS('Results (detail)'!$B$2:$B$311,A19,'Results (detail)'!$I$2:$I$311,"FAIL") | P19: =COUNTIFS('Results (detail)'!$B$2:$B$311,A19,'Results (detail)'!$I$2:$I$311,"BLOCKED")+COUNTIFS('Results (detail)'!$B$2:$B$311,A19,'Results (detail)'!$I$2:$I$311,"NOT RUN")+COUNTIFS('Results (detail)'!$B$2:$B$311,A19,'Results (detail)'!$I$2:$I$311,"ISSUE") | Q19: PASS | R19: 29,996 rows, every checksum equal, 0 missing parents on 111 cross-database links | S19: docs/db-split-2026-10/VERIFICATION_REPORT_test_2026-10-13.md
A20: TR-19 | B20: 2026-10-14 | C20: Production databases (Neon us-east-2) | D20: Seller / customer database split - production verification (run #19) + cross-database reads (run #20) | E20: PLT-015 | F20: #157-#164 | G20: Database split workflow: migrate + verify, fdw | H20: 190 | I20: 190 | J20: 0 | K20: 0 | L20: =COUNTIF('Results (detail)'!$B$2:$B$311,A20) | M20: =COUNTIFS('Results (detail)'!$B$2:$B$311,A20,'Results (detail)'!$I$2:$I$311,"PASS") | N20: =COUNTIFS('Results (detail)'!$B$2:$B$311,A20,'Results (detail)'!$I$2:$I$311,"OK (recorded)") | O20: =COUNTIFS('Results (detail)'!$B$2:$B$311,A20,'Results (detail)'!$I$2:$I$311,"FAIL") | P20: =COUNTIFS('Results (detail)'!$B$2:$B$311,A20,'Results (detail)'!$I$2:$I$311,"BLOCKED")+COUNTIFS('Results (detail)'!$B$2:$B$311,A20,'Results (detail)'!$I$2:$I$311,"NOT RUN")+COUNTIFS('Results (detail)'!$B$2:$B$311,A20,'Results (detail)'!$I$2:$I$311,"ISSUE") | Q20: PASS | R20: 486 rows, every checksum equal, 0 missing parents on 111 links. Site still on one database. Please confirm the split databases' names (shown as PROD_SELLER_DATABASE_URL / PROD_CUSTOMER_DATABASE_URL) | S20: docs/db-split-2026-10/VERIFICATION_REPORT_production_2026-10-14.md
A21: TR-20 | B21: 2026-10-08 | C21: CI (staging 76e2cc5) | D21: Automated suite on the staging merge of #104 | E21: QA-001 | F21: #104 | G21: Automated (vitest) | H21: 1484 | I21: 1483 | J21: 1 | K21: 0 | L21: =COUNTIF('Results (detail)'!$B$2:$B$311,A21) | M21: =COUNTIFS('Results (detail)'!$B$2:$B$311,A21,'Results (detail)'!$I$2:$I$311,"PASS") | N21: =COUNTIFS('Results (detail)'!$B$2:$B$311,A21,'Results (detail)'!$I$2:$I$311,"OK (recorded)") | O21: =COUNTIFS('Results (detail)'!$B$2:$B$311,A21,'Results (detail)'!$I$2:$I$311,"FAIL") | P21: =COUNTIFS('Results (detail)'!$B$2:$B$311,A21,'Results (detail)'!$I$2:$I$311,"BLOCKED")+COUNTIFS('Results (detail)'!$B$2:$B$311,A21,'Results (detail)'!$I$2:$I$311,"NOT RUN")+COUNTIFS('Results (detail)'!$B$2:$B$311,A21,'Results (detail)'!$I$2:$I$311,"ISSUE") | Q21: FAIL | R21: Flaky login-profile test (background email reached the next test's outbox) - fixed by bf8df50, merged with #92 on 9 Oct | S21: Actions run 37855030692
A22: TR-21 | B22: - | C22: test.gokesari.com | D22: 791-case test plan (smoke, P0, P1, P2) and 35 end-to-end scenarios | E22: All | F22: - | G22: Manual / browser | H22: 791 | I22: 0 | J22: 0 | K22: 791 | L22: =COUNTIF('Results (detail)'!$B$2:$B$311,A22) | M22: =COUNTIFS('Results (detail)'!$B$2:$B$311,A22,'Results (detail)'!$I$2:$I$311,"PASS") | N22: =COUNTIFS('Results (detail)'!$B$2:$B$311,A22,'Results (detail)'!$I$2:$I$311,"OK (recorded)") | O22: =COUNTIFS('Results (detail)'!$B$2:$B$311,A22,'Results (detail)'!$I$2:$I$311,"FAIL") | P22: =COUNTIFS('Results (detail)'!$B$2:$B$311,A22,'Results (detail)'!$I$2:$I$311,"BLOCKED")+COUNTIFS('Results (detail)'!$B$2:$B$311,A22,'Results (detail)'!$I$2:$I$311,"NOT RUN")+COUNTIFS('Results (detail)'!$B$2:$B$311,A22,'Results (detail)'!$I$2:$I$311,"ISSUE") | Q22: NOT RUN | R22: Not executed; see the '791-case plan' sheet | S22: test-cases.xlsx
A23: TR-22 | B23: - | C23: test.gokesari.com | D23: Order lifecycle on staging: sign-up -> order -> delivery code -> done | E23: QA-008 | F23: - | G23: Browser + Cashfree sandbox | L23: =COUNTIF('Results (detail)'!$B$2:$B$311,A23) | M23: =COUNTIFS('Results (detail)'!$B$2:$B$311,A23,'Results (detail)'!$I$2:$I$311,"PASS") | N23: =COUNTIFS('Results (detail)'!$B$2:$B$311,A23,'Results (detail)'!$I$2:$I$311,"OK (recorded)") | O23: =COUNTIFS('Results (detail)'!$B$2:$B$311,A23,'Results (detail)'!$I$2:$I$311,"FAIL") | P23: =COUNTIFS('Results (detail)'!$B$2:$B$311,A23,'Results (detail)'!$I$2:$I$311,"BLOCKED")+COUNTIFS('Results (detail)'!$B$2:$B$311,A23,'Results (detail)'!$I$2:$I$311,"NOT RUN")+COUNTIFS('Results (detail)'!$B$2:$B$311,A23,'Results (detail)'!$I$2:$I$311,"ISSUE") | Q23: NOT RUN | R23: Run locally only (21/21); staging run is next | S23: docs/document-upload-2026-10/TEST_RESULTS.md (Not run yet)

Sheet Results (detail)
A1: # | B1: Run ID | C1: Source | D1: Section | E1: Time (UTC) | F1: Area / flow | G1: Step / check | H1: Result as recorded | I1: Outcome
A2: RES-0001 | B2: TR-02 | C2: docs/four-features-2026-10/TEST_RESULTS.md | D2: 2. Step by step (UTC times, 8 Oct 2026) | E2: 18:59 | F2: Regression · login | G2: Customer sanjaymorankar+gk-cust signs in with the emailed code (phone width) | H2: PASS — code emailed, signed in, sent to /onboarding | I2: PASS
A3: RES-0002 | B3: TR-02 | C3: docs/four-features-2026-10/TEST_RESULTS.md | D3: 2. Step by step (UTC times, 8 Oct 2026) | E3: 19:19 | F3: Regression · profile | G3: Onboarding: name + mobile 7397100101 saved | H3: PASS | I3: PASS
A4: RES-0003 | B4: TR-02 | C4: docs/four-features-2026-10/TEST_RESULTS.md | D4: 2. Step by step (UTC times, 8 Oct 2026) | E4: 19:22 | F4: Regression · address | G4: Map "Confirm location" (geo-tag) on /profile/addresses | H4: PRE-EXISTING ISSUE on test (old code): "Something went wrong. Please try again." — geo-tag optional | I4: ISSUE
A5: RES-0004 | B5: TR-02 | C5: docs/four-features-2026-10/TEST_RESULTS.md | D5: 2. Step by step (UTC times, 8 Oct 2026) | E5: 19:23 | F5: Regression · address | G5: Address saved without geo-tag, default | H5: PASS | I5: PASS
A6: RES-0005 | B6: TR-02 | C6: docs/four-features-2026-10/TEST_RESULTS.md | D6: 2. Step by step (UTC times, 8 Oct 2026) | E6: 19:24 | F6: Regression · wallet | G6: ₹500 top-up: gateway order (Cashfree sandbox) → paid by UPI collect testsuccess@gocash (sandbox-pay workflow run 37831015803) → /api/wallet/verify | H6: PASS — balance ₹0 → ₹500, alreadyProcessed false | I6: PASS
A7: RES-0006 | B7: TR-02 | C7: docs/four-features-2026-10/TEST_RESULTS.md | D7: 2. Step by step (UTC times, 8 Oct 2026) | E7: 19:35 | F7: Deploy | G7: PR #102 merged into staging (58bb4c0); Hostinger rebuilt test.gokesari.com — new routes live 19:38 | H7: PASS | I7: PASS
A8: RES-0007 | B8: TR-02 | C8: docs/four-features-2026-10/TEST_RESULTS.md | D8: 2. Step by step (UTC times, 8 Oct 2026) | E8: 19:36 | F8: Deploy · DB | G8: Test database run 37833141417: backup gokesari_test_2026-10-08_1936_run11.dump → migrate (67 rows, newest 0064) → four rules on → E2E admin/operator roles → verify | H8: PASS | I8: PASS
A9: RES-0008 | B9: TR-02 | C9: docs/four-features-2026-10/TEST_RESULTS.md | D9: 2. Step by step (UTC times, 8 Oct 2026) | E9: 19:39 | F9: Admin | G9: /admin/settings shows fulfilmentOptions, legalDocuments, bankAccounts, shopReferral with test values | H9: PASS | I9: PASS
A10: RES-0009 | B10: TR-02 | C10: docs/four-features-2026-10/TEST_RESULTS.md | D10: 2. Step by step (UTC times, 8 Oct 2026) | E10: 19:40 | F10: F4 setup · admin | G10: Referral code E2ETEST1 created (Admin → Referral codes) | H10: PASS | I10: PASS
A11: RES-0010 | B11: TR-02 | C11: docs/four-features-2026-10/TEST_RESULTS.md | D11: 2. Step by step (UTC times, 8 Oct 2026) | E11: 19:40 | F11: Regression · rider | G11: Admin approves delivery partner "E2E Rider Vijay" | H11: PASS | I11: PASS
A12: RES-0011 | B12: TR-02 | C12: docs/four-features-2026-10/TEST_RESULTS.md | D12: 2. Step by step (UTC times, 8 Oct 2026) | E12: 19:42 | F12: F4 · registration (desktop) | G12: Empty code → blocked in browser ("A referral code is required…"), 0 requests sent | H12: PASS | I12: PASS
... A127: RES-0126 | B127: TR-06 | C127: docs/four-features-2026-10/TEST_RESULTS.md | D127: 7. Bank check with Cashfree (O-7), tested on test | E127: 12:59 | F127: O7.1 · finance card | G127: Admin → Bank accounts: "Bank check with Cashfree (no ₹1 payment)" · Rule on · Keys not found. The website's environment has none of the expected names (CASHFREE_VERIFICATION_CLIENT_ID / _CLIENT_SECRET, _APP_ID / _SECRET_KEY), so saving a bank account records "not configured" and keeps the ₹1 check, as designed | H127: BLOCKED (keys) | I127: BLOCKED
A128: RES-0127 | B128: TR-07 | C128: docs/tile-board-2026-10/TEST_RESULTS.md | D128: 1. Summary | G128: npm run typecheck | H128: Pass | I128: PASS
A129: RES-0128 | B129: TR-07 | C129: docs/tile-board-2026-10/TEST_RESULTS.md | D129: 1. Summary | G129: npx eslint src tests --ext .ts,.tsx | H129: Pass — 0 errors; 4 warnings, all pre-existing on staging (none in new files) | I129: PASS
A130: RES-0129 | B130: TR-07 | C130: docs/tile-board-2026-10/TEST_RESULTS.md | D130: 1. Summary | G130: npm test (Vitest, real PostgreSQL 16) | H130: Pass — 125 files, 1,610 tests (29 new in tests/unit/tile-board.test.ts) | I130: PASS
A131: RES-0130 | B131: TR-07 | C131: docs/tile-board-2026-10/TEST_RESULTS.md | D131: 1. Summary | G131: npm run build | H131: Pass | I131: PASS
A132: RES-0131 | B132: TR-07 | C132: docs/tile-board-2026-10/TEST_RESULTS.md | D132: 1. Summary | G132: Board fits the first screen, no horizontal scroll — 4 roles × 2 sizes × 3 languages (local) | H132: Pass, 24/24 (plus signed-out, new customer, empty shop and pending shop: 24/24) | I132: PASS
A133: RES-0132 | B133: TR-07 | C133: docs/tile-board-2026-10/TEST_RESULTS.md | D133: 1. Summary | G133: Every tile and chip opens a real page, HTTP 200, no redirect home (local) | H133: Pass — customer 28/28, shop owner 32/32, admin 37/37, operator 21/21, signed-out 14/14 links | I133: PASS
A134: RES-0133 | B134: TR-07 | C134: docs/tile-board-2026-10/TEST_RESULTS.md | D134: 1. Summary | G134: Language switch (click, cookie, server render, survives reload) | H134: Pass | I134: PASS
A135: RES-0134 | B135: TR-07 | C135: docs/tile-board-2026-10/TEST_RESULTS.md | D135: 1. Summary | G135: Other pages keep the site header and layout | H135: Pass | I135: PASS
A136: RES-0135 | B136: TR-07 | C136: docs/tile-board-2026-10/TEST_RESULTS.md | D136: 1. Summary | G136: test.gokesari.com (PR #112 merged to staging as 6d60dbc; board served ~2 min later) | H136: Live. Signed-out board verified on the site; signed-in roles verified locally only — see §5 | I136: OK (recorded)
A137: RES-0136 | B137: TR-07 | C137: docs/tile-board-2026-10/TEST_RESULTS.md | D137: 3.3 Interaction | G137: Tap मरा → board re-renders in Marathi (lang="mr-IN"), cookie gk_lang=mr, still Marathi after reload; EN switches back | H137: Pass (phone and desktop, dev and production build) | I137: PASS
A138: RES-0137 | B138: TR-07 | C138: docs/tile-board-2026-10/TEST_RESULTS.md | D138: 3.3 Interaction | G138: Deliver-to opens the location chooser | H138: Pass | I138: PASS
A139: RES-0138 | B139: TR-07 | C139: docs/tile-board-2026-10/TEST_RESULTS.md | D139: 3.3 Interaction | G139: Account menu: name, profile links, sign out (role switcher shows for users with several roles) | H139: Pass | I139: PASS
... A143: RES-0142 | B143: TR-07 | C143: docs/tile-board-2026-10/TEST_RESULTS.md | D143: 3.3 Interaction | G143: Site header hidden only while a board is on the page; /shops, /orders, /wallet, /profile, /admin/orders, /admin/dashboard, /shop without a shop all unchanged | H143: Pass | I143: PASS
A144: RES-0143 | B144: TR-07 | C144: docs/tile-board-2026-10/TEST_RESULTS.md | D144: 5. test.gokesari.com | F144: Fit, 360×800 and 1366×768 × EN/HI/MR (6 runs) | H144: Pass — 800/800 and 752/768, no horizontal scroll, site header hidden on / | I144: PASS
A145: RES-0144 | B145: TR-07 | C145: docs/tile-board-2026-10/TEST_RESULTS.md | D145: 5. test.gokesari.com | F145: Every tile/chip link (14) | H145: Pass — all 200, no redirect home; account-only entries open /signin | I145: PASS
A146: RES-0145 | B146: TR-07 | C146: docs/tile-board-2026-10/TEST_RESULTS.md | D146: 5. test.gokesari.com | F146: Language switch (phone and desktop): click मरा → Marathi, cookie set, survives reload, EN back | H146: Pass | I146: PASS
A147: RES-0146 | B147: TR-07 | C147: docs/tile-board-2026-10/TEST_RESULTS.md | D147: 5. test.gokesari.com | F147: Deliver-to opens the location chooser; cart bar on the first screen | H147: Pass | I147: PASS
A148: RES-0147 | B148: TR-07 | C148: docs/tile-board-2026-10/TEST_RESULTS.md | D148: 5. test.gokesari.com | F148: Live figures: shop count 9 and "All 45" categories come from the test database | H148: Pass | I148: PASS
A149: RES-0148 | B149: TR-07 | C149: docs/tile-board-2026-10/TEST_RESULTS.md | D149: 5. test.gokesari.com | F149: /shop and /admin signed out → sign-in page, site header shown; /search, /categories unchanged | H149: Pass | I149: PASS
A150: RES-0149 | B150: TR-07 | C150: docs/tile-board-2026-10/TEST_RESULTS.md | D150: 5.1 Mobile app ("GoKesari Test" preview build) | G150: Board fits, no horizontal scroll, header 57 px, EN and MR | H150: Pass | I150: PASS
A151: RES-0150 | B151: TR-07 | C151: docs/tile-board-2026-10/TEST_RESULTS.md | D151: 5.1 Mobile app ("GoKesari Test" preview build) | G151: Tapping a chip (Open now) opens /shops?open=1 | H151: Pass | I151: PASS
A152: RES-0151 | B152: TR-07 | C152: docs/tile-board-2026-10/TEST_RESULTS.md | D152: 5.1 Mobile app ("GoKesari Test" preview build) | G152: Language switch and cart bar | H152: Pass (same page as §5) | I152: PASS
A153: RES-0152 | B153: TR-08 | C153: docs/tile-board-2026-10/GoKesari_UI_Test_Report_2026-10-09.xlsx | D153: End-to-end (B) | E153: 20:42 | F153: Customer · Wallet | G153: C-01 Top up the wallet (Cashfree sandbox, UPI testsuccess@gocash) | H153: Not completed: the wallet screen created the Cashfree sandbox session (session_iPGj…), but GitHub Actions did not start the Sandbox payment job (run 37973592123: “recent account payments have failed or your spending limit needs to be increased”). This session cannot reach Cashfree itself | I153: NOT RUN
A154: RES-0153 | B154: TR-08 | C154: docs/tile-board-2026-10/GoKesari_UI_Test_Report_2026-10-09.xlsx | D154: End-to-end (B) | E154: 20:21 | F154: Customer · Search | G154: C-02 Search from the board (phone) | H154: /search?q=bread: 14 product cards | I154: PASS
A155: RES-0154 | B155: TR-08 | C155: docs/tile-board-2026-10/GoKesari_UI_Test_Report_2026-10-09.xlsx | D155: End-to-end (B) | E155: 20:21 | F155: Customer · Browse | G155: C-03 Categories → category page (phone) | H155: /category/BAKERY: 60 products | I155: PASS
A156: RES-0155 | B156: TR-08 | C156: docs/tile-board-2026-10/GoKesari_UI_Test_Report_2026-10-09.xlsx | D156: End-to-end (B) | E156: 20:21 | F156: Customer · Browse | G156: C-04 Shops tile → shop page shows products first | H156: first product card at y=571 px (screen 800); shop info folded: true | I156: PASS
A157: RES-0156 | B157: TR-08 | C157: docs/tile-board-2026-10/GoKesari_UI_Test_Report_2026-10-09.xlsx | D157: End-to-end (B) | E157: 20:21 | F157: Customer · Cart | G157: C-05 Add to cart (phone card: Add, then −/+) | H157: stepper shown; cart: Burger Bun×1 | I157: PASS
A158: RES-0157 | B158: TR-08 | C158: docs/tile-board-2026-10/GoKesari_UI_Test_Report_2026-10-09.xlsx | D158: End-to-end (B) | E158: 20:21 | F158: Customer · Cancel | G158: C-15 Accepted order: Cancel follows the business rule | H158: order shown: true; Cancel button: 0; direct API cancel → 409 {"error":{"code":"CONFLICT","message":"This order is already being prepared. Please contact the shop to cancel it."}} | I158: PASS
A159: RES-0158 | B159: TR-08 | C159: docs/tile-board-2026-10/GoKesari_UI_Test_Report_2026-10-09.xlsx | D159: End-to-end (B) | E159: 20:23 | F159: Customer · Checkout | G159: C-06 Checkout (wallet, or cash on delivery when the wallet is short) | H159: order DB-20261009-LSIMHV CONFIRMED (WALLET), total ₹50; wallet ₹80 → ₹30; URL /orders?placed=1 | I159: PASS
A160: RES-0159 | B160: TR-08 | C160: docs/tile-board-2026-10/GoKesari_UI_Test_Report_2026-10-09.xlsx | D160: End-to-end (B) | E160: 20:35 | F160: Customer · Tracking | G160: C-07 Track an order from 'Do now' (phone) | H160: Do now said "Track order ready · E2E Four Features Bakery" (→ /orders?tab=active#order-DB-20261008-8QZBEQ); landed on /orders?tab=active#order-DB-20261008-8QZBEQ with 1 active order card(s) | I160: PASS
A161: RES-0160 | B161: TR-08 | C161: docs/tile-board-2026-10/GoKesari_UI_Test_Report_2026-10-09.xlsx | D161: End-to-end (B) | E161: 19:45 | F161: Customer · Returns | G161: C-10 Return an item from a delivered order | H161: RT-30B14E73 UNDER_REVIEW, refund due ₹40, created 19:41 UTC; listed on Returns tab: true | I161: PASS
A162: RES-0161 | B162: TR-08 | C162: docs/tile-board-2026-10/GoKesari_UI_Test_Report_2026-10-09.xlsx | D162: End-to-end (B) | E162: 19:43 | F162: Customer · Disputes | G162: C-11 Raise a dispute on a delivered order | H162: opened /disputes/c8150aa7-282f-4c35-80d1-8ac0a90cfe65?opened=1 | I162: PASS
A163: RES-0162 | B163: TR-08 | C163: docs/tile-board-2026-10/GoKesari_UI_Test_Report_2026-10-09.xlsx | D163: End-to-end (B) | E163: 19:39 | F163: Customer · Help | G163: C-12 Report a problem (support ticket) | H163: Reported — ticket GRV-000002. We will get back to you. | I163: PASS
A164: RES-0163 | B164: TR-08 | C164: docs/tile-board-2026-10/GoKesari_UI_Test_Report_2026-10-09.xlsx | D164: End-to-end (B) | E164: 19:40 | F164: Customer · Subscriptions | G164: C-13 Set up a daily subscription (saved as a draft) | H164: /subscriptions/8e2cb590-4cac-45aa-9f40-25301a82de27; subscriptions: Burger Bun DRAFT | I164: PASS
... A209: RES-0208 | B209: TR-08 | C209: docs/tile-board-2026-10/GoKesari_UI_Test_Report_2026-10-09.xlsx | D209: End-to-end (B) | E209: 20:48 | F209: Operator · Slow network | G209: D-NET-Operator-_admin /admin on slow 4G (150 ms, 1.6 Mbps down) | H209: usable after 3.6 s, fully loaded 4.0 s | I209: FAIL
A210: RES-0209 | B210: TR-09 | C210: docs/tile-board-2026-10/TEST_RESULTS_UI_PASS.md | D210: Production (gokesari.com) after release #126, 9 Oct 21:44 UTC | G210: Pages load: /, /shops, /categories, /signin, /search?q=milk, /legal/terms | H210: 200 (0.39–1.24 s) — PASS | I210: PASS
A211: RES-0210 | B211: TR-09 | C211: docs/tile-board-2026-10/TEST_RESULTS_UI_PASS.md | D211: Production (gokesari.com) after release #126, 9 Oct 21:44 UTC | G211: Signed-in pages without a sign-in: /admin, /shop, /profile, /orders | H211: 307 to /signin — PASS | I211: PASS
A212: RES-0211 | B212: TR-09 | C212: docs/tile-board-2026-10/TEST_RESULTS_UI_PASS.md | D212: Production (gokesari.com) after release #126, 9 Oct 21:44 UTC | G212: New build live (“Shop list” heading on /shops) | H212: yes, 21:44:41 UTC — PASS | I212: PASS
A213: RES-0212 | B213: TR-09 | C213: docs/tile-board-2026-10/TEST_RESULTS_UI_PASS.md | D213: Production (gokesari.com) after release #126, 9 Oct 21:44 UTC | G213: Lighthouse mobile (perf / a11y / best practices / SEO) | H213: home 93/100/100/100 (cold first visit, server 3.7 s); shops 98; categories 99; search 93 (cold, server 4.1 s); sign-in 100 | I213: OK (recorded)
A214: RES-0213 | B214: TR-09 | C214: docs/tile-board-2026-10/TEST_RESULTS_UI_PASS.md | D214: Production (gokesari.com) after release #126, 9 Oct 21:44 UTC | G214: Lighthouse desktop | H214: home 92 (cold, server 4.0 s); shops 100 | I214: OK (recorded)
A215: RES-0214 | B215: TR-09 | C215: docs/tile-board-2026-10/TEST_RESULTS_UI_PASS.md | D215: Production (gokesari.com) after release #126, 9 Oct 21:44 UTC | G215: Home and search, warm repeat visits (5 each) | H215: 0.9–1.3 s to first byte | I215: OK (recorded)
A216: RES-0215 | B216: TR-10 | C216: docs/nearby-referral-2026-10/TEST_RESULTS.md | D216: 1. Summary | F216: F1 Nearby — permission allowed | H216: Pass — Android, iPhone, desktop: "kharadi, Pune 411014 · accurate to about 15 m", shops nearest first | I216: PASS
A217: RES-0216 | B217: TR-10 | C217: docs/nearby-referral-2026-10/TEST_RESULTS.md | D217: 1. Summary | F217: F1 — each radius (1 / 3 / 5 / 10 km) | H217: Pass — 2 / 4 / 4 / 6 shops, counts on the chips match | I217: PASS
A218: RES-0217 | B218: TR-10 | C218: docs/nearby-referral-2026-10/TEST_RESULTS.md | D218: 1. Summary | F218: F1 — distance text | H218: Pass — 540 m, 830 m, 1.7 km, 2.2 km, 6.1 km, 8.9 km | I218: PASS
A219: RES-0218 | B219: TR-10 | C219: docs/nearby-referral-2026-10/TEST_RESULTS.md | D219: 1. Summary | F219: F1 — distance accuracy (6 shops) | H219: Pass — within 0.1–28 m (≤ 0.5 %) of an independent WGS-84 geodesic (§3) | I219: PASS
A220: RES-0219 | B220: TR-10 | C220: docs/nearby-referral-2026-10/TEST_RESULTS.md | D220: 1. Summary | F220: F1 — open / closed | H220: Pass — "Closed" shown for every test shop (opening hours, evening IST) | I220: PASS
A221: RES-0220 | B221: TR-10 | C221: docs/nearby-referral-2026-10/TEST_RESULTS.md | D221: 1. Summary | F221: F1 — Directions (desktop and phones) | H221: Pass — https://www.google.com/maps/dir/?api=1&origin=18.5515%2C73.9348&destination=…, new tab; see note N-3 | I221: PASS
A222: RES-0221 | B222: TR-10 | C222: docs/nearby-referral-2026-10/TEST_RESULTS.md | D222: 1. Summary | F222: F1 — Map view | H222: Pass — Google map (browser key works on test), blue "You are here" dot, radius ring, 6 shop pins; tapping a pin opens name, "540 m away · Closed", Directions (phone and desktop) | I222: PASS
A223: RES-0222 | B223: TR-10 | C223: docs/nearby-referral-2026-10/TEST_RESULTS.md | D223: 1. Summary | F223: F1 — permission denied | H223: Pass — "Location permission is off … enter a PIN code or area below" + PIN box | I223: PASS
A224: RES-0223 | B224: TR-10 | C224: docs/nearby-referral-2026-10/TEST_RESULTS.md | D224: 1. Summary | F224: F1 — manual PIN / area | H224: Pass — 411014 → 4 shops (380 m …); "Kharadi" → same place; 999999 → "We couldn't find that PIN code or area…" | I224: PASS
A225: RES-0224 | B225: TR-10 | C225: docs/nearby-referral-2026-10/TEST_RESULTS.md | D225: 1. Summary | F225: F1 — no shops in range | H225: Pass — 3 km: "No shops found within 3 km · 1 shop within 5 km · Widen to 5 km" → EcoMed 4.0 km; Nagpur: "No shops found within 5 km · none within 10 km either · See all shops" | I225: PASS
A226: RES-0225 | B226: TR-10 | C226: docs/nearby-referral-2026-10/TEST_RESULTS.md | D226: 1. Summary | F226: F1 — prompt never answered | H226: Fixed (S-1) — waited forever; now offers the PIN box after 12 s | I226: PASS
A227: RES-0226 | B227: TR-10 | C227: docs/nearby-referral-2026-10/TEST_RESULTS.md | D227: 1. Summary | F227: F1 — shops without coordinates | H227: Pass — left out of Nearby; Admin → Shops without location lists 9 (operator 200, customer and shop owner sent home), CSV download; coordinates pasted for 4 shops → saved, report drops them, they appear in Nearby; bad input refused | I227: PASS
... A239: RES-0238 | B239: TR-10 | C239: docs/nearby-referral-2026-10/TEST_RESULTS.md | D239: 1. Summary | F239: Regression — payments | H239: Pass — ₹10 wallet top-up, Cashfree sandbox UPI testsuccess@gocash (sandbox-pay run 38080594690) → site verified with Cashfree → balance ₹30 → ₹40 | I239: PASS
A240: RES-0239 | B240: TR-10 | C240: docs/nearby-referral-2026-10/TEST_RESULTS.md | D240: 2. Nearby, step by step (UTC) | E240: 19:12 | G240: Shops without location as customer / shop owner / operator | H240: / · / · 9 rows | I240: OK (recorded)
A241: RES-0240 | B241: TR-10 | C241: docs/nearby-referral-2026-10/TEST_RESULTS.md | D241: 2. Nearby, step by step (UTC) | E241: 19:13 | G241: Admin: CSV download; "Fill all from address" | H241: CSV with 9 shops; each shop: "API keys with referer restrictions cannot be used with this API." — nothing saved (N-1) | I241: OK (recorded)
A242: RES-0241 | B242: TR-10 | C242: docs/nearby-referral-2026-10/TEST_RESULTS.md | D242: 2. Nearby, step by step (UTC) | E242: 19:13 | G242: Admin pastes coordinates for Agtci, Chikan Shop, E2E Four Features Stationery, EcoMed Solutions | H242: "Saved." ×4; "hello" → "Paste latitude, longitude — for example …"; 5 left | I242: OK (recorded)
A243: RES-0242 | B243: TR-10 | C243: docs/nearby-referral-2026-10/TEST_RESULTS.md | D243: 2. Nearby, step by step (UTC) | E243: 19:14 | G243: Android, GPS 18.5515, 73.9348 | H243: location "kharadi, Pune 411014"; 1 km: Chikan Shop 540 m, Agtci 830 m; 3 km: + Samarth tea center 1.7 km, Asmy Exports 2.2 km; 10 km: + EcoMed Solutions 6.1 km, E2E Four Features Bakery 8.9 km | I243: OK (recorded)
A244: RES-0243 | B244: TR-10 | C244: docs/nearby-referral-2026-10/TEST_RESULTS.md | D244: 2. Nearby, step by step (UTC) | E244: 19:14 | G244: iPhone, same | H244: same lists and distances | I244: OK (recorded)
A245: RES-0244 | B245: TR-10 | C245: docs/nearby-referral-2026-10/TEST_RESULTS.md | D245: 2. Nearby, step by step (UTC) | E245: 19:15 | G245: Desktop, same | H245: same | I245: OK (recorded)
A246: RES-0245 | B246: TR-10 | C246: docs/nearby-referral-2026-10/TEST_RESULTS.md | D246: 2. Nearby, step by step (UTC) | E246: 19:15 | G246: Map view, tap Chikan Shop (phone, desktop) | H246: bubble "Chikan Shop · 540 m away · Closed · Directions" → …origin=18.5515%2C73.9348&destination=18.54684%2C73.93618 | I246: OK (recorded)
A247: RES-0246 | B247: TR-10 | C247: docs/nearby-referral-2026-10/TEST_RESULTS.md | D247: 2. Nearby, step by step (UTC) | E247: 19:20 | G247: Location blocked in the browser | H247: message + PIN box | I247: OK (recorded)
A248: RES-0247 | B248: TR-10 | C248: docs/nearby-referral-2026-10/TEST_RESULTS.md | D248: 2. Nearby, step by step (UTC) | E248: 19:20 | G248: PIN 411014 / "Kharadi" / 999999 | H248: results / results / clear error | I248: OK (recorded)
A249: RES-0248 | B249: TR-10 | C249: docs/nearby-referral-2026-10/TEST_RESULTS.md | D249: 2. Nearby, step by step (UTC) | E249: 19:20 | G249: Nagpur (21.1458, 79.0882) | H249: "No shops found within 5 km" + widen / see all | I249: OK (recorded)
A250: RES-0249 | B250: TR-10 | C250: docs/nearby-referral-2026-10/TEST_RESULTS.md | D250: 2. Nearby, step by step (UTC) | E250: 19:20 | G250: 18.48, 73.90, radius 3 km | H250: "1 shop within 5 km · Widen to 5 km" → EcoMed Solutions 4.0 km | I250: OK (recorded)
A251: RES-0250 | B251: TR-10 | C251: docs/nearby-referral-2026-10/TEST_RESULTS.md | D251: 2. Nearby, step by step (UTC) | E251: 19:20 | G251: Home board | H251: Nearby chip → /shops/nearby | I251: OK (recorded)
A252: RES-0251 | B252: TR-11 | C252: docs/nearby-referral-2026-10/TEST_RESULTS.md | D252: 6. Production (gokesari.com) | G252: /, /shops, /search?q=milk, /categories, /signin, /legal/wallet-terms | H252: 200 (before: 200) | I252: PASS
A253: RES-0252 | B253: TR-11 | C253: docs/nearby-referral-2026-10/TEST_RESULTS.md | D253: 6. Production (gokesari.com) | G253: /shops/nearby | H253: 200 (before: 404) | I253: PASS
A254: RES-0253 | B254: TR-11 | C254: docs/nearby-referral-2026-10/TEST_RESULTS.md | D254: 6. Production (gokesari.com) | G254: /api/referral-settings | H254: {"customer":"OPTIONAL","shop":"OPTIONAL"} (before: 404) | I254: OK (recorded)
A255: RES-0254 | B255: TR-11 | C255: docs/nearby-referral-2026-10/TEST_RESULTS.md | D255: 6. Production (gokesari.com) | G255: /api/shops/nearby?lat=18.5204&lng=73.8567 | H255: 200 (before: 500 (old /api/shops/{id} route)) | I255: PASS
A256: RES-0255 | B256: TR-11 | C256: docs/nearby-referral-2026-10/TEST_RESULTS.md | D256: 6. Production (gokesari.com) | G256: Nearby screen, Android and desktop, GPS Pune centre | H256: "Dattwadi, Pune 411011", all radii, empty state, 0 page errors (before: —) | I256: OK (recorded)
A257: RES-0256 | B257: TR-11 | C257: docs/nearby-referral-2026-10/TEST_RESULTS.md | D257: 6. Production (gokesari.com) | G257: Home board Nearby chip | H257: /shops/nearby (before: /shops) | I257: OK (recorded)
A258: RES-0257 | B258: TR-12 | C258: docs/nearby-referral-2026-10/TEST_RESULTS.md | D258: 8. Fix: referral codes showed 0 shops (11 Oct 2026) | G258: New integration tests (codes with 2 and 0 shops; a society with founder + approved resident + pending request) | H258: Fail on the old code, pass with the fix | I258: PASS
A259: RES-0258 | B259: TR-12 | C259: docs/nearby-referral-2026-10/TEST_RESULTS.md | D259: 8. Fix: referral codes showed 0 shops (11 Oct 2026) | G259: PR #138 → staging, CI | H259: Green; merged 02:11 UTC | I259: PASS
A260: RES-0259 | B260: TR-12 | C260: docs/nearby-referral-2026-10/TEST_RESULTS.md | D260: 8. Fix: referral codes showed 0 shops (11 Oct 2026) | G260: test.gokesari.com, Admin → Referral codes (GET /api/referral-codes as admin) | H260: E2ENEARBY1 4, E2ETEST1 4, E2EANIL1 1, GKCMUWB6K 0 (it was 0 for all) | I260: OK (recorded)
A261: RES-0260 | B261: TR-12 | C261: docs/nearby-referral-2026-10/TEST_RESULTS.md | D261: 8. Fix: referral codes showed 0 shops (11 Oct 2026) | G261: Societies on test | H261: None exist, so this is covered by the integration test only | I261: OK (recorded)
A262: RES-0261 | B262: TR-12 | C262: docs/nearby-referral-2026-10/TEST_RESULTS.md | D262: 8. Fix: referral codes showed 0 shops (11 Oct 2026) | G262: PR #139 staging → main, CI | H262: Green; merged 02:32 UTC | I262: PASS
A263: RES-0262 | B263: TR-12 | C263: docs/nearby-referral-2026-10/TEST_RESULTS.md | D263: 8. Fix: referral codes showed 0 shops (11 Oct 2026) | G263: gokesari.com, read-only smoke at 02:40 UTC | H263: /, /shops, /shops/nearby, /signin, /api/referral-settings, /api/shops/nearby all 200; Nearby on Android and desktop: location named, all radii, 0 page errors | I263: OK (recorded)
... A267: RES-0266 | B267: TR-13 | C267: docs/seller-central-2026-10/TEST_RESULTS.md | D267: Automated checks | G267: New tests | H267: 5 passed | I267: PASS
A268: RES-0267 | B268: TR-13 | C268: docs/seller-central-2026-10/TEST_RESULTS.md | D268: Manual checks (dev server on seeded demo data, Chromium) | F268: 1 | G268: /sell signed out: hero, benefits, how it works, tools, shop types, register options, FAQ, footer; shopping header hidden | 1366 × 900 | H268: Pass | I268: PASS
A269: RES-0268 | B269: TR-13 | C269: docs/seller-central-2026-10/TEST_RESULTS.md | D269: Manual checks (dev server on seeded demo data, Chromium) | F269: 2 | G269: /sell on a phone: every section stacks, no sideways scrolling | 390 × 844 | H269: Pass | I269: PASS
A270: RES-0269 | B270: TR-13 | C270: docs/seller-central-2026-10/TEST_RESULTS.md | D270: Manual checks (dev server on seeded demo data, Chromium) | F270: 3 | G270: /shop as an approved owner (Kesari Dairy Farm): seller top bar with "Live" pill, sidebar groups, dashboard sections, all-tools grid | 1440 × 900 | H270: Pass | I270: PASS
A271: RES-0270 | B271: TR-13 | C271: docs/seller-central-2026-10/TEST_RESULTS.md | D271: Manual checks (dev server on seeded demo data, Chromium) | F271: 4 | G271: /shop on a phone: the approved tile board, full screen with its own header (no seller top bar), page height exactly one screen | 390 × 844 | H271: Pass | I271: PASS
A272: RES-0271 | B272: TR-13 | C272: docs/seller-central-2026-10/TEST_RESULTS.md | D272: Manual checks (dev server on seeded demo data, Chromium) | F272: 4a | G272: /shop on a tablet: tile board, one screen | 820 × 1180 | H272: Pass | I272: PASS
A273: RES-0272 | B273: TR-13 | C273: docs/seller-central-2026-10/TEST_RESULTS.md | D273: Manual checks (dev server on seeded demo data, Chromium) | F273: 4b | G273: Tile board → Orders tile: /shop/orders opens in Seller Central with ☰ and the shop line | 390 × 844 | H273: Pass | I273: PASS
A274: RES-0273 | B274: TR-13 | C274: docs/seller-central-2026-10/TEST_RESULTS.md | D274: Manual checks (dev server on seeded demo data, Chromium) | F274: 5 | G274: ☰ on a seller page → Inventory: opens /shop/inventory and the drawer closes | 390 × 844 | H274: Pass | I274: PASS
A275: RES-0274 | B275: TR-13 | C275: docs/seller-central-2026-10/TEST_RESULTS.md | D275: Manual checks (dev server on seeded demo data, Chromium) | F275: 6 | G275: /shop/orders: Orders highlighted in the sidebar with New / Packing / Ready / Out underneath | 1440 × 900 | H275: Pass | I275: PASS
...

Sheet Defects
A1: Defect | B1: Found in run | C1: Feature IDs | D1: What | E1: Status | F1: Fixed in PR | G1: Notes
A2: D-01 | B2: TR-02 | C2: NEW-039 | D2: A repeated 'Packed - mark ready' (double tap / retry) answered 409 | E2: Fixed | F2: #103 | G2: Re-checked in TR-03: 200, 200, one event, one charge
A3: D-02 | B3: TR-02 | C3: NEW-041 | D3: Rs 1 refund stayed 'refund pending' after Cashfree accepted it | E3: Fixed | F3: #103 | G3: Re-checked in TR-03: 'refunded'
A4: D-03 | B4: TR-02 | C4: NEW-040, NEW-042 | D4: Old referral error stayed visible after correcting the code; 'fssai' lower-case | E4: Fixed | F4: #103 | G4: Re-checked in TR-03
A5: D-04 | B5: TR-02 | C5: GS-055 | D5: Test site's mail host refused mail after its hourly cap (451 rate limit); some emails late or DEAD | E5: Open | F5: - | G5: Raise the limit or use a transactional email service before go-live (GAP-009)
A6: D-05 | B6: TR-02 | C6: GS-004 | D6: Map 'Confirm location' answers 500 on test | E6: Owner action | F6: - | G6: Cause found in TR-10 (N-1): the Maps server key is restricted by HTTP referrer - switch to an IP restriction (GAP-008)
A7: D-06 | B7: TR-20 | C7: QA-001 | D7: Flaky integration test login-profile: a background email reached the next test's outbox | E7: Fixed | F7: #92 (bf8df50) | G7: Test waits for pending emails before clearing the outbox
A8: D-07 | B8: TR-08 | C8: NEW-051 | D8: 5 pages take over 3 s on slow 4G | E8: Open | F8: - | G8: Database far from the web server (GAP-010, hosting decision)
A9: D-08 | B9: TR-08 | C9: NEW-046 | D9: Shop owner board 2 px over one screen at 320x640 with two alerts | E9: Accepted | F9: - | G9: Accepted by the owner (D-02 in the UI pass)
A10: D-09 | B10: TR-10 | C10: NEW-057 | D10: Nearby waited forever when the location prompt was never answered | E10: Fixed | F10: #136 | G10: PIN box after 12 s
A11: D-10 | B11: TR-10 | C11: NEW-059 | D11: 'Fill from address' cannot work on test: Google refuses the server key (N-1) | E11: Owner action | F11: - | G11: Same key fix as D-05
A12: D-11 | B12: TR-10 | C12: NEW-038, NEW-058 | D12: No SMS provider on test (SMS_PROVIDER=none) - /shop/join cannot be completed (N-2) | E12: Open | F12: - | G12: Pre-existing; waits on the SMS vendor (D2)
... A24: D-23 | B24: TR-06 | C24: NEW-050 | D24: Bank check with Cashfree: Verification Suite keys not found by test.gokesari.com | E24: Owner action | F24: - | G24: Put the keys in the Hostinger environment of the test site (not only GitHub), then run O7.2-O7.5

Sheet Not run & gaps
A1: What was not tested | B1: Feature IDs | C1: Why | D1: Covered by / run
A2: 791-case plan (smoke, P0, P1, P2) and 35 end-to-end scenarios | B2: All | C2: Never executed; no results recorded | D2: TR-21
A3: Order lifecycle on staging (sign-up -> order -> delivery code -> done) | B3: QA-008 | C3: Run locally only (21/21); staging run is next and needs the Sandbox payment workflow | D3: TR-22
A4: Shop settlement refused without a verified bank account | B4: NEW-041 | C4: No settlement can exist on test for a new shop until the hold period passes | D4: Integration tests
A5: Payer-name mismatch on the Rs 1 payment | B5: NEW-041 | C5: Cashfree sandbox reports no payer name | D5: Integration tests
A6: Arrival of request emails in the referrals@gokesari.com inbox | B6: NEW-042 | C6: Mailbox not readable from the test run (SMTP accepted) | D6: Owner to confirm
A7: Paid self-registration (/shop/join) end to end | B7: NEW-038, NEW-058 | C7: No SMS provider on test (N-2) | D7: Integration tests
A8: Wallet top-up and shop wallet recharge in the UI pass (C-01, S-13) | B8: GS-029, NEW-033 | C8: GitHub Actions billing stop on 9 Oct (Sandbox payment did not start) | D8: Covered in TR-02 and TR-10 regression
A9: Return pickup, inspection and refund (S-11b) | B9: GS-057 | C9: Needs a rider to collect the pickup | D9: -
A10: Seller Central on test / production | B10: NEW-060 | C10: Only local checks recorded | D10: TR-13
A11: Saffron wordmark (#153) on test / production | B11: NEW-064 | C11: No run recorded after the change | D11: -
A12: Directions on a real phone | B12: NEW-057 | C12: Test environment cannot reach google.com | D12: -
... A14: Admin pages on production (referral settings, referral-code counts) | B14: NEW-058, NEW-065 | C14: Need a production admin sign-in | D14: Verified on test

Sheet 791-case plan
A1: Module | B1: Cases | C1: P0 cases | D1: Pass | E1: Fail | F1: Blocked | G1: Not run
A2: Preflight & smoke | B2: 12 | C2: 11 | D2: 0 | E2: 0 | F2: 0 | G2: 12
A3: Login, onboarding & profile | B3: 54 | C3: 24 | D3: 0 | E3: 0 | F3: 0 | G3: 54
A4: Roles & access control | B4: 24 | C4: 15 | D4: 0 | E4: 0 | F4: 0 | G4: 24
A5: Location, addresses & serviceability | B5: 32 | C5: 11 | D5: 0 | E5: 0 | F5: 0 | G5: 32
A6: Discovery, search & price comparison | B6: 24 | C6: 8 | D6: 0 | E6: 0 | F6: 0 | G6: 24
A7: Cart & checkout | B7: 30 | C7: 18 | D7: 0 | E7: 0 | F7: 0 | G7: 30
A8: Wallet, vouchers & gateway | B8: 35 | C8: 19 | D8: 0 | E8: 0 | F8: 0 | G8: 35
A9: Cash on delivery | B9: 12 | C9: 3 | D9: 0 | E9: 0 | F9: 0 | G9: 12
A10: Order state machine & cancellation | B10: 19 | C10: 9 | D10: 0 | E10: 0 | F10: 0 | G10: 19
A11: Shop fulfilment & substitution | B11: 18 | C11: 10 | D11: 0 | E11: 0 | F11: 0 | G11: 18
A12: Rider dispatch & assignment rules | B12: 26 | C12: 9 | D12: 0 | E12: 0 | F12: 0 | G12: 26
A13: Rider delivery & handover | B13: 31 | C13: 14 | D13: 0 | E13: 0 | F13: 0 | G13: 31
... A29: Sell, purchase & inventory | B29: 28 | C29: 14 | D29: 0 | E29: 0 | F29: 0 | G29: 28
A30: Total | B30: =SUM(B2:B29) | C30: =SUM(C2:C29) | D30: =SUM(D2:D29) | E30: =SUM(E2:E29) | F30: =SUM(F2:F29) | G30: =SUM(G2:G29)
A32: Source: test-cases.xlsx (prepared 3 Oct 2026; 791 cases, 35 end-to-end scenarios). Status read 14 Oct 2026: every case and scenario is 'Not run'. Update the Status column there as cases are executed.
