Workbook

Sheet Read me
A1: GoKesari - test scenarios and test cases
A2: Prepared 3 Oct 2026 for execution by Claude in a browser against the test site. Nothing here has been run yet - every Expected result is a claim to confirm or refute. Updated 3 Oct with three new requirements (NEW-008 to NEW-010), field-level, log out and sell / purchase / inventory cases - see the Change log sheet. Updated 4 Oct: the 24 open features are treated as completed and have positive and negative cases.
A4: What is in this workbook
A5: Test cases | B5: 826 cases across 30 modules (P0 320, P1 345, P2 161; the QA automation module TC-QA-001 to 007 and the Purchase lists module TC-LIST-001 to 028 added 24 Oct). One row per case with steps, expected result, the feature IDs it covers and the earlier plan it comes from. 213 cases were added on 3 Oct and 106 on 4 Oct.
A6: E2E scenarios | B6: 37 end-to-end journeys built from the ten workflows (WF-001 to WF-010), the MVP vertical flow, the 3-Oct requirements (SC-23 to SC-28) and the open features treated as completed (SC-29 to SC-35); SC-36 and SC-37 (24 Oct) are the QA release check and the Claude QA agent's signed-in run.
A7: Coverage | B7: Every feature ID from the 28-Sep status report plus NEW-001 to NEW-010, with the test cases that cover it.
A8: Not yet testable | B8: Features still with no code behind them and not in the 3-Oct open-features list. Listed so nobody reports them as defects.
A9: Test data | B9: Accounts and seed data to prepare before the run.
A10: Run summary | B10: Live pass/fail counts per module, driven by the Status column.
A11: Change log | B11: What was added or changed on 3 Oct and 4 Oct, and the open questions to confirm with the owner.
A13: Sources used
A14: Feature lists | B14: Gokesari_Complete_Features_and_Workflows.xlsx (Feature Master, Workflow Master, RBAC Matrix, State Machines, Gig Assignment Rules, Navigation, KPIs); GOKESARI_FEATURE_STATUS_REPORT 27-Sep, 28-Sep and the 2-Oct re-audit in the repository; GOKESARI_IMPLEMENTATION_PRIORITY_UPDATED.xlsx (fast go-live priority, MVP vertical flow).
A15: Earlier test plans | B15: docs/gokesari-audit/QA_TEST_PLAN_COMPLETE_IN_PROGRESS.md (Phases A-J), GOKESARI_TEST_PLAN.md, the 'Testing handoff' blocks in PHASE1_DEV_LOG.md (Slices 1, 3-4, 6, Phases 2, 3, 4.3, 4.5, duplicate-shop fix, closed-shop ordering), docs/login-profile/DEPLOY_AND_TEST.md, GOKESARI_REGRESSION_MATRIX.xlsx, tests/e2e/acceptance.spec.ts, API.md, RBAC_PLAN.md.
A17: Rules for the run
A18: 1. Environment | B18: Run everything on https://test.gokesari.com. Production (gokesari.com) gets only the read-only smoke case TC-PRE-010. Check the host before every write.
A19: 2. Start with Preflight | B19: Run TC-PRE-001 to TC-PRE-008 first. They show which build and migrations are on test and which modules will be Blocked.
A20: 3. Order of work | B20: Preflight -> Login -> Access control -> Location -> Discovery -> Cart -> Wallet -> Fulfilment -> Dispatch -> Delivery -> Order state/cancellation -> the rest. P0 first inside each module, then the E2E scenarios.
A21: 4. Sign-in | B21: Claude does not type passwords. The owner signs each test account in (or reads out the email code) in the browser Claude is driving. Keep one browser profile per role where two roles must act at the same time.
A22: 5. Method column | B22: UI = through the pages. API = a fetch from the signed-in browser session to the listed endpoint, reading status and JSON. DB = needs database access to the TEST database; mark Blocked if not available. Never point any test tooling at the production database.
A23: 6. Money | B23: Use mock / sandbox payments only, for wallet top-ups and for online order payments. Never complete a real payment. Amounts are integer paise in the API (Rs 70.00 = 7000) and quantities are milli-units (2 L = 2000).
A24: 7. Time-based cases | B24: Cases that wait for expiry or cron (OTP expiry, offer expiry, rider search limits, notification retries) can be shortened by lowering the rule in /admin/settings on test, then restoring the default.
A25: 8. Recording results | B25: Set Status to Pass, Fail, Blocked or Not run. For a Fail write the actual result, the URL, the request/response or a screenshot name. For Blocked say why. Log defects with the TC ID.
A26: 9. Clean up | B26: Restore every rule changed in /admin/settings, reinstate suspended shops/users, and note any test data left behind.
A27: 10. New requirements | B27: NEW-008 to NEW-010 were stated on 3 Oct. Run TC-PRE-011 first; where the build does not have a requirement yet, mark its cases Blocked, not Fail. Open questions in the Change log decide a few Expected results.
A28: 11. Open features | B28: The 24 open features are written as if built. Run TC-PRE-012 first; where a feature is not on the test build yet, mark its cases Blocked, not Fail.
A30: Status values | B30: Pass = behaves as Expected. Fail = differs. Blocked = cannot be tested (say why). Not run = not attempted.
A31: Priority | B31: P0 = go-live blocker path (login, order, pay, fulfil, deliver, money, access control). P1 = important. P2 = secondary / edge.

Sheet Run summary
A1: Module | B1: Cases | C1: Pass | D1: Fail | E1: Blocked | F1: Not run | G1: P0 cases | H1: P0 not passed
A2: Preflight & smoke | B2: =COUNTIF('Test cases'!$B$2:$B$840,A2) | C2: =COUNTIFS('Test cases'!$B$2:$B$840,$A2,'Test cases'!$M$2:$M$840,"Pass") | D2: =COUNTIFS('Test cases'!$B$2:$B$840,$A2,'Test cases'!$M$2:$M$840,"Fail") | E2: =COUNTIFS('Test cases'!$B$2:$B$840,$A2,'Test cases'!$M$2:$M$840,"Blocked") | F2: =COUNTIFS('Test cases'!$B$2:$B$840,$A2,'Test cases'!$M$2:$M$840,"Not run") | G2: =COUNTIFS('Test cases'!$B$2:$B$840,$A2,'Test cases'!$F$2:$F$840,"P0") | H2: =G2-COUNTIFS('Test cases'!$B$2:$B$840,$A2,'Test cases'!$F$2:$F$840,"P0",'Test cases'!$M$2:$M$840,"Pass")
A3: Login, onboarding & profile | B3: =COUNTIF('Test cases'!$B$2:$B$840,A3) | C3: =COUNTIFS('Test cases'!$B$2:$B$840,$A3,'Test cases'!$M$2:$M$840,"Pass") | D3: =COUNTIFS('Test cases'!$B$2:$B$840,$A3,'Test cases'!$M$2:$M$840,"Fail") | E3: =COUNTIFS('Test cases'!$B$2:$B$840,$A3,'Test cases'!$M$2:$M$840,"Blocked") | F3: =COUNTIFS('Test cases'!$B$2:$B$840,$A3,'Test cases'!$M$2:$M$840,"Not run") | G3: =COUNTIFS('Test cases'!$B$2:$B$840,$A3,'Test cases'!$F$2:$F$840,"P0") | H3: =G3-COUNTIFS('Test cases'!$B$2:$B$840,$A3,'Test cases'!$F$2:$F$840,"P0",'Test cases'!$M$2:$M$840,"Pass")
A4: Roles & access control | B4: =COUNTIF('Test cases'!$B$2:$B$840,A4) | C4: =COUNTIFS('Test cases'!$B$2:$B$840,$A4,'Test cases'!$M$2:$M$840,"Pass") | D4: =COUNTIFS('Test cases'!$B$2:$B$840,$A4,'Test cases'!$M$2:$M$840,"Fail") | E4: =COUNTIFS('Test cases'!$B$2:$B$840,$A4,'Test cases'!$M$2:$M$840,"Blocked") | F4: =COUNTIFS('Test cases'!$B$2:$B$840,$A4,'Test cases'!$M$2:$M$840,"Not run") | G4: =COUNTIFS('Test cases'!$B$2:$B$840,$A4,'Test cases'!$F$2:$F$840,"P0") | H4: =G4-COUNTIFS('Test cases'!$B$2:$B$840,$A4,'Test cases'!$F$2:$F$840,"P0",'Test cases'!$M$2:$M$840,"Pass")
A5: Location, addresses & serviceability | B5: =COUNTIF('Test cases'!$B$2:$B$840,A5) | C5: =COUNTIFS('Test cases'!$B$2:$B$840,$A5,'Test cases'!$M$2:$M$840,"Pass") | D5: =COUNTIFS('Test cases'!$B$2:$B$840,$A5,'Test cases'!$M$2:$M$840,"Fail") | E5: =COUNTIFS('Test cases'!$B$2:$B$840,$A5,'Test cases'!$M$2:$M$840,"Blocked") | F5: =COUNTIFS('Test cases'!$B$2:$B$840,$A5,'Test cases'!$M$2:$M$840,"Not run") | G5: =COUNTIFS('Test cases'!$B$2:$B$840,$A5,'Test cases'!$F$2:$F$840,"P0") | H5: =G5-COUNTIFS('Test cases'!$B$2:$B$840,$A5,'Test cases'!$F$2:$F$840,"P0",'Test cases'!$M$2:$M$840,"Pass")
A6: Discovery, search & price comparison | B6: =COUNTIF('Test cases'!$B$2:$B$840,A6) | C6: =COUNTIFS('Test cases'!$B$2:$B$840,$A6,'Test cases'!$M$2:$M$840,"Pass") | D6: =COUNTIFS('Test cases'!$B$2:$B$840,$A6,'Test cases'!$M$2:$M$840,"Fail") | E6: =COUNTIFS('Test cases'!$B$2:$B$840,$A6,'Test cases'!$M$2:$M$840,"Blocked") | F6: =COUNTIFS('Test cases'!$B$2:$B$840,$A6,'Test cases'!$M$2:$M$840,"Not run") | G6: =COUNTIFS('Test cases'!$B$2:$B$840,$A6,'Test cases'!$F$2:$F$840,"P0") | H6: =G6-COUNTIFS('Test cases'!$B$2:$B$840,$A6,'Test cases'!$F$2:$F$840,"P0",'Test cases'!$M$2:$M$840,"Pass")
A7: Cart & checkout | B7: =COUNTIF('Test cases'!$B$2:$B$840,A7) | C7: =COUNTIFS('Test cases'!$B$2:$B$840,$A7,'Test cases'!$M$2:$M$840,"Pass") | D7: =COUNTIFS('Test cases'!$B$2:$B$840,$A7,'Test cases'!$M$2:$M$840,"Fail") | E7: =COUNTIFS('Test cases'!$B$2:$B$840,$A7,'Test cases'!$M$2:$M$840,"Blocked") | F7: =COUNTIFS('Test cases'!$B$2:$B$840,$A7,'Test cases'!$M$2:$M$840,"Not run") | G7: =COUNTIFS('Test cases'!$B$2:$B$840,$A7,'Test cases'!$F$2:$F$840,"P0") | H7: =G7-COUNTIFS('Test cases'!$B$2:$B$840,$A7,'Test cases'!$F$2:$F$840,"P0",'Test cases'!$M$2:$M$840,"Pass")
A8: Wallet, vouchers & gateway | B8: =COUNTIF('Test cases'!$B$2:$B$840,A8) | C8: =COUNTIFS('Test cases'!$B$2:$B$840,$A8,'Test cases'!$M$2:$M$840,"Pass") | D8: =COUNTIFS('Test cases'!$B$2:$B$840,$A8,'Test cases'!$M$2:$M$840,"Fail") | E8: =COUNTIFS('Test cases'!$B$2:$B$840,$A8,'Test cases'!$M$2:$M$840,"Blocked") | F8: =COUNTIFS('Test cases'!$B$2:$B$840,$A8,'Test cases'!$M$2:$M$840,"Not run") | G8: =COUNTIFS('Test cases'!$B$2:$B$840,$A8,'Test cases'!$F$2:$F$840,"P0") | H8: =G8-COUNTIFS('Test cases'!$B$2:$B$840,$A8,'Test cases'!$F$2:$F$840,"P0",'Test cases'!$M$2:$M$840,"Pass")
A9: Cash on delivery | B9: =COUNTIF('Test cases'!$B$2:$B$840,A9) | C9: =COUNTIFS('Test cases'!$B$2:$B$840,$A9,'Test cases'!$M$2:$M$840,"Pass") | D9: =COUNTIFS('Test cases'!$B$2:$B$840,$A9,'Test cases'!$M$2:$M$840,"Fail") | E9: =COUNTIFS('Test cases'!$B$2:$B$840,$A9,'Test cases'!$M$2:$M$840,"Blocked") | F9: =COUNTIFS('Test cases'!$B$2:$B$840,$A9,'Test cases'!$M$2:$M$840,"Not run") | G9: =COUNTIFS('Test cases'!$B$2:$B$840,$A9,'Test cases'!$F$2:$F$840,"P0") | H9: =G9-COUNTIFS('Test cases'!$B$2:$B$840,$A9,'Test cases'!$F$2:$F$840,"P0",'Test cases'!$M$2:$M$840,"Pass")
A10: Order state machine & cancellation | B10: =COUNTIF('Test cases'!$B$2:$B$840,A10) | C10: =COUNTIFS('Test cases'!$B$2:$B$840,$A10,'Test cases'!$M$2:$M$840,"Pass") | D10: =COUNTIFS('Test cases'!$B$2:$B$840,$A10,'Test cases'!$M$2:$M$840,"Fail") | E10: =COUNTIFS('Test cases'!$B$2:$B$840,$A10,'Test cases'!$M$2:$M$840,"Blocked") | F10: =COUNTIFS('Test cases'!$B$2:$B$840,$A10,'Test cases'!$M$2:$M$840,"Not run") | G10: =COUNTIFS('Test cases'!$B$2:$B$840,$A10,'Test cases'!$F$2:$F$840,"P0") | H10: =G10-COUNTIFS('Test cases'!$B$2:$B$840,$A10,'Test cases'!$F$2:$F$840,"P0",'Test cases'!$M$2:$M$840,"Pass")
A11: Shop fulfilment & substitution | B11: =COUNTIF('Test cases'!$B$2:$B$840,A11) | C11: =COUNTIFS('Test cases'!$B$2:$B$840,$A11,'Test cases'!$M$2:$M$840,"Pass") | D11: =COUNTIFS('Test cases'!$B$2:$B$840,$A11,'Test cases'!$M$2:$M$840,"Fail") | E11: =COUNTIFS('Test cases'!$B$2:$B$840,$A11,'Test cases'!$M$2:$M$840,"Blocked") | F11: =COUNTIFS('Test cases'!$B$2:$B$840,$A11,'Test cases'!$M$2:$M$840,"Not run") | G11: =COUNTIFS('Test cases'!$B$2:$B$840,$A11,'Test cases'!$F$2:$F$840,"P0") | H11: =G11-COUNTIFS('Test cases'!$B$2:$B$840,$A11,'Test cases'!$F$2:$F$840,"P0",'Test cases'!$M$2:$M$840,"Pass")
A12: Rider dispatch & assignment rules | B12: =COUNTIF('Test cases'!$B$2:$B$840,A12) | C12: =COUNTIFS('Test cases'!$B$2:$B$840,$A12,'Test cases'!$M$2:$M$840,"Pass") | D12: =COUNTIFS('Test cases'!$B$2:$B$840,$A12,'Test cases'!$M$2:$M$840,"Fail") | E12: =COUNTIFS('Test cases'!$B$2:$B$840,$A12,'Test cases'!$M$2:$M$840,"Blocked") | F12: =COUNTIFS('Test cases'!$B$2:$B$840,$A12,'Test cases'!$M$2:$M$840,"Not run") | G12: =COUNTIFS('Test cases'!$B$2:$B$840,$A12,'Test cases'!$F$2:$F$840,"P0") | H12: =G12-COUNTIFS('Test cases'!$B$2:$B$840,$A12,'Test cases'!$F$2:$F$840,"P0",'Test cases'!$M$2:$M$840,"Pass")
A13: Rider delivery & handover | B13: =COUNTIF('Test cases'!$B$2:$B$840,A13) | C13: =COUNTIFS('Test cases'!$B$2:$B$840,$A13,'Test cases'!$M$2:$M$840,"Pass") | D13: =COUNTIFS('Test cases'!$B$2:$B$840,$A13,'Test cases'!$M$2:$M$840,"Fail") | E13: =COUNTIFS('Test cases'!$B$2:$B$840,$A13,'Test cases'!$M$2:$M$840,"Blocked") | F13: =COUNTIFS('Test cases'!$B$2:$B$840,$A13,'Test cases'!$M$2:$M$840,"Not run") | G13: =COUNTIFS('Test cases'!$B$2:$B$840,$A13,'Test cases'!$F$2:$F$840,"P0") | H13: =G13-COUNTIFS('Test cases'!$B$2:$B$840,$A13,'Test cases'!$F$2:$F$840,"P0",'Test cases'!$M$2:$M$840,"Pass")
... A32: App install & updates | B32: =COUNTIF('Test cases'!$B$2:$B$840,A32) | C32: =COUNTIFS('Test cases'!$B$2:$B$840,$A32,'Test cases'!$M$2:$M$840,"Pass") | D32: =COUNTIFS('Test cases'!$B$2:$B$840,$A32,'Test cases'!$M$2:$M$840,"Fail") | E32: =COUNTIFS('Test cases'!$B$2:$B$840,$A32,'Test cases'!$M$2:$M$840,"Blocked") | F32: =COUNTIFS('Test cases'!$B$2:$B$840,$A32,'Test cases'!$M$2:$M$840,"Not run") | G32: =COUNTIFS('Test cases'!$B$2:$B$840,$A32,'Test cases'!$F$2:$F$840,"P0") | H32: =G32-COUNTIFS('Test cases'!$B$2:$B$840,$A32,'Test cases'!$F$2:$F$840,"P0",'Test cases'!$M$2:$M$840,"Pass")
A33: Total | B33: =SUM(B2:B32) | C33: =SUM(C2:C32) | D33: =SUM(D2:D32) | E33: =SUM(E2:E32) | F33: =SUM(F2:F32) | G33: =SUM(G2:G32) | H33: =SUM(H2:H32)

Sheet Change log
A1: Item | B1: Change | C1: Detail
A2: NEW-008 | B2: New requirement | C2: Loose goods: the price is left empty until the shop sets it. TC-CAT-027 to TC-CAT-036, SC-24.
A3: NEW-009 | B3: New requirement | C3: When a shop owner adds a product category, every product in it is added to the shop inventory at stock 100; products with no price are priced by the owner. TC-CAT-037 to TC-CAT-056, SC-23.
A4: NEW-010 | B4: New requirement | C4: An MRP changed by a shop owner applies to that shop only. TC-CAT-057 to TC-CAT-067, SC-25.
A5: TC-PRE-011 | B5: New case | C5: Preflight check that the three new requirements are on the test build; if not, their cases are Blocked.
A6: TC-AUTH-032 to TC-AUTH-045 | B6: New cases | C6: 14 log out / log off cases: every role, protected pages, session replay, tabs and devices, shared phone, automatic log off.
A7: TC-FLD-001 to TC-FLD-129 | B7: New module | C7: 'Field-level validation': 129 cases, one per field or field group on every form, each with blank, wrong format, boundary, script text and valid entries, checked on the page and through the API.
A8: TC-SPI-001 to TC-SPI-028 | B8: New module | C8: 'Sell, purchase & inventory': 28 cases tying each purchase and sale to its stock movement and money.
A9: SC-23 to SC-28 | B9: New scenarios | C9: Six end-to-end journeys: category stock-up to first sale, loose goods, shop MRP, sell / purchase / inventory reconciliation, log out on a shared phone, field validation on the first order.
A10: TC-PRE-008 | B10: Updated | C10: Seed data extended for the loose product, the test category and Shop C.
A11: TC-AUTH-030 | B11: Updated | C11: Pointer to the new log out cases.
A12: TC-DISC-011 | B12: Updated | C12: Unpriced rows added.
... A73: AI 31-Oct | B73: New module | C73: App install & updates (AI-001 to AI-006, docs/app-install-2026-10): TC-APP-001 to TC-APP-013. Automated in tests/qa/guest/app-install.spec.ts (production-safe, Android and iPhone profiles) and tests/qa/signed-in/app-install.spec.ts (account record). TC-APP-010 needs a deploy and TC-APP-012 a phone: declared manual.

Sheet Test cases
A1: TC ID | B1: Module | C1: Feature IDs | D1: Test case | E1: Type | F1: Priority | G1: Role | H1: Method | I1: Preconditions / data | J1: Steps | K1: Expected result | L1: Source (earlier plan / spec) | M1: Status | N1: Actual result | O1: Defect / evidence | P1: Run date
A2: TC-PRE-001 | B2: Preflight & smoke | C2: INF | D2: Test site is reachable and renders | E2: Positive | F2: P0 | G2: Guest | H2: UI | J2: 1. Open https://test.gokesari.com/ 2. Read the page and the browser console | K2: Home page renders with header (logo, Cart, Sign in), a 'Deliver to' location bar and shop shelves. No 500 page. No React hydration error (#418) in the console. | L2: Decisions & Deployment sheet; Dev log 2-Oct | M2: Pass | N2: Local Pass · Staging Pass · Production Pass local: customer: header (logo, cart, account menu), Deliver to, shelves; no hydration errors ‖ http://localhost:3351 renders; console errors: none staging: https://test.gokesari.com renders; console errors: none production: https://gokesari.com renders; console errors: none | O2: E-02 | P2: 2026-10-29 14:00
A3: TC-PRE-002 | B3: Preflight & smoke | C3: INF | D3: Database-backed pages load (no 500s) | E3: Positive | F3: P0 | G3: Guest | H3: UI | J3: 1. Open /shops, /search?q=milk, /categories, one /shops/{slug} page and one /products/{id} page | K3: Every page returns content. None shows a 500 or 'Something went wrong'. Record any that fail with URL and console/network error. | L3: Decisions & Deployment: 'test site returns 500 on all database pages' | M3: Pass | N3: Local Pass · Staging Pass · Production Pass local: loaded: /shops, /search?q=milk, /categories, /shops/anand-dairy-bakery, /products/ff3f256b-67d9-4fd3-ace9-f27d94c02bec ‖ loaded signed in: /shops, /search?q=milk, /categories, /shops/qa-shop-a-mvmkyclr-mvmkycqv-1, /products/c1046049-c1db-4f95-8571-86224a07ff84, /orders, /wallet staging: loaded: /shops, /search?q=milk, /categories, /shops/agtci-yivu6, /products/246c8d08-c44c-44b9-9ddd-458955580ba5 production: loaded: /shops, /search?q=milk, /categories, /shops/agtci-yivu6, /products/246c8d08-c44c-44b9-9ddd-458955580ba5 | P3: 2026-10-29 14:00
A4: TC-PRE-003 | B4: Preflight & smoke | C4: INF | D4: Deployed build matches the code under test | E4: Positive | F4: P0 | G4: Admin | H4: UI | I4: Signed in as ADMIN | J4: 1. Open each of: /admin/dashboard, /admin/orders, /admin/exceptions, /admin/settings, /admin/suspensions, /admin/rider-earnings, /admin/price-references, /admin/mrp, /admin/shop-categories, /admin/returns, /admin/cod, /admin/risk, /admin/analytics, /admin/campaigns, /admin/societies, /admin/product-master, /admin/consents, /admin/ratings 2. Note which load and which 404/500 | K4: All pages load. A 404 means the build on test is older than the features in this suite; a 500 usually means a migration (0025-0037) is not applied. Record the list - it decides which modules below are Blocked. | L4: Status report 2-Oct: 'migrations 0025-0036 unapplied as of last dev log' | M4: Pass | N4: Local Pass · Staging Pass · Production Not run local: 18/18 admin pages load: none blocks a module staging: 18/18 admin pages load: none blocks a module | P4: 2026-10-24 17:10
A5: TC-PRE-004 | B5: Preflight & smoke | C5: INF | D5: Business-rule defaults are in place before testing | E5: Positive | F5: P0 | G5: Admin | H5: UI | I5: Signed in as ADMIN | J5: 1. Open /admin/settings 2. Note every rule group and whether 'current' differs from 'default' | K5: Nine rule groups are listed (otp, dispatch, riderEarnings, returns, images, notifications, suspension, mrp, externalPrices). Record any non-default value so later results can be interpreted. Restore defaults unless a case says otherwise. | L5: QA plan S-01; NEW-001 | M5: Pass | N5: Passed, partly covered. Local Pass (partial) · Staging Pass (partial) · Production Not run local: not covered: the listing of the nine groups is the signed-tier TC-PRE-004 check ‖ not covered: restoring overridden rules to their defaults is admin-settings work kept to the local tier (tests/qa/local/access-admin.spec.ts) staging: not covered: restoring overridden rules to their defaults is admin-settings work kept to the local tier (tests/qa/local/access-admin.spec.ts) | P5: 2026-10-24 17:12
A6: TC-PRE-005 | B6: Preflight & smoke | C6: INF | D6: Email (SMTP) is configured on test | E6: Positive | F6: P0 | G6: Guest | H6: UI | J6: 1. Open /signin | K6: The mobile/email sign-in form is shown. If a warning says codes cannot be sent, SMTP is missing: mark every OTP and email-notification case Blocked. | L6: Login-profile DEPLOY_AND_TEST; QA plan section 0 | M6: Pass | N6: Passed, partly covered. Local Pass (partial) · Staging Pass (partial) · Production Not run local: not covered: a code actually reaching a mailbox is the local-tier check (local mail catcher) staging: not covered: a code actually reaching a mailbox is the local-tier check (local mail catcher) | P6: 2026-10-24 20:55
A7: TC-PRE-006 | B7: Preflight & smoke | C7: INF | D7: Cron jobs are running on test | E7: Positive | F7: P0 | G7: Admin | H7: UI+API | I7: CRON_SECRET supplied by the owner, or cron scheduled on the host | J7: 1. GET /api/cron/daily-orders with the bearer token (health probe) 2. Mark an order READY with no riders online and watch the attempt counter for 2-3 minutes | K7: Health probe returns 200 and generates nothing. The 'Looking for a rider - attempt N' counter rises about once a minute, proving delivery-dispatch cron runs. If it never rises, mark cron-dependent cases Blocked. | L7: Test plan section 5.2; QA plan section 0 | M7: Pass | N7: Passed, partly covered. Local Pass (partial) · Staging Not run (rule) · Production Not run local: not covered: the local server has no scheduler, so the test calls the dispatch cron as the host's scheduler would; whether the host schedules it every minute is checked on the test site (the exceptions page warns 'dispatch looks stalled') staging: not run on staging: needs the server's database (local run only) | P7: 2026-10-24 17:05
A8: TC-PRE-007 | B8: Preflight & smoke | C8: INF | D8: Required test accounts exist and can sign in | E8: Positive | F8: P0 | G8: All | H8: UI | I8: See 'Test data' sheet | J8: 1. Sign in as each account in turn (the owner enters credentials / codes) 2. Check the header role switcher and landing page for each | K8: ADMIN, OPERATOR, 2 SHOP_OWNERs, 2 CUSTOMERs, 1 approved online rider, 1 verified society admin all sign in and land on the right portal. | L8: QA plan section 0 | M8: Pass | N8: Passed, partly covered. Local Pass (partial) · Staging Blocked · Production Not run local: not covered: one seeded account signs in for real (each code request counts against the hourly limit); every account's session and portal is the signed-tier TC-PRE-007 check ‖ not covered: sessions are the target's own (minted locally, saved sign-ins on the test site); a real emailed-code sign-in is TC-PRE-005/TC-PRE-007 in tests/qa/local/access-platform.spec.ts staging: needs a SHOP_OWNER test account "shopB" | P8: 2026-10-24 17:42
A9: TC-PRE-008 | B9: Preflight & smoke | C9: INF | D9: Seed data is sufficient | E9: Positive | F9: P0 | G9: Admin | H9: UI | J9: 1. Confirm: Shop A approved, delivering, pinned location, stock >= 20 on 3+ products, one packaged product with an MRP; Shop B approved in the same PIN selling at least one of the same master products at a different price; Customer 1 has an address with coordinates inside Shop A's radius and wallet >= Rs 2,000 One loose product (sold by weight) in the master. Category X with at least 5 master products: one with no catalogue price, one loose, one already listed by Shop A. Shop C approved with no products. | K9: All present. Create whatever is missing before starting and note it in the run log. | L9: QA plan section 0; Updated 3-Oct | M9: Fail | N9: Local Fail · Staging Blocked · Production Not run local: shop C has no products | expect(received).toBe(expected) // Object.is equality | Expected: 0 | Received: 10 staging: needs shop B in this site's test data | P9: 2026-10-24 17:12
A10: TC-PRE-009 | B10: Preflight & smoke | C10: INF, GS-071 | D10: Production is not touched by this run | E10: Security | F10: P0 | G10: All | H10: UI | J10: 1. Before every write action confirm the address bar host is test.gokesari.com | K10: No order, payment, suspension, settings change or registration is made on gokesari.com. Production checks in this suite are read-only smoke checks only. | L10: Test plan section 6 | M10: Pass | N10: Passed, partly covered. Local Pass (partial) · Staging Pass (partial) · Production Pass (partial) local: not covered: proves the suite cannot order, pay, suspend, change settings or register on gokesari.com; a person's manual discipline on production is outside automation ‖ not covered: proves the suite's guard; a manual run's discipline is outside automation staging: not covered: proves the suite's guard; a manual run's discipline is outside automation production: not covered: proves the suite's guard; a manual run's discipline is outside automation | P10: 2026-10-29 13:58
A11: TC-PRE-010 | B11: Preflight & smoke | C11: INF | D11: Production read-only smoke | E11: Regression | F11: P1 | G11: Guest | H11: UI | I11: Run last | J11: 1. Open https://gokesari.com/ , /shops, /search?q=milk, /signin, /legal/terms | K11: Pages load without errors. Do not sign in, order or submit any form on production. | L11: Deployment plan | M11: Pass | N11: Passed, partly covered. Local Pass (partial) · Staging Pass (partial) · Production Pass (partial) local: not covered: proves the suite cannot order, pay, suspend, change settings or register on gokesari.com; a person's manual discipline on production is outside automation ‖ not covered: 'Add to cart / subscribe prompts sign-in' is checked in TC-RBAC-001 add-to-cart below staging: not covered: 'Add to cart / subscribe prompts sign-in' is checked in TC-RBAC-001 add-to-cart below production: not covered: 'Add to cart / subscribe prompts sign-in' is checked in TC-RBAC-001 add-to-cart below | P11: 2026-10-29 14:00
A12: TC-PRE-011 | B12: Preflight & smoke | C12: INF, NEW-008, NEW-009, NEW-010 | D12: The 3-Oct requirements are deployed on test | E12: Positive | F12: P0 | G12: Shop | H12: UI | I12: Signed in as SHOP_OWNER A | J12: 1. Open a loose product on /shop/prices and check whether a price is pre-filled 2. Open the shop category screen and check whether the owner can add a product category 3. Open a packaged listing and check whether the MRP can be edited by the owner | K12: Record for each of NEW-008, NEW-009 and NEW-010 whether the behaviour is present. Any that is missing makes its cases below Blocked (not Fail) until the build is deployed. | L12: New requirements 3-Oct | M12: Pass | N12: Passed, partly covered. Local Pass (partial) · Staging Pass (partial) · Production Not run local: not covered: record-only (the case decides Blocked vs run for later modules); src/server/authz/permissions.ts documents the owner may dispute an MRP but never write it (§13) staging: not covered: record-only (the case decides Blocked vs run for later modules); src/server/authz/permissions.ts documents the owner may dispute an MRP but never write it (§13) | P12: 2026-10-24 17:12
A13: TC-PRE-012 | B13: Preflight & smoke | C13: INF | D13: The open features treated as completed are deployed on test | E13: Positive | F13: P0 | G13: Admin | H13: UI | I13: Signed in as ADMIN | J13: 1. Check on test for: SMS code at sign-in, SMS / WhatsApp / push channels, online payment at checkout, coupon field, scheduled slots, master order reference, shop KYC document upload, rider profile edit, image moderation queue, customer referral, home comparison widgets, shop-page offers, tax invoice, photo proof of delivery | K13: Record which are present. The 3-Oct open-features list shows these as not yet built; any that is missing makes its cases Blocked (not Fail) until deployed. | L13: Open features 3-Oct, treated as completed 4-Oct | M13: Pass | N13: Passed, partly covered. Local Pass (partial) · Staging Pass (partial) · Production Not run local: not covered: record-only: presence of each screen/API and the switch of its business rule; the features' own cases test their behaviour staging: not covered: record-only: presence of each screen/API and the switch of its business rule; the features' own cases test their behaviour | P13: 2026-10-24 17:13
A14: TC-AUTH-001 | B14: Login, onboarding & profile | C14: GS-001 | D14: New user signs up with an unused mobile number | E14: Positive | F14: P0 | G14: Guest | H14: UI | I14: Unused 10-digit mobile and unused email whose inbox can be read | J14: 1. Open /signin 2. Enter the mobile 3. Enter the email when asked 4. Enter the 6-digit code from the email | K14: Step 2 says the number is not registered yet and asks for an email. Message shows the masked email (ab***@...). Email subject is 'NNNNNN is your Gokesari sign-in code'. After the code, 'Tell us about you' opens with mobile pre-filled and email read-only. | L14: Login-profile checklist: New user via mobile | M14: Pass | N14: Passed, partly covered. Local Pass (partial) · Staging Not run (rule) · Production Not run local: not covered: step 2 no longer says 'not registered yet': the reply is the same for every number (expected result superseded by docs/login-profile/DEPLOY_AND_TEST.md 'New user via mobile' and src/components/otp-login-form.tsx) — the sign-up starts from 'Sign up with your email' staging: not run on staging: needs the server's database (local run only) | O14: D-99 | P14: 2026-10-24 17:05
A15: TC-AUTH-002 | B15: Login, onboarding & profile | C15: GS-001 | D15: First-time profile: details then address with geo-tag | E15: Positive | F15: P0 | G15: Customer | H15: UI | I15: Continue from previous case | J15: 1. Enter name and gender, Save 2. On 'Delivery address' tap 'Use my current location' (drag the pin if Maps is configured) 3. Fill the address fields, Save | K15: Lands on home. /profile shows name, gender, mobile, email and the default address with 'Geo-tagged at ...'. A wallet exists with balance 0. | L15: Login-profile checklist | M15: Pass | N15: Passed, partly covered. Local Pass (partial) · Staging Not run (rule) · Production Not run local: not covered: dragging the map pin needs a Google Maps key (not set locally): 'Use my current location' geo-tags the address staging: not run on staging: needs the server's database (local run only) | P15: 2026-10-24 17:05
A16: TC-AUTH-003 | B16: Login, onboarding & profile | C16: GS-001 | D16: Returning user signs in with registered mobile | E16: Positive | F16: P0 | G16: Guest | H16: UI | I16: Account from the previous cases | J16: 1. Sign out 2. Enter the same mobile 3. Enter the code | K16: Code goes straight to the account's email, shown masked. After the code, home opens with no onboarding form. | L16: Login-profile checklist; QA A-02..A-04 | M16: Pass | N16: Passed, partly covered. Local Pass (partial) · Staging Not run (rule) · Production Not run local: not covered: the account email is no longer shown masked for a mobile sign-in (expected result superseded by docs/login-profile/DEPLOY_AND_TEST.md 'Returning user via mobile': no address shown) staging: not run on staging: needs the server's database (local run only) | P16: 2026-10-24 17:05
A17: TC-AUTH-004 | B17: Login, onboarding & profile | C17: GS-001 | D17: New user signs up with email only | E17: Positive | F17: P0 | G17: Guest | H17: UI | I17: Unused email | J17: 1. Enter the email on /signin 2. Enter the code 3. Save details without a mobile 4. On the address step choose 'Fill in later' | K17: Account and wallet are created. Details form shows an empty mobile field. Home opens after 'Fill in later'. | L17: Login-profile checklist: New user via email | M17: Pass | N17: Local Pass · Staging Not run (rule) · Production Not run local: qa-auth-email-signup-mvmliqqd-89411c@test.local: account + wallet, details form with empty mobile, saved without a mobile, 'Fill in later' → home staging: not run on staging: needs the server's database (local run only) | P17: 2026-10-24 17:05
A18: TC-AUTH-005 | B18: Login, onboarding & profile | C18: GS-001 | D18: 'Add your mobile number' prompt for accounts without a mobile | E18: Positive | F18: P1 | G18: Customer | H18: UI | I18: Email-only account with details saved | J18: 1. Sign out and in again with the email 2. Click 'Not now' 3. Sign out and in again 4. Add a valid number in the popup 5. Sign out and in again | K18: Popup appears after each sign-in until a number is added. 'Not now' closes it. After adding a valid number it never appears again. | L18: Login-profile checklist | M18: Pass | N18: Passed, partly covered. Local Pass (partial) · Staging Not run (rule) · Production Not run local: not covered: the minute between sign-ins is simulated by ageing the codes staging: not run on staging: needs the server's database (local run only) | P18: 2026-10-24 17:05
A19: TC-AUTH-006 | B19: Login, onboarding & profile | C19: GS-001 | D19: Existing pre-release account is prompted once and keeps its data | E19: Regression | F19: P0 | G19: Customer | H19: UI | I19: An account created before migration 0037 with wallet balance and orders | J19: 1. Sign in (code, magic link or Google) | K19: Details form appears. Wallet balance and order history are unchanged. | L19: Login-profile checklist: Existing email-only user | M19: Pass | N19: Passed, partly covered. Local Pass (partial) · Staging Not run (rule) · Production Not run local: not covered: signed in by emailed code; the magic link is TC-AUTH-009, Google needs a Google account (TC-AUTH-008) staging: not run on staging: needs the server's database (local run only) | P19: 2026-10-24 17:05
A20: TC-AUTH-007 | B20: Login, onboarding & profile | C20: GS-001 | D20: Skip onboarding, then be asked at checkout | E20: Positive | F20: P0 | G20: Customer | H20: UI | I20: Brand-new account | J20: 1. Choose 'Fill in later' on step 1 2. Top up the wallet 3. Add an item from a delivering shop and open the cart 4. Add mobile and address 5. Place the order 6. Before saving details, sign out and in again (separate run) | K20: Home and wallet work after skipping. Cart shows 'Add your mobile number...' and 'Add a delivery address...' instead of the pay button. After adding both the pay button appears and the order carries the address. Unsaved profile shows the details form again at next sign-in. | L20: Login-profile checklist: Skip and fill in later | M20: Pass | N20: Passed, partly covered. Local Pass (partial) · Staging Not run (rule) · Production Not run local: not covered: the wallet top-up is settled in the database (a gateway payment is not available on a local production build); top-ups are covered by the wallet specs staging: not run on staging: needs the server's database (local run only) | P20: 2026-10-24 17:05
A21: TC-AUTH-008 | B21: Login, onboarding & profile | C21: GS-001 | D21: Google sign-in still works | E21: Regression | F21: P0 | G21: Guest | H21: UI | I21: A Google account | J21: 1. On /signin choose Google and complete the Google flow | K21: Signed in; session persists across page loads; wallet exists. | L21: QA plan section 12; Regression AUTH-01 | M21: Blocked | N21: Manual (not automatable): Local Manual · Staging Not run (rule) · Production Not run local: not automated: needs a Google account and Google OAuth keys (AUTH_GOOGLE_ID / AUTH_GOOGLE_SECRET are not set on the local server, whose sign-in page says 'Google sign-in is not configured'); run by hand on test.gokesari.com staging: not run on staging: needs the server's database (local run only) | P21: 2026-10-24 17:05
A22: TC-AUTH-009 | B22: Login, onboarding & profile | C22: GS-001 | D22: Email magic-link sign-in still works | E22: Regression | F22: P1 | G22: Guest | H22: UI | I22: SMTP configured | J22: 1. Request a sign-in link by email 2. Open the link | K22: Signed in. Link cannot be reused after sign-out. | L22: Dev log Wave 1; QA plan section 12 | M22: Pass | N22: Local Pass · Staging Not run (rule) · Production Not run local: link mailed and signed in; after signing out the same link → /signin?error=Verification, not signed in staging: not run on staging: needs the server's database (local run only) | P22: 2026-10-24 17:05
A23: TC-AUTH-010 | B23: Login, onboarding & profile | C23: GS-001 | D23: Mobile login channel step offers SMS and email | E23: Positive | F23: P2 | G23: Guest | H23: UI | J23: 1. Enter a registered mobile on /signin and look at the OTP destination step | K23: Email and SMS are both selectable. Choosing SMS sends the code by SMS (see the SMS cases added 4-Oct). | L23: QA A-02; Updated 4-Oct (feature treated as completed) | M23: Pass | N23: Passed, partly covered. Local Pass (partial) · Staging Not run (rule) · Production Not run local: not covered: SMS codes are a Phase 2 stub with no vendor (src/server/otp/providers.ts; docs/decision-log.md D-A02, D-F08), so no SMS option is offered and the SMS half needs a vendor and a handset staging: not run on staging: needs the server's database (local run only) | P23: 2026-10-24 17:05
A24: TC-AUTH-011 | B24: Login, onboarding & profile | C24: GS-001 | D24: No account enumeration on unregistered number | E24: Security | F24: P0 | G24: Guest | H24: UI+API | J24: 1. POST /api/otp/request for a registered number and for an unregistered one 2. Compare status, body and timing | K24: Flow never reveals whether another person's number or email has an account beyond what the designed 'not registered - enter your email' step shows to the person typing it; error and throttle responses are identical for known and unknown values. | L24: QA A-05 | M24: Pass | N24: Passed, partly covered. Local Pass (partial) · Staging Not run (rule) · Production Not run local: not covered: the designed 'Sign up with your email' link shows for every number (no 'not registered' message at all) staging: not run on staging: needs the server's database (local run only) | P24: 2026-10-24 17:05
A25: TC-AUTH-012 | B25: Login, onboarding & profile | C25: GS-001 | D25: Wrong code five times locks the code | E25: Negative | F25: P0 | G25: Guest | H25: UI | I25: Default otp rule (5 attempts) | J25: 1. Request a code 2. Enter a wrong code 5 times 3. Enter the correct code | K25: Each failure: 'That code is wrong or has expired...'. After 5, the right code is refused ('Too many wrong attempts'); a new code must be requested. | L25: QA A-06; Login-profile checklist | M25: Pass | N25: Local Pass · Staging Not run (rule) · Production Not run local: 5 × 'That code is wrong or has expired…'; the right code then → 'Too many wrong attempts. Request a new code.'; not signed in staging: not run on staging: needs the server's database (local run only) | P25: 2026-10-24 17:05
A26: TC-AUTH-013 | B26: Login, onboarding & profile | C26: GS-001 | D26: Expired code is refused | E26: Negative | F26: P1 | G26: Guest | H26: UI | I26: Default expiry 10 min (or set otp expiry to 1 min) | J26: 1. Request a code 2. Wait past expiry 3. Enter it | K26: Refused with the generic wrong/expired message. | L26: QA A-07 | M26: Pass | N26: Passed, partly covered. Local Pass (partial) · Staging Not run (rule) · Production Not run local: not covered: default expiry is now 5 minutes, not 10 (expected result superseded by docs/decision-log.md D-A01); the wait is simulated by moving the code's expiry into the past staging: not run on staging: needs the server's database (local run only) | P26: 2026-10-24 17:05
A27: TC-AUTH-014 | B27: Login, onboarding & profile | C27: GS-001 | D27: Older code is superseded by a newer one | E27: Negative | F27: P1 | G27: Guest | H27: UI | J27: 1. Request a code, wait 60 s, request another 2. Enter the first 3. Enter the second | K27: First refused, second works. | L27: QA A-08 | M27: Pass | N27: Passed, partly covered. Local Pass (partial) · Staging Not run (rule) · Production Not run local: not covered: the 60 s wait between the two codes is simulated by ageing the first code staging: not run on staging: needs the server's database (local run only) | P27: 2026-10-24 17:05
A28: TC-AUTH-015 | B28: Login, onboarding & profile | C28: GS-001 | D28: Used code cannot be replayed | E28: Security | F28: P0 | G28: Guest | H28: UI | J28: 1. Sign in with a code 2. Sign out 3. Try the same code again | K28: Refused. | L28: QA A-11 | M28: Pass | N28: Local Pass · Staging Not run (rule) · Production Not run local: signed in with 315641, signed out; the same code → "That code is wrong or has expired…"; no session staging: not run on staging: needs the server's database (local run only) | P28: 2026-10-24 17:05
A29: TC-AUTH-016 | B29: Login, onboarding & profile | C29: GS-001 | D29: Resend cooldown | E29: Boundary | F29: P1 | G29: Guest | H29: UI | I29: Default 60 s | J29: 1. Request a code 2. Click Resend immediately 3. Wait for the countdown, click Resend | K29: Resend is disabled with a countdown for 60 seconds; an immediate API call is refused with 'wait N seconds'. After the cooldown a new code arrives. | L29: QA A-09 | M29: Pass | N29: Local Pass · Staging Not run (rule) · Production Not run local: Resend disabled with a countdown; API at once → 429 "Please wait 60 seconds before requesting another code."; after 60 s Resend sent a new code (586989 → 652526) that signed in staging: not run on staging: needs the server's database (local run only) | P29: 2026-10-24 17:05
A30: TC-AUTH-017 | B30: Login, onboarding & profile | C30: GS-001 | D30: Hourly code limit per email / number | E30: Boundary | F30: P1 | G30: Guest | H30: UI+API | I30: Default 5 per hour | J30: 1. Request codes repeatedly for the same identifier (respecting cooldown) | K30: The 6th request is refused ('Too many code requests'). Unknown identifiers are throttled the same way. | L30: QA A-10 | M30: Pass | N30: Passed, partly covered. Local Pass (partial) · Staging Not run (rule) · Production Not run local: not covered: the 60 s between requests is simulated by ageing each code staging: not run on staging: needs the server's database (local run only) | P30: 2026-10-24 17:05
A31: TC-AUTH-018 | B31: Login, onboarding & profile | C31: GS-001 | D31: Per-IP request limit | E31: Boundary | F31: P2 | G31: Guest | H31: API | I31: Default 20 per IP per hour | J31: 1. Send more than 20 OTP requests for different identifiers from one browser | K31: Requests after the limit return 429 RATE_LIMITED with retryAfterSeconds. | L31: Login-profile rules; QA section 13 | M31: Pass | N31: Local Pass · Staging Not run (rule) · Production Not run local: 20 × 200 from 10.160.7.170; 21st → 429 RATE_LIMITED, retryAfterSeconds 3599; another IP still 200 staging: not run on staging: needs the server's database (local run only) | P31: 2026-10-24 17:05
A32: TC-AUTH-019 | B32: Login, onboarding & profile | C32: GS-001 | D32: Invalid mobile / email input | E32: Negative | F32: P1 | G32: Guest | H32: UI | J32: 1. Enter each of: 12345, 5876543210, abcdefghij, +91 5xxxxxxxxx, abc@, empty | K32: Clear field-level validation message each time. No email is sent. Only Indian mobiles (10 digits starting 6-9) are accepted. | L32: QA A-12; Login-profile checklist | M32: Pass | N32: Passed, partly covered. Local Pass (partial) · Staging Pass (partial) · Production Pass (partial) local: not covered: blank and over-254-character emails, and how a valid number is stored, run on the local tier ‖ not covered: a number typed with spaces is accepted and normalised, by design (src/lib/contact.ts: accepts "98765 43210") staging: not covered: blank and over-254-character emails, and how a valid number is stored, run on the local tier production: not covered: blank and over-254-character emails, and how a valid number is stored, run on the local tier | P32: 2026-10-29 14:00
A33: TC-AUTH-020 | B33: Login, onboarding & profile | C33: GS-001 | D33: Mobile already linked to another account | E33: Negative | F33: P0 | G33: Customer | H33: UI | I33: Two accounts; number linked to account 1 | J33: 1. On account 2 add the same number from profile, from the popup and during onboarding | K33: Each refuses: 'This mobile number is already linked to another account...'. | L33: QA A-13; Login-profile checklist | M33: Pass | N33: Passed, partly covered. Local Pass (partial) · Staging Blocked · Production Not run local: not covered: the onboarding-form half (first-time details) is in tests/qa/local/auth-profile.spec.ts; TC-AUTH-054: a free number is saved without an SMS code by design (numbers are not SMS-verified — docs/login-profile/DEPLOY_AND_TEST.md), so only a number already linked elsewhere is protected ‖ not covered: the My Profile and popup halves are in tests/qa/signed-in/auth-profile.spec.ts staging: customer 2 must have no mobile for the popup half | P33: 2026-10-24 18:06
A34: TC-AUTH-021 | B34: Login, onboarding & profile | C34: GS-001 | D34: Unregistered mobile + email that belongs to a different mobile | E34: Negative | F34: P1 | G34: Guest | H34: UI | I34: Account X has email E and mobile M1 | J34: 1. On /signin enter new mobile M2 2. Enter email E | K34: 'This email is already registered with a different mobile number...'. No account is changed. | L34: Login-profile checklist | M34: Pass | N34: Passed, partly covered. Local Pass (partial) · Staging Not run (rule) · Production Not run local: not covered: no 'already registered with a different mobile' refusal: the code goes to the email and signs in to its account (expected result superseded by docs/login-profile/DEPLOY_AND_TEST.md 'Duplicate mobile or email' and the comment in src/server/otp/service.ts requestLoginOtp — refusing would reveal which numbers have accounts) staging: not run on staging: needs the server's database (local run only) | P34: 2026-10-24 17:05
A35: TC-AUTH-022 | B35: Login, onboarding & profile | C35: GS-001, RBAC-013 | D35: Admin releases a claimed mobile number | E35: Positive | F35: P1 | G35: Admin | H35: UI | I35: Number M claimed by account 1 | J35: 1. Admin console -> 'Release a mobile number' -> enter M 2. On account 2 add M | K35: Release succeeds and is audited. Account 2 can now add M. Account 1 no longer shows it. | L35: Login-profile DEPLOY_AND_TEST | M35: Pass | N35: Local Pass · Staging Not run (rule) · Production Not run local: released +916210570509 from the console (audited by the admin); holder's profile shows no mobile; the claimant added it staging: not run on staging: needs the server's database (local run only) | P35: 2026-10-24 17:05
A36: TC-AUTH-023 | B36: Login, onboarding & profile | C36: GS-001 | D36: Edit name and gender on My Profile | E36: Positive | F36: P1 | G36: Customer | H36: UI | J36: 1. Open /profile 2. Change name and gender 3. Save details | K36: 'Saved' confirmation. Header initial updates. Values persist after reload. | L36: Login-profile checklist | M36: Pass | N36: Local Pass · Staging Pass · Production Not run local: name → "Zara QA mvmn5pup", gender → Male; 'Saved.'; header initial Z; both kept after reload ‖ [phone] name → "Zara QA mvml9j40", gender → Male; 'Saved.'; header initial Z; both kept after reload staging: name → "Zara QA mvmphu8y", gender → Male; 'Saved.'; header initial Z; both kept after reload ‖ [phone] name → "Zara QA mvmvdlwt", gender → Male; 'Saved.'; header initial Z; both kept after reload | P36: 2026-10-24 20:57
A37: TC-AUTH-024 | B37: Login, onboarding & profile | C37: GS-001 | D37: Change and remove mobile on My Profile | E37: Positive | F37: P1 | G37: Customer | H37: UI | J37: 1. Change mobile to a new valid number 2. Remove it 3. Open the cart with a delivery item | K37: New number shows; after removal it shows 'Not added' and the cart asks for a mobile again. A 'Mobile number changed' security notification is sent. | L37: Login-profile checklist; QA A-01, F-09 | M37: Fail | N37: Local Fail · Staging Pass (partial) · Production Not run local: add a delivery item — HTTP 409: This product is currently unavailable online. | expect(received).toContain(expected) // indexOf | Expected value: 409 | Received array: [200, 201] staging: not covered: the notice is checked in-app; its email copy follows the customer's notification settings (notification specs) | P37: 2026-10-24 18:06
A38: TC-AUTH-025 | B38: Login, onboarding & profile | C38: GS-001 | D38: Change email with verification on the new address | E38: Positive | F38: P0 | G38: Customer | H38: UI | I38: Inbox access for old and new address | J38: 1. Start a change of email 2. Enter a wrong code 3. Enter the right code 4. Sign out and sign in with the new email | K38: Code goes to the NEW address. Wrong code: error, email unchanged. Right code: email updated and the OLD address receives a 'was changed' email. New email signs in. | L38: Login-profile checklist | M38: Pass | N38: Local Pass · Staging Not run (rule) · Production Not run local: code to qa***@ ("NNNNNN is your Gokesari email confirmation code"); wrong code → error, email kept; right code → changed, old address mailed "was changed", audited; the new email signs in staging: not run on staging: needs the server's database (local run only) | P38: 2026-10-24 17:05
A39: TC-AUTH-026 | B39: Login, onboarding & profile | C39: GS-001 | D39: Change email to one used by another account | E39: Negative | F39: P1 | G39: Customer | H39: UI | J39: 1. Enter another account's email as the new email | K39: 'This email address is already used by another account.' | L39: Login-profile checklist | M39: Pass | N39: Local Pass · Staging Pass · Production Not run local: page and API (409) refuse qa***@test.local; email unchanged staging: page and API (409) refuse sa***@gmail.com; email unchanged | P39: 2026-10-24 18:06
A40: TC-AUTH-027 | B40: Login, onboarding & profile | C40: GS-001 | D40: Suspended account cannot sign in | E40: Security | F40: P0 | G40: Guest | H40: UI | I40: Account suspended by admin | J40: 1. Try mobile, email-code and Google sign-in | K40: All refused; /signin?error=AccessDenied explains the account is suspended or closed with a link to the grievance form. No session is created. | L40: QA A-14; Dev log Phase 4.5 | M40: Pass | N40: Passed, partly covered. Local Pass (partial) · Staging Not run (rule) · Production Not run local: not covered: Google sign-in is not configured on the local server (needs a Google account and OAuth keys); the emailed link is the next check staging: not run on staging: needs the server's database (local run only) | O40: D-19 | P40: 2026-10-24 17:05
A41: TC-AUTH-028 | B41: Login, onboarding & profile | C41: GS-001, GS-067 | D41: OTP events are audited and codes are never exposed | E41: Security | F41: P0 | G41: Admin | H41: UI+DB | J41: 1. Admin audit log: search 'auth.otp_' 2. Inspect network responses of /api/otp/request 3. (DB if available) select code_hash from login_otps | K41: Requested / verified / failed / blocked rows exist; numbers are masked; no code appears in any response, page or log. code_hash looks like salt:hex. | L41: QA A-16, A-17 | M41: Pass | N41: Passed, partly covered. Local Pass (partial) · Staging Not run (rule) · Production Not run local: not covered: the admin audit page lists the latest 100 events and has no search box; SMS text, sender and template need an SMS vendor (Phase 2 — TC-AUTH-052's SMS half) staging: not run on staging: needs the server's database (local run only) | P41: 2026-10-24 17:05
A42: TC-AUTH-029 | B42: Login, onboarding & profile | C42: NEW-001, GS-001 | D42: OTP limits follow /admin/settings | E42: Positive | F42: P1 | G42: Admin | H42: UI | J42: 1. Set otp: expiry 1, attempts 2, cooldown 5 2. Repeat the wrong-code, expiry and resend cases 3. Restore default | K42: New limits apply within about 15 s; Restore default reverts them. | L42: QA A-15 | M42: Pass | N42: Passed, partly covered. Local Pass (partial) · Staging Not run (rule) · Production Not run local: not covered: the rule is set through the admin settings API (PUT/DELETE /api/admin/settings, the endpoint the /admin/settings form uses); the 1-minute expiry is read from the stored code rather than waited out staging: not run on staging: needs the server's database (local run only) | P42: 2026-10-24 17:05
A43: TC-AUTH-030 | B43: Login, onboarding & profile | C43: GS-001 | D43: Sign out ends the session | E43: Security | F43: P1 | G43: Customer | H43: UI+API | J43: 1. Sign out 2. Use the back button to /wallet 3. GET /api/wallet | K43: Redirected to sign in; API returns 401 UNAUTHENTICATED. Further log out cases: TC-AUTH-032 to TC-AUTH-045. | L43: e2e acceptance: access control; Updated 3-Oct | M43: Pass | N43: Local Pass · Staging Not run (rule) · Production Not run local: after Sign out: Back → /signin; /wallet → /signin; API 401 UNAUTHENTICATED staging: not run on staging: needs the server's database (local run only) | P43: 2026-10-24 18:08
A44: TC-AUTH-031 | B44: Login, onboarding & profile | C44: GS-001 | D44: Session persists across pages and reloads | E44: Positive | F44: P2 | G44: Customer | H44: UI | J44: 1. Sign in 2. Visit /wallet, /orders, /profile 3. Reload each | K44: Stays signed in; no repeated prompts. | L44: Regression AUTH-03 | M44: Pass | N44: Local Pass · Staging Pass · Production Not run local: /wallet, /orders, /profile: stayed signed in through each reload ‖ [phone] /wallet, /orders, /profile: stayed signed in through each reload staging: /wallet, /orders, /profile: stayed signed in through each reload ‖ [phone] /wallet, /orders, /profile: stayed signed in through each reload | P44: 2026-10-24 20:58
A45: TC-AUTH-032 | B45: Login, onboarding & profile | C45: GS-001 | D45: Log out from the header menu in every role | E45: Positive | F45: P0 | G45: All | H45: UI | I45: One account per role signed in | J45: 1. As customer, shop owner, rider, society admin, operator and admin in turn: open the account menu and choose Sign out | K45: Each role is signed out and lands on the home or sign-in page. The header shows Sign in and no name, role switcher or portal links. | L45: Request 3-Oct: log out / log off coverage | M45: Pass | N45: Local Pass · Staging Not run (rule) · Production Not run local: customer (/, account-dropdown) → /; shop (/shop, seller-account-button) → /; rider (/delivery-partner, account-button) → /; society (/society, account-button) → /; ops (/admin, board-account) → /; admin (/admin, board-account) → / staging: not run on staging: needs the server's database (local run only) | P45: 2026-10-24 18:09
A46: TC-AUTH-033 | B46: Login, onboarding & profile | C46: GS-001, GS-002 | D46: Protected pages are closed after log out | E46: Security | F46: P0 | G46: All | H46: UI | I46: Just signed out | J46: 1. Open /orders, /wallet, /profile, /cart 2. Open /shop, /shop/inventory, /shop/prices 3. Open the rider, society, operator and admin portals 4. Use the browser Back button to a page viewed while signed in | K46: Every page redirects to sign in. Back shows no cached personal, order, wallet or shop data. | L46: Request 3-Oct: log out / log off coverage; extends TC-AUTH-030 | M46: Fail | N46: Local Pass (partial) · Staging Pass · Production Fail local: not covered: the signed-out guest half of TC-AUTH-033 (every page) is in tests/qa/guest/access.spec.ts staging: 194 signed-in pages and account APIs not closed to a guest: all refused production: 7 of 194 signed-in pages and account APIs not closed to a guest: | /admin/dealers → 404 | /admin/dealers/analytics → 404 | /admin/dealers/claims → 404 | O46: E-12 | P46: 2026-10-29 14:04
A47: TC-AUTH-034 | B47: Login, onboarding & profile | C47: GS-001, GS-071 | D47: Old session cannot be replayed after log out | E47: Security | F47: P0 | G47: Customer | H47: API | I47: Session cookie copied before signing out | J47: 1. Sign out 2. Send GET /api/wallet and POST /api/cart with the copied cookie | K47: 401 UNAUTHENTICATED on both. The session is ended on the server, not only removed from the browser. | L47: Request 3-Oct: log out / log off coverage | M47: Pass | N47: Local Pass · Staging Not run (rule) · Production Not run local: both refused with 401 staging: not run on staging: needs the server's database (local run only) | O47: D-17, D-99 | P47: 2026-10-24 18:09
A48: TC-AUTH-035 | B48: Login, onboarding & profile | C48: GS-001 | D48: Log out in one tab ends the other tabs | E48: Positive | F48: P1 | G48: Customer | H48: UI | I48: Same account open in two tabs | J48: 1. Sign out in tab 1 2. In tab 2 click a link and submit a form | K48: Tab 2 is sent to sign in on its next action. No write goes through. | L48: Request 3-Oct: log out / log off coverage | M48: Pass | N48: Local Pass · Staging Not run (rule) · Production Not run local: tab 2: Save details refused (name unchanged), next link → /signin staging: not run on staging: needs the server's database (local run only) | P48: 2026-10-24 18:09
A49: TC-AUTH-036 | B49: Login, onboarding & profile | C49: GS-001 | D49: Log out on one device and the session on another device | E49: Positive | F49: P2 | G49: Customer | H49: UI | I49: Same account signed in on two browser profiles | J49: 1. Sign out on device 1 2. Reload on device 2 | K49: Record the behaviour: device 2 either stays signed in (per-device sessions) or is signed out. Whichever it is must be the same every time. | L49: Request 3-Oct: log out / log off coverage | M49: Pass | N49: Local Pass · Staging Not run (rule) · Production Not run local: device 2 after device 1 signs out: still signed in, still signed in (per-device sessions) staging: not run on staging: needs the server's database (local run only) | P49: 2026-10-24 18:09
A50: TC-AUTH-037 | B50: Login, onboarding & profile | C50: GS-001, GS-024 | D50: Cart is kept for the user and hidden from the next user | E50: Positive | F50: P1 | G50: Customer | H50: UI | I50: Customer 1 has two items in the cart | J50: 1. Customer 1 signs out 2. Customer 2 signs in on the same browser and opens the cart 3. Customer 2 signs out; Customer 1 signs in again | K50: Customer 2 sees only an own cart, never Customer 1 items. Customer 1 finds the two items again. | L50: Request 3-Oct: log out / log off coverage | M50: Fail | N50: Local Fail · Staging Not run (rule) · Production Not run local: item 1 — HTTP 409: This product is currently unavailable online. | expect(received).toContain(expected) // indexOf | Expected value: 409 | Received array: [200, 201] staging: not run on staging: needs the server's database (local run only) | P50: 2026-10-24 18:09
A51: TC-AUTH-038 | B51: Login, onboarding & profile | C51: GS-001, GS-071 | D51: Next user on a shared phone sees nothing of the previous user | E51: Security | F51: P0 | G51: All | H51: UI | I51: Shop owner A just signed out on the browser | J51: 1. Customer 2 signs in on the same browser 2. Check header name, delivery location, saved addresses, notifications, wallet and role switcher 3. Open /shop | K51: Everything shown belongs to Customer 2. No shop portal, role or location carried over from owner A. /shop is refused. | L51: Request 3-Oct: log out / log off coverage | M51: Pass | N51: Passed, partly covered. Local Pass (partial) · Staging Not run (rule) · Production Not run local: not covered: the second person signs in with their own session cookie on the same browser (no emailed code in the signed-in tier) staging: not run on staging: needs the server's database (local run only) | O51: D-21 | P51: 2026-10-24 18:09
A52: TC-AUTH-039 | B52: Login, onboarding & profile | C52: GS-001, NAV-001 | D52: Log out with unsaved changes on an edit screen | E52: Positive | F52: P2 | G52: Shop | H52: UI | I52: A price field changed but not saved | J52: 1. Choose Sign out | K52: A warning is shown before the changes are lost, or the user is signed out with the old value kept. Nothing half-saved. | L52: Request 3-Oct: log out / log off coverage; TC-UX-005 | M52: Pass | N52: Local Pass · Staging Not run (rule) · Production Not run local: edited the price of QA Butter 100 g mvmkyclr without saving, signed out without a warning; price still 5800 paise staging: not run on staging: needs the server's database (local run only) | P52: 2026-10-24 18:09
A53: TC-AUTH-040 | B53: Login, onboarding & profile | C53: GS-001, GS-038 | D53: Rider logs out while online | E53: Positive | F53: P1 | G53: Rider | H53: UI | I53: Rider 1 online with no active job | J53: 1. Sign out 2. Mark an order READY at Shop A 3. Sign in again as the rider | K53: Record the behaviour and confirm it with the owner: expected is that a logged-out rider is not offered jobs (set offline, or offers lapse). The rider must not be left online and unreachable. | L53: Request 3-Oct: log out / log off coverage | M53: Blocked | N53: Local Blocked · Staging Not run (rule) · Production Not run local: "QA Butter 100 g mvmkyclr" cannot be added to the cart — HTTP 409: This product is currently unavailable online. staging: not run on staging: needs the server's database (local run only) | O53: D-20 | P53: 2026-10-24 18:09
A54: TC-AUTH-041 | B54: Login, onboarding & profile | C54: GS-001, GS-003 | D54: Log out while acting in a second role | E54: Positive | F54: P2 | G54: Shop | H54: UI | I54: Multi-role user switched to the Shop role | J54: 1. Sign out 2. Sign in again | K54: Sign-in works. Record which role is active on return; it must be a role the user holds. | L54: Request 3-Oct: log out / log off coverage | M54: Pass | N54: Passed, partly covered. Local Pass (partial) · Staging Not run (rule) · Production Not run local: not covered: signing in again reuses the account's session (no emailed code in the signed-in tier) staging: not run on staging: needs the server's database (local run only) | P54: 2026-10-24 18:09
A55: TC-AUTH-042 | B55: Login, onboarding & profile | C55: GS-001, GS-071 | D55: Log out cannot be triggered by another site | E55: Security | F55: P1 | G55: Customer | H55: API | I55: Signed in | J55: 1. From a different origin send a plain GET and a POST without the CSRF token to the sign-out address | K55: The user stays signed in. Only the real Sign out action ends the session. | L55: Request 3-Oct: log out / log off coverage | M55: Pass | N55: Passed, partly covered. Local Pass (partial) · Staging Not run (rule) · Production Not run local: not covered: Next.js server actions (the menu's Sign out) are protected by Next's own origin check, not probed here staging: not run on staging: needs the server's database (local run only) | P55: 2026-10-24 18:09
A56: TC-AUTH-043 | B56: Login, onboarding & profile | C56: GS-001, NAV-001 | D56: Log out is reachable on a phone screen | E56: Positive | F56: P1 | G56: Customer | H56: UI | I56: Mobile viewport (360 px wide) | J56: 1. Open the menu 2. Choose Sign out | K56: Sign out is visible without horizontal scrolling and works. | L56: Request 3-Oct: log out / log off coverage | M56: Pass | N56: Local Pass · Staging Not run (rule) · Production Not run local: 360 px: menu → Sign out at x=12–298 px, no sideways scroll, signed out ‖ [phone] 360 px: menu → Sign out at x=12–298 px, no sideways scroll, signed out staging: not run on staging: needs the server's database (local run only) | P56: 2026-10-24 20:58
A57: TC-AUTH-044 | B57: Login, onboarding & profile | C57: GS-001 | D57: Automatic log off after the session lifetime | E57: Boundary | F57: P1 | G57: Customer | H57: UI | I57: Signed in; session lifetime known or shortened on test | J57: 1. Leave the browser idle past the session lifetime 2. Click a link 3. Sign in again | K57: Record the lifetime. After it passes the user is sent to sign in, then returned to the page asked for. No error page. | L57: Request 3-Oct: log out / log off coverage | M57: Fail | N57: Local Fail · Staging Not run (rule) · Production Not run local: signed in again; the sign-in page was /signin and after the code it went to /, not back to /wallet | expect(received).toBe(expected) // Object.is equality | Expected: "/wallet" | Received: "/" staging: not run on staging: needs the server's database (local run only) | O57: D-23 | P57: 2026-10-24 17:05
A58: TC-AUTH-045 | B58: Login, onboarding & profile | C58: GS-001, GS-067 | D58: Log out and log in are recorded; repeated log out is harmless | E58: Positive | F58: P2 | G58: Admin | H58: UI | J58: 1. A customer signs out and in again 2. Double-click Sign out; open the sign-out address when already signed out 3. Admin opens the sign-in activity / audit view | K58: Sign-in and sign-out events appear with time and user. Repeated or duplicate sign-out shows the home page, never an error. | L58: Request 3-Oct: log out / log off coverage | M58: Pass | N58: Passed, partly covered. Local Pass (partial) · Staging Not run (rule) · Production Not run local: not covered: the sign-out address shows the Auth.js 'Sign out' confirmation page, not the home page; the recorded events are the next check ‖ not covered: read from the audit table the admin's audit view lists (/admin/console/audit-log) staging: not run on staging: needs the server's database (local run only) | O58: D-22 | P58: 2026-10-24 17:05
A59: TC-AUTH-046 | B59: Login, onboarding & profile | C59: GS-001 | D59: New mobile sign-up receives the code by SMS | E59: Positive | F59: P0 | G59: Guest | H59: UI | I59: Unused Indian mobile that can receive SMS | J59: 1. Enter the mobile on /signin 2. Choose SMS 3. Enter the code from the SMS | K59: SMS arrives within a minute with the code. Sign-in succeeds, onboarding opens and the mobile is marked verified. | L59: Open features 3-Oct, treated as completed 4-Oct | M59: Blocked | N59: Manual (not automatable): Local Manual · Staging Not run (rule) · Production Not run local: not automated: needs an SMS vendor in test mode and a real handset: SMS codes are a Phase 2 stub on this build (src/server/otp/providers.ts SmsOtpProvider; docs/decision-log.md D-A02, D-F08) and new mobiles sign up through email staging: not run on staging: needs the server's database (local run only) | P59: 2026-10-24 17:05
A60: TC-AUTH-047 | B60: Login, onboarding & profile | C60: GS-001 | D60: Returning user chooses SMS or email for the code | E60: Positive | F60: P0 | G60: Guest | H60: UI | I60: Account with mobile and email | J60: 1. Enter the mobile 2. Choose SMS and sign in 3. Sign out and repeat choosing email | K60: Both channels are selectable and work. The destination is shown masked. | L60: Open features 3-Oct, treated as completed 4-Oct | M60: Pass | N60: Passed, partly covered. Local Pass (partial) · Staging Not run (rule) · Production Not run local: not covered: SMS codes are a Phase 2 stub with no vendor (src/server/otp/providers.ts; docs/decision-log.md D-A02, D-F08), so no SMS option is offered and the SMS half needs a vendor and a handset staging: not run on staging: needs the server's database (local run only) | P60: 2026-10-24 17:05
A61: TC-AUTH-048 | B61: Login, onboarding & profile | C61: GS-001 | D61: Wrong, expired and superseded SMS codes | E61: Negative | F61: P0 | G61: Guest | H61: UI | J61: 1. Enter a wrong code 5 times 2. Request a new code and wait past its validity 3. Request two codes and enter the first | K61: Five wrong attempts lock the code. Expired and older codes are refused. Limits are the same as for email codes (/admin/settings). | L61: Open features 3-Oct, treated as completed 4-Oct | M61: Blocked | N61: Manual (not automatable): Local Manual · Staging Not run (rule) · Production Not run local: not automated: needs an SMS vendor and a handset to read SMS codes; the same rules for emailed codes are TC-AUTH-012/013/014/029 staging: not run on staging: needs the server's database (local run only) | P61: 2026-10-24 17:05
A62: TC-AUTH-049 | B62: Login, onboarding & profile | C62: GS-001 | D62: SMS resend cooldown and hourly limit | E62: Boundary | F62: P1 | G62: Guest | H62: UI+API | J62: 1. Tap Resend before the cooldown ends 2. Request codes until the hourly limit is passed | K62: Resend is disabled during the cooldown. Requests past the hourly limit are refused and no SMS is sent (no SMS cost run-up). | L62: Open features 3-Oct, treated as completed 4-Oct | M62: Blocked | N62: Manual (not automatable): Local Manual · Staging Not run (rule) · Production Not run local: not automated: needs an SMS vendor and a handset (no SMS cost can be observed without one); the same limits for emailed codes are TC-AUTH-016/017 staging: not run on staging: needs the server's database (local run only) | P62: 2026-10-24 17:05
A63: TC-AUTH-050 | B63: Login, onboarding & profile | C63: GS-001 | D63: No SMS to invalid numbers and no account enumeration | E63: Security | F63: P0 | G63: Guest | H63: UI+API | J63: 1. Enter 5876543210, a 9-digit number and a non-Indian number 2. Enter a valid number with no account and one with an account; compare responses | K63: No SMS is sent for invalid numbers. The responses for registered and unregistered numbers do not reveal which exists. | L63: Open features 3-Oct, treated as completed 4-Oct | M63: Pass | N63: Passed, partly covered. Local Pass (partial) · Staging Not run (rule) · Production Not run local: not covered: SMS itself is not sent by this build (SMS codes are a Phase 2 stub — src/server/otp/providers.ts, docs/decision-log.md D-A02/D-F08); a handset is needed to prove no SMS goes out staging: not run on staging: needs the server's database (local run only) | P63: 2026-10-24 17:05
A64: TC-AUTH-051 | B64: Login, onboarding & profile | C64: GS-001, GS-074 | D64: SMS provider failure during sign-in | E64: Negative | F64: P1 | G64: Guest | H64: UI | I64: SMS provider switched off or failing on test | J64: 1. Request a code by SMS | K64: The user is told the SMS could not be sent and is offered email. The failure is recorded; nothing claims an SMS was sent. | L64: Open features 3-Oct, treated as completed 4-Oct | M64: Pass | N64: Passed, partly covered. Local Pass (partial) · Staging Not run (rule) · Production Not run local: not covered: telling the person that the SMS failed is not done: a mobile request always gets the same reply so it cannot reveal which numbers have accounts (expected result superseded by src/server/otp/service.ts requestLoginOtp and docs/login-profile/DEPLOY_AND_TEST.md); the generic text still mentions SMS as a possible channel staging: not run on staging: needs the server's database (local run only) | P64: 2026-10-24 17:05
A65: TC-AUTH-052 | B65: Login, onboarding & profile | C65: GS-001, GS-071 | D65: SMS content and code secrecy | E65: Security | F65: P1 | G65: Admin | H65: UI+DB | J65: 1. Read the SMS text and sender 2. Check the audit log and stored records for the code | K65: SMS uses the registered sender and template and carries only the code and validity. The code is never visible in the audit log, API responses or stored in plain text. | L65: Open features 3-Oct, treated as completed 4-Oct | M65: Pass | N65: Passed, partly covered. Local Pass (partial) · Staging Not run (rule) · Production Not run local: not covered: the admin audit page lists the latest 100 events and has no search box; SMS text, sender and template need an SMS vendor (Phase 2 — TC-AUTH-052's SMS half) staging: not run on staging: needs the server's database (local run only) | P65: 2026-10-24 17:05
A66: TC-AUTH-053 | B66: Login, onboarding & profile | C66: GS-001 | D66: Mobile change is proven by an SMS code to the new number | E66: Positive | F66: P0 | G66: Customer | H66: UI | J66: 1. On My Profile enter a new mobile 2. Enter a wrong code, then the right one | K66: Code goes to the NEW number. Wrong code: mobile unchanged. Right code: mobile updated and marked verified. | L66: Open features 3-Oct, treated as completed 4-Oct | M66: Blocked | N66: Manual (not automatable): Local Manual · Staging Not run (rule) · Production Not run local: not automated: needs an SMS vendor and a handset; on this build a profile mobile is saved unverified by design (docs/login-profile/DEPLOY_AND_TEST.md: 'Numbers are not SMS-verified'; src/server/otp/service.ts linkPhone) and an admin can release a wrongly claimed number (TC-AUTH-022) staging: not run on staging: needs the server's database (local run only) | P66: 2026-10-24 17:05
A67: TC-AUTH-054 | B67: Login, onboarding & profile | C67: GS-001 | D67: A mobile cannot be taken over without its SMS code | E67: Security | F67: P0 | G67: Customer | H67: UI+API | I67: Mobile X belongs to another account | J67: 1. Try to add mobile X to this account 2. Send the change through the API without a code | K67: Refused both ways. The other account is unaffected. | L67: Open features 3-Oct, treated as completed 4-Oct | M67: Pass | N67: Passed, partly covered. Local Pass (partial) · Staging Blocked · Production Not run local: not covered: the onboarding-form half (first-time details) is in tests/qa/local/auth-profile.spec.ts; TC-AUTH-054: a free number is saved without an SMS code by design (numbers are not SMS-verified — docs/login-profile/DEPLOY_AND_TEST.md), so only a number already linked elsewhere is protected staging: customer 2 must have no mobile for the popup half | P67: 2026-10-24 18:06
A68: TC-RBAC-001 | B68: Roles & access control | C68: GS-002, RBAC-001 | D68: Guest can browse and search without signing in | E68: Positive | F68: P0 | G68: Guest | H68: UI | J68: 1. Open /, /shops, /search, a shop page and a product comparison page | K68: All readable. Add to cart / subscribe prompts sign-in. | L68: RBAC Matrix: Browse/search | M68: Pass | N68: Passed, partly covered. Local Pass (partial) · Staging Pass (partial) · Production Pass (partial) local: not covered: 'Add to cart / subscribe prompts sign-in' is checked in TC-RBAC-001 add-to-cart below ‖ not covered: browse/search and Add to cart are tests/qa/guest/storefront.spec.ts staging: not covered: 'Add to cart / subscribe prompts sign-in' is checked in TC-RBAC-001 add-to-cart below production: not covered: 'Add to cart / subscribe prompts sign-in' is checked in TC-RBAC-001 add-to-cart below | P68: 2026-10-29 14:00
A69: TC-RBAC-002 | B69: Roles & access control | C69: GS-002, GS-071 | D69: Guest is blocked from every signed-in area | E69: Security | F69: P0 | G69: Guest | H69: UI+API | J69: 1. Open /wallet, /orders, /cart, /profile, /subscriptions, /shop, /delivery-partner, /society, /admin, /operator 2. GET /api/wallet, /api/orders, /api/cart, /api/notifications | K69: Pages redirect to sign-in. APIs return 401. | L69: e2e acceptance; QA section 13 | M69: Fail | N69: Local Pass (partial) · Staging Pass · Production Fail local: not covered: the no-cookie sweep of every page and write API is tests/qa/guest/access.spec.ts; known D-01 routes answer 404/422 there staging: 194 signed-in pages and account APIs not closed to a guest: all refused ‖ 368 session-protected write endpoints not refusing a guest: all refused production: 7 of 194 signed-in pages and account APIs not closed to a guest: | /admin/dealers → 404 | /admin/dealers/analytics → 404 | /admin/dealers/claims → 404 ‖ 25 of 368 session-protected write endpoints not refusing a guest: | POST /api/admin/dealer-analytics → 404 NOT_FOUND | POST /api/admin/dealer-commission → 404 NOT_FOUND | POST /api/admin/dealer-disputes/[id] → 404 NOT_FOUND | O69: D-01, E-12 | P69: 2026-10-29 14:06
A70: TC-RBAC-003 | B70: Roles & access control | C70: GS-002 | D70: Customer cannot reach shop, rider, society, operator or admin portals | E70: Security | F70: P0 | G70: Customer | H70: UI+API | J70: 1. Open /admin and every /admin/* page from the preflight list, /operator, /shop/orders, /shop/finance, /shop/marketing, /shop/analytics, /delivery-partner, /gig/orders, /society/{id} 2. Call one write API from each area | K70: Each page redirects away (home or the apply/register page). APIs return 403 FORBIDDEN. | L70: e2e acceptance; RBAC Matrix | M70: Pass | N70: Passed, partly covered. Local Pass (partial) · Staging Pass (partial) · Production Not run local: not covered: pages only; the write APIs of each area are the next check ‖ not covered: an empty body and an id that exists nowhere; the refusal must come before validation or a lookup staging: not covered: pages only; the write APIs of each area are the next check ‖ not covered: an empty body and an id that exists nowhere; the refusal must come before validation or a lookup | O70: D-81 | P70: 2026-10-24 18:00
A71: TC-RBAC-004 | B71: Roles & access control | C71: GS-002, RBAC-004, RBAC-005 | D71: Shop owner limited to own shop | E71: Security | F71: P0 | G71: Shop | H71: UI+API | I71: Shop owner A; Shop B belongs to another owner | J71: 1. As A: open /shop pages 2. PATCH /api/shops/{B}, POST /api/shops/{B}/products, PATCH a shop-product of B, GET /api/shops/{B}/inventory, POST /api/excel-uploads for B | K71: Own shop works. Every call against B returns 403/404 and changes nothing. | L71: Regression RBAC-02; Test plan section 3 | M71: Pass | N71: Passed, partly covered. Local Pass (partial) · Staging Blocked · Production Not run local: not covered: empty bodies refused with 422 before the ownership check reveal field names only (the D-01 pattern, here for a signed-in owner); with a valid body each is refused staging: needs shop B in this site's test data | P71: 2026-10-24 17:48
A72: TC-RBAC-005 | B72: Roles & access control | C72: GS-002 | D72: Shop owner cannot open admin or other roles' portals | E72: Security | F72: P0 | G72: Shop | H72: UI+API | J72: 1. Open /admin/*, /delivery-partner (without rider role), /society/{id} of a society they do not manage | K72: Redirected / 403. | L72: RBAC Matrix | M72: Pass | N72: Local Pass · Staging Pass · Production Not run local: 71 admin pages + /operator, /delivery-partner, /society/{id} refused (/operator 307→/admin; /delivery-partner 307→/delivery-partner/apply; /society/238274e0-6beb-4f5b-8a36-fc6da9efd430 404); settings API 403 ‖ 106 admin API calls: 403×106 staging: 71 admin pages + /operator, /delivery-partner refused (/admin/users/00000000-0000-4000-8000-000000000000/privileges 307→/; /operator 307→/admin; /delivery-partner 307→/delivery-partner/apply); settings API 403 ‖ 106 admin API calls: 403×106 | O72: D-81 | P72: 2026-10-24 17:48
A73: TC-RBAC-006 | B73: Roles & access control | C73: GS-002, RBAC-008 | D73: Rider limited to own jobs and availability | E73: Security | F73: P0 | G73: Rider | H73: UI+API | J73: 1. Open /delivery-partner 2. PATCH /api/delivery-orders/{id} for a delivery assigned to another rider 3. PATCH /api/delivery-partner/{otherId} | K73: Own dashboard works. Other riders' deliveries and profiles: 403/404. | L73: RBAC Matrix: Manage own availability | M73: Pass | N73: Passed, partly covered. Local Pass (partial) · Staging Blocked · Production Not run local: not covered: locally the other riders go offline so the offer reaches rider 2; on the test site rider2 does not exist (blocked) staging: needs a second rider account (rider2) | P73: 2026-10-24 17:48
A74: TC-RBAC-007 | B74: Roles & access control | C74: RBAC-006, RBAC-014, RBAC-015 | D74: Operator can verify shops but not admin-only functions | E74: Security | F74: P0 | G74: Operator | H74: UI+API | J74: 1. Open /admin 2. Approve/reject a shop 3. Try /admin/settings, finance approve/pay, POST /api/users/{id}/suspend, PATCH /api/users/{id}/role, /admin/rider-earnings rules | K74: Shop verification works. /admin/settings redirects. Finance approve/pay, user suspend and role changes return 403. Audit log shows the limited view only. | L74: QA S-01; Dev log Slice 6 K; RBAC Matrix | M74: Pass | N74: Passed, partly covered. Local Pass (partial) · Staging Pass (partial) · Production Not run local: not covered: the refusals of admin-only functions are the signed-tier TC-RBAC-007 check ‖ not covered: approving / rejecting a shop as operator is in tests/qa/local/access-roles.spec.ts; the limited audit view is TC-RBAC-021 staging: not covered: approving / rejecting a shop as operator is in tests/qa/local/access-roles.spec.ts; the limited audit view is TC-RBAC-021 | P74: 2026-10-24 17:49
A75: TC-RBAC-008 | B75: Roles & access control | C75: RBAC-003 | D75: Operator 'Limited' shop management - record current behaviour | E75: Positive | F75: P2 | G75: Operator | H75: UI+API | I75: Decision pending - not built | J75: 1. As OPERATOR try PATCH /api/shops/{id} (name, hours, radius) and shop product edits | K75: Record exactly what an operator can and cannot change today. This is evidence for the pending decision, not a pass/fail. | L75: Open items: RBAC-003 | M75: Pass | N75: Passed, partly covered. Local Pass (partial) · Staging Not run (rule) · Production Not run local: not covered: evidence for the pending 'Limited' decision (TC-RBAC-008 is record-only): an operator holds SHOP_UPDATE_ANY and SHOP_PRODUCT_MANAGE_ANY staging: not run on staging: needs the server's database (local run only) | P75: 2026-10-24 17:05
A76: TC-RBAC-009 | B76: Roles & access control | C76: RBAC-013 | D76: Admin sets a user's role | E76: Positive | F76: P0 | G76: Admin | H76: UI | I76: A CUSTOMER account | J76: 1. Open /admin/users/{id} 2. Grant OPERATOR 3. Sign in as that user | K76: Role saved with a Save confirmation; audited; a role-change security notification is sent. User now sees the operator console. | L76: Regression RBAC-03; QA F-09 | M76: Pass | N76: Local Pass · Staging Not run (rule) · Production Not run local: "Privileges updated for QA rbac009"; CUSTOMER→OPERATOR audited (user.privileges_updated); notification received; /admin 200 staging: not run on staging: needs the server's database (local run only) | P76: 2026-10-24 17:05
A77: TC-RBAC-010 | B77: Roles & access control | C77: RBAC-013 | D77: Admin privilege change needs confirmation and is audited | E77: Positive | F77: P1 | G77: Admin | H77: UI | J77: 1. Open /admin/users/{id}/privileges 2. Change a privilege 3. Try to leave without saving 4. Save | K77: Save button enabled only after a change; unsaved-changes warning on leaving; confirmation before saving; success message; audit row with old and new values. | L77: tests admin-save-flows; chat brief 2-Oct | M77: Pass | N77: Passed, partly covered. Local Pass (partial) · Staging Not run (rule) · Production Not run local: not covered: links outside the form (site header, 'Edit profile') leave without a prompt by design (src/components/unsaved-changes-guard.tsx: the guard is page-scoped) staging: not run on staging: needs the server's database (local run only) | P77: 2026-10-24 17:05
A78: TC-RBAC-011 | B78: Roles & access control | C78: GS-003 | D78: User holds several roles and switches between them | E78: Positive | F78: P0 | G78: Shop | H78: UI+API | I78: Shop owner applies as a rider and is approved | J78: 1. Check the header role switcher 2. Switch SHOP_OWNER -> DELIVERY_PARTNER -> CUSTOMER 3. GET /api/me/roles | K78: Both roles are held; switching changes the portal and navigation. Active role is reflected by the API. | L78: Dev log Phase 3: GS-003 | M78: Pass | N78: Local Pass · Staging Not run (rule) · Production Not run local: held CUSTOMER+SHOP_OWNER+DELIVERY_PARTNER; DELIVERY_PARTNER→/delivery-partner; CUSTOMER→/; SHOP_OWNER→/shop staging: not run on staging: needs the server's database (local run only) | P78: 2026-10-24 17:05
A79: TC-RBAC-012 | B79: Roles & access control | C79: GS-003 | D79: Cannot switch to a role not held | E79: Security | F79: P0 | G79: Customer | H79: API | J79: 1. PUT /api/me/roles {role:'ADMIN'} and {role:'OPERATOR'} | K79: 403/422; active role unchanged. | L79: Dev log Phase 3 | M79: Pass | N79: Local Pass · Staging Pass · Production Not run local: ADMIN 403, OPERATOR 403, SHOP_OWNER 403, NOT_A_ROLE 422; still CUSTOMER (["CUSTOMER"]) staging: ADMIN 403, OPERATOR 403, SHOP_OWNER 403, NOT_A_ROLE 422; still CUSTOMER (["CUSTOMER"]) | P79: 2026-10-24 17:48
A80: TC-RBAC-013 | B80: Roles & access control | C80: GS-003 | D80: Revoking the active role falls back to CUSTOMER | E80: Positive | F80: P1 | G80: Admin | H80: UI+API | I80: User with OPERATOR active | J80: 1. Admin: DELETE /api/users/{id}/roles?role=OPERATOR 2. User reloads | K80: User becomes CUSTOMER immediately and loses console access. | L80: Dev log Phase 3 | M80: Pass | N80: Local Pass · Staging Not run (rule) · Production Not run local: OPERATOR → revoked → CUSTOMER at once; /admin now 307 → / staging: not run on staging: needs the server's database (local run only) | P80: 2026-10-24 17:05
A81: TC-RBAC-014 | B81: Roles & access control | C81: GS-003 | D81: Staff roles are exclusive | E81: Negative | F81: P1 | G81: Admin | H81: UI | I81: User who is a SHOP_OWNER | J81: 1. Grant OPERATOR then ADMIN | K81: Staff roles replace each other rather than stack; behaviour matches 'staff roles exclusive'. Record the exact result. | L81: Dev log Phase 3 | M81: Pass | N81: Local Pass · Staging Not run (rule) · Production Not run local: after OPERATOR: CUSTOMER+SHOP_OWNER+OPERATOR (active OPERATOR); after ADMIN: CUSTOMER+SHOP_OWNER+ADMIN (active ADMIN); both at once → 422 staging: not run on staging: needs the server's database (local run only) | P81: 2026-10-24 17:05
A82: TC-RBAC-015 | B82: Roles & access control | C82: GS-003 | D82: Existing users kept access after migration backfill | E82: Regression | F82: P1 | G82: All | H82: UI | J82: 1. Sign in as a pre-existing shop owner, rider and operator | K82: Each still reaches their portal; each has a grant for the role. | L82: Dev log Phase 3 | M82: Pass | N82: Passed, partly covered. Local Pass (partial) · Staging Not run (rule) · Production Not run local: not covered: the local database has no accounts from before the role-grant migration; the backfill is read from drizzle/0023 and the grant query is the one to run on the sites' databases staging: not run on staging: needs the server's database (local run only) | P82: 2026-10-24 17:05
A83: TC-RBAC-016 | B83: Roles & access control | C83: RBAC-002 | D83: Every role can place a personal order | E83: Positive | F83: P0 | G83: Shop | H83: UI | I83: Shop owner with wallet balance | J83: 1. As SHOP_OWNER (and separately as rider, operator) add items from another shop and check out as PERSONAL | K83: Order placed normally. | L83: Wave 1 decision RBAC-002 | M83: Pass | N83: Passed, partly covered. Local Pass (partial) · Staging Blocked · Production Not run local: not covered: the shop owner's personal order is the signed-tier TC-RBAC-016 check; wallets topped up in the database first ‖ not covered: rider and operator personal orders need their wallets funded: tests/qa/local/access-roles.spec.ts staging: needs shop A's location in this site's test data | P83: 2026-10-24 17:49
A84: TC-RBAC-017 | B84: Roles & access control | C84: RBAC-002 | D84: B2B order by a shop owner | E84: Positive | F84: P1 | G84: Shop | H84: UI+API | I84: Owner's shop is APPROVED | J84: 1. Check out with orderType B2B and buyerShopId = own shop, cart from another shop | K84: Order created with order_type B2B. Mobile/address rules for personal orders do not apply. | L84: API.md checkout | M84: Pass | N84: Local Pass · Staging Blocked · Production Not run local: DB-20261024-J0FKXM B2B for QA Shop A mvmkyclr from QA Shop B mvmkyclr, no address sent, ₹45 staging: needs shop B in this site's test data | P84: 2026-10-24 17:49
A85: TC-RBAC-018 | B85: Roles & access control | C85: RBAC-002 | D85: B2B refused for a customer, for another owner's shop and for own-shop items | E85: Negative | F85: P1 | G85: Customer | H85: API | J85: 1. POST /api/checkout B2B as CUSTOMER 2. As owner with buyerShopId of another shop 3. As owner with cart items from the same shop 4. PERSONAL with buyerShopId set | K85: 403 / 422 each time; nothing created or debited. | L85: API.md checkout | M85: Fail | N85: Local Fail · Staging Pass (partial) · Production Not run local: owner A, own shop's items: add to cart — HTTP 409: This product is currently unavailable online. | expect(received).toContain(expected) // indexOf | Expected value: 409 | Received array: [200, 201] staging: blocked: needs shop B in this site's test data | P85: 2026-10-24 18:00
A86: TC-RBAC-019 | B86: Roles & access control | C86: RBAC-010 | D86: Order visibility is role-scoped | E86: Security | F86: P0 | G86: All | H86: UI+API | I86: Orders exist for two customers and two shops | J86: 1. Customer: /orders and GET /api/orders 2. Shop: /shop/orders 3. Rider: deliveries 4. Society admin: dashboard deliveries 5. Operator: /admin/orders 6. Admin: /admin/orders | K86: Customer sees own only; shop sees own shop only; rider own jobs; society sees society deliveries with no customer PII or order contents; operator and admin see all shops. | L86: RBAC Matrix: View all orders; Status report RBAC-010 | M86: Pass | N86: Passed, partly covered. Local Pass (partial) · Staging Blocked · Production Not run local: not covered: no order is delivered to a society address in this run, so the deliveries list is empty: the check proves the page and the absence of PII, not a populated list ‖ blocked: "QA Butter 100 g mvmkyclr" cannot be added to the cart — HTTP 409: This product is currently unavailable online. staging: needs shop B in this site's test data ‖ needs a verified society in this site's test data | P86: 2026-10-24 17:50
A87: TC-RBAC-020 | B87: Roles & access control | C87: RBAC-012 | D87: Settlement visibility per role | E87: Security | F87: P0 | G87: All | H87: UI+API | J87: 1. Shop: /shop/finance 2. Rider: earnings and payouts 3. Operator: /admin/finance and /admin/finance/exceptions 4. Customer: /shop/finance, /api/finance/summary | K87: Shop and rider see only their own statements. Operator sees exceptions only, with no settlement or payout totals. Customer is refused. | L87: Dev log Slice 6 K | M87: Pass | N87: Local Pass · Staging Blocked · Production Not run local: shop /shop/finance 200 (own shop only); rider earnings 200 (own); operator: /admin/finance → exceptions; summary/settlements/payouts/ledger 403; exceptions 200; customer: /shop/finance refused, finance summary 403; owner A on B's wallet 403 staging: needs shop B in this site's test data | P87: 2026-10-24 17:50
A88: TC-RBAC-021 | B88: Roles & access control | C88: RBAC-015, GS-067 | D88: Audit log viewer: admin full, operator limited | E88: Positive | F88: P1 | G88: Admin | H88: UI | J88: 1. Open the audit section as ADMIN then as OPERATOR | K88: Admin sees all actions with actor, role, old/new values. Operator sees the limited subset. Customer/shop cannot open it. | L88: RBAC plan Phase 11 | M88: Pass | N88: Local Pass · Staging Pass · Production Not run local: admin: also credit_note.issued, user.profile_updated, order.status_changed, order.placed, delivery_order.offered, delivery_order.accepted, with actor role and before/after; operator: 'operational entries' with shop.updated, no role or settings changes; customer and shop redirected staging: admin: also wallet.topup_verified, user.profile_updated, order.status_changed, order.placed, consent.recorded, society.registered, with actor role and before/after; operator: 'operational entries' with shop.updated, no role or settings changes; customer and shop redirected | P88: 2026-10-24 17:50
A89: TC-RBAC-022 | B89: Roles & access control | C89: GS-067 | D89: Audit log is append-only | E89: Security | F89: P1 | G89: Admin | H89: DB | I89: DB access to the TEST database only | J89: 1. Attempt UPDATE and DELETE on one audit_logs row | K89: Both are refused by the database trigger. | L89: Dev log Wave 1 | M89: Pass | N89: Local Pass · Staging Not run (rule) · Production Not run local: update: refused (audit_logs is append-only: UPDATE is not allowed); delete: refused (audit_logs is append-only: DELETE is not allowed) staging: not run on staging: needs the server's database (local run only) | P89: 2026-10-24 17:05
A90: TC-RBAC-023 | B90: Roles & access control | C90: GS-071 | D90: IDOR sweep on customer-owned resources | E90: Security | F90: P0 | G90: Customer | H90: API | I90: Customer 2's address, order, subscription, return and notification ids | J90: 1. As Customer 1 call GET/PATCH/DELETE on /api/addresses/{id}, /api/orders/{id}/status, /api/orders/{id}/rating, /api/orders/{id}/issue, /api/subscriptions/{id} (+pause/skip/calendar/history), /api/returns/{id}, /api/tracking/{orderId} | K90: Every call returns 403 or 404; nothing changes; no data of Customer 2 is returned. | L90: Test plan section 3 (IDOR); Dev log Phase 2 fix | M90: Blocked | N90: Local Blocked · Staging Blocked · Production Not run local: "QA Butter 100 g mvmkyclr" cannot be added to the cart — HTTP 409: This product is currently unavailable online. staging: no delivery offer reached the rider for order f82cbd1c-5874-4040-96c3-32c5a3e358df within 45 s (rider offline or busy?) | P90: 2026-10-24 17:54
A91: TC-RBAC-024 | B91: Roles & access control | C91: GS-002 | D91: Suspended user loses the session on the next request | E91: Security | F91: P0 | G91: Admin | H91: UI | I91: Customer signed in on a second browser/profile | J91: 1. Admin suspends the customer 2. Customer loads any page | K91: Customer is signed out on the next request and cannot sign in again. | L91: Dev log Phase 4.5 | M91: Pass | N91: Local Pass · Staging Not run (rule) · Production Not run local: suspended mid-session: /orders → /signin, /api/wallet 401; sign-in again refused: "no code step" staging: not run on staging: needs the server's database (local run only) | P91: 2026-10-24 17:05
A92: TC-LOC-001 | B92: Location, addresses & serviceability | C92: GS-004 | D92: Set delivery location by PIN code | E92: Positive | F92: P0 | G92: Guest | H92: UI | J92: 1. Home -> 'Deliver to' -> Change -> enter a valid 6-digit PIN | K92: Label updates. 'Shops that deliver to you' refreshes. Choice persists across pages and reloads (gk_location cookie). | L92: Dev log Slice 1 handoff; QA B-03 | M92: Fail | N92: Local Fail · Staging Pass · Production Pass local: expect(locator).toBeVisible() failed | Locator: getByTestId('home-shops').getByTestId('shop-card').filter({ hasText: 'QA Shop A mvmkyclr' }).first() | Expected: visible | Timeout: 15000ms staging: PIN 411038 set from the location bar, then cleared production: PIN 411038 set from the location bar, then cleared | P92: 2026-10-29 14:02
A93: TC-LOC-002 | B93: Location, addresses & serviceability | C93: GS-004 | D93: Invalid PIN is rejected | E93: Negative | F93: P1 | G93: Guest | H93: UI+API | J93: 1. Enter 12345, 1234567, abcdef, 000000 | K93: Field error; location unchanged; POST /api/location returns 422. | L93: Dev log Slice 1 handoff | M93: Pass | N93: Local Pass (partial) · Staging Pass · Production Pass local: not covered: PINs starting with 0 (000000, 011001) are accepted — known defect D-04, asserted by the guest check in guest/storefront.spec.ts staging: 7 digits cut to 6; refused on the field: 12345, 011001, abcdef; API 000000 → 422 production: 7 digits cut to 6; refused on the field: 12345, 011001, abcdef; API 000000 → 422 | O93: D-04 | P93: 2026-10-29 14:02
A94: TC-LOC-003 | B94: Location, addresses & serviceability | C94: GS-004 | D94: Set location from device position - allow and deny | E94: Positive | F94: P1 | G94: Guest | H94: UI | J94: 1. Choose 'Use my current location' and allow 2. Repeat and deny the browser prompt | K94: Allow: location set (coordinates rounded to 4 decimals). Deny: a clear message and the previous location is kept. | L94: Dev log Slice 1 handoff | M94: Pass | N94: Local Pass · Staging Blocked · Production Not run local: allowed: 18.50745678,73.80771234 stored as 18.5075,73.8077; denied: "Location permission was not given…", PIN 411038 kept ‖ [phone] allowed: 18.50745678,73.80771234 stored as 18.5075,73.8077; denied: "Location permission was not given…", PIN 411038 kept staging: needs the test data's location (shop A's coordinates) | P94: 2026-10-24 21:56
A95: TC-LOC-004 | B95: Location, addresses & serviceability | C95: GS-004 | D95: Set location from a saved address | E95: Positive | F95: P0 | G95: Customer | H95: UI | I95: Two saved addresses | J95: 1. Pick each saved address in the location picker | K95: List of delivering shops changes accordingly; the cart preselects that address. | L95: QA B-03 | M95: Pass | N95: Passed, partly covered. Local Pass (partial) · Staging Blocked · Production Not run local: blocked: "QA Butter 100 g mvmkyclr" cannot be added — HTTP 409: This product is currently unavailable online. staging: needs the "packaged" listing of the test data | P95: 2026-10-24 21:56
A96: TC-LOC-005 | B96: Location, addresses & serviceability | C96: GS-004 | D96: Signed-in customer defaults to the default address | E96: Positive | F96: P1 | G96: Customer | H96: UI | I96: Default address set; no location cookie | J96: 1. Clear the location 2. Reload home | K96: Discovery uses the default address. | L96: Dev log Slice 1 handoff | M96: Pass | N96: Passed, partly covered. Local Pass (partial) · Staging Blocked · Production Not run local: not covered: TC-LOC-007's guest half (all shops / a prompt) is guest/storefront.spec.ts staging: needs the test data's location (shop A's coordinates) | P96: 2026-10-24 21:56
A97: TC-LOC-006 | B97: Location, addresses & serviceability | C97: GS-004, GS-072 | D97: Search an address with Places and save it | E97: Positive | F97: P1 | G97: Customer | H97: UI | I97: Maps key configured | J97: 1. Change -> 'Search an address' -> pick a result 2. Accept the offer to save it | K97: Location label updates; shop list refreshes; the place is saved as an address. | L97: QA B-02 | M97: Blocked | N97: Local Blocked · Staging Blocked · Production Not run local: Google Maps is not configured on this site (NEXT_PUBLIC_GOOGLE_MAPS_API_KEY unset): the chooser offers no 'Search an address' staging: the Places search box needs live Google Places suggestions, which this run cannot reach | P97: 2026-10-24 20:46
A98: TC-LOC-007 | B98: Location, addresses & serviceability | C98: GS-004 | D98: Clear location | E98: Positive | F98: P2 | G98: Guest | H98: UI+API | J98: 1. Clear the location (DELETE /api/location) | K98: Cookie cleared; pages show all shops or ask for a location. | L98: API.md | M98: Pass | N98: Local Pass (partial) · Staging Pass · Production Pass local: not covered: TC-LOC-007's guest half (all shops / a prompt) is guest/storefront.spec.ts staging: PIN 411038 set from the location bar, then cleared production: PIN 411038 set from the location bar, then cleared | P98: 2026-10-29 14:02
A99: TC-LOC-008 | B99: Location, addresses & serviceability | C99: GS-004 | D99: Address book: create, edit, set default, delete | E99: Positive | F99: P0 | G99: Customer | H99: UI | J99: 1. /profile/addresses -> add with type Home/Work/Other, recipient name and mobile, landmark, PIN, map pin 2. Edit 3. Set default 4. Delete a non-default address | K99: All fields persist and display. Default flag moves. Deleted address disappears and is no longer selectable in the cart. | L99: QA B-01; Regression CUS-01 | M99: Pass | N99: Passed, partly covered. Local Pass (partial) · Staging Blocked · Production Not run local: blocked: "QA Butter 100 g mvmkyclr" cannot be added — HTTP 409: This product is currently unavailable online. staging: needs the test data's location (shop A's coordinates) | P99: 2026-10-24 21:56
A100: TC-LOC-009 | B100: Location, addresses & serviceability | C100: GS-004 | D100: Invalid recipient mobile on an address | E100: Negative | F100: P1 | G100: Customer | H100: UI | J100: 1. Save an address with recipient mobile 12345 | K100: Rejected with a field message. | L100: QA B-01 | M100: Pass | N100: Passed, partly covered. Local Pass (partial) · Staging Blocked · Production Not run local: not covered: blank is accepted: the field is labelled '(optional)' in src/components/address-manager.tsx (expected result superseded) staging: needs the test data's location (shop A's coordinates) | O100: D-09 | P100: 2026-10-24 20:46
...

Sheet E2E scenarios
A1: Scenario ID | B1: Scenario | C1: Workflows / features | D1: Priority | E1: Journey | F1: Expected outcome | G1: Status | H1: Notes
A2: SC-01 | B2: Customer buys from a local shop and receives it (wallet) | C2: WF-001, WF-002, WF-003, WF-005, WF-010 | D2: P0 | E2: 1. Customer signs in and sets a delivery location 2. Searches a product, opens Compare prices, picks the lowest-price delivering shop 3. Adds to cart, chooses address and delivery window, pays from wallet 4. Shop accepts, picks, packs, marks READY 5. Rider is offered automatically, accepts, enters the pickup code, starts delivery 6. Rider arrives, enters the customer's OTP - DELIVERED 7. Customer rates shop and rider 8. Admin opens the money trace: snapshot, commission, rider earning | F2: Order moves through every state with notifications at each step; wallet debited once; stock reduced; one finance snapshot; rider earning recorded; ratings saved. | G2: Pass | H2: [Run 2026-10-24 17:07: Local Pass · Staging Not run (rule) · Production Not run. local: DB-20261024-GQT21Y: compare page → QA Shop A mvmkyclr; window STANDARD_60; CONFIRMED → … → DELIVERED; customer notified 9× (order.confirmed, order.accepted, order.ready, order.rider_search, order.assigned, order.picked_up, order.out_for_delivery, rating.requested, order.delivered); rated 5/4; snapshot 0bp commission ₹0, earning ₹28.01 staging: not run on staging: needs the server's database (local run only)]
A3: SC-02 | B3: Multi-shop cart | C3: GS-025, GS-033 | D3: P0 | E3: 1. Add items from two delivering shops 2. Pay from wallet 3. Each shop fulfils independently; one is delivered, the other is rejected by the shop | F3: Two independent orders and debits; the rejected one is fully refunded with stock restored; the other completes. | G3: Pass | H3: [Run 2026-10-24 17:07: Local Pass · Staging Not run (rule) · Production Not run. local: DB-20261024-X42NMQ (A) delivered; DB-20261024-FON5AH (B) rejected → refunded ₹50, stock 10 again staging: not run on staging: needs the server's database (local run only)]
A4: SC-03 | B4: Item unavailable - substitution | C4: GS-035, GS-036 | D4: P0 | E4: 1. Place a 3-line order 2. Shop accepts, proposes a cheaper substitute for line 1 and removes line 2 3. Customer approves the substitute 4. Shop marks READY; delivery completes | F4: Difference and removed line refunded immediately; READY blocked until the customer decides; final snapshot uses the reduced goods value. | G4: Pass | H4: [Run 2026-10-24 17:07: Local Pass · Staging Not run (rule) · Production Not run. local: DB-20261024-B4FYYX: line 2 refunded ₹30 and the ₹8 difference at once; READY refused (409) until approval; delivered with goods ₹62 staging: not run on staging: needs the server's database (local run only)]
A5: SC-04 | B5: Shop rejects the order | C5: GS-034 | D5: P0 | E5: 1. Customer orders 2. Shop rejects with a reason | F5: Full refund, stock restored, customer notified with the reason, order never reaches a settlement. | G5: Pass | H5: [Run 2026-10-24 17:07: Local Pass · Staging Not run (rule) · Production Not run. local: DB-20261024-T9T7FT rejected: refunded ₹80, stock 5, notice "Your order DB-20261024-T9T7FT was cancelled: Rejected by shop: QA: our oven broke down" staging: not run on staging: needs the server's database (local run only)]
A6: SC-05 | B6: No rider available | C6: GA-009, RBAC-007 | D6: P0 | E6: 1. All riders offline; shop marks READY 2. Watch attempts until the search stops 3. A rider comes online; shop presses 'Try finding a rider again' 4. Delivery completes | F6: Bounded search with one notification at start and one at stop; restart offers the rider; order completes. | G6: Pass | H6: [Run 2026-10-24 17:07: Local Pass · Staging Not run (rule) · Production Not run. local: DB-20261024-I2KN5G: search stopped after 2 attempts (STOPPED); shop told delivery.unassigned → delivery.search_stopped; restarted, offered, delivered staging: not run on staging: needs the server's database (local run only)]
A7: SC-06 | B7: Rider declines / offer lapses | C7: GS-039, GA-009 | D7: P0 | E7: 1. Two riders online 2. Rider 1 declines (or lets 2 minutes pass) 3. Rider 2 accepts and delivers | F7: Rider 1 is never re-offered; only one active assignment at any time. | G7: Blocked | H7: [Run 2026-10-24 17:07: Local Blocked · Staging Not run (rule) · Production Not run. local: no delivery offer reached the rider for order 6abbb3b4-a55d-4d9d-993b-998aa2a8a752 within 45 s (rider offline or busy?) staging: not run on staging: needs the server's database (local run only)]
A8: SC-07 | B8: Customer unavailable - failed delivery and return to shop | C8: WF-005 | D8: P0 | E8: 1. Rider picks up and starts delivery 2. Rider reports customer not reachable 3. Shop marks RETURNED | F8: Order FAILED then cancelled and refunded per policy; rider paid per the failed-delivery rule; stock restored. | G8: Pass | H8: [Run 2026-10-24 17:07: Local Pass (partial) · Staging Not run (rule) · Production Not run. local: not covered: marking the goods RETURNED alone neither refunds nor restocks: the shop (or operations) then cancels the order, which does both staging: not run on staging: needs the server's database (local run only)]
A9: SC-08 | B9: Society authorised delivery | C9: WF-004, GA-001, GS-045, GS-046, GS-047 | D9: P0 | E9: 1. Society registered and verified; admin lists a rider and turns on exclusive riders and security notices 2. Resident joins, links an address, places an order 3. Shop marks READY 4. Only the listed rider is offered; accepts 5. Security staff notified; rider sees gate notes; delivers with OTP | F9: Dispatch honours the list; dashboard shows the delivery without PII. | G9: Pass | H9: [Run 2026-10-24 17:07: Local Pass · Staging Not run (rule) · Production Not run. local: DB-20261024-6LNKEX: offered to rider 2 only (rider 1 nearer, not listed); 'Delivery rider on the way' to society staff; rider saw "QA SC-08 Society mvmmqb1z Gate: Security calls the resident before letting you in QA SC-08: use gate 2, park by the club house mvmmqb1z"; delivered with the code; dashboard row createdAt, orderNumber, promisedByAt, riderName, riderVehicle, riderVehicleNumber, shopName, status, unitLabel — no PII staging: not run on staging: needs the server's database (local run only)]
A10: SC-09 | B10: Daily milk subscription | C10: WF-006, GS-048, GS-050, GS-051 | D10: P0 | E10: 1. Top up the wallet 2. Subscribe to 2 L/day of milk 3. Daily-orders cron runs for the start date, then again 4. Change tomorrow to 3 L; skip the day after; pause the following two days 5. Run the cron for each date 6. Let the wallet run short one day, then top up and retry | F10: Rs 140 then Rs 210 charged once each; no order on skipped/paused days; the failed day is recovered by retry with a single debit. | G10: Pass | H10: [Run 2026-10-24 17:07: Local Pass · Staging Not run (rule) · Production Not run. local: 2026-10-25 CONFIRMED ₹140; 2026-10-26 CONFIRMED ₹210; 2026-10-30 CONFIRMED ₹140; second retry → 409 staging: not run on staging: needs the server's database (local run only)]
A11: SC-10 | B11: Return and refund with rider pickup | C11: WF-007, GS-057 | D11: P0 | E11: 1. Customer requests a return on a delivered order with a photo 2. Shop approves 3. Rider accepts the pickup, enters the handover code 4. Shop receives, inspects and accepts a partial amount 5. Refund completes | F11: Each status visible to the customer; wallet credited once; shop share adjusted in the next settlement; rider paid the pickup fee. | G11: Pass | H11: [Run 2026-10-24 17:07: Local Pass (partial) · Staging Not run (rule) · Production Not run. local: not covered: TC-FIN-019's 'return-pickup fee in the payout' is shown as the fee in the rider's unpaid statement, which the weekly payout batches staging: not run on staging: needs the server's database (local run only)]
A12: SC-11 | B12: Cancellation at every stage (D10) | C12: NEW-006 | D12: P0 | E12: 1. Place 7 orders and bring them to CONFIRMED, ACCEPTED, PREPARING, READY, ASSIGNED, PICKED_UP, OUT_FOR_DELIVERY 2. Customer tries to cancel each 3. Shop cancels the ones the customer could not | F12: Customer: allowed at CONFIRMED (full refund), blocked at four middle states, goods-only after pickup. Shop: full refund always. | G12: Pass | H12: [Run 2026-10-24 17:07: Local Pass · Staging Not run (rule) · Production Not run. local: CONFIRMED customer ✓ ₹20; ACCEPTED customer ✗ (409) → shop ✓ ₹20; PREPARING customer ✗ (409) → shop ✓ ₹20; READY customer ✗ (409) → shop ✓ ₹20; ASSIGNED customer ✗ (409) → shop ✓ ₹20; PICKED_UP customer ✓ ₹20; OUT_FOR_DELIVERY customer ✓ ₹20 staging: not run on staging: needs the server's database (local run only)]
... A38: SC-37 | B38: Signed-in test run by the Claude QA agent | C38: QA-011, QA-010 | D38: P1 | E38: 1. The agent signs the staging test accounts in with the emailed codes (owner's mailbox) 2. It runs the signed-in tier on test.gokesari.com 3. It collects the results and rebuilds the register | F38: A staging run with signed-in checks that passed (so the sessions worked), collected into docs/testing/qa-runs. | G38: Pass | H38: Added 24-Oct (QA automation) [Run 2026-10-29 13:59: Local Blocked · Staging Pass · Production Pass. local: needs a collected staging run with signed-in checks staging: 177 signed-in checks passed on test.gokesari.com (133 case IDs) production: 177 signed-in checks passed on test.gokesari.com (133 case IDs)]

Sheet Coverage
A1: Feature ID | B1: Module | C1: Feature | D1: Development status | E1: Test cases | F1: TC IDs | G1: Not-yet-testable part
A2: RBAC-002 | B2: Security | C2: Place order (Customer, Admin only) | D2: COMPLETED | E2: 4 | F2: TC-RBAC-016, TC-RBAC-017, TC-RBAC-018, TC-SPI-007
A3: RBAC-007 | B3: Security | C3: Assign delivery | D3: COMPLETED (2-Oct) | E3: 4 | F3: TC-DSP-009, TC-DSP-010, TC-DSP-014, TC-DSP-015
A4: RBAC-003 | B4: Security | C4: Manage own shop (Operator Limited) | D4: UNCLEAR | E4: 1 | F4: TC-RBAC-008 | G4: Part not built: Operator 'Limited' shop management
A5: GS-002 | B5: Identity & Access | C5: Role-based access control | D5: COMPLETED | E5: 10 | F5: TC-RBAC-001, TC-RBAC-002, TC-RBAC-003, TC-RBAC-004, TC-RBAC-005, TC-RBAC-006, TC-RBAC-024, TC-AUTH-033, TC-CAT-048, TC-SPI-027
A6: GS-001 | B6: Identity & Access | C6: Mobile/email/Gmail login | D6: TREATED AS COMPLETED 4-Oct (open-features list 3-Oct: IN PROGRESS) - confirm on test with TC-PRE-012 | E6: 63 | F6: TC-AUTH-001, TC-AUTH-002, TC-AUTH-003, TC-AUTH-004, TC-AUTH-005, TC-AUTH-006, TC-AUTH-007, TC-AUTH-008, TC-AUTH-009, TC-AUTH-010, TC-AUTH-011, TC-AUTH-012, TC-AUTH-013, TC-AUTH-014, TC-AUTH-015, TC-AUTH-016, TC-AUTH-017, TC-AUTH-018, TC-AUTH-019, TC-AUTH-020, TC-AUTH-021, TC-AUTH-022, TC-AUTH-023, TC-AUTH-024, TC-AUTH-025, TC-AUTH-026, TC-AUTH-027, TC-AUTH-028, TC-AUTH-029, TC-AUTH-030, TC-AUTH-031, TC-CART-015, TC-AUTH-032, TC-AUTH-033, TC-AUTH-034, TC-AUTH-035, TC-AUTH-036, TC-AUTH-037, TC-AUTH-038, TC-AUTH-039, TC-AUTH-040, TC-AUTH-041, TC-AUTH-042, TC-AUTH-043, TC-AUTH-044, TC-AUTH-045, TC-FLD-001, TC-FLD-002, TC-FLD-003, TC-FLD-005, TC-FLD-006, TC-FLD-007, TC-FLD-008, TC-FLD-009, TC-AUTH-046, TC-AUTH-047, TC-AUTH-048, TC-AUTH-049, TC-AUTH-050, TC-AUTH-051, TC-AUTH-052, TC-AUTH-053, TC-AUTH-054
A7: GS-070 | B7: Security | C7: Privacy/consent management | D7: COMPLETED | E7: 6 | F7: TC-MKT-001, TC-MKT-002, TC-MKT-006, TC-FLD-004, TC-FLD-124, TC-NTF-019
A8: GS-067 | B8: Admin | C8: Audit logs | D8: COMPLETED | E8: 7 | F8: TC-AUTH-028, TC-RBAC-021, TC-RBAC-022, TC-AUTH-045, TC-CAT-051, TC-CAT-064, TC-SPI-021 | G8: Part not built: Dedicated Auditor role
A9: RBAC-010 | B9: Security | C9: View orders (role-scoped) | D9: COMPLETED (2-Oct) | E9: 3 | F9: TC-RBAC-019, TC-SOC-009, TC-CART-026
A10: SM-001 | B10: Orders | C10: Order state machine | D10: COMPLETED | E10: 6 | F10: TC-ORD-001, TC-ORD-002, TC-ORD-003, TC-ORD-004, TC-ORD-005, TC-SPI-018
A11: SM-005 | B11: Payments | C11: Payment state machine | D11: TREATED AS COMPLETED 4-Oct (open-features list 3-Oct: IN PROGRESS) - confirm on test with TC-PRE-012 | E11: 8 | F11: TC-PAY-006, TC-PAY-019, TC-PAY-020, TC-PAY-023, TC-PAY-026, TC-PAY-027, TC-PAY-031, TC-PAY-032
A12: SM-002 | B12: Shop Onboarding | C12: Shop state machine | D12: TREATED AS COMPLETED 4-Oct (open-features list 3-Oct: IN PROGRESS) - confirm on test with TC-PRE-012 | E12: 6 | F12: TC-ONB-031, TC-ONB-038, TC-ONB-040, TC-ONB-041, TC-ONB-042, TC-ONB-043
A13: SM-003 | B13: Delivery | C13: Gig state machine | D13: TREATED AS COMPLETED 4-Oct (open-features list 3-Oct: IN PROGRESS) - confirm on test with TC-PRE-012 | E13: 4 | F13: TC-DEL-015, TC-DEL-025, TC-DEL-026, TC-DEL-027
A14: SM-004 | B14: Subscription | C14: Subscription state machine | D14: TREATED AS COMPLETED 4-Oct (open-features list 3-Oct: IN PROGRESS) - confirm on test with TC-PRE-012 | E14: 7 | F14: TC-SUB-008, TC-SUB-011, TC-SUB-012, TC-SUB-016, TC-SUB-017, TC-SUB-018, TC-SUB-019
A15: SM-006 | B15: Support | C15: Issue state machine | D15: TREATED AS COMPLETED 4-Oct (open-features list 3-Oct: IN PROGRESS) - confirm on test with TC-PRE-012 | E15: 4 | F15: TC-SUP-005, TC-SUP-012, TC-SUP-013, TC-SUP-014
A16: GS-004 | B16: Location | C16: PIN / address selection | D16: COMPLETED | E16: 19 | F16: TC-LOC-001, TC-LOC-002, TC-LOC-003, TC-LOC-004, TC-LOC-005, TC-LOC-006, TC-LOC-007, TC-LOC-008, TC-LOC-009, TC-LOC-010, TC-FLD-010, TC-FLD-011, TC-FLD-012, TC-FLD-013, TC-FLD-014, TC-FLD-015, TC-FLD-016, TC-FLD-018, TC-FLD-020
A17: GS-010 | B17: Shop Onboarding | C17: Service radius / delivery zone | D17: COMPLETED | E17: 9 | F17: TC-LOC-011, TC-LOC-012, TC-LOC-013, TC-LOC-014, TC-LOC-015, TC-LOC-016, TC-FLD-046, TC-FLD-049, TC-LOC-032
A18: GS-026 | B18: Checkout | C18: Address validation | D18: COMPLETED | E18: 10 | F18: TC-LOC-018, TC-LOC-019, TC-LOC-020, TC-LOC-021, TC-FLD-013, TC-FLD-015, TC-FLD-016, TC-FLD-017, TC-FLD-025, TC-PAY-035
A19: GS-072 | B19: Integration | C19: Maps/navigation | D19: TREATED AS COMPLETED 4-Oct (open-features list 3-Oct: IN PROGRESS) - confirm on test with TC-PRE-012 | E19: 9 | F19: TC-LOC-006, TC-LOC-010, TC-DEL-012, TC-FLD-017, TC-FLD-021, TC-LOC-029, TC-LOC-030, TC-LOC-031, TC-LOC-032
A20: GS-007 | B20: Shop Onboarding | C20: Business KYC | D20: TREATED AS COMPLETED 4-Oct (open-features list 3-Oct: IN PROGRESS) - confirm on test with TC-PRE-012 | E20: 18 | F20: TC-ONB-016, TC-ONB-017, TC-ONB-018, TC-ONB-019, TC-ONB-020, TC-FLD-040, TC-FLD-041, TC-FLD-042, TC-FLD-043, TC-FLD-044, TC-FLD-045, TC-FLD-047, TC-FLD-121, TC-ONB-044, TC-ONB-045, TC-ONB-046, TC-ONB-047, TC-FIN-029
A21: GS-008 | B21: Shop Onboarding | C21: Payment reference verification | D21: IN PROGRESS | E21: 6 | F21: TC-ONB-021, TC-ONB-022, TC-ONB-023, TC-ONB-024, TC-FLD-112, TC-FLD-113 | G21: Part not built: KYC document upload; single KYC status; fee-payment gate before approval; shop states KYC_PENDING / PAYMENT_PENDING / VERIFIED / CLOSED
A22: GS-009 | B22: Shop Onboarding | C22: Shop categories | D22: COMPLETED (2-Oct) | E22: 10 | F22: TC-ONB-004, TC-ONB-026, TC-ONB-027, TC-ONB-028, TC-CAT-037, TC-CAT-053, TC-FLD-039, TC-FLD-069, TC-FLD-072, TC-FLD-080
A23: GS-015 | B23: Catalog | C23: MRP / selling price / discount | D23: COMPLETED (2-Oct) | E23: 20 | F23: TC-CART-006, TC-CAT-005, TC-CAT-006, TC-CAT-007, TC-CAT-008, TC-CAT-009, TC-CAT-010, TC-CAT-011, TC-CAT-029, TC-CAT-031, TC-CAT-032, TC-CAT-039, TC-CAT-040, TC-CAT-057, TC-CAT-058, TC-CAT-060, TC-CAT-063, TC-FLD-058, TC-FLD-060, TC-FLD-079
A24: WF-008 | B24: Shop Onboarding | C24: Shop onboarding | D24: TREATED AS COMPLETED 4-Oct (open-features list 3-Oct: IN PROGRESS) - confirm on test with TC-PRE-012 | E24: 4 | F24: TC-ONB-001, TC-FLD-121, TC-ONB-040, TC-ONB-044
A25: GS-019 | B25: Search | C25: Shop search | D25: COMPLETED | E25: 8 | F25: TC-LOC-013, TC-LOC-017, TC-DISC-002, TC-DISC-003, TC-DISC-004, TC-DISC-005, TC-SOC-015, TC-FLD-022
A26: GS-020 | B26: Search | C26: Product search | D26: COMPLETED | E26: 3 | F26: TC-DISC-006, TC-DISC-007, TC-FLD-022
A27: GS-021 | B27: Search | C27: All shops selling product | D27: COMPLETED | E27: 2 | F27: TC-DISC-008, TC-DISC-012
A28: GS-022 | B28: Comparison | C28: Local price comparison | D28: COMPLETED | E28: 7 | F28: TC-DISC-009, TC-DISC-010, TC-DISC-011, TC-CAT-034, TC-CAT-059, TC-SPI-023, TC-DISC-021
A29: NAV-001 | B29: Customer | C29: Customer portal - Home | D29: TREATED AS COMPLETED 4-Oct (open-features list 3-Oct: IN PROGRESS) - confirm on test with TC-PRE-012 | E29: 13 | F29: TC-DISC-001, TC-UX-001, TC-UX-002, TC-UX-003, TC-UX-004, TC-UX-005, TC-UX-006, TC-AUTH-039, TC-AUTH-043, TC-FLD-125, TC-FLD-126, TC-DISC-021, TC-DISC-022
A30: NAV-002 | B30: Customer | C30: Customer portal - Shop | D30: TREATED AS COMPLETED 4-Oct (open-features list 3-Oct: IN PROGRESS) - confirm on test with TC-PRE-012 | E30: 4 | F30: TC-DISC-013, TC-CAT-050, TC-DISC-023, TC-DISC-024
A31: GS-027 | B31: Checkout | C31: Delivery slot | D31: TREATED AS COMPLETED 4-Oct (open-features list 3-Oct: IN PROGRESS) - confirm on test with TC-PRE-012 | E31: 7 | F31: TC-CART-008, TC-FLD-026, TC-CART-020, TC-CART-021, TC-CART-022, TC-CART-023, TC-FLD-131
A32: GS-028 | B32: Payments | C32: UPI/card/netbanking gateway | D32: TREATED AS COMPLETED 4-Oct (open-features list 3-Oct: IN PROGRESS) - confirm on test with TC-PRE-012 | E32: 13 | F32: TC-PAY-004, TC-PAY-006, TC-PAY-007, TC-PAY-017, TC-PAY-018, TC-PAY-019, TC-PAY-020, TC-PAY-021, TC-PAY-024, TC-PAY-025, TC-PAY-033, TC-PAY-034, TC-PAY-035
A33: GS-073 | B33: Integration | C33: Payment gateway | D33: TREATED AS COMPLETED 4-Oct (open-features list 3-Oct: IN PROGRESS) - confirm on test with TC-PRE-012 | E33: 9 | F33: TC-PAY-002, TC-PAY-004, TC-PAY-005, TC-PAY-022, TC-PAY-023, TC-PAY-028, TC-PAY-029, TC-PAY-030, TC-ORD-019
... A38: GS-034 | B38: Orders | C38: Shop accept/reject | D38: COMPLETED | E38: 8 | F38: TC-ORD-010, TC-ORD-015, TC-FUL-001, TC-FUL-002, TC-FUL-003, TC-FUL-004, TC-FLD-082, TC-ORD-016
A39: GS-036 | B39: Orders | C39: Pick and pack | D39: COMPLETED | E39: 6 | F39: TC-FUL-005, TC-FUL-006, TC-FUL-013, TC-FUL-014, TC-FLD-083, TC-SPI-011 | G39: Part not built: Pick-pack SLA reporting
A40: NAV-006 | B40: Shop | C40: Shop portal - Dashboard | D40: COMPLETED (2-Oct) | E40: 8 | F40: TC-ONB-029, TC-ADM-006, TC-FLD-052, TC-FLD-053, TC-FLD-054, TC-FLD-055, TC-FLD-056, TC-SPI-009
A41: WF-002 | B41: Orders | C41: Shop fulfillment | D41: COMPLETED | E41: 7 | F41: TC-FUL-001, TC-FUL-016, TC-SPI-008, TC-SPI-009, TC-SPI-010, TC-SPI-011, TC-SPI-012
A42: GS-005 | B42: Location | C42: Society identification | D42: COMPLETED | E42: 7 | F42: TC-LOC-027, TC-LOC-028, TC-SOC-004, TC-SOC-005, TC-SOC-007, TC-SOC-015, TC-FLD-019
A43: GS-044 | B43: Society | C43: Society registration | D43: COMPLETED | E43: 5 | F43: TC-SOC-001, TC-SOC-002, TC-SOC-003, TC-SOC-017, TC-FLD-104 | G43: Part not built: Map pin picker on the society form
A44: GS-045 | B44: Society | C44: Authorized Gig worker whitelist | D44: COMPLETED | E44: 4 | F44: TC-DSP-019, TC-SOC-011, TC-SOC-012, TC-FLD-106
A45: RBAC-009 | B45: Security | C45: Whitelist Gig workers | D45: COMPLETED | E45: 3 | F45: TC-SOC-006, TC-SOC-009, TC-SOC-010
A46: GS-047 | B46: Society | C46: Delivery instructions | D46: COMPLETED | E46: 4 | F46: TC-DEL-021, TC-SOC-013, TC-FLD-029, TC-FLD-105
A47: NAV-014 | B47: Society | C47: Society portal - Dashboard | D47: COMPLETED | E47: 1 | F47: TC-SOC-008
A48: GA-006 | B48: Delivery | C48: Shop readiness | D48: COMPLETED | E48: 2 | F48: TC-FUL-006, TC-DSP-001
A49: GS-039 | B49: Delivery | C49: Job assignment | D49: COMPLETED | E49: 5 | F49: TC-DSP-001, TC-DSP-005, TC-DSP-012, TC-DEL-001, TC-DEL-002
A50: GA-005 | B50: Delivery | C50: Current load | D50: TREATED AS COMPLETED 4-Oct (open-features list 3-Oct: IN PROGRESS) - confirm on test with TC-PRE-012 | E50: 5 | F50: TC-DSP-004, TC-DSP-023, TC-DSP-024, TC-DSP-025, TC-DSP-026
A51: GA-009 | B51: Delivery | C51: No worker fallback | D51: COMPLETED | E51: 6 | F51: TC-DSP-005, TC-DSP-006, TC-DSP-007, TC-DSP-008, TC-DSP-011, TC-DSP-013 | G51: Part not built: Radius widening when no rider is found
A52: GA-001 | B52: Delivery | C52: Society authorization | D52: COMPLETED | E52: 3 | F52: TC-DSP-016, TC-DSP-018, TC-DSP-019
A53: GA-002 | B53: Delivery | C53: Society preferred partner | D53: COMPLETED | E53: 1 | F53: TC-DSP-017
A54: GS-040 | B54: Delivery | C54: Society priority assignment | D54: COMPLETED | E54: 2 | F54: TC-DSP-016, TC-DSP-017
A55: WF-003 | B55: Delivery | C55: Gig assignment | D55: COMPLETED | E55: 2 | F55: TC-DSP-022, TC-DSP-024 | G55: Part not built: Lower priority for busy riders and multi-order batching
A56: WF-004 | B56: Society | C56: Society authorized delivery | D56: COMPLETED | E56: 1 | F56: TC-SOC-016
A57: GS-041 | B57: Delivery | C57: Pickup OTP/QR | D57: COMPLETED | E57: 4 | F57: TC-FUL-015, TC-DEL-004, TC-DEL-010, TC-FLD-085 | G57: Part not built: QR pickup variant; photo / signature proof of delivery
A58: GS-043 | B58: Delivery | C58: Delivery OTP/POD | D58: COMPLETED | E58: 8 | F58: TC-DEL-007, TC-DEL-008, TC-DEL-009, TC-DEL-010, TC-FLD-086, TC-FLD-087, TC-FLD-088, TC-DEL-022 | G58: Part not built: QR pickup variant; photo / signature proof of delivery
A59: GS-042 | B59: Delivery | C59: Live tracking | D59: IN PROGRESS | E59: 2 | F59: TC-DEL-018, TC-DEL-019 | G59: Part not built: Customer / operations live-tracking screen
A60: WF-005 | B60: Delivery | C60: Delivery | D60: COMPLETED (2-Oct) | E60: 3 | F60: TC-DEL-005, TC-DEL-011, TC-DEL-020
A61: NAV-013 | B61: Gig | C61: Gig portal - Profile | D61: TREATED AS COMPLETED 4-Oct (open-features list 3-Oct: IN PROGRESS) - confirm on test with TC-PRE-012 | E61: 5 | F61: TC-DEL-017, TC-DEL-028, TC-DEL-029, TC-DEL-030, TC-DEL-031
A62: GS-055 | B62: Notifications | C62: Order notifications | D62: COMPLETED (2-Oct) | E62: 11 | F62: TC-LOC-025, TC-NTF-001, TC-NTF-002, TC-NTF-003, TC-NTF-004, TC-NTF-005, TC-NTF-006, TC-NTF-008, TC-NTF-009, TC-NTF-012, TC-NTF-013
A63: GS-074 | B63: Integration | C63: SMS/WhatsApp/email/push | D63: TREATED AS COMPLETED 4-Oct (open-features list 3-Oct: IN PROGRESS) - confirm on test with TC-PRE-012 | E63: 14 | F63: TC-NTF-002, TC-NTF-007, TC-NTF-010, TC-NTF-011, TC-FLD-124, TC-AUTH-051, TC-NTF-013, TC-NTF-014, TC-NTF-015, TC-NTF-016, TC-NTF-017, TC-NTF-018, TC-NTF-019, TC-NTF-020
A64: GS-056 | B64: Support | C64: Report an issue | D64: COMPLETED | E64: 8 | F64: TC-SUP-001, TC-SUP-002, TC-SUP-003, TC-SUP-004, TC-SUP-011, TC-FLD-100, TC-FLD-101, TC-FLD-103
A65: GS-057 | B65: Support | C65: Returns/refunds | D65: COMPLETED (2-Oct) | E65: 20 | F65: TC-COD-011, TC-RET-001, TC-RET-002, TC-RET-003, TC-RET-004, TC-RET-005, TC-RET-006, TC-RET-010, TC-RET-011, TC-RET-013, TC-RET-014, TC-RET-015, TC-RET-016, TC-RET-017, TC-FLD-094, TC-FLD-095, TC-FLD-096, TC-FLD-097, TC-FLD-098, TC-SPI-020
A66: GS-058 | B66: Support | C66: Dispute management | D66: IN PROGRESS | E66: 2 | F66: TC-RET-020, TC-SUP-013 | G66: Part not built: Dispute case lifecycle with escalation; grievance states TRIAGED / INVESTIGATING / RESOLUTION_PROPOSED / ESCALATED
A67: RBAC-011 | B67: Security | C67: Refund approval | D67: COMPLETED | E67: 6 | F67: TC-RET-017, TC-RET-018, TC-RET-019, TC-FLD-098, TC-FLD-099, TC-PAY-030
A68: WF-007 | B68: Support | C68: Return/refund | D68: COMPLETED (2-Oct) | E68: 6 | F68: TC-RET-007, TC-RET-008, TC-RET-009, TC-RET-010, TC-RET-012, TC-RET-022 | G68: Part not built: Replacement instead of refund
A69: NAV-004 | B69: Customer | C69: Customer portal - Orders | D69: IN PROGRESS | E69: 3 | F69: TC-RET-001, TC-RET-021, TC-SPI-006 | G69: Part not built: Customer / operations live-tracking screen
A70: GS-061 | B70: Finance | C70: Shop commission | D70: COMPLETED | E70: 6 | F70: TC-FIN-001, TC-FIN-002, TC-FIN-003, TC-FLD-111, TC-SPI-014, TC-CART-029
A71: GS-062 | B71: Finance | C71: Shop settlement | D71: COMPLETED | E71: 6 | F71: TC-ORD-014, TC-FIN-006, TC-FIN-007, TC-FIN-008, TC-FIN-009, TC-FLD-118
A72: GS-063 | B72: Finance | C72: Gig earnings | D72: COMPLETED (2-Oct) | E72: 8 | F72: TC-FIN-011, TC-FIN-012, TC-FIN-013, TC-FIN-014, TC-FIN-015, TC-FIN-016, TC-FIN-017, TC-FLD-115
A73: GS-064 | B73: Finance | C73: Gig payout | D73: COMPLETED | E73: 4 | F73: TC-COD-010, TC-FIN-019, TC-FLD-116, TC-DEL-029
A74: WF-010 | B74: Finance | C74: Settlement | D74: COMPLETED | E74: 7 | F74: TC-FIN-004, TC-FIN-005, TC-FIN-020, TC-FIN-024, TC-FIN-025, TC-FIN-026, TC-SPI-014
A75: RBAC-012 | B75: Security | C75: Settlement visibility | D75: COMPLETED | E75: 3 | F75: TC-RBAC-020, TC-FIN-009, TC-FIN-027
A76: NAV-010 | B76: Shop | C76: Shop portal - Finance | D76: COMPLETED | E76: 1 | F76: TC-FIN-010
A77: NAV-012 | B77: Gig | C77: Gig portal - Earnings | D77: COMPLETED | E77: 1 | F77: TC-FIN-018
A78: WF-006 | B78: Subscription | C78: Subscription | D78: COMPLETED | E78: 2 | F78: TC-SUB-002, TC-SUB-013
A79: GS-065 | B79: Admin | C79: Global dashboard | D79: COMPLETED (2-Oct) | E79: 3 | F79: TC-ADM-001, TC-ADM-002, TC-SPI-028
A80: GS-066 | B80: Admin | C80: Operator console | D80: COMPLETED (2-Oct) | E80: 1 | F80: TC-ADM-003
A81: NAV-015 | B81: Operator | C81: Operator portal - Operations | D81: COMPLETED (2-Oct) | E81: 3 | F81: TC-FIN-023, TC-ADM-003, TC-ADM-021
... A83: NAV-017 | B83: Admin | C83: Admin portal - Control Tower | D83: COMPLETED (2-Oct) | E83: 1 | F83: TC-ADM-001
A84: NAV-019 | B84: Admin | C84: Admin portal - Security | D84: IN PROGRESS | E84: 1 | F84: TC-ADM-019 | G84: Part not built: Operations consent view
A85: GS-069 | B85: Analytics | C85: Marketplace KPI dashboard | D85: COMPLETED | E85: 3 | F85: TC-KPI-001, TC-KPI-002, TC-KPI-013
A86: KPI-001 | B86: Analytics | C86: GMV | D86: COMPLETED | E86: 2 | F86: TC-FIN-024, TC-KPI-003
A87: KPI-002 | B87: Analytics | C87: Order fill rate | D87: COMPLETED | E87: 1 | F87: TC-KPI-004
A88: KPI-003 | B88: Analytics | C88: Shop acceptance time | D88: COMPLETED | E88: 1 | F88: TC-KPI-005
A89: KPI-004 | B89: Analytics | C89: Pick-pack time | D89: COMPLETED | E89: 1 | F89: TC-KPI-005
A90: KPI-005 | B90: Analytics | C90: Assignment time | D90: COMPLETED | E90: 1 | F90: TC-KPI-006
A91: KPI-006 | B91: Analytics | C91: Delivery time | D91: COMPLETED | E91: 1 | F91: TC-KPI-006
A92: KPI-007 | B92: Analytics | C92: On-time delivery rate | D92: COMPLETED | E92: 1 | F92: TC-KPI-007
A93: KPI-008 | B93: Analytics | C93: Cancellation rate | D93: COMPLETED | E93: 1 | F93: TC-KPI-008
A94: KPI-009 | B94: Analytics | C94: Refund rate | D94: COMPLETED | E94: 1 | F94: TC-KPI-008
A95: KPI-010 | B95: Analytics | C95: Customer repeat rate | D95: COMPLETED | E95: 1 | F95: TC-KPI-009
A96: KPI-011 | B96: Analytics | C96: Subscription retention | D96: COMPLETED | E96: 1 | F96: TC-KPI-010
... A177: AI-006 | B177: App install & updates | C177: Native app update check (Android / iPhone 1.5.0) | D177: BUILT 31-Oct | E177: 2 | F177: TC-APP-011, TC-APP-012

Sheet Not yet testable
A1: Feature IDs | B1: What is missing | C1: Why | D1: What this suite does instead
A2: GS-042 / NAV-004 | B2: Customer / operations live-tracking screen | C2: Component exists but is not mounted; nothing posts rider location | D2: Tracking API privacy is tested; record that no screen exists.
A3: GS-041 / GS-043 | B3: QR pickup variant; signature proof of delivery | C3: Not built | D3: Code-based pickup, OTP delivery and photo proof are tested.
A4: GA-009 | B4: Radius widening when no rider is found | C4: Not built | D4: Bounded retry search is tested.
A5: WF-007 | B5: Replacement instead of refund | C5: Not built | D5: Refund path is tested.
A6: NAV-019 | B6: Operations consent view | C6: Reported not built (a /admin/consents route exists) | D6: Record what the page shows.
A7: RBAC-003 | B7: Operator 'Limited' shop management | C7: Scope not defined | D7: Record current operator behaviour as evidence for the decision.
A8: GS-067 | B8: Dedicated Auditor role | C8: Optional, not built | D8: Admin / operator audit views are tested.
A9: GS-036 | B9: Pick-pack SLA reporting | C9: Not built | D9: Pick-pack time KPI is tested.
A10: GS-044 | B10: Map pin picker on the society form | C10: Not built | D10: PIN-based matching is tested.

Sheet Test data
A1: Kind | B1: Item | C1: What is needed | D1: Used by
A2: Account | B2: ADMIN | C2: One admin account on test. | D2: All admin cases
A3: Account | B3: OPERATOR | C3: One operator. | D3: Verification, refunds, exceptions, risk
A4: Account | B4: SHOP_OWNER A | C4: Approved, delivering, pinned location, radius 5 km, COD off to start. Sells 3+ products with stock >= 20 incl. one packaged product with a verified MRP and one subscribable milk product at Rs 70/L. | D4: Most order cases
A5: Account | B5: SHOP_OWNER B | C5: Approved, same PIN as A, sells at least one of the same master products at a different price. One offline-only product. | D5: Comparison, multi-shop cart, IDOR
A6: Account | B6: CUSTOMER 1 | C6: Mobile linked, default address with coordinates inside Shop A's radius, wallet >= Rs 2,000, marketing consent on. | D6: Ordering
A7: Account | B7: CUSTOMER 2 | C7: Email-only, no mobile, an address outside Shop A's radius. | D7: IDOR, onboarding prompts, serviceability
A8: Account | B8: RIDER 1 | C8: Approved delivery partner, online, location pinned near Shop A. | D8: Dispatch and delivery
A9: Account | B9: RIDER 2 | C9: Approved, online, farther away. | D9: Ranking, decline/re-offer
A10: Account | B10: SOCIETY ADMIN | C10: Admin of one verified society whose address is inside Shop A's zone. | D10: Society cases
A11: Account | B11: New sign-ups | C11: 3 unused email inboxes that can be read during the run and 2 unused Indian mobile numbers. | D11: Login cases
A12: Config | B12: SMTP | C12: AUTH_EMAIL_FROM and AUTH_EMAIL_SERVER set on test. | D12: OTP and email cases
... A30: Account | B30: New shop for the state path | C30: One unapproved shop registration to take through KYC_PENDING to ACTIVE; shortened accept timeout in /admin/settings. | D30: Shop state and accept-timeout cases
