Workbook

Sheet Inventory
A1: ID | B1: Module | C1: Feature | D1: Frontend | E1: Backend | F1: Database | G1: API | H1: Status | I1: Working? | J1: Location | K1: Notes
A2: AUTH-01 | B2: Authentication | C2: Google OAuth sign-in (Auth.js v5, Drizzle adapter) | D2: Yes | E2: Yes | F2: Yes | G2: Yes | H2: EXISTING_WORKING | I2: Yes in use on hosted envs; not automatable here | J2: src/server/auth.ts; /signin; /api/auth/[...nextauth] | K2: JWT sessions (30 d) - older docs still say database sessions. New user => CUSTOMER role + wallet + TERMS_AND_PRIVACY consent. Providers probe 2026-09-22: hosted test and live expose only 'google'.
A3: AUTH-02 | B3: Authentication | C3: Dev/test credentials sign-in (email only) | D3: Yes | E3: Yes | F3: Yes | G3: Yes | H3: EXISTING_WORKING | I3: Yes - code-verified only (no dedicated test) | J3: src/server/auth.ts:47-87 | K3: Disabled when NODE_ENV=production (provider list and authorize()). Verified absent on test.gokesari.com and gokesari.com.
A4: AUTH-03 | B4: Authentication | C4: Role and status re-read from DB on every request; suspended/deleted accounts get no session | D4: n/a | E4: Yes | F4: Yes | G4: n/a | H4: EXISTING_WORKING | I4: Yes - automated tests pass | J4: src/server/auth.ts:109-157; src/server/authz/guards.ts:25-36 | K4: Stale JWT cannot keep old privileges.
A5: AUTH-04 | B5: Authentication | C5: Bootstrap admin (BOOTSTRAP_ADMIN_EMAILS + two permanent emails in source) | D5: n/a | E5: Yes | F5: Yes | G5: n/a | H5: EXISTING_PARTIAL | I5: Yes - code-verified only (no dedicated test) | J5: src/lib/env.ts:137-158; src/server/auth.ts:139-148 | K5: Works, but two personal admin emails are hard-coded and re-promoted to ADMIN on every session (finding SEC-03).
A6: AUTH-05 | B6: Authentication | C6: Phone number capture / OTP verification | D6: No | E6: No | F6: Partial | G6: No | H6: MISSING | I6: n/a - not built | J6: users.phone (nullable, unverified) | K6: No SMS/OTP provider exists anywhere in the codebase.
A7: AUTH-06 | B7: Authentication | C7: Profile page (name, email, role, addresses link, sign-out, notification list) | D7: Yes | E7: Partial | F7: Yes | G7: No | H7: EXISTING_PARTIAL | I7: Yes - code-verified only (no dedicated test) | J7: src/app/profile/page.tsx | K7: Read-only: no API/UI to edit name or phone. Notification list is shown here (no bell, no mark-read control).
A8: RBAC-01 | B8: RBAC | C8: Server-side capability matrix: 5 roles (CUSTOMER, SHOP_OWNER, OPERATOR, ADMIN, DELIVERY_PARTNER), ~76 permissions | D8: n/a | E8: Yes | F8: Yes | G8: Yes | H8: EXISTING_WORKING | I8: Yes - automated tests pass | J8: src/server/authz/permissions.ts | K8: 27 permissions are never referenced by name outside the matrix (ownership or role logic enforces some; some are unused).
A9: RBAC-02 | B9: RBAC | C9: Ownership guards (requireShopAccess, requireSubscriptionAccess) - IDOR protection | D9: n/a | E9: Yes | F9: Yes | G9: Yes | H9: EXISTING_PARTIAL | I9: Partly - see notes | J9: src/server/authz/guards.ts:83-122 | K9: Blocks a genuine cross-user IDOR (a different user's shop/subscription) - that part works and is tested. But 'capability and ownership are both checked' is not true for requireShopAccess's OWNER branch: it returns as soon as shop.ownerId matches, before any can() call, so role demotion and shop suspension do not revoke a shop owner's own write access (finding SEC-06, found on Opus review 2026-09-22).
A10: RBAC-03 | B10: RBAC | C10: Admin sets a user's role | D10: Yes | E10: Yes | F10: Yes | G10: Yes | H10: EXISTING_WORKING | I10: Yes - automated tests pass | J10: /api/users/[id]/role; src/components/user-role-manager.tsx | K10: Role never accepted from a request body except this ADMIN route.
A11: RBAC-04 | B11: RBAC | C11: roles / permissions / role_permissions tables | D11: n/a | E11: Partial | F11: Yes | G11: n/a | H11: EXISTING_PARTIAL | I11: Yes - code-verified only (no dedicated test) | J11: src/server/db/schema.ts:465-487; src/server/db/seed.ts | K11: Seeded mirror for reporting only; runtime checks use the in-code matrix.
A12: RBAC-05 | B12: RBAC | C12: Suspend a user account | D12: No | E12: Partial | F12: Yes | G12: No | H12: EXISTING_PLACEHOLDER | I12: Service layer only - tested, but no API route or UI reaches it | J12: USER_SUSPEND permission (unused); auth.ts honours status=SUSPENDED | K12: No route or screen sets a user to SUSPENDED.
A13: RBAC-06 | B13: RBAC | C13: Shop Staff role (sub-users of a shop) | D13: No | E13: No | F13: No | G13: No | H13: MISSING | I13: n/a - not built | J13: - | K13: Only the shop owner can act for a shop.
A14: RBAC-07 | B14: RBAC | C14: Society Administrator role | D14: No | E14: No | F14: No | G14: No | H14: MISSING | I14: n/a - not built | J14: -
A15: RBAC-08 | B15: RBAC | C15: Super Admin role | D15: No | E15: No | F15: No | G15: No | H15: MISSING | I15: n/a - not built | J15: - | K15: ADMIN is the highest role today; decide whether a distinct role is really required.
A16: RBAC-09 | B16: RBAC | C16: System configuration UI (SYSTEM_CONFIG) | D16: No | E16: No | F16: No | G16: No | H16: EXISTING_PLACEHOLDER | I16: n/a - not built | J16: SYSTEM_CONFIG permission (unused) | K16: Only registration-fee and delivery-earnings configuration screens exist.
A17: CUS-01 | B17: Customer | C17: Address book: create/edit/delete, default, landmark, delivery instructions | D17: Yes | E17: Yes | F17: Yes | G17: Yes | H17: EXISTING_WORKING | I17: Yes - automated tests pass | J17: /profile/addresses; /api/addresses*; src/server/services/addresses.ts
A18: CUS-02 | B18: Customer | C18: Map picker + Google Geocoding (verify once, store coordinates) | D18: Yes | E18: Yes | F18: Yes | G18: Yes | H18: EXISTING_WORKING | I18: Yes - automated tests pass | J18: src/components/map-picker.tsx; /api/geo/verify-location; geocoding.ts | K18: Needs Google keys; falls back to manual entry. Tests stub fetch.
A19: CUS-03 | B19: Customer | C19: Society / block / flat on an address | D19: No | E19: No | F19: No | G19: No | H19: MISSING | I19: n/a - not built | J19: addresses table has line1/line2/area/landmark only
A20: CUS-04 | B20: Customer | C20: Browse categories and department pages | D20: Yes | E20: Yes | F20: Yes | G20: Yes | H20: EXISTING_WORKING | I20: Yes - code-verified only (no dedicated test) | J20: /categories; /category/[type]; /dairy; /bakery | K20: Not covered by an automated UI test; Playwright suite was not runnable here.
A21: CUS-05 | B21: Customer | C21: Shop discovery: list and filter by city, area, PIN, type, classification, delivery | D21: Yes | E21: Yes | F21: Yes | G21: Yes | H21: EXISTING_WORKING | I21: Yes - code-verified only (no dedicated test) | J21: /shops; GET /api/shops; shops.ts:679-718 | K21: Text/PIN filters only.
A22: CUS-06 | B22: Customer | C22: Nearby shops by customer location / sort by distance | D22: No | E22: No | F22: Partial | G22: No | H22: MISSING | I22: n/a - not built | J22: shops.latitude/longitude exist | K22: searchShops has no geospatial filter or ordering (orders by name).
A23: CUS-07 | B23: Customer | C23: Shop storefront page with catalogue | D23: Yes | E23: Yes | F23: Yes | G23: Yes | H23: EXISTING_WORKING | I23: Yes - code-verified only (no dedicated test) | J23: /shops/[slug]; catalogue.ts:listStorefrontProducts
A24: CUS-08 | B24: Customer | C24: Unified search (products, shops, area, PIN) | D24: Yes | E24: Yes | F24: Yes | G24: Yes | H24: EXISTING_WORKING | I24: Yes - code-verified only (no dedicated test) | J24: /search; catalogue.ts:867-947 | K24: ILIKE substring match; no relevance ranking, typo tolerance or synonyms.
A25: CUS-09 | B25: Customer | C25: Product detail page | D25: No | E25: No | F25: Yes | G25: No | H25: MISSING | I25: n/a - not built | J25: - | K25: Product cards only; no /product/[id] page.
A26: CUS-10 | B26: Customer | C26: All shops selling one product + local price comparison | D26: No | E26: Partial | F26: Yes | G26: No | H26: EXISTING_PARTIAL | I26: Partly - see notes | J26: products <-> shop_products (GTIN partial-unique) | K26: Data supports it; search returns one row per shop-product, ungrouped, no sort by price/distance/ETA and no comparison view.
A27: CUS-11 | B27: Customer | C27: External e-commerce price references | D27: No | E27: Partial | F27: Yes | G27: Partial | H27: EXISTING_PARTIAL | I27: Partly - see notes | J27: pmd.offers, price history; /api/product-master/products/[id]/offers | K27: Staff-only. Open data only; every marketplace source is BLOCKED_NEEDS_AGREEMENT by policy (no scraping). Not shown to customers.
A28: CUS-12 | B28: Customer | C28: Cart: multi-shop grouping, live prices, purchasable flag, per-shop delivery fee | D28: Yes | E28: Yes | F28: Yes | G28: Yes | H28: EXISTING_WORKING | I28: Yes - automated tests pass | J28: /cart; /api/cart*; cart.ts
A29: CUS-13 | B29: Customer | C29: Checkout: wallet-paid, one order per shop, idempotent requestId, atomic stock + debit | D29: Yes | E29: Yes | F29: Yes | G29: Yes | H29: EXISTING_WORKING | I29: Yes - automated tests pass | J29: POST /api/checkout; orders.ts:113-307 | K29: Wallet is the only payment instrument (see PAY-06).
A30: CUS-14 | B30: Customer | C30: Delivery window at checkout (Express 30 / Standard 60 / Scheduled) with live feasibility | D30: Yes | E30: Yes | F30: Yes | G30: Yes | H30: EXISTING_WORKING | I30: Yes - automated tests pass | J30: GET /api/checkout/delivery-windows; delivery-feasibility.ts | K30: 'SCHEDULED' carries no date/time slot. Feasibility treats only ACCEPTED as busy (DEF-05).
A31: CUS-15 | B31: Customer | C31: Serviceability check (address inside shop's delivery reach) | D31: No | E31: No | F31: No | G31: No | H31: MISSING | I31: n/a - not built | J31: - | K31: Only rider availability is checked; shops have a delivery on/off flag but no radius or area.
A32: CUS-16 | B32: Customer | C32: Order history list | D32: Yes | E32: Yes | F32: Yes | G32: Yes | H32: EXISTING_WORKING | I32: Yes - code-verified only (no dedicated test) | J32: /orders; GET /api/orders
A33: CUS-17 | B33: Customer | C33: Order detail / live tracking (timeline, rider, ETA, map) | D33: No | E33: Partial | F33: Yes | G33: No | H33: MISSING | I33: n/a - not built | J33: order_status_history table; orders.ts:getOrder (no caller) | K33: No GET /api/orders/[id] and no detail page; rider location is stored but never shown to customers.
A34: CUS-18 | B34: Customer | C34: Cancel order with automatic wallet refund (idempotent) | D34: Yes | E34: Yes | F34: Yes | G34: Yes | H34: EXISTING_PARTIAL | I34: Partly - see notes | J34: PATCH /api/orders/[id]/status; orders.ts:372-441 | K34: Does NOT return stock (finding DEF-01). More significantly: has NO cancellation policy at all - a customer can cancel their own order from any pre-terminal status including OUT_FOR_DELIVERY, no time window, no fee, and ORDER_CANCEL_OWN is defined but never actually enforced anywhere (finding DEF-08, found on Opus review 2026-09-22). The refund includes the delivery fee, and an active rider assignment is orphaned rather than cancelled or reassigned.
A35: CUS-19 | B35: Customer | C35: Refund / return / replacement request | D35: No | E35: No | F35: No | G35: No | H35: MISSING | I35: n/a - not built | J35: - | K35: Refund exists only as the automatic result of a cancellation.
A36: CUS-20 | B36: Customer | C36: Ratings and reviews (shop, gig worker, product) | D36: No | E36: No | F36: No | G36: No | H36: MISSING | I36: n/a - not built | J36: -
A37: CUS-21 | B37: Customer | C37: Vouchers: wallet top-up bonus (code or auto-apply, budgets, redemption ledger) | D37: Yes | E37: Yes | F37: Yes | G37: Yes | H37: EXISTING_WORKING | I37: Yes - automated tests pass | J37: vouchers.ts; /api/vouchers*; voucher-manager.tsx | K37: Applies to wallet top-ups, not to order totals.
A38: CUS-22 | B38: Customer | C38: Coupons / discounts applied at checkout | D38: No | E38: No | F38: No | G38: No | H38: MISSING | I38: n/a - not built | J38: -
A39: CUS-23 | B39: Customer | C39: Customer referral programme | D39: No | E39: No | F39: No | G39: No | H39: MISSING | I39: n/a - not built | J39: - | K39: referral_codes exist but attribute SHOPS to operator-managed codes.
A40: CUS-24 | B40: Customer | C40: Grievance / complaint form and public ticket lookup (IT Rules 2021) | D40: Yes | E40: Yes | F40: Yes | G40: Yes | H40: EXISTING_WORKING | I40: Yes - automated tests pass | J40: /grievance; /api/grievances* | K40: A compliance register, not an order-linked helpdesk or chat.
A41: CUS-25 | B41: Customer | C41: In-app notifications | D41: Partial | E41: Yes | F41: Yes | G41: Yes | H41: EXISTING_PARTIAL | I41: Partly - see notes | J41: notifications.ts; GET/PATCH /api/notifications; /profile | K41: Listed on the profile page only. EMAIL/SMS/PUSH transports are console stubs (INF-09). Almost no events emit notifications (DEF-02).
A42: CUS-26 | B42: Customer | C42: Consent records (T&C at sign-up; marketing consent) | D42: Partial | E42: Yes | F42: Yes | G42: No | H42: EXISTING_PARTIAL | I42: Partly - see notes | J42: consents.ts; user_consents | K42: MARKETING_COMMUNICATIONS type has no capture UI, and consent history is not exposed to the user.
A43: CUS-27 | B43: Customer | C43: Legal and policy pages (terms, privacy, refund, shipping, seller, subscription, voucher, wallet, cookie, grievance) | D43: Yes | E43: n/a | F43: n/a | G43: n/a | H43: EXISTING_WORKING | I43: Yes - code-verified only (no dedicated test) | J43: /legal/*
A44: SHP-01 | B44: Shop | C44: Shop self-registration (44 shop types); owner promoted to SHOP_OWNER | D44: Yes | E44: Yes | F44: Yes | G44: Yes | H44: EXISTING_WORKING | I44: Yes - automated tests pass | J44: /shop/register; POST /api/shops; shops.ts:76
A45: SHP-02 | B45: Shop | C45: Operator/admin registers a shop on behalf of an owner | D45: No | E45: Yes | F45: Yes | G45: Yes | H45: EXISTING_PARTIAL | I45: Partly - see notes | J45: POST /api/shops with ownerId (privileged) | K45: API only - no operator 'Add shop' form (RBAC_PLAN 'Not built').
A46: SHP-03 | B46: Shop | C46: Approve / reject shop; Kesari-Green classification with immutable history | D46: Yes | E46: Yes | F46: Yes | G46: Yes | H46: EXISTING_WORKING | I46: Yes - automated tests pass | J46: shop-approval-panel.tsx; /api/shops/[id]/approve|reject|classification
A47: SHP-04 | B47: Shop | C47: Suspend / reactivate a shop | D47: No | E47: Yes | F47: Yes | G47: No | H47: EXISTING_PLACEHOLDER | I47: Service layer only - tested, but no API route or UI reaches it | J47: shops.ts:430 setShopStatus (no caller); SHOP_SUSPEND unused
A48: SHP-05 | B48: Shop | C48: Shop profile & settings: hours, delivery flag/fee, free-delivery threshold, prep time, description, logo URL | D48: Yes | E48: Yes | F48: Yes | G48: Yes | H48: EXISTING_WORKING | I48: Yes - code-verified only (no dedicated test) | J48: shop-settings-form.tsx; PATCH /api/shops/[id]
A49: SHP-06 | B49: Shop | C49: Shop location: geocode-verified main location + separate pickup point | D49: Yes | E49: Yes | F49: Yes | G49: Yes | H49: EXISTING_WORKING | I49: Yes - automated tests pass | J49: shop-location-settings-form.tsx; geocoding.ts
A50: SHP-07 | B50: Shop | C50: Service radius / delivery area per shop | D50: No | E50: No | F50: No | G50: No | H50: MISSING | I50: n/a - not built | J50: - | K50: Radius exists only per delivery partner.
A51: SHP-08 | B51: Shop | C51: Holidays / special closures | D51: No | E51: No | F51: No | G51: No | H51: MISSING | I51: n/a - not built | J51: lib/shop-hours.ts (weekly hours only)
A52: SHP-09 | B52: Shop | C52: GST and PAN self-service submission + operator verification (PAN AES-256-GCM) | D52: Yes | E52: Yes | F52: Yes | G52: Yes | H52: EXISTING_WORKING | I52: Yes - automated tests pass | J52: /api/shops/[id]/gst|pan; gst-pan-verification.ts; pan-crypto.ts | K52: No automated GST/PAN provider - verification is manual.
A53: SHP-10 | B53: Shop | C53: Seller compliance fields (legal name, GSTIN, FSSAI, return policy) | D53: Yes | E53: Yes | F53: Yes | G53: Yes | H53: EXISTING_WORKING | I53: Yes - code-verified only (no dedicated test) | J53: /api/shops/[id]/compliance; shop-compliance-manager.tsx
A54: SHP-11 | B54: Shop | C54: KYC / document / image file upload | D54: No | E54: No | F54: No | G54: No | H54: MISSING | I54: n/a - not built | J54: - | K54: No file storage anywhere; logos, photos and product images are URL strings.
A55: SHP-12 | B55: Shop | C55: Staff accounts for a shop | D55: No | E55: No | F55: No | G55: No | H55: MISSING | I55: n/a - not built | J55: -
A56: SHP-13 | B56: Shop | C56: Registration fee schedule; immutable shop-payment ledger with reversal; fee report | D56: Yes | E56: Yes | F56: Yes | G56: Yes | H56: EXISTING_WORKING | I56: Yes - automated tests pass | J56: registration-fees.ts; shop-payments.ts; shop-finance-manager.tsx | K56: No CSV/XLSX export of the fee report.
A57: SHP-14 | B57: Shop | C57: Referral codes: create, attribute shops, performance | D57: Yes | E57: Yes | F57: Yes | G57: Yes | H57: EXISTING_WORKING | I57: Yes - code-verified only (no dedicated test) | J57: referrals.ts; /api/referral-codes; referral-manager.tsx | K57: No dedicated test. Codes cannot be edited or deactivated from the UI (updateReferralCode has no caller).
A58: SHP-15 | B58: Shop | C58: Shop order queue: view, advance status, cancel | D58: Yes | E58: Yes | F58: Yes | G58: Yes | H58: EXISTING_WORKING | I58: Partly - see notes | J58: /shop/orders; shop-order-manager.tsx; PATCH /api/orders/[id]/status | K58: Service logic tested; HTTP route and screen untested.
A59: SHP-16 | B59: Shop | C59: Accept / reject an incoming order | D59: No | E59: No | F59: No | G59: No | H59: MISSING | I59: n/a - not built | J59: - | K59: Paid orders arrive as CONFIRMED; the shop can only move them to PREPARING or cancel.
A60: SHP-17 | B60: Shop | C60: New-order alert to the shop | D60: No | E60: No | F60: Yes | G60: No | H60: EXISTING_PLACEHOLDER | I60: No - see notes | J60: NOTIFICATION_TYPES has no 'new order' type | K60: The shop must refresh /shop/orders to notice a new order (DEF-02).
A61: SHP-18 | B61: Shop | C61: Stock check / substitution / partial fulfilment at pick | D61: No | E61: No | F61: No | G61: No | H61: MISSING | I61: n/a - not built | J61: -
A62: SHP-19 | B62: Shop | C62: Request a delivery partner for a READY order (manual click) | D62: Yes | E62: Yes | F62: Yes | G62: Yes | H62: EXISTING_WORKING | I62: Yes - automated tests pass | J62: POST /api/orders/[id]/assign; shop-order-manager.tsx:89 | K62: Not automatic on READY.
A63: SHP-20 | B63: Shop | C63: Shop sales / earnings reports | D63: No | E63: No | F63: Partial | G63: No | H63: EXISTING_PLACEHOLDER | I63: n/a - not built | J63: REPORT_VIEW_SHOP unused; /shop has no sales panel
A64: CAT-01 | B64: Catalogue | C64: Master catalogue: categories per shop type, subcategories, brands, products | D64: Yes | E64: Yes | F64: Yes | G64: Yes | H64: EXISTING_WORKING | I64: Yes - automated tests pass | J64: products, product_categories, brands; seed.ts
A65: CAT-02 | B65: Catalogue | C65: Shop offering with independent online/offline price and stock (DB CHECK-guarded) | D65: Yes | E65: Yes | F65: Yes | G65: Yes | H65: EXISTING_WORKING | I65: Yes - automated tests pass | J65: shop_products; catalogue.ts; shop-product-manager.tsx
A66: CAT-03 | B66: Catalogue | C66: Shop-created product with duplicate suggestion + admin approval before other shops see it | D66: Yes | E66: Yes | F66: Yes | G66: Yes | H66: EXISTING_WORKING | I66: Yes - automated tests pass | J66: POST /api/products; add-product-panel.tsx; product-approval-queue.tsx
A67: CAT-04 | B67: Catalogue | C67: Map shop product to master (suggestions by shop type, catalogue search) | D67: Yes | E67: Yes | F67: Yes | G67: Yes | H67: EXISTING_WORKING | I67: Yes - automated tests pass | J67: /api/shops/[id]/catalogue-search; /api/shops/[id]/products
A68: CAT-05 | B68: Catalogue | C68: Excel bulk upload of goods and prices: validate -> preview -> apply, formula-injection sanitising | D68: Yes | E68: Yes | F68: Yes | G68: Yes | H68: EXISTING_WORKING | I68: Yes - automated tests pass | J68: excel.ts; /api/excel-uploads; excel-price-upload.tsx | K68: XLSX via ExcelJS. CSV upload not verified.
A69: CAT-06 | B69: Catalogue | C69: Price-change approval (operator proposes, owner approves, admin override) | D69: Yes | E69: Yes | F69: Yes | G69: Yes | H69: EXISTING_WORKING | I69: Yes - automated tests pass | J69: price-requests.ts; pending-price-approvals.tsx
A70: CAT-07 | B70: Catalogue | C70: Product identity: GTIN (EAN/UPC folded in), HSN, GST rate, MRP + provenance, manufacturer, origin, net quantity | D70: No | E70: Yes | F70: Yes | G70: No | H70: EXISTING_PARTIAL | I70: Service layer only - tested, but no API route or UI reaches it | J70: products table (migration 0014); product-master.ts | K70: POST /api/products accepts only 'specifications'. Values arrive only through Product Master promotion. Owners/operators cannot enter or edit them.
A71: CAT-08 | B71: Catalogue | C71: Master MRP governance: set MRP, dispute/correction request, history | D71: No | E71: Yes | F71: Yes | G71: No | H71: EXISTING_PARTIAL | I71: Service layer only - tested, but no API route or UI reaches it | J71: product-master.ts setMasterMrp/submitMrpCorrection/getMrpHistory (no callers)
A72: CAT-09 | B72: Catalogue | C72: Brand and category management | D72: No | E72: Yes | F72: Yes | G72: No | H72: EXISTING_PLACEHOLDER | I72: Service layer only - tested, but no API route or UI reaches it | J72: brands.ts createBrand/updateBrand; catalogue.ts createCategory (no callers) | K72: Brands arrive via promotion, categories via seed.
A73: CAT-10 | B73: Catalogue | C73: Product images (URL string; product_images gallery table) | D73: Partial | E73: Partial | F73: Yes | G73: Partial | H73: EXISTING_PARTIAL | I73: Partly - see notes | J73: products.image_url; product_images | K73: No upload/storage. Gallery table has no UI.
A74: CAT-11 | B74: Catalogue | C74: Specifications (free text) | D74: Yes | E74: Yes | F74: Yes | G74: Yes | H74: EXISTING_WORKING | I74: Yes - code-verified only (no dedicated test) | J74: products.specifications
A75: INV-01 | B75: Inventory | C75: Online/offline stock; conditional-UPDATE consume; movement ledger | D75: Yes | E75: Yes | F75: Yes | G75: Yes | H75: EXISTING_WORKING | I75: Yes - automated tests pass | J75: catalogue.ts:1067-1112; inventory_movements
A76: INV-02 | B76: Inventory | C76: Return stock when an order is cancelled or refunded | D76: n/a | E76: No | F76: Yes | G76: n/a | H76: EXISTING_BROKEN | I76: No - see notes | J76: orders.ts:372-441 (no restock call); catalogue.ts:1114 restockOnline has no production caller | K76: Confirmed by code reading: cancelled paid orders keep the stock deducted (DEF-01). No test covers it.
A77: INV-03 | B77: Inventory | C77: Low-stock threshold, reorder level/quantity, min/max order quantity, stock alerts | D77: No | E77: Yes | F77: Yes | G77: No | H77: EXISTING_PARTIAL | I77: Service layer only - tested, but no API route or UI reaches it | J77: inventory-alerts.ts; stock_alerts; shop_products.* (migration 0014) | K77: No route or screen sets thresholds or lists alerts (zero references in src/app and src/components). notifyOpenStockAlerts is never called, so STOCK_LOW notifications never fire.
A78: ORD-01 | B78: Orders | C78: Order state machine with validated transitions, status history and audit | D78: Yes | E78: Yes | F78: Yes | G78: Yes | H78: EXISTING_WORKING | I78: Yes - automated tests pass | J78: orders.ts:46-62,311-365; order_status_history | K78: 11 states.
A79: ORD-02 | B79: Orders | C79: Multi-shop cart split into one independent order per shop | D79: Yes | E79: Yes | F79: Yes | G79: Yes | H79: EXISTING_WORKING | I79: Yes - automated tests pass | J79: orders.ts:147-304 | K79: Each order has its own wallet debit, fulfilment and refund.
A80: ORD-03 | B80: Orders | C80: Master (parent) order grouping the per-shop orders | D80: No | E80: No | F80: No | G80: No | H80: MISSING | I80: n/a - not built | J80: - | K80: Additive column/table needed; customer sees separate orders.
A81: ORD-04 | B81: Orders | C81: Idempotent checkout / duplicate-order protection | D81: Yes | E81: Yes | F81: Yes | G81: Yes | H81: EXISTING_WORKING | I81: Yes - automated tests pass | J81: orders.ts:113-165 (requestId + wallet idempotency key)
A82: ORD-05 | B82: Orders | C82: Target states: SHOP_PENDING, ACCEPTED, REJECTED, ASSIGNED, RETURNED, DISPUTED, PARTIALLY_REFUNDED | D82: No | E82: No | F82: No | G82: No | H82: MISSING | I82: n/a - not built | J82: order_status enum has PENDING, CONFIRMED, PREPARING, READY, OUT_FOR_DELIVERY, DELIVERED, CANCELLED, PAYMENT_FAILED, WALLET_INSUFFICIENT, REFUND_PENDING, REFUNDED
A83: ORD-06 | B83: Orders | C83: Manual confirmation of an unpaid order via the status endpoint | D83: n/a | E83: Yes | F83: Yes | G83: Yes | H83: EXISTING_BROKEN | I83: No - see notes | J83: orders.ts:46-49; api/orders/[id]/status/route.ts:20-27,53-56 | K83: A shop owner or operator can move WALLET_INSUFFICIENT / PAYMENT_FAILED / PENDING to CONFIRMED with no payment and no paidAt (DEF-06).
A84: ORD-07 | B84: Orders | C84: Tax calculation and tax invoice | D84: No | E84: No | F84: Partial | G84: No | H84: EXISTING_PLACEHOLDER | I84: No - see notes | J84: taxPaise hard-coded 0 in orders.ts:215, cart.ts:273,288, subscriptions.ts:957 | K84: Products carry hsn_code and gst_rate_bp but no order uses them. No invoice document.
A85: ORD-08 | B85: Orders | C85: Order-status notifications to the customer | D85: No | E85: No | F85: Yes | G85: No | H85: EXISTING_PLACEHOLDER | I85: No - see notes | J85: NOTIFICATION_TYPES.ORDER_* defined (notifications.ts:17-21), never emitted | K85: Only wallet-low-balance and stock notifications are emitted, and stock ones never fire (DEF-02).
A86: ORD-09 | B86: Orders | C86: Exception workflows (wrong address, customer unavailable, missing/wrong/damaged item, late delivery, shop rejection, no reply) | D86: No | E86: No | F86: No | G86: No | H86: MISSING | I86: n/a - not built | J86: - | K86: Only wallet-insufficient, payment-failed and cancel exist.
A87: ORD-10 | B87: Orders | C87: Cancellation policy by state/time | D87: Yes | E87: Partial | F87: Yes | G87: Yes | H87: EXISTING_PARTIAL | I87: Partly - see notes | J87: orders.ts:46-58 | K87: Cancel allowed until OUT_FOR_DELIVERY, always a full refund; no fees, cut-offs or reasons taxonomy.
A88: PAY-01 | B88: Payments | C88: Cashfree wallet top-up: create order -> client checkout -> server-side confirmation -> credit | D88: Yes | E88: Yes | F88: Yes | G88: Yes | H88: EXISTING_WORKING | I88: Yes - automated tests pass | J88: payments.ts; /api/wallet/topup|verify | K88: Only WALLET_TOPUP purpose exists.
A89: PAY-02 | B89: Payments | C89: Cashfree webhook: HMAC over raw body, idempotent, retry-safe | D89: n/a | E89: Yes | F89: Yes | G89: Yes | H89: EXISTING_WORKING | I89: Yes - automated tests pass | J89: /api/webhooks/cashfree | K89: Only PAYMENT_SUCCESS_WEBHOOK acts; failure/refund/dispute events are acknowledged and ignored.
A90: PAY-03 | B90: Payments | C90: Mock gateway for development/test (never in production) | D90: Yes | E90: Yes | F90: Yes | G90: Yes | H90: EXISTING_WORKING | I90: Yes - automated tests pass | J90: payments.ts:settleMockTopUp; /api/dev/settle-topup | K90: Route returns 404 when NODE_ENV=production or live keys present.
A91: PAY-04 | B91: Payments | C91: Duplicate-payment protection (unique gateway ids; conditional status UPDATE) | D91: n/a | E91: Yes | F91: Yes | G91: Yes | H91: EXISTING_WORKING | I91: Yes - automated tests pass | J91: schema.ts:1525-1526
A92: PAY-05 | B92: Payments | C92: Failed payment recorded; nothing credited | D92: n/a | E92: Yes | F92: Yes | G92: Yes | H92: EXISTING_WORKING | I92: Yes - automated tests pass | J92: payments.ts
A93: PAY-06 | B93: Payments | C93: Direct order payment at checkout (UPI / card / net banking) | D93: No | E93: No | F93: No | G93: No | H93: MISSING | I93: n/a - not built | J93: - | K93: Business-model difference: customers must top up a wallet first (decision D1).
A94: PAY-07 | B94: Payments | C94: Cash on delivery | D94: No | E94: No | F94: No | G94: No | H94: MISSING | I94: n/a - not built | J94: -
A95: PAY-08 | B95: Payments | C95: Gateway refund to source; partial refund | D95: No | E95: No | F95: Partial | G95: No | H95: MISSING | I95: n/a - not built | J95: payment_status has REFUNDED | K95: Refunds are wallet credits only.
A96: PAY-09 | B96: Payments | C96: Payment states AUTHORIZED / CAPTURED / RECONCILED / CHARGEBACK | D96: No | E96: No | F96: No | G96: No | H96: MISSING | I96: n/a - not built | J96: payment_status = CREATED, PENDING, SUCCESS, FAILED, REFUNDED
A97: PAY-10 | B97: Payments | C97: Gateway reconciliation and settlement reports | D97: No | E97: No | F97: No | G97: No | H97: MISSING | I97: n/a - not built | J97: -
A98: WAL-01 | B98: Wallet | C98: Wallet ledger: integer paise, FOR UPDATE, idempotency keys, CHECK balance >= 0 (concurrency-proven) | D98: Yes | E98: Yes | F98: Yes | G98: Yes | H98: EXISTING_WORKING | I98: Yes - automated tests pass | J98: wallet.ts; /api/wallet | K98: Concurrent debit, overdraw and ledger-contiguity tests.
A99: WAL-02 | B99: Wallet | C99: Promotional vs customer-funded split preserved through refunds | D99: Yes | E99: Yes | F99: Yes | G99: Yes | H99: EXISTING_WORKING | I99: Yes - automated tests pass | J99: wallet.ts:376-424
A100: WAL-03 | B100: Wallet | C100: Low-balance warning (subscription forecast) | D100: Yes | E100: Yes | F100: Yes | G100: Yes | H100: EXISTING_WORKING | I100: Yes - automated tests pass | J100: subscriptions.ts:1249 | K100: Emitted by the subscription engine only.
...

Sheet Summary
A1: Existing feature inventory - summary
A2: Counts are live formulas over the Inventory sheet (recalculated when the file is opened). The blue 'Snapshot' column is the value at generation time, for cross-checking.
A4: Status | B4: Count (formula) | C4: Snapshot | D4: Share (formula)
A5: EXISTING_WORKING | B5: =COUNTIF(Inventory!$H$2:$H$159,A5) | C5: 70 | D5: =B5/$B$10
A6: EXISTING_PARTIAL | B6: =COUNTIF(Inventory!$H$2:$H$159,A6) | C6: 22 | D6: =B6/$B$10
A7: EXISTING_BROKEN | B7: =COUNTIF(Inventory!$H$2:$H$159,A7) | C7: 2 | D7: =B7/$B$10
A8: EXISTING_PLACEHOLDER | B8: =COUNTIF(Inventory!$H$2:$H$159,A8) | C8: 11 | D8: =B8/$B$10
A9: MISSING | B9: =COUNTIF(Inventory!$H$2:$H$159,A9) | C9: 53 | D9: =B9/$B$10
A10: Total | B10: =SUM(B5:B9) | C10: 158
A11: Rows in Inventory (check) | B11: =COUNTA(Inventory!$A$2:$A$159)
A13: By module (formulas)
A14: Module | B14: EXISTING_WORKING | C14: EXISTING_PARTIAL | D14: EXISTING_BROKEN | E14: EXISTING_PLACEHOLDER | F14: MISSING | G14: Total
A15: Authentication | B15: =COUNTIFS(Inventory!$B$2:$B$159,$A15,Inventory!$H$2:$H$159,B$14) | C15: =COUNTIFS(Inventory!$B$2:$B$159,$A15,Inventory!$H$2:$H$159,C$14) | D15: =COUNTIFS(Inventory!$B$2:$B$159,$A15,Inventory!$H$2:$H$159,D$14) | E15: =COUNTIFS(Inventory!$B$2:$B$159,$A15,Inventory!$H$2:$H$159,E$14) | F15: =COUNTIFS(Inventory!$B$2:$B$159,$A15,Inventory!$H$2:$H$159,F$14) | G15: =SUM(B15:F15)
A16: RBAC | B16: =COUNTIFS(Inventory!$B$2:$B$159,$A16,Inventory!$H$2:$H$159,B$14) | C16: =COUNTIFS(Inventory!$B$2:$B$159,$A16,Inventory!$H$2:$H$159,C$14) | D16: =COUNTIFS(Inventory!$B$2:$B$159,$A16,Inventory!$H$2:$H$159,D$14) | E16: =COUNTIFS(Inventory!$B$2:$B$159,$A16,Inventory!$H$2:$H$159,E$14) | F16: =COUNTIFS(Inventory!$B$2:$B$159,$A16,Inventory!$H$2:$H$159,F$14) | G16: =SUM(B16:F16)
A17: Customer | B17: =COUNTIFS(Inventory!$B$2:$B$159,$A17,Inventory!$H$2:$H$159,B$14) | C17: =COUNTIFS(Inventory!$B$2:$B$159,$A17,Inventory!$H$2:$H$159,C$14) | D17: =COUNTIFS(Inventory!$B$2:$B$159,$A17,Inventory!$H$2:$H$159,D$14) | E17: =COUNTIFS(Inventory!$B$2:$B$159,$A17,Inventory!$H$2:$H$159,E$14) | F17: =COUNTIFS(Inventory!$B$2:$B$159,$A17,Inventory!$H$2:$H$159,F$14) | G17: =SUM(B17:F17)
A18: Shop | B18: =COUNTIFS(Inventory!$B$2:$B$159,$A18,Inventory!$H$2:$H$159,B$14) | C18: =COUNTIFS(Inventory!$B$2:$B$159,$A18,Inventory!$H$2:$H$159,C$14) | D18: =COUNTIFS(Inventory!$B$2:$B$159,$A18,Inventory!$H$2:$H$159,D$14) | E18: =COUNTIFS(Inventory!$B$2:$B$159,$A18,Inventory!$H$2:$H$159,E$14) | F18: =COUNTIFS(Inventory!$B$2:$B$159,$A18,Inventory!$H$2:$H$159,F$14) | G18: =SUM(B18:F18)
A19: Catalogue | B19: =COUNTIFS(Inventory!$B$2:$B$159,$A19,Inventory!$H$2:$H$159,B$14) | C19: =COUNTIFS(Inventory!$B$2:$B$159,$A19,Inventory!$H$2:$H$159,C$14) | D19: =COUNTIFS(Inventory!$B$2:$B$159,$A19,Inventory!$H$2:$H$159,D$14) | E19: =COUNTIFS(Inventory!$B$2:$B$159,$A19,Inventory!$H$2:$H$159,E$14) | F19: =COUNTIFS(Inventory!$B$2:$B$159,$A19,Inventory!$H$2:$H$159,F$14) | G19: =SUM(B19:F19)
A20: Inventory | B20: =COUNTIFS(Inventory!$B$2:$B$159,$A20,Inventory!$H$2:$H$159,B$14) | C20: =COUNTIFS(Inventory!$B$2:$B$159,$A20,Inventory!$H$2:$H$159,C$14) | D20: =COUNTIFS(Inventory!$B$2:$B$159,$A20,Inventory!$H$2:$H$159,D$14) | E20: =COUNTIFS(Inventory!$B$2:$B$159,$A20,Inventory!$H$2:$H$159,E$14) | F20: =COUNTIFS(Inventory!$B$2:$B$159,$A20,Inventory!$H$2:$H$159,F$14) | G20: =SUM(B20:F20)
A21: Orders | B21: =COUNTIFS(Inventory!$B$2:$B$159,$A21,Inventory!$H$2:$H$159,B$14) | C21: =COUNTIFS(Inventory!$B$2:$B$159,$A21,Inventory!$H$2:$H$159,C$14) | D21: =COUNTIFS(Inventory!$B$2:$B$159,$A21,Inventory!$H$2:$H$159,D$14) | E21: =COUNTIFS(Inventory!$B$2:$B$159,$A21,Inventory!$H$2:$H$159,E$14) | F21: =COUNTIFS(Inventory!$B$2:$B$159,$A21,Inventory!$H$2:$H$159,F$14) | G21: =SUM(B21:F21)
A22: Payments | B22: =COUNTIFS(Inventory!$B$2:$B$159,$A22,Inventory!$H$2:$H$159,B$14) | C22: =COUNTIFS(Inventory!$B$2:$B$159,$A22,Inventory!$H$2:$H$159,C$14) | D22: =COUNTIFS(Inventory!$B$2:$B$159,$A22,Inventory!$H$2:$H$159,D$14) | E22: =COUNTIFS(Inventory!$B$2:$B$159,$A22,Inventory!$H$2:$H$159,E$14) | F22: =COUNTIFS(Inventory!$B$2:$B$159,$A22,Inventory!$H$2:$H$159,F$14) | G22: =SUM(B22:F22)
A23: Wallet | B23: =COUNTIFS(Inventory!$B$2:$B$159,$A23,Inventory!$H$2:$H$159,B$14) | C23: =COUNTIFS(Inventory!$B$2:$B$159,$A23,Inventory!$H$2:$H$159,C$14) | D23: =COUNTIFS(Inventory!$B$2:$B$159,$A23,Inventory!$H$2:$H$159,D$14) | E23: =COUNTIFS(Inventory!$B$2:$B$159,$A23,Inventory!$H$2:$H$159,E$14) | F23: =COUNTIFS(Inventory!$B$2:$B$159,$A23,Inventory!$H$2:$H$159,F$14) | G23: =SUM(B23:F23)
A24: Subscriptions | B24: =COUNTIFS(Inventory!$B$2:$B$159,$A24,Inventory!$H$2:$H$159,B$14) | C24: =COUNTIFS(Inventory!$B$2:$B$159,$A24,Inventory!$H$2:$H$159,C$14) | D24: =COUNTIFS(Inventory!$B$2:$B$159,$A24,Inventory!$H$2:$H$159,D$14) | E24: =COUNTIFS(Inventory!$B$2:$B$159,$A24,Inventory!$H$2:$H$159,E$14) | F24: =COUNTIFS(Inventory!$B$2:$B$159,$A24,Inventory!$H$2:$H$159,F$14) | G24: =SUM(B24:F24)
A25: Delivery | B25: =COUNTIFS(Inventory!$B$2:$B$159,$A25,Inventory!$H$2:$H$159,B$14) | C25: =COUNTIFS(Inventory!$B$2:$B$159,$A25,Inventory!$H$2:$H$159,C$14) | D25: =COUNTIFS(Inventory!$B$2:$B$159,$A25,Inventory!$H$2:$H$159,D$14) | E25: =COUNTIFS(Inventory!$B$2:$B$159,$A25,Inventory!$H$2:$H$159,E$14) | F25: =COUNTIFS(Inventory!$B$2:$B$159,$A25,Inventory!$H$2:$H$159,F$14) | G25: =SUM(B25:F25)
A26: Society | B26: =COUNTIFS(Inventory!$B$2:$B$159,$A26,Inventory!$H$2:$H$159,B$14) | C26: =COUNTIFS(Inventory!$B$2:$B$159,$A26,Inventory!$H$2:$H$159,C$14) | D26: =COUNTIFS(Inventory!$B$2:$B$159,$A26,Inventory!$H$2:$H$159,D$14) | E26: =COUNTIFS(Inventory!$B$2:$B$159,$A26,Inventory!$H$2:$H$159,E$14) | F26: =COUNTIFS(Inventory!$B$2:$B$159,$A26,Inventory!$H$2:$H$159,F$14) | G26: =SUM(B26:F26)
... A31: Platform | B31: =COUNTIFS(Inventory!$B$2:$B$159,$A31,Inventory!$H$2:$H$159,B$14) | C31: =COUNTIFS(Inventory!$B$2:$B$159,$A31,Inventory!$H$2:$H$159,C$14) | D31: =COUNTIFS(Inventory!$B$2:$B$159,$A31,Inventory!$H$2:$H$159,D$14) | E31: =COUNTIFS(Inventory!$B$2:$B$159,$A31,Inventory!$H$2:$H$159,E$14) | F31: =COUNTIFS(Inventory!$B$2:$B$159,$A31,Inventory!$H$2:$H$159,F$14) | G31: =SUM(B31:F31)
A32: Total | B32: =SUM(B15:B31) | C32: =SUM(C15:C31) | D32: =SUM(D15:D31) | E32: =SUM(E15:E31) | F32: =SUM(F15:F31) | G32: =SUM(G15:G31)

Sheet Legend
A1: Legend and method
A3: Scope | B3: GoKesari Next.js app, repo D:\Claude_development\bkesari, audited 2026-09-22. Base: e76ccf2 (branch feature/pmd-review-decide; content equals origin/staging 40ba7b4). Includes explicit MISSING rows for target features so nothing is silently absent.
A4: EXISTING_WORKING | B4: Built, reachable and verified. Verified means: code read AND (automated tests pass OR marked 'code-verified only').
A5: EXISTING_PARTIAL | B5: Works but is incomplete, or has a defect/hole that must be fixed, or is reachable only in part.
A6: EXISTING_BROKEN | B6: Behaves incorrectly today. Confirmed by code reading; a reproducing test is the first step of the fix.
A7: EXISTING_PLACEHOLDER | B7: A type, permission, setting or service exists but nothing uses it, or it does nothing.
A8: MISSING | B8: Not built.
A9: Frontend / Backend / Database / API | B9: Yes = present and connected; Partial = present but not fully connected; No = absent; n/a = does not apply.
A10: Working? | B10: 'Yes - automated tests pass' = the named suites pass in the baseline. 'Service layer only' = the logic is tested but no route or screen calls it. Browser rendering was not exercised (no Playwright browser installed).
A11: Reachability method | B11: Every exported service function (241) was searched for callers in src/app, src/components and src/lib; functions with none are reported as service-only.
A12: Evidence | B12: docs/gokesari-audit/evidence/ (vitest JSON + log, build log, route scan). Findings referenced here (SEC-*, DEF-*) are in GOKESARI_AUDIT_FINDINGS.md.
