Workbook

Sheet Summary
A1: GoKesari feature status - 6 Oct 2026
A2: Your workbook (Gokesari_Complete_Features_and_Workflows.xlsx: 148 rows + flow diagram) compared with the code on main @579fd42 (6 Oct 2026). Status is development status from code and tests, not QA sign-off.
A3: Checked on main @579fd42 (6 Oct 2026), fresh PostgreSQL 16 with migrations 0000-0050 applied: typecheck clean, lint 0 errors (4 unused-variable warnings), 1152/1152 tests passed in 83 files (vitest).
A4: Buckets: COMPLETED = built and merged to main (some behind a business rule that is off by default - see 'Switched on?'); IN PROGRESS = partly built, remaining work needs no one else; BLOCKED = remaining work waits on a decision, vendor or another feature; YET TO START = no code. A row stays COMPLETED when its only gap is tracked by another open row (named in 'Remaining scope / caveat').
A6: Headline | B6: 3 Oct | C6: 6 Oct (now) | D6: Change
A7: Total features tracked | B7: =COUNTA('All features'!$J$2:$J$159)-COUNTIF('All features'!$J$2:$J$159,"-") -> 157 | C7: =COUNTA('All features'!$K$2:$K$159) -> 158 | D7: =C7-B7 -> 1
A8: COMPLETED | B8: =COUNTIF('All features'!$J$2:$J$159,"COMPLETED") -> 132 | C8: =COUNTIF('All features'!$K$2:$K$159,"COMPLETED") -> 143 | D8: =C8-B8 -> 11
A9: IN PROGRESS | B9: =COUNTIF('All features'!$J$2:$J$159,"IN PROGRESS") -> 23 | C9: =COUNTIF('All features'!$K$2:$K$159,"IN PROGRESS") -> 4 | D9: =C9-B9 -> -19
A10: BLOCKED | B10: =COUNTIF('All features'!$J$2:$J$159,"BLOCKED") -> 0 | C10: =COUNTIF('All features'!$K$2:$K$159,"BLOCKED") -> 10 | D10: =C10-B10 -> 10
A11: YET TO START | B11: =COUNTIF('All features'!$J$2:$J$159,"YET TO START") -> 1 | C11: =COUNTIF('All features'!$K$2:$K$159,"YET TO START") -> 1 | D11: =C11-B11 -> 0
A12: UNCLEAR | B12: =COUNTIF('All features'!$J$2:$J$159,"UNCLEAR") -> 1 | C12: =COUNTIF('All features'!$K$2:$K$159,"UNCLEAR") -> 0 | D12: =C12-B12 -> -1
A13: % complete | B13: =IFERROR(B8/B7,0) -> 0.84076433 | C13: =IFERROR(C8/C7,0) -> 0.90506329 | D13: =C13-B13 -> 0.06429896
A14: 3 Oct column is counted from the 'Status 3 Oct' column (source: GOKESARI_FEATURE_STATUS_REPORT_2026-10-03.xlsx); NEW-010 has no 3 Oct status.
A16: Section | B16: Total | C16: COMPLETED | D16: IN PROGRESS | E16: BLOCKED | F16: YET TO START | G16: % complete
A17: Feature Master | B17: =COUNTIF('All features'!$B$2:$B$159,A17) -> 74 | C17: =COUNTIFS('All features'!$B$2:$B$159,$A17,'All features'!$K$2:$K$159,"COMPLETED") -> 68 | D17: =COUNTIFS('All features'!$B$2:$B$159,$A17,'All features'!$K$2:$K$159,"IN PROGRESS") -> 1 | E17: =COUNTIFS('All features'!$B$2:$B$159,$A17,'All features'!$K$2:$K$159,"BLOCKED") -> 5 | F17: =COUNTIFS('All features'!$B$2:$B$159,$A17,'All features'!$K$2:$K$159,"YET TO START") -> 0 | G17: =IFERROR(C17/B17,0) -> 0.91891892
A18: Workflow Master | B18: =COUNTIF('All features'!$B$2:$B$159,A18) -> 10 | C18: =COUNTIFS('All features'!$B$2:$B$159,$A18,'All features'!$K$2:$K$159,"COMPLETED") -> 9 | D18: =COUNTIFS('All features'!$B$2:$B$159,$A18,'All features'!$K$2:$K$159,"IN PROGRESS") -> 0 | E18: =COUNTIFS('All features'!$B$2:$B$159,$A18,'All features'!$K$2:$K$159,"BLOCKED") -> 1 | F18: =COUNTIFS('All features'!$B$2:$B$159,$A18,'All features'!$K$2:$K$159,"YET TO START") -> 0 | G18: =IFERROR(C18/B18,0) -> 0.9
A19: RBAC Matrix | B19: =COUNTIF('All features'!$B$2:$B$159,A19) -> 15 | C19: =COUNTIFS('All features'!$B$2:$B$159,$A19,'All features'!$K$2:$K$159,"COMPLETED") -> 14 | D19: =COUNTIFS('All features'!$B$2:$B$159,$A19,'All features'!$K$2:$K$159,"IN PROGRESS") -> 0 | E19: =COUNTIFS('All features'!$B$2:$B$159,$A19,'All features'!$K$2:$K$159,"BLOCKED") -> 1 | F19: =COUNTIFS('All features'!$B$2:$B$159,$A19,'All features'!$K$2:$K$159,"YET TO START") -> 0 | G19: =IFERROR(C19/B19,0) -> 0.93333333
A20: State Machines | B20: =COUNTIF('All features'!$B$2:$B$159,A20) -> 6 | C20: =COUNTIFS('All features'!$B$2:$B$159,$A20,'All features'!$K$2:$K$159,"COMPLETED") -> 2 | D20: =COUNTIFS('All features'!$B$2:$B$159,$A20,'All features'!$K$2:$K$159,"IN PROGRESS") -> 2 | E20: =COUNTIFS('All features'!$B$2:$B$159,$A20,'All features'!$K$2:$K$159,"BLOCKED") -> 2 | F20: =COUNTIFS('All features'!$B$2:$B$159,$A20,'All features'!$K$2:$K$159,"YET TO START") -> 0 | G20: =IFERROR(C20/B20,0) -> 0.33333333
A21: Gig Assignment Rules | B21: =COUNTIF('All features'!$B$2:$B$159,A21) -> 9 | C21: =COUNTIFS('All features'!$B$2:$B$159,$A21,'All features'!$K$2:$K$159,"COMPLETED") -> 8 | D21: =COUNTIFS('All features'!$B$2:$B$159,$A21,'All features'!$K$2:$K$159,"IN PROGRESS") -> 1 | E21: =COUNTIFS('All features'!$B$2:$B$159,$A21,'All features'!$K$2:$K$159,"BLOCKED") -> 0 | F21: =COUNTIFS('All features'!$B$2:$B$159,$A21,'All features'!$K$2:$K$159,"YET TO START") -> 0 | G21: =IFERROR(C21/B21,0) -> 0.88888889
A22: Navigation | B22: =COUNTIF('All features'!$B$2:$B$159,A22) -> 19 | C22: =COUNTIFS('All features'!$B$2:$B$159,$A22,'All features'!$K$2:$K$159,"COMPLETED") -> 18 | D22: =COUNTIFS('All features'!$B$2:$B$159,$A22,'All features'!$K$2:$K$159,"IN PROGRESS") -> 0 | E22: =COUNTIFS('All features'!$B$2:$B$159,$A22,'All features'!$K$2:$K$159,"BLOCKED") -> 1 | F22: =COUNTIFS('All features'!$B$2:$B$159,$A22,'All features'!$K$2:$K$159,"YET TO START") -> 0 | G22: =IFERROR(C22/B22,0) -> 0.94736842
A23: KPIs | B23: =COUNTIF('All features'!$B$2:$B$159,A23) -> 15 | C23: =COUNTIFS('All features'!$B$2:$B$159,$A23,'All features'!$K$2:$K$159,"COMPLETED") -> 15 | D23: =COUNTIFS('All features'!$B$2:$B$159,$A23,'All features'!$K$2:$K$159,"IN PROGRESS") -> 0 | E23: =COUNTIFS('All features'!$B$2:$B$159,$A23,'All features'!$K$2:$K$159,"BLOCKED") -> 0 | F23: =COUNTIFS('All features'!$B$2:$B$159,$A23,'All features'!$K$2:$K$159,"YET TO START") -> 0 | G23: =IFERROR(C23/B23,0) -> 1
A24: Added after the target workbook | B24: =COUNTIF('All features'!$B$2:$B$159,A24) -> 10 | C24: =COUNTIFS('All features'!$B$2:$B$159,$A24,'All features'!$K$2:$K$159,"COMPLETED") -> 9 | D24: =COUNTIFS('All features'!$B$2:$B$159,$A24,'All features'!$K$2:$K$159,"IN PROGRESS") -> 0 | E24: =COUNTIFS('All features'!$B$2:$B$159,$A24,'All features'!$K$2:$K$159,"BLOCKED") -> 0 | F24: =COUNTIFS('All features'!$B$2:$B$159,$A24,'All features'!$K$2:$K$159,"YET TO START") -> 1 | G24: =IFERROR(C24/B24,0) -> 0.9
A25: TOTAL | B25: =SUM(B17:B24) -> 158 | C25: =SUM(C17:C24) -> 143 | D25: =SUM(D17:D24) -> 4 | E25: =SUM(E17:E24) -> 10 | F25: =SUM(F17:F24) -> 1 | G25: =IFERROR(C25/B25,0) -> 0.90506329
A27: Your flow diagram | B27: Steps
A28: COMPLETED | B28: =COUNTIF('Flow diagram status'!$D$5:$D$52,A28) -> 44
A29: IN PROGRESS | B29: =COUNTIF('Flow diagram status'!$D$5:$D$52,A29) -> 1
A30: BLOCKED | B30: =COUNTIF('Flow diagram status'!$D$5:$D$52,A30) -> 3
A31: YET TO START | B31: =COUNTIF('Flow diagram status'!$D$5:$D$52,A31) -> 0
A32: Total steps | B32: =SUM(B28:B31) -> 48

Sheet Flow diagram status
A1: Your flow diagram, step by step, against the build
A2: Status is the weakest part a step needs; 'What works' says what a user can do today.
A4: # | B4: Box in your diagram | C4: Step | D4: Status 6 Oct | E4: Feature IDs | F4: What works in the build | G4: Gap
A5: 1 | B5: Customer | C5: Location / Society | D5: COMPLETED | E5: GS-004, GS-005 | F5: Saved address, device position or PIN; address linked to a registered society. | G5: -
A6: 2 | B6: Customer | C6: Search shop or product | D6: COMPLETED | E6: GS-019, GS-020, GS-021 | F6: Shops that deliver here, nearest first; product search limited to serviceable shops; every shop selling a product. | G6: -
A7: 3 | B7: Customer | C7: Compare local + online prices | D7: BLOCKED | E7: GS-022, NAV-001, GS-023 | F7: Local comparison per unit / pack with lowest price; home-page comparison (F9, off by default). | G7: Online (e-commerce) prices hidden from customers until D7 - licensed source - is decided.
A8: 4 | B8: Customer | C8: Cart / Subscription | D8: COMPLETED | E8: GS-024, GS-025, GS-048, GS-049, NAV-003 | F8: Single and multi-shop cart; coupons (F7) and shop offers (F8) off by default; milk and daily-goods subscriptions. | G8: -
A9: 5 | B9: Customer | C9: Payment | D9: BLOCKED | E9: GS-028, GS-029, GS-030 | F9: Wallet (topped up through Cashfree UPI / card / netbanking) and COD with risk limits. | G9: No per-order UPI / card / netbanking payment - waits on the go-ahead (GS-028 / NEW-007).
A10: 6 | B10: Order engine | C10: Validate stock + service area | D10: COMPLETED | E10: GS-026, GS-016 | F10: Checkout hard-blocks non-serviceable shops, out-of-stock lines, paused shops and minimum order. | G10: -
A11: 7 | B11: Order engine | C11: Split order by shop | D11: COMPLETED | E11: GS-033, GS-025 | F11: One order per shop; one parent GK- reference for the checkout (F6, off by default). | G11: -
A12: 8 | B12: Order engine | C12: Confirm payment | D12: BLOCKED | E12: GS-028, SM-005 | F12: Wallet debit or COD confirmed inside the order transaction, idempotent. | G12: Gateway confirmation and the payment state machine wait on GS-028.
A13: 9 | B13: Order engine | C13: Create fulfillment tasks | D13: COMPLETED | E13: GS-032, WF-002 | F13: Shop order created and the shop notified. | G13: -
A14: 10 | B14: Shop owner | C14: Receive order | D14: COMPLETED | E14: GS-055, NAV-008 | F14: In-app + email notice; orders board. | G14: SMS / WhatsApp alerts wait on D2.
A15: 11 | B15: Shop owner | C15: Accept / reject / substitute | D15: COMPLETED | E15: GS-034, GS-035 | F15: Accept, reject (full refund + restock), substitution with customer approval; late acceptance flagged to ops. | G15: Auto-cancel on accept timeout is part of NEW-007 (yet to start).
A16: 12 | B16: Shop owner | C16: Pick + pack | D16: COMPLETED | E16: GS-036 | F16: Per-line picking and packing. | G16: -
... A52: 48 | B52: Marketplace data | C52: Analytics | D52: COMPLETED | E52: GS-069 | F52: KPI suite. | G52: -
B54: Flow steps by status
B55: COMPLETED | C55: =COUNTIF($D$5:$D$52,B55) -> 44
B56: IN PROGRESS | C56: =COUNTIF($D$5:$D$52,B56) -> 1
B57: BLOCKED | C57: =COUNTIF($D$5:$D$52,B57) -> 3
B58: YET TO START | C58: =COUNTIF($D$5:$D$52,B58) -> 0
B59: Total | C59: =SUM(C55:C58) -> 48

Sheet All features
A1: Seq | B1: Section (your workbook) | C1: ID | D1: Module / portal | E1: Feature | F1: Priority | G1: Phase | H1: Requirement (your workbook) | I1: Rule / note (your workbook) | J1: Status 3 Oct | K1: Status 6 Oct | L1: Change since 3 Oct | M1: Switched on? | N1: What is built (checked in code, 6 Oct) | O1: Remaining scope / caveat | P1: Blocked on | Q1: Evidence (file)
A2: 1 | B2: Feature Master | C2: GS-001 | D2: Identity & Access | E2: Mobile/email/Gmail login | F2: P0 | G2: MVP | H2: Secure registration and authentication. (Roles: Customer, Shop, Gig, Operator, Admin, Society) | I2: RBAC mandatory. | J2: IN PROGRESS | K2: BLOCKED | L2: IN PROGRESS -> BLOCKED | M2: Live (email OTP); SMS OTP not available | N2: Google, email magic link and a single mobile-or-email form; first-time /onboarding profile; My Profile with verified email change; checkout requires a mobile; admin can release a wrongly claimed number. Login rebuild now on main (was staging-only on 3 Oct). | O2: SMS delivery of the OTP so a mobile number is proven (OTP provider seam ready). | P2: D2 - SMS/OTP vendor with DLT registration | Q2: src/server/otp/providers.ts; src/app/onboarding; src/app/profile; drizzle/0038_login_profile.sql
A3: 2 | B3: Feature Master | C3: GS-002 | D3: Identity & Access | E3: Role-based access control | F3: P0 | G3: MVP | H3: Permissions by role and scope. (Roles: All roles) | I3: Least privilege. | J3: COMPLETED | K3: COMPLETED | L3: No change | M3: Live | N3: SOCIETY_ADMIN role; society roles scoped per membership (ADMIN/OPERATOR/RESIDENT) | O3: - | P3: - | Q3: src/server/authz/permissions.ts; src/server/db/schema.ts (userRoleEnum)
A4: 3 | B4: Feature Master | C4: GS-003 | D4: Identity & Access | E4: Multi-role user account | F4: P1 | G4: Phase 2 | H4: Allow approved users to hold multiple roles. (Roles: All) | I4: Separate approval per role. | J4: COMPLETED | K4: COMPLETED | L4: No change | M4: Live | N4: user_role_grants; active role switcher in the header; /api/me/roles; admin revoke; shop/rider/society flows grant roles; staff roles exclusive | O4: - | P4: - | Q4: src/server/services/roles.ts; src/app/api/me/roles/route.ts
A5: 4 | B5: Feature Master | C5: GS-004 | D5: Location | E5: PIN / address selection | F5: P0 | G5: MVP | H5: Select delivery address and service area. (Roles: Customer) | I5: Use address geocoding. | J5: COMPLETED | K5: COMPLETED | L5: No change | M5: Live | N5: 'Deliver to' location: saved address, device position or PIN, remembered in a cookie. Phase B added Maps Places address search, a 'save this place' path, and recipient name / recipient mobile / Home-Work-Other on addresses | O5: - | P5: - | Q5: src/lib/geo/provider.ts; src/components/location-bar.tsx; drizzle/0026
A6: 5 | B6: Feature Master | C6: GS-005 | D6: Location | E6: Society identification | F6: P0 | G6: MVP | H6: Associate address with registered society. (Roles: Customer, Society) | I6: Society rules apply. | J6: COMPLETED | K6: COMPLETED | L6: No change | M6: Live | N6: Society membership; address <-> society link; orders.society_id | O6: - | P6: - | Q6: src/server/services/societies.ts
A7: 6 | B7: Feature Master | C7: GS-006 | D7: Shop Onboarding | E7: Shop registration | F7: P0 | G7: MVP | H7: Create shop profile, category, owner and location. (Roles: Shop, Operator) | I7: Operator approval before live. | J7: COMPLETED | K7: COMPLETED | L7: No change | M7: Live | N7: - | O7: 6 Oct: GST field added at registration; at least one of PAN / Udyam / GST / Shop Act required (135f29a). | P7: - | Q7: -
A8: 7 | B8: Feature Master | C8: GS-007 | D8: Shop Onboarding | E8: Business KYC | F8: P0 | G8: MVP | H8: Collect GST/PAN/license and required documents. (Roles: Shop, Operator, Admin) | I8: Verification status tracked. | J8: IN PROGRESS | K8: COMPLETED | L8: IN PROGRESS -> COMPLETED | M8: Live; vendor checks run on the MOCK vendor until Gridlines keys are set (KYC_PROVIDER) | N8: Seller verification Parts 1-4: PAN, GSTIN, Udyam, FSSAI and Shop Act per shop with document upload, vendor check (provider-agnostic, Gridlines adapter + mock), name matching, cross-document consistency score, per-document status, admin review queue (approve / reject with reason / re-check), daily re-check and expiry job, auto-suspend on lapse, DPDP retention/erasure. | O8: Real vendor: Gridlines sandbox then live keys and written confirmation of response fields, Shop Act coverage, prices, DPA. By design, verification informs shop approval but does not block it. | P8: - | Q8: src/server/services/seller-verification*.ts; src/server/kyc/; /shop/verification; /admin/seller-verification; drizzle/0040, 0041; docs/seller-verification/
A9: 8 | B9: Feature Master | C9: GS-008 | D9: Shop Onboarding | E9: Payment reference verification | F9: P0 | G9: MVP | H9: Verify onboarding/subscription payment and authorize shop. (Roles: Operator) | I9: Audit every action. | J9: COMPLETED | K9: COMPLETED | L9: No change | M9: Live | N9: approveShop() now refuses unless fee_payment_status = PAID (derived from the shop_payments ledger), naming the amount outstanding; waived fee (zero snapshot) is written PAID at registration; approval queue shows each pending shop's fee state. Gate is on the transition only - shops already APPROVED untouched | O9: - | P9: - | Q9: src/server/services/shops.ts (approveShop); src/components/shop-approval-panel.tsx; tests/integration/registration-fees.test.ts
A10: 9 | B10: Feature Master | C10: GS-009 | D10: Shop Onboarding | E10: Shop categories | F10: P0 | G10: MVP | H10: Support grocery, dairy, pharmacy, clothing, electronics, repair, etc. (Roles: Admin, Operator) | I10: Configurable category master. | J10: COMPLETED | K10: COMPLETED | L10: No change | M10: Live | N10: Admin-configurable category master: shop_categories + shop_category_mapping (many per shop), seeded from the 44 shop types and backfilled; registration requires at least one category; owners edit their own on /shop; operators/admins manage the list at /admin/shop-categories and assign per shop; uncategorised shops flagged; categories feed search relevance | O10: - | P10: - | Q10: src/server/services/shop-categories.ts; src/app/admin/shop-categories/page.tsx; drizzle/0035
A11: 10 | B11: Feature Master | C11: GS-010 | D11: Shop Onboarding | E11: Service radius / delivery zone | F11: P0 | G11: MVP | H11: Define where shop can serve customers. (Roles: Shop, Operator) | I11: Geospatial validation. | J11: COMPLETED | K11: COMPLETED | L11: No change | M11: Live | N11: shops.service_radius_km (1-50 km) editable by the shop; Phase B added extra delivery zones by PIN code (shops.delivery_pincodes), honoured by serviceability, checkout and discovery | O11: - | P11: - | Q11: src/server/services/serviceability.ts; src/server/db/schema.ts:691; drizzle/0019, 0026
A12: 11 | B12: Feature Master | C12: GS-011 | D12: Catalog | E12: Product master | F12: P0 | G12: MVP | H12: Central product catalog with SKU/GTIN/HSN/GST/brand/pack size. (Roles: Admin, Operator) | I12: One canonical product identity. | J12: COMPLETED | K12: COMPLETED | L12: No change | M12: Live | N12: - | O12: - | P12: - | Q12: -
A13: 12 | B13: Feature Master | C13: GS-012 | D13: Catalog | E13: Shop catalog mapping | F13: P0 | G13: MVP | H13: Map products to shop-specific price, stock and availability. (Roles: Shop, Operator) | I13: Shop-specific sellable SKU. | J13: COMPLETED | K13: COMPLETED | L13: No change | M13: Live | N13: - | O13: - | P13: - | Q13: -
... A159: 158 | B159: Added after the target workbook | C159: NEW-010 | D159: Catalog | E159: Shop inventory fill when a category is added; per-shop prices | F159: n/a | G159: n/a | H159: Not in the target workbook; delivered 3-5 Oct (0e2d77f, 1221420) | I159: - | J159: - | K159: COMPLETED | L159: New row | M159: Live | N159: Adding a category to a shop lists every live product in it with stock 100; packaged goods start at master MRP and on sale, loose goods / no-MRP start unpriced and off sale; owner sees how many need a price and saves prices in bulk (PATCH /api/shops/[id]/prices); buyers see 'Price on request' + 'Ask shop'. | O159: - | P159: - | Q159: tests/integration/shop-inventory-fill.test.ts; commits 0e2d77f, 1221420

Sheet Completed
A1: # | B1: ID | C1: Section | D1: Feature | E1: Priority | F1: Status 3 Oct | G1: Switched on? | H1: What is built | I1: Remaining scope / caveat | J1: Blocked on
A2: 1 | B2: GS-002 | C2: Feature Master | D2: Role-based access control | E2: P0 | F2: COMPLETED | G2: Live | H2: SOCIETY_ADMIN role; society roles scoped per membership (ADMIN/OPERATOR/RESIDENT) | I2: - | J2: -
A3: 2 | B3: GS-003 | C3: Feature Master | D3: Multi-role user account | E3: P1 | F3: COMPLETED | G3: Live | H3: user_role_grants; active role switcher in the header; /api/me/roles; admin revoke; shop/rider/society flows grant roles; staff roles exclusive | I3: - | J3: -
A4: 3 | B4: GS-004 | C4: Feature Master | D4: PIN / address selection | E4: P0 | F4: COMPLETED | G4: Live | H4: 'Deliver to' location: saved address, device position or PIN, remembered in a cookie. Phase B added Maps Places address search, a 'save this place' path, and recipient name / recipient mobile / Home-Work-Other on addresses | I4: - | J4: -
A5: 4 | B5: GS-005 | C5: Feature Master | D5: Society identification | E5: P0 | F5: COMPLETED | G5: Live | H5: Society membership; address <-> society link; orders.society_id | I5: - | J5: -
A6: 5 | B6: GS-006 | C6: Feature Master | D6: Shop registration | E6: P0 | F6: COMPLETED | G6: Live | H6: - | I6: 6 Oct: GST field added at registration; at least one of PAN / Udyam / GST / Shop Act required (135f29a). | J6: -
A7: 6 | B7: GS-007 | C7: Feature Master | D7: Business KYC | E7: P0 | F7: IN PROGRESS | G7: Live; vendor checks run on the MOCK vendor until Gridlines keys are set (KYC_PROVIDER) | H7: Seller verification Parts 1-4: PAN, GSTIN, Udyam, FSSAI and Shop Act per shop with document upload, vendor check (provider-agnostic, Gridlines adapter + mock), name matching, cross-document consistency score, per-document status, admin review queue (approve / reject with reason / re-check), daily re-check and expiry job, auto-suspend on lapse, DPDP retention/erasure. | I7: Real vendor: Gridlines sandbox then live keys and written confirmation of response fields, Shop Act coverage, prices, DPA. By design, verification informs shop approval but does not block it. | J7: -
A8: 7 | B8: GS-008 | C8: Feature Master | D8: Payment reference verification | E8: P0 | F8: COMPLETED | G8: Live | H8: approveShop() now refuses unless fee_payment_status = PAID (derived from the shop_payments ledger), naming the amount outstanding; waived fee (zero snapshot) is written PAID at registration; approval queue shows each pending shop's fee state. Gate is on the transition only - shops already APPROVED untouched | I8: - | J8: -
A9: 8 | B9: GS-009 | C9: Feature Master | D9: Shop categories | E9: P0 | F9: COMPLETED | G9: Live | H9: Admin-configurable category master: shop_categories + shop_category_mapping (many per shop), seeded from the 44 shop types and backfilled; registration requires at least one category; owners edit their own on /shop; operators/admins manage the list at /admin/shop-categories and assign per shop; uncategorised shops flagged; categories feed search relevance | I9: - | J9: -
A10: 9 | B10: GS-010 | C10: Feature Master | D10: Service radius / delivery zone | E10: P0 | F10: COMPLETED | G10: Live | H10: shops.service_radius_km (1-50 km) editable by the shop; Phase B added extra delivery zones by PIN code (shops.delivery_pincodes), honoured by serviceability, checkout and discovery | I10: - | J10: -
A11: 10 | B11: GS-011 | C11: Feature Master | D11: Product master | E11: P0 | F11: COMPLETED | G11: Live | H11: - | I11: - | J11: -
A12: 11 | B12: GS-012 | C12: Feature Master | D12: Shop catalog mapping | E12: P0 | F12: COMPLETED | G12: Live | H12: - | I12: - | J12: -
A13: 12 | B13: GS-013 | C13: Feature Master | D13: Bulk product upload | E13: P0 | F13: COMPLETED | G13: Live | H13: - | I13: - | J13: -
... A144: 143 | B144: NEW-010 | C144: Added after the target workbook | D144: Shop inventory fill when a category is added; per-shop prices | E144: n/a | F144: - | G144: Live | H144: Adding a category to a shop lists every live product in it with stock 100; packaged goods start at master MRP and on sale, loose goods / no-MRP start unpriced and off sale; owner sees how many need a price and saves prices in bulk (PATCH /api/shops/[id]/prices); buyers see 'Price on request' + 'Ask shop'. | I144: - | J144: -

Sheet In progress
A1: # | B1: ID | C1: Section | D1: Feature | E1: Priority | F1: Status 3 Oct | G1: Switched on? | H1: What is built | I1: Remaining scope / caveat | J1: Blocked on
A2: 1 | B2: GS-027 | C2: Feature Master | D2: Delivery slot | E2: P0 | F2: IN PROGRESS | G2: Off by default in code - switch on in Admin > Business rules (scripts/enable-new-features.sql does it for test) (rule: deliverySlots.enabled) | H2: EXPRESS_30 / STANDARD_60 / SCHEDULED windows with feasibility preview, plus F5 slot capacity per shop / PIN code / default with an advisory lock so a slot cannot be overbooked (full slots shown unavailable). | I2: Customer cannot pick a date or time for a scheduled delivery - a scheduled order is booked against the day it is placed. | J2: -
A3: 2 | B3: SM-002 | C3: State Machines | D3: Shop state machine | E3: n/a | F3: IN PROGRESS | G3: Live once migration 0042 is applied | H3: F1: shop lifecycle PENDING / ACTIVE / PAUSED / SUSPENDED / REJECTED / CLOSED derived by trigger, transitions enforced and logged; suspension policy with impact preview; KYC status per document (seller verification) and registration-fee status exist as separate fields. | I3: APPLIED -> KYC_PENDING -> PAYMENT_PENDING -> VERIFIED are all one PENDING stage; show them as lifecycle stages (the data already exists). | J3: -
A4: 3 | B4: SM-004 | C4: State Machines | D4: Subscription state machine | E4: n/a | F4: IN PROGRESS | G4: Live once migration 0042 is applied | H4: F1: subscription lifecycle ACTIVE / PAUSED / CANCELLED / EXPIRED with enforced, logged transitions; PAYMENT_PENDING and per-date skips in the detailed status; subscription_events history. | I4: DRAFT, RENEWAL_PENDING and per-cycle ORDER_CREATED / FULFILLED stages; SKIPPED and PAYMENT_FAILED as named lifecycle states. | J4: -
A5: 4 | B5: GA-005 | C5: Gig Assignment Rules | D5: Current load | E5: P0 | F5: IN PROGRESS | G5: Off by default in code - switch on in Admin > Business rules (scripts/enable-new-features.sql does it for test) (rule: dispatch.busyRidersAsFallback) | H5: F3: riders with active jobs are ranked after free riders (up to maxActiveDeliveriesPerRider, default 2) instead of being excluded. | I5: Multi-order batching ('unless batching is beneficial') not built. | J5: -

Sheet Blocked
A1: # | B1: ID | C1: Section | D1: Feature | E1: Priority | F1: Status 3 Oct | G1: Switched on? | H1: What is built | I1: Remaining scope / caveat | J1: Blocked on
A2: 1 | B2: GS-001 | C2: Feature Master | D2: Mobile/email/Gmail login | E2: P0 | F2: IN PROGRESS | G2: Live (email OTP); SMS OTP not available | H2: Google, email magic link and a single mobile-or-email form; first-time /onboarding profile; My Profile with verified email change; checkout requires a mobile; admin can release a wrongly claimed number. Login rebuild now on main (was staging-only on 3 Oct). | I2: SMS delivery of the OTP so a mobile number is proven (OTP provider seam ready). | J2: D2 - SMS/OTP vendor with DLT registration
A3: 2 | B3: GS-023 | C3: Feature Master | D3: E-commerce price benchmark | E3: P1 | F3: IN PROGRESS | G3: Hidden from customers (externalPrices.showToCustomers = false) | H3: External reference prices with source, time, location, URL, verification and audit history; shops and operations see them. | I3: Turn on the customer display - one rule flip, no code. | J3: D7 - lawful / licensed price source
A4: 3 | B4: GS-028 | C4: Feature Master | D4: UPI/card/netbanking gateway | E4: P0 | F4: IN PROGRESS | G4: Live | H4: Cashfree live for wallet top-up only (create order, server verify, HMAC webhook, mock mode). Orders are paid by WALLET or COD; payment_method enum is still WALLET | COD. | I4: Per-order ONLINE payment via Cashfree hosted checkout (design signed off 1 Oct). | J4: Go-ahead to build per-order payment, or a decision to launch wallet + COD only
A5: 4 | B5: GS-073 | C5: Feature Master | D5: Payment gateway | E5: P0 | F5: IN PROGRESS | G5: Live | H5: Gateway plumbing reusable; refunds are wallet credits (journaled, idempotent). | I5: Order payment intents, callbacks and gateway refunds. | J5: Needs GS-028
A6: 5 | B6: GS-074 | C6: Feature Master | D6: SMS/WhatsApp/email/push | E6: P1 | F6: IN PROGRESS | G6: Email + in-app live (email needs SMTP) | H6: Email and in-app notifications live; SMS, PUSH and WHATSAPP channels have a provider seam with no vendor. | I6: Real SMS / push / WhatsApp providers. | J6: D2 - vendor choice (DLT registration)
A7: 6 | B7: WF-001 | C7: Workflow Master | D7: Customer product purchase | E7: n/a | F7: IN PROGRESS | G7: Live | H7: Every step works: location, search, eligible shops, comparison, cart, address, slot, payment by wallet or COD, order created; out-of-stock substitution; closed-shop confirmation. | I7: Direct online payment for the order. | J7: Needs GS-028
A8: 7 | B8: RBAC-003 | C8: RBAC Matrix | D8: Manage own shop | E8: n/a | F8: UNCLEAR | G8: Live | H8: Shop owners manage their own shop; admins full. No 'Limited' operator scope for shop management. | I8: Define what an operator may change on a shop, then implement. | J8: Decision: what 'Limited' means
A9: 8 | B9: SM-005 | C9: State Machines | D9: Payment state machine | E9: n/a | F9: IN PROGRESS | G9: Live | H9: Unchanged: payment_status CREATED / PENDING / SUCCESS / FAILED / REFUNDED (wallet top-ups only). | I9: INITIATED -> AUTHORIZED -> CAPTURED -> RECONCILED; CHARGEBACK. | J9: Per-order online payment go-ahead (GS-028 / NEW-007)
A10: 9 | B10: SM-006 | C10: State Machines | D10: Issue state machine | E10: n/a | F10: IN PROGRESS | G10: Live | H10: Tickets linked to orders; returns 13-status machine; dispute cases have OPEN / TRIAGED / INVESTIGATING / RESOLUTION_PROPOSED / ESCALATED / RESOLVED; grievances still OPEN / IN_PROGRESS / RESOLVED / CLOSED. | I10: Either add the four states to grievances or accept the dispute lifecycle as the issue state machine. | J10: Decision: does the dispute lifecycle satisfy SM-006?
A11: 10 | B11: NAV-003 | C11: Navigation | D11: Customer portal - Cart & Checkout | E11: n/a | F11: IN PROGRESS | G11: Coupons: Off by default in code - switch on in Admin > Business rules (scripts/enable-new-features.sql does it for test) (rule: coupons.enabled) | H11: Cart, address re-validation with actions, slot choice with capacity (F5), F7 order-level coupons (flat / %, minimum order, dates, total and per-customer limits, split by goods value, server-validated), F8 offers priced in cart, wallet / COD payment. | I11: Online payment at checkout. | J11: Needs GS-028

Sheet Yet to start
A1: # | B1: ID | C1: Section | D1: Feature | E1: Priority | F1: Status 3 Oct | G1: Switched on? | H1: What is built | I1: Remaining scope / caveat | J1: Blocked on
A2: 1 | B2: NEW-007 | C2: Added after the target workbook | D2: Direct per-order payments, tax invoicing, photo POD, accept timeout | E2: n/a | F2: YET TO START | G2: - | H2: Design only (DESIGN_PAYMENTS_INVOICING_POD_SLA.md). Re-checked 6 Oct: no ONLINE payment method, no invoice code, no photo proof of delivery, no accept-timeout auto-cancel. | I2: Per-order online payment (needs the GS-028 go-ahead); tax invoicing (shop invoices goods, platform invoices its fees); photo proof of delivery; auto-cancel with full refund when a shop does not accept in time. The last three do not depend on the payment decision. | J2: Go-ahead to build

Sheet Changed since 3 Oct
A1: ID | B1: Feature | C1: Status 3 Oct | D1: Status 6 Oct | E1: What changed | F1: Delivered in
A2: GS-001 | B2: Mobile/email/Gmail login | C2: IN PROGRESS | D2: BLOCKED | E2: Google, email magic link and a single mobile-or-email form; first-time /onboarding profile; My Profile with verified email change; checkout requires a mobile; admin can release a wrongly claimed number. Login rebuild now on main (was staging-only on 3 Oct). | F2: PR #42/#43 (login rebuild to main)
A3: GS-006 | B3: Shop registration | C3: COMPLETED | D3: COMPLETED | E3: 6 Oct: GST field added at registration; at least one of PAN / Udyam / GST / Shop Act required (135f29a). | F3: -
A4: GS-007 | B4: Business KYC | C4: IN PROGRESS | D4: COMPLETED | E4: Seller verification Parts 1-4: PAN, GSTIN, Udyam, FSSAI and Shop Act per shop with document upload, vendor check (provider-agnostic, Gridlines adapter + mock), name matching, cross-document consistency score, per-document status, admin review queue (approve / reject with reason / re-check), daily re-check and expiry job, auto-suspend on lapse, DPDP retention/erasure. | F4: Seller verification 0a7fafa, 9cdec04, 896f082
A5: GS-014 | B5: Product images/specifications | C5: IN PROGRESS | D5: COMPLETED | E5: Image store with several images per product/listing, primary, reorder, alt text; F10 moderation queue (pending -> approve / reject with reason) at /admin/image-moderation; existing photos stay live. | F5: F10 0c9894f
A6: GS-023 | B6: E-commerce price benchmark | C6: IN PROGRESS | D6: BLOCKED | E6: External reference prices with source, time, location, URL, verification and audit history; shops and operations see them. | F6: Decision / dependency only
A7: GS-027 | B7: Delivery slot | C7: IN PROGRESS | D7: IN PROGRESS | E7: EXPRESS_30 / STANDARD_60 / SCHEDULED windows with feasibility preview, plus F5 slot capacity per shop / PIN code / default with an advisory lock so a slot cannot be overbooked (full slots shown unavailable). | F7: F5 742e6d2
A8: GS-028 | B8: UPI/card/netbanking gateway | C8: IN PROGRESS | D8: BLOCKED | E8: Cashfree live for wallet top-up only (create order, server verify, HMAC webhook, mock mode). Orders are paid by WALLET or COD; payment_method enum is still WALLET | COD. | F8: Decision / dependency only
A9: GS-033 | B9: Shop order split | C9: IN PROGRESS | D9: COMPLETED | E9: One order per shop from a multi-shop cart, plus F6 parent reference (GK-...) linking them; customer page /orders/group/[reference]. | F9: F6 e95af6f
A10: GS-054 | B10: Referral program | C10: IN PROGRESS | D10: COMPLETED | E10: Shop referral attribution, plus F11 customer referral code and link (/refer, /r/CODE): both rewarded on the friend's first delivered order; self-referral, duplicate-account and per-referrer cap guards; /admin/customer-referrals. | F10: F11 db5c400
A11: GS-072 | B11: Maps/navigation | C11: IN PROGRESS | D11: COMPLETED | E11: F4: road distance and travel time from Google Routes or OSRM behind one provider interface, cached per ~100 m cell and logged; arrival time for customer (tracking map) and rider (dashboard); straight-line fallback when off or failing. Navigation is a Google Maps deep link. | F11: F4 e26d9c7
A12: GS-073 | B12: Payment gateway | C12: IN PROGRESS | D12: BLOCKED | E12: Gateway plumbing reusable; refunds are wallet credits (journaled, idempotent). | F12: Decision / dependency only
... A32: - | B32: Playwright acceptance tests | C32: - | D32: - | E32: Updated to the current sign-in and wallet flows (b65fcec); 10/10 passing per docs/marketplace-features-2026-10/README.md. | F32: 4 Oct

Sheet Decisions & go-live
A1: Type | B1: Item | C1: What is needed | D1: Unblocks | E1: Status
A2: Decision | B2: Per-order online payment (GS-028 / NEW-007) | C2: Approve building per-order Cashfree payment, OR launch with wallet + COD only. | D2: GS-028, GS-073, SM-005, NAV-003, WF-001, part of NEW-007 | E2: Pending (no change since 3 Oct)
A3: Decision / vendor | B3: D2 - SMS / OTP vendor | C3: Pick a DLT-registered SMS provider. | D3: GS-001, GS-074 | E3: Pending
A4: Decision | B4: D7 - external price source | C4: Approve a lawful / licensed source for customer-visible reference prices. | D4: GS-023 (one rule flip) | E4: Pending
A5: Decision | B5: RBAC-003 - operator 'Limited' shop management | C5: Define what an operator may change on a shop. | D5: RBAC-003 | E5: Pending
A6: Decision | B6: SM-006 scope | C6: Accept the dispute lifecycle as the issue state machine, or add its states to grievances. | D6: SM-006 | E6: Pending
A7: Decision | B7: NEW-007 go-ahead | C7: Approve building invoicing, photo POD and accept-timeout (these three do not need the payment decision). | D7: NEW-007, NAV-010 invoices, GS-034 auto-cancel | E7: Pending
A8: Decision | B8: D10 - cancellation policy | C8: Confirm ACCEPTED / ASSIGNED (customer blocked) and PICKED_UP (goods-only refund). | D8: NEW-006 sign-off | E8: Pending (per 3 Oct)
A9: Decision | B9: Switch on F3-F11 in production | C9: Decide which of the off-by-default features to switch on (Admin > Business rules). | D9: GA-005, GS-072, GS-027, GS-033, NAV-001/002/003, GS-014, GS-054 | E9: Pending
A10: Vendor | B10: Gridlines (seller verification) | C10: Sandbox then live keys; written confirmation of FSSAI / GSTIN fields, Shop Act coverage, prices, IP whitelist, retention and DPA. | D10: Automatic KYC checks for GS-007 (mock vendor until then) | E10: Pending
A11: Legal | B11: Lawyer / CA confirmation | C11: Retention period after closure (default 1,095 days) and Shop Act needs for non-MH / home sellers. | D11: GS-007 compliance | E11: Pending
A12: Go-live blocker | B12: No browser / QA sign-off | C12: Nothing since Phase 1 has been signed off in a browser; status is code + automated tests. | D12: Go-live | E12: Open
A13: Go-live blocker | B13: Production migrations and cron jobs | C13: Apply migrations up to 0050 and add the seller-verification and dispute-escalation crons (DEPLOY_RUNBOOK.md, docs/seller-verification/DEPLOY.md). | D13: Everything delivered after Phase 1 | E13: Open
