Workbook

Sheet Baseline Tests
A1: Test ID | B1: Module | C1: Feature | D1: Steps | E1: Expected result | F1: Actual result | G1: Pass/Fail | H1: Existing defect | I1: Screenshot/log
A2: BT-0001 | B2: Customer | C2: Address book | D2: Automated. npx vitest run tests/integration/addresses.test.ts -> suite 'createAddress' -> test 'saves an address without coordinates as unverified' | E2: As asserted by the test: saves an address without coordinates as unverified | F2: Passed in 401 ms | G2: Pass | H2: None observed | I2: evidence/vitest-baseline.log (tests/integration/addresses.test.ts)
A3: BT-0002 | B3: Customer | C3: Address book | D3: Automated. npx vitest run tests/integration/addresses.test.ts -> suite 'createAddress' -> test 'marks the address GOOGLE_VERIFIED when coordinates geocode successfully' | E3: As asserted by the test: marks the address GOOGLE_VERIFIED when coordinates geocode successfully | F3: Passed in 231 ms | G3: Pass | H3: None observed | I3: evidence/vitest-baseline.log (tests/integration/addresses.test.ts)
A4: BT-0003 | B4: Customer | C4: Address book | D4: Automated. npx vitest run tests/integration/addresses.test.ts -> suite 'createAddress' -> test 'still saves the address, unverified, when geocoding fails' | E4: As asserted by the test: still saves the address, unverified, when geocoding fails | F4: Passed in 228 ms | G4: Pass | H4: None observed | I4: evidence/vitest-baseline.log (tests/integration/addresses.test.ts)
A5: BT-0004 | B5: Customer | C5: Address book | D5: Automated. npx vitest run tests/integration/addresses.test.ts -> suite 'createAddress' -> test 'rejects an invalid pincode' | E5: As asserted by the test: rejects an invalid pincode | F5: Passed in 229 ms | G5: Pass | H5: None observed | I5: evidence/vitest-baseline.log (tests/integration/addresses.test.ts)
A6: BT-0005 | B6: Customer | C6: Address book | D6: Automated. npx vitest run tests/integration/addresses.test.ts -> suite 'createAddress' -> test 'unsets other defaults when a new default address is added' | E6: As asserted by the test: unsets other defaults when a new default address is added | F6: Passed in 247 ms | G6: Pass | H6: None observed | I6: evidence/vitest-baseline.log (tests/integration/addresses.test.ts)
A7: BT-0006 | B7: Customer | C7: Address book | D7: Automated. npx vitest run tests/integration/addresses.test.ts -> suite 'updateAddress' -> test 're-verifies only when the coordinates actually change' | E7: As asserted by the test: re-verifies only when the coordinates actually change | F7: Passed in 256 ms | G7: Pass | H7: None observed | I7: evidence/vitest-baseline.log (tests/integration/addresses.test.ts)
A8: BT-0007 | B8: Customer | C8: Address book | D8: Automated. npx vitest run tests/integration/addresses.test.ts -> suite 'updateAddress' -> test 're-verifies when the pin moves' | E8: As asserted by the test: re-verifies when the pin moves | F8: Passed in 259 ms | G8: Pass | H8: None observed | I8: evidence/vitest-baseline.log (tests/integration/addresses.test.ts)
A9: BT-0008 | B9: Customer | C9: Address book | D9: Automated. npx vitest run tests/integration/addresses.test.ts -> suite 'updateAddress' -> test 'throws NOT_FOUND for another user's address' | E9: As asserted by the test: throws NOT_FOUND for another user's address | F9: Passed in 238 ms | G9: Pass | H9: None observed | I9: evidence/vitest-baseline.log (tests/integration/addresses.test.ts)
A10: BT-0009 | B10: Customer | C10: Address book | D10: Automated. npx vitest run tests/integration/addresses.test.ts -> suite 'listAddresses / getAddress / deleteAddress' -> test 'lists only the caller's own, non-deleted addresses, default first' | E10: As asserted by the test: lists only the caller's own, non-deleted addresses, default first | F10: Passed in 263 ms | G10: Pass | H10: None observed | I10: evidence/vitest-baseline.log (tests/integration/addresses.test.ts)
A11: BT-0010 | B11: Customer | C11: Address book | D11: Automated. npx vitest run tests/integration/addresses.test.ts -> suite 'listAddresses / getAddress / deleteAddress' -> test 'soft-deletes so the address no longer appears in the list' | E11: As asserted by the test: soft-deletes so the address no longer appears in the list | F11: Passed in 260 ms | G11: Pass | H11: None observed | I11: evidence/vitest-baseline.log (tests/integration/addresses.test.ts)
A12: BT-0011 | B12: Customer | C12: Address book | D12: Automated. npx vitest run tests/integration/addresses.test.ts -> suite 'listAddresses / getAddress / deleteAddress' -> test 'refuses to delete another user's address' | E12: As asserted by the test: refuses to delete another user's address | F12: Passed in 240 ms | G12: Pass | H12: None observed | I12: evidence/vitest-baseline.log (tests/integration/addresses.test.ts)
... A638: BT-S09 | B638: Not run | C638: Live Cashfree sandbox, Google OAuth, Google Geocoding | D638: - | E638: - | F638: NOT RUN: external services; tests stub or mock them. | G638: Not run | H638: - | I638: -

Sheet Summary
A1: Baseline test report - summary
A2: Run 2026-09-22 on Windows 11, Node v24.18.1, PostgreSQL 16 (local, 127.0.0.1:54329, database gokesari_pmd_test, 16 migrations). Formulas are live; blue = snapshot at generation.
A4: Measure | B4: Value (formula) | C4: Snapshot
A5: Automated tests executed | B5: =COUNTIF('Baseline Tests'!$A$2:$A$629,"BT-0*") | C5: 628
A6: Passed | B6: =COUNTIFS('Baseline Tests'!$A$2:$A$629,"BT-0*",'Baseline Tests'!$G$2:$G$629,"Pass") | C6: 626
A7: Failed | B7: =COUNTIFS('Baseline Tests'!$A$2:$A$629,"BT-0*",'Baseline Tests'!$G$2:$G$629,"Fail") | C7: 2
A8: Pass rate | B8: =B6/B5 | C8: 0.99681529
A9: Failed tests that are Windows CRLF artefacts (pmd-docs) | B9: =COUNTIFS('Baseline Tests'!$C$2:$C$629,"Generated docs match code (unit)",'Baseline Tests'!$G$2:$G$629,"Fail") | C9: 2
A10: Functional failures (failed minus CRLF artefacts) | B10: =B7-B9 | C10: 0
A12: By module (formulas over automated rows)
A13: Module | B13: Tests | C13: Passed | D13: Failed
A14: Customer | B14: =COUNTIFS('Baseline Tests'!$B$2:$B$629,A14,'Baseline Tests'!$A$2:$A$629,"BT-0*") | C14: =COUNTIFS('Baseline Tests'!$B$2:$B$629,A14,'Baseline Tests'!$G$2:$G$629,"Pass",'Baseline Tests'!$A$2:$A$629,"BT-0*") | D14: =B14-C14
A15: RBAC | B15: =COUNTIFS('Baseline Tests'!$B$2:$B$629,A15,'Baseline Tests'!$A$2:$A$629,"BT-0*") | C15: =COUNTIFS('Baseline Tests'!$B$2:$B$629,A15,'Baseline Tests'!$G$2:$G$629,"Pass",'Baseline Tests'!$A$2:$A$629,"BT-0*") | D15: =B15-C15
A16: Payments | B16: =COUNTIFS('Baseline Tests'!$B$2:$B$629,A16,'Baseline Tests'!$A$2:$A$629,"BT-0*") | C16: =COUNTIFS('Baseline Tests'!$B$2:$B$629,A16,'Baseline Tests'!$G$2:$G$629,"Pass",'Baseline Tests'!$A$2:$A$629,"BT-0*") | D16: =B16-C16
A17: Orders | B17: =COUNTIFS('Baseline Tests'!$B$2:$B$629,A17,'Baseline Tests'!$A$2:$A$629,"BT-0*") | C17: =COUNTIFS('Baseline Tests'!$B$2:$B$629,A17,'Baseline Tests'!$G$2:$G$629,"Pass",'Baseline Tests'!$A$2:$A$629,"BT-0*") | D17: =B17-C17
A18: Delivery | B18: =COUNTIFS('Baseline Tests'!$B$2:$B$629,A18,'Baseline Tests'!$A$2:$A$629,"BT-0*") | C18: =COUNTIFS('Baseline Tests'!$B$2:$B$629,A18,'Baseline Tests'!$G$2:$G$629,"Pass",'Baseline Tests'!$A$2:$A$629,"BT-0*") | D18: =B18-C18
A19: Catalogue | B19: =COUNTIFS('Baseline Tests'!$B$2:$B$629,A19,'Baseline Tests'!$A$2:$A$629,"BT-0*") | C19: =COUNTIFS('Baseline Tests'!$B$2:$B$629,A19,'Baseline Tests'!$G$2:$G$629,"Pass",'Baseline Tests'!$A$2:$A$629,"BT-0*") | D19: =B19-C19
A20: Shop/Customer | B20: =COUNTIFS('Baseline Tests'!$B$2:$B$629,A20,'Baseline Tests'!$A$2:$A$629,"BT-0*") | C20: =COUNTIFS('Baseline Tests'!$B$2:$B$629,A20,'Baseline Tests'!$G$2:$G$629,"Pass",'Baseline Tests'!$A$2:$A$629,"BT-0*") | D20: =B20-C20
A21: Compliance | B21: =COUNTIFS('Baseline Tests'!$B$2:$B$629,A21,'Baseline Tests'!$A$2:$A$629,"BT-0*") | C21: =COUNTIFS('Baseline Tests'!$B$2:$B$629,A21,'Baseline Tests'!$G$2:$G$629,"Pass",'Baseline Tests'!$A$2:$A$629,"BT-0*") | D21: =B21-C21
A22: Shop | B22: =COUNTIFS('Baseline Tests'!$B$2:$B$629,A22,'Baseline Tests'!$A$2:$A$629,"BT-0*") | C22: =COUNTIFS('Baseline Tests'!$B$2:$B$629,A22,'Baseline Tests'!$G$2:$G$629,"Pass",'Baseline Tests'!$A$2:$A$629,"BT-0*") | D22: =B22-C22
A23: Product Master | B23: =COUNTIFS('Baseline Tests'!$B$2:$B$629,A23,'Baseline Tests'!$A$2:$A$629,"BT-0*") | C23: =COUNTIFS('Baseline Tests'!$B$2:$B$629,A23,'Baseline Tests'!$G$2:$G$629,"Pass",'Baseline Tests'!$A$2:$A$629,"BT-0*") | D23: =B23-C23
A24: Catalogue/Inventory | B24: =COUNTIFS('Baseline Tests'!$B$2:$B$629,A24,'Baseline Tests'!$A$2:$A$629,"BT-0*") | C24: =COUNTIFS('Baseline Tests'!$B$2:$B$629,A24,'Baseline Tests'!$G$2:$G$629,"Pass",'Baseline Tests'!$A$2:$A$629,"BT-0*") | D24: =B24-C24
A25: Subscriptions | B25: =COUNTIFS('Baseline Tests'!$B$2:$B$629,A25,'Baseline Tests'!$A$2:$A$629,"BT-0*") | C25: =COUNTIFS('Baseline Tests'!$B$2:$B$629,A25,'Baseline Tests'!$G$2:$G$629,"Pass",'Baseline Tests'!$A$2:$A$629,"BT-0*") | D25: =B25-C25
A26: Wallet | B26: =COUNTIFS('Baseline Tests'!$B$2:$B$629,A26,'Baseline Tests'!$A$2:$A$629,"BT-0*") | C26: =COUNTIFS('Baseline Tests'!$B$2:$B$629,A26,'Baseline Tests'!$G$2:$G$629,"Pass",'Baseline Tests'!$A$2:$A$629,"BT-0*") | D26: =B26-C26

Sheet Checks & Not Run
A1: Type | B1: Detail
A2: Safety controls | B2: All database work used the LOCAL cluster only. TEST_DATABASE_URL and DATABASE_URL were forced to postgresql://pmd_admin@127.0.0.1:54329/gokesari_pmd_test; the script aborts if that is not the effective URL. .env points at Neon, so nothing else would have been safe.
A3: Safety controls | B3: Google Maps server/browser keys, Google OAuth, Cashfree keys and the PAN encryption key from .env were overridden with blanks or test values so no billable or real-credential call could occur.
A4: Not run | B4: Playwright E2E (tests/e2e/acceptance.spec.ts): needs a browser download; not part of CI. Recommend installing browsers and running it before Phase 4 begins.
A5: Not run | B5: Browser UI smoke test: the automated suite exercises services and the database, not screens or route wiring (only the Product Master routes have route-level tests).
A6: Not run | B6: Anything on the hosted sites beyond a read-only GET of /api/auth/providers. No writes were made to test.gokesari.com, gokesari.com, Neon or any hosted database.
A7: Limits | B7: Test titles are the specification of 'expected'; the two Windows CRLF failures are documented in the Existing defect column.
A8: Limits | B8: Cron scheduling for the daily-order engine on hosted environments cannot be observed from the repository.

Sheet Files
A1: Test file (tests/**/<name>.test.ts) | B1: Module | C1: Tests | D1: Result
A2: addresses | B2: Customer | C2: 11 | D2: Pass
A3: authorization | B3: RBAC | C3: 28 | D3: Pass
A4: cashfree order confirmation | B4: Payments | C4: 6 | D4: Pass
A5: checkout | B5: Orders | C5: 7 | D5: Pass
A6: consents | B6: Customer | C6: 4 | D6: Pass
A7: delivery assignment | B7: Delivery | C7: 14 | D7: Pass
A8: delivery partners | B8: Delivery | C8: 17 | D8: Pass
A9: excel goods upload | B9: Catalogue | C9: 9 | D9: Pass
A10: geocoding | B10: Shop/Customer | C10: 7 | D10: Pass
A11: grievances | B11: Compliance | C11: 14 | D11: Pass
A12: gst pan verification | B12: Shop | C12: 16 | D12: Pass
A13: order cancel refund | B13: Orders | C13: 2 | D13: Pass
... A42: webhook signature | B42: Payments | C42: 5 | D42: Pass
