Workbook

Sheet Summary
A1: GoKesari (gokesari.com) - features, process flows and PR status
A2: As of 18 Oct 2026, 13:45 UTC. Production = main @c96cd04 (gokesari.com, migrations to 0078): release #185 (16 Oct 04:24 UTC) added the PMD loader fix (#184) and report docs (#181, #182) to the 15 Oct releases (#175, #177, #179). Test site = staging @3a701c9, same application code as main (#186, #187). Open PRs: #183 (status-report docs), #188 (competitive analysis deck, docs). Sub-feature sheets: 'Bulk Product Upload' and 'Inventory & Accounting'.
A3: Baseline = the 16 Oct status report (267 features, PR #183), plus PRs #185-#188. 'Status 16 Oct' is that report's status for comparison.
A4: Status is development status read from code, PRs, docs, recorded test runs and live checks - not QA sign-off. 'Baseline' in a PR column = code that predates PR #1 in this repository (Aug-Sep 2026 history).
A5: To update: change Status in the Feature Register (column I) or a step in the Process Flow Tree (column G) with the dropdown - every count on this sheet is a formula. 'Status 16 Oct' is unchanged for comparison.
A7: 1. Features by status
A8: Status | B8: Features | C8: % of total | D8: Status 16 Oct | E8: Meaning
A9: COMPLETED | B9: =COUNTIF('Feature Register'!$I$2:$I$268,A9) | C9: =IF($B$13=0,0,B9/$B$13) | D9: =COUNTIF('Feature Register'!$P$2:$P$268,A9) | E9: Built, merged and live on gokesari.com (incl. built but switched off by default), or finished tooling / test runs
A10: IN PROGRESS | B10: =COUNTIF('Feature Register'!$I$2:$I$268,A10) | C10: =IF($B$13=0,0,B10/$B$13) | D10: =COUNTIF('Feature Register'!$P$2:$P$268,A10) | E10: Started: partly working, being run, or built and on the test site but not yet released
A11: YET TO START | B11: =COUNTIF('Feature Register'!$I$2:$I$268,A11) | C11: =IF($B$13=0,0,B11/$B$13) | D11: =COUNTIF('Feature Register'!$P$2:$P$268,A11) | E11: Not built yet (designed, planned or a known gap)
A12: BLOCKED | B12: =COUNTIF('Feature Register'!$I$2:$I$268,A12) | C12: =IF($B$13=0,0,B12/$B$13) | D12: =COUNTIF('Feature Register'!$P$2:$P$268,A12) | E12: Cannot proceed until a decision, vendor, account, agreement or CA/legal check
A13: Total features tracked | B13: =SUM(B9:B12) | C13: =SUM(C9:C12) | D13: =SUM(D9:D12) | E13: Status 16 Oct counts the 16 Oct report's status for every row (267).
A15: 2. Features by section and status
A16: Section | B16: COMPLETED | C16: IN PROGRESS | D16: YET TO START | E16: BLOCKED | F16: Total | G16: % complete
A17: Feature Master | B17: =COUNTIFS('Feature Register'!$B$2:$B$268,$A17,'Feature Register'!$I$2:$I$268,B$16) | C17: =COUNTIFS('Feature Register'!$B$2:$B$268,$A17,'Feature Register'!$I$2:$I$268,C$16) | D17: =COUNTIFS('Feature Register'!$B$2:$B$268,$A17,'Feature Register'!$I$2:$I$268,D$16) | E17: =COUNTIFS('Feature Register'!$B$2:$B$268,$A17,'Feature Register'!$I$2:$I$268,E$16) | F17: =SUM(B17:E17) | G17: =IF(F17=0,0,B17/F17)
A18: Workflow Master | B18: =COUNTIFS('Feature Register'!$B$2:$B$268,$A18,'Feature Register'!$I$2:$I$268,B$16) | C18: =COUNTIFS('Feature Register'!$B$2:$B$268,$A18,'Feature Register'!$I$2:$I$268,C$16) | D18: =COUNTIFS('Feature Register'!$B$2:$B$268,$A18,'Feature Register'!$I$2:$I$268,D$16) | E18: =COUNTIFS('Feature Register'!$B$2:$B$268,$A18,'Feature Register'!$I$2:$I$268,E$16) | F18: =SUM(B18:E18) | G18: =IF(F18=0,0,B18/F18)
A19: RBAC Matrix | B19: =COUNTIFS('Feature Register'!$B$2:$B$268,$A19,'Feature Register'!$I$2:$I$268,B$16) | C19: =COUNTIFS('Feature Register'!$B$2:$B$268,$A19,'Feature Register'!$I$2:$I$268,C$16) | D19: =COUNTIFS('Feature Register'!$B$2:$B$268,$A19,'Feature Register'!$I$2:$I$268,D$16) | E19: =COUNTIFS('Feature Register'!$B$2:$B$268,$A19,'Feature Register'!$I$2:$I$268,E$16) | F19: =SUM(B19:E19) | G19: =IF(F19=0,0,B19/F19)
A20: State Machines | B20: =COUNTIFS('Feature Register'!$B$2:$B$268,$A20,'Feature Register'!$I$2:$I$268,B$16) | C20: =COUNTIFS('Feature Register'!$B$2:$B$268,$A20,'Feature Register'!$I$2:$I$268,C$16) | D20: =COUNTIFS('Feature Register'!$B$2:$B$268,$A20,'Feature Register'!$I$2:$I$268,D$16) | E20: =COUNTIFS('Feature Register'!$B$2:$B$268,$A20,'Feature Register'!$I$2:$I$268,E$16) | F20: =SUM(B20:E20) | G20: =IF(F20=0,0,B20/F20)
A21: Gig Assignment Rules | B21: =COUNTIFS('Feature Register'!$B$2:$B$268,$A21,'Feature Register'!$I$2:$I$268,B$16) | C21: =COUNTIFS('Feature Register'!$B$2:$B$268,$A21,'Feature Register'!$I$2:$I$268,C$16) | D21: =COUNTIFS('Feature Register'!$B$2:$B$268,$A21,'Feature Register'!$I$2:$I$268,D$16) | E21: =COUNTIFS('Feature Register'!$B$2:$B$268,$A21,'Feature Register'!$I$2:$I$268,E$16) | F21: =SUM(B21:E21) | G21: =IF(F21=0,0,B21/F21)
A22: Navigation | B22: =COUNTIFS('Feature Register'!$B$2:$B$268,$A22,'Feature Register'!$I$2:$I$268,B$16) | C22: =COUNTIFS('Feature Register'!$B$2:$B$268,$A22,'Feature Register'!$I$2:$I$268,C$16) | D22: =COUNTIFS('Feature Register'!$B$2:$B$268,$A22,'Feature Register'!$I$2:$I$268,D$16) | E22: =COUNTIFS('Feature Register'!$B$2:$B$268,$A22,'Feature Register'!$I$2:$I$268,E$16) | F22: =SUM(B22:E22) | G22: =IF(F22=0,0,B22/F22)
A23: KPIs | B23: =COUNTIFS('Feature Register'!$B$2:$B$268,$A23,'Feature Register'!$I$2:$I$268,B$16) | C23: =COUNTIFS('Feature Register'!$B$2:$B$268,$A23,'Feature Register'!$I$2:$I$268,C$16) | D23: =COUNTIFS('Feature Register'!$B$2:$B$268,$A23,'Feature Register'!$I$2:$I$268,D$16) | E23: =COUNTIFS('Feature Register'!$B$2:$B$268,$A23,'Feature Register'!$I$2:$I$268,E$16) | F23: =SUM(B23:E23) | G23: =IF(F23=0,0,B23/F23)
A24: Added features (to 6 Oct) | B24: =COUNTIFS('Feature Register'!$B$2:$B$268,$A24,'Feature Register'!$I$2:$I$268,B$16) | C24: =COUNTIFS('Feature Register'!$B$2:$B$268,$A24,'Feature Register'!$I$2:$I$268,C$16) | D24: =COUNTIFS('Feature Register'!$B$2:$B$268,$A24,'Feature Register'!$I$2:$I$268,D$16) | E24: =COUNTIFS('Feature Register'!$B$2:$B$268,$A24,'Feature Register'!$I$2:$I$268,E$16) | F24: =SUM(B24:E24) | G24: =IF(F24=0,0,B24/F24)
A25: Delivered or started since 6 Oct | B25: =COUNTIFS('Feature Register'!$B$2:$B$268,$A25,'Feature Register'!$I$2:$I$268,B$16) | C25: =COUNTIFS('Feature Register'!$B$2:$B$268,$A25,'Feature Register'!$I$2:$I$268,C$16) | D25: =COUNTIFS('Feature Register'!$B$2:$B$268,$A25,'Feature Register'!$I$2:$I$268,D$16) | E25: =COUNTIFS('Feature Register'!$B$2:$B$268,$A25,'Feature Register'!$I$2:$I$268,E$16) | F25: =SUM(B25:E25) | G25: =IF(F25=0,0,B25/F25)
A26: Delivered or started since 8 Oct | B26: =COUNTIFS('Feature Register'!$B$2:$B$268,$A26,'Feature Register'!$I$2:$I$268,B$16) | C26: =COUNTIFS('Feature Register'!$B$2:$B$268,$A26,'Feature Register'!$I$2:$I$268,C$16) | D26: =COUNTIFS('Feature Register'!$B$2:$B$268,$A26,'Feature Register'!$I$2:$I$268,D$16) | E26: =COUNTIFS('Feature Register'!$B$2:$B$268,$A26,'Feature Register'!$I$2:$I$268,E$16) | F26: =SUM(B26:E26) | G26: =IF(F26=0,0,B26/F26)
A27: Delivered or started since 9 Oct | B27: =COUNTIFS('Feature Register'!$B$2:$B$268,$A27,'Feature Register'!$I$2:$I$268,B$16) | C27: =COUNTIFS('Feature Register'!$B$2:$B$268,$A27,'Feature Register'!$I$2:$I$268,C$16) | D27: =COUNTIFS('Feature Register'!$B$2:$B$268,$A27,'Feature Register'!$I$2:$I$268,D$16) | E27: =COUNTIFS('Feature Register'!$B$2:$B$268,$A27,'Feature Register'!$I$2:$I$268,E$16) | F27: =SUM(B27:E27) | G27: =IF(F27=0,0,B27/F27)
A28: Delivered or started since 10 Oct | B28: =COUNTIFS('Feature Register'!$B$2:$B$268,$A28,'Feature Register'!$I$2:$I$268,B$16) | C28: =COUNTIFS('Feature Register'!$B$2:$B$268,$A28,'Feature Register'!$I$2:$I$268,C$16) | D28: =COUNTIFS('Feature Register'!$B$2:$B$268,$A28,'Feature Register'!$I$2:$I$268,D$16) | E28: =COUNTIFS('Feature Register'!$B$2:$B$268,$A28,'Feature Register'!$I$2:$I$268,E$16) | F28: =SUM(B28:E28) | G28: =IF(F28=0,0,B28/F28)
... A33: Known gaps (not started) | B33: =COUNTIFS('Feature Register'!$B$2:$B$268,$A33,'Feature Register'!$I$2:$I$268,B$16) | C33: =COUNTIFS('Feature Register'!$B$2:$B$268,$A33,'Feature Register'!$I$2:$I$268,C$16) | D33: =COUNTIFS('Feature Register'!$B$2:$B$268,$A33,'Feature Register'!$I$2:$I$268,D$16) | E33: =COUNTIFS('Feature Register'!$B$2:$B$268,$A33,'Feature Register'!$I$2:$I$268,E$16) | F33: =SUM(B33:E33) | G33: =IF(F33=0,0,B33/F33)
A34: Total | B34: =SUM(B17:B33) | C34: =SUM(C17:C33) | D34: =SUM(D17:D33) | E34: =SUM(E17:E33) | F34: =SUM(F17:F33) | G34: =IF(F34=0,0,B34/F34)
A36: 3. Where features run
A37: Where it runs | B37: Features
A38: Production (gokesari.com) | B38: =COUNTIF('Feature Register'!$J$2:$J$268,A38)
A39: Production - built, switched off by default | B39: =COUNTIF('Feature Register'!$J$2:$J$268,A39)
A40: Production - partly live | B40: =COUNTIF('Feature Register'!$J$2:$J$268,A40)
A41: Test site only (test.gokesari.com) | B41: =COUNTIF('Feature Register'!$J$2:$J$268,A41)
A42: Test site only - production release reverted (#87) | B42: =COUNTIF('Feature Register'!$J$2:$J$268,A42)
A43: Open PR - not merged | B43: =COUNTIF('Feature Register'!$J$2:$J$268,A43)
A44: Mobile app - Android test builds only (not in stores) | B44: =COUNTIF('Feature Register'!$J$2:$J$268,A44)
A45: GitHub Actions (runs from main) | B45: =COUNTIF('Feature Register'!$J$2:$J$268,A45)
A46: GitHub Actions (runs from staging) | B46: =COUNTIF('Feature Register'!$J$2:$J$268,A46)
A47: On staging only - not yet runnable | B47: =COUNTIF('Feature Register'!$J$2:$J$268,A47)
A48: Not started | B48: =COUNTIF('Feature Register'!$J$2:$J$268,A48)
A49: Total | B49: =SUM(B38:B48)
A51: 4. Process flow steps by status
A52: Status | B52: Steps (level 3) | C52: Stages (level 2) | D52: Flows (level 1)
A53: COMPLETED | B53: =COUNTIFS('Process Flow Tree'!$B$5:$B$217,3,'Process Flow Tree'!$G$5:$G$217,$A53) | C53: =COUNTIFS('Process Flow Tree'!$B$5:$B$217,2,'Process Flow Tree'!$G$5:$G$217,$A53) | D53: =COUNTIFS('Process Flow Tree'!$B$5:$B$217,1,'Process Flow Tree'!$G$5:$G$217,$A53)
A54: IN PROGRESS | B54: =COUNTIFS('Process Flow Tree'!$B$5:$B$217,3,'Process Flow Tree'!$G$5:$G$217,$A54) | C54: =COUNTIFS('Process Flow Tree'!$B$5:$B$217,2,'Process Flow Tree'!$G$5:$G$217,$A54) | D54: =COUNTIFS('Process Flow Tree'!$B$5:$B$217,1,'Process Flow Tree'!$G$5:$G$217,$A54)
A55: YET TO START | B55: =COUNTIFS('Process Flow Tree'!$B$5:$B$217,3,'Process Flow Tree'!$G$5:$G$217,$A55) | C55: =COUNTIFS('Process Flow Tree'!$B$5:$B$217,2,'Process Flow Tree'!$G$5:$G$217,$A55) | D55: =COUNTIFS('Process Flow Tree'!$B$5:$B$217,1,'Process Flow Tree'!$G$5:$G$217,$A55)
A56: BLOCKED | B56: =COUNTIFS('Process Flow Tree'!$B$5:$B$217,3,'Process Flow Tree'!$G$5:$G$217,$A56) | C56: =COUNTIFS('Process Flow Tree'!$B$5:$B$217,2,'Process Flow Tree'!$G$5:$G$217,$A56) | D56: =COUNTIFS('Process Flow Tree'!$B$5:$B$217,1,'Process Flow Tree'!$G$5:$G$217,$A56)
A57: Total | B57: =SUM(B53:B56) | C57: =SUM(C53:C56) | D57: =SUM(D53:D56)
A59: 5. Pull requests
A60: PR state | B60: PRs
A61: Merged | B61: =COUNTIF('PR Register'!$F$2:$F$189,A61)
A62: Open | B62: =COUNTIF('PR Register'!$F$2:$F$189,A62)
A63: Open (draft) | B63: =COUNTIF('PR Register'!$F$2:$F$189,A63)
A64: Closed - not merged | B64: =COUNTIF('PR Register'!$F$2:$F$189,A64)
A65: Total | B65: =SUM(B61:B64)
A66: PR type | B66: PRs
A67: Branding | B67: =COUNTIF('PR Register'!$C$2:$C$189,A67)
A68: DevOps / repo | B68: =COUNTIF('PR Register'!$C$2:$C$189,A68)
A69: Docs / reports | B69: =COUNTIF('PR Register'!$C$2:$C$189,A69)
A70: Feature | B70: =COUNTIF('PR Register'!$C$2:$C$189,A70)
A71: Fix / hotfix | B71: =COUNTIF('PR Register'!$C$2:$C$189,A71)
A72: Improvement | B72: =COUNTIF('PR Register'!$C$2:$C$189,A72)
A73: Platform port | B73: =COUNTIF('PR Register'!$C$2:$C$189,A73)
A74: QA / tests | B74: =COUNTIF('PR Register'!$C$2:$C$189,A74)
A75: Release (staging -> main) | B75: =COUNTIF('PR Register'!$C$2:$C$189,A75)
A76: Release + direct commits (Phases A-J) | B76: =COUNTIF('PR Register'!$C$2:$C$189,A76)
A77: Revert | B77: =COUNTIF('PR Register'!$C$2:$C$189,A77)
A78: Security / dependencies | B78: =COUNTIF('PR Register'!$C$2:$C$189,A78)
A79: Test data / settings | B79: =COUNTIF('PR Register'!$C$2:$C$189,A79)
A80: Total | B80: =SUM(B67:B79)
A82: 6. Headlines (18 Oct 2026)
A83: 1. Release #185 (16 Oct 04:24 UTC, no migrations) put the PMD loader race fix (#184) on gokesari.com; staging is level with main (#187). No feature changed status since 16 Oct: 227 of 267 COMPLETED (85 %), 2 IN PROGRESS, 19 YET TO START, 19 BLOCKED. Live checks 18 Oct 13:45 UTC: gokesari.com, /shops and test.gokesari.com 200; /shop/accounts and /shop/product-import 307 (sign-in).
A84: 2. Live on gokesari.com since 15 Oct: Inventory & Accounting for shop owners (NEW-067: 49 of 56 sub-features Done, 6 Blocked on owner choices / accounts, 1 In progress) and bulk product upload (GS-013: 15 of 17 sub-features Done on Prod; Android store build in progress, iPhone build blocked on Apple / Expo accounts).
A85: 3. Blockers #56 (flaky PMD parallel-loader test) is resolved on main. Correction: #178 (#169 test results) was merged on 15 Oct, not an open draft.
A86: 4. Open PRs are docs only: #183 (15/16 Oct status workbooks - merge or close, this report supersedes it) and #188 (competitive analysis deck vs Amazon, Flipkart, Blinkit, Zepto, Instamart and others, 18 Oct).
A87: 5. Biggest go-live gates unchanged: per-order online payment decision (GS-028 / NEW-007, Blockers #5), SMS / OTP vendor (D2, #6), 791-case browser QA plan not run (QA-003, #3), production cron jobs (#4), email sending capacity (#25), and the production lifecycle run with a real payment (QA-009, #44).
A88: 6. Database split (PLT-015): production run 19 PASSED; the site still reads one database; phases 2-4 not started.
A89: 7. Still open owner actions: reset the database password posted in chat (#33); delete the copy-shops SQL files (#39); PROD_DATABASE_URL for Actions (#32); Maps server key (#31); Apple / Expo secrets (#29); valid INTEGRATION_ENCRYPTION_KEY (#51); GSP choice (#52).

Sheet Batch 2026-10
A1: GoKesari build & integrate batch (18 Oct 2026) — status of every flow step in the brief
A2: DONE = built, merged, tested; DONE-SANDBOX = complete on the sandbox/mock provider, production flag OFF until the owner's keys exist
A4: Flow / step ID | B4: Step | C4: Batch status | D4: PR(s) | E4: Gap / note
A5: F1.1.2 | B5: Prove the mobile number by SMS OTP | C5: DONE | D5: #190, #192, #194 | E5: Email channel live: OtpProvider routing, 6-digit codes, 5-minute expiry (verified on test.gokesari.com: emails now say 5 minutes), 5 attempts, resend cooldown, DB-backed limits per email/user/IP, hashed + audited, hourly purge. 'OTP sent to your email' wording. SMS = Phase-2 stub (vendor decision D2).
A6: F1.4.3 | B6: Online (e-commerce) reference prices shown to customers | C6: DROPPED | D6: #190, #194 | E6: Dropped by a code constant (not a setting): hidden on product pages and for shops, public API 404, admin menu entry removed, no scraping or external calls at runtime; PR #23 code kept and isolated; offline Open Prices CLI refuses to run.
A7: F1.7.3 | B7: Pay the order directly by UPI / card / netbanking | C7: DONE-SANDBOX | D7: #190, #192, #194 | E7: PaymentGateway interface: sandbox (working on test.gokesari.com after #192), Cashfree adapter, Razorpay/PhonePe scaffolds; UPI/card/netbanking via hosted checkout only (no card data). Production flag onlinePayments OFF until gateway choice, merchant account, live keys and webhook secret (Owner inputs §1-2).
A8: F1.8.4 | B8: Gateway payment confirmation and payment state machine | C8: DONE-SANDBOX | D8: #190, #192, #194 | E8: Payment state machine CREATED>PENDING>AUTHORIZED>CAPTURED>(PARTIALLY_)REFUNDED + FAILED/EXPIRED; signed webhooks, idempotent by event id, reconciled with the gateway's order status; 5-minute reconciliation job; order idempotency key; order CONFIRMED only on CAPTURED.
A9: F3.3.2 | B9: Broadcast offers / widen the radius | C9: DONE | D9: #190, #194 | E9: Rider side: broadcast after N s, radius 2>4>6 km, atomic first accept, 'Offer taken' (rule dispatchBroadcast, OFF until the owner switches it on). Owner request: admin/operator broadcasts (audience, city/PIN, schedule, expiry) + Notification Centre (bell + /notifications, read/unread) on web and app; push/email by opt-in.
A10: F4.1.3 | B10: Pickup by QR code | C10: DONE | D10: #190, #192, #194 | E10: Signed single-use QR (HMAC) on the shop screen and printable packing slip; camera scan in the rider app; PICKED_UP with time + GPS, customer told at once; typed-code fallback. Rule pickupQr OFF; on gokesari.com set PICKUP_QR_SECRET first.
A11: F4.2.2 | B11: In-app turn-by-turn navigation | C11: DONE-SANDBOX | D11: #190, #194 | E11: RoutingProvider (mock / Google Routes / OSRM): route line, next manoeuvre, ETA, off-route re-route, voice prompts, Open-in-Google-Maps; keeps feeding live tracking. Mock router on test; real directions need a Google Routes key or own OSRM server. Rule riderNavigation OFF.
A12: F4.2.6 | B12: Signature capture | C12: DEFERRED-PHASE-2 | D12: - | E12: Signature capture deferred to Phase 2 by the owner; not built.
A13: F6.1.3 | B13: After-packing treatments (D10) signed off | C13: DONE | D13: #190, #194 | E13: Before packing: full refund incl. delivery (unchanged). After packing: per-shop fee (amount or %, cap, on/off) within admin limits, shown before confirming, written to the order ledger. Rule afterPackingCancellation OFF until the refund policy text is updated.
A14: F6.2.3 | B14: Refund to card / UPI | C14: DONE-SANDBOX | D14: #190, #194 | E14: Itemised refund breakdown; customer chooses original method (gateway refund API, intent > REFUNDED/PARTIALLY_REFUNDED) or instant wallet (wallet created if missing); wallet/COD orders refund to wallet; email + push; refund timeline in the order. Original-method refunds live with onlinePayments.
A15: F6.3.3 | B15: Issue state machine scope (SM-006) | C15: DONE | D15: #190, #194 | E15: Ticket state machine (OPEN>ACK>IN_PROGRESS>AWAITING_CUSTOMER/SHOP>RESOLVED>CLOSED + REOPENED/ESCALATED), portal + from the order, attachments, queues, assignment, internal notes, canned replies, SLA timers + escalation (Rule 4: 48 h / one month, configurable), CSAT, notify every change, Grievance Officer editable in Admin. Counsel to confirm the rule text.
... A28: F15.2.3 | B28: gokesari.com links open the app (deep links) | C28: BLOCKED-OWNER-INPUT | D28: #190, #194 | E28: Built and live on test: assetlinks.json (host-aware package) and apple-app-site-association (no extension, application/json) always served, intent filters with autoVerify, associated domains, route map product/shop/order/invite/notification/ticket, in-app routing, web fallback. Activates when the owner sets the SHA-256 fingerprint and Apple Team ID (docs/deep-links-activation.md).
A30: Totals
A31: DONE | B31: =COUNTIF($C$5:$C$28,"DONE")
A32: DONE-SANDBOX | B32: =COUNTIF($C$5:$C$28,"DONE-SANDBOX")
A33: DROPPED | B33: =COUNTIF($C$5:$C$28,"DROPPED")
A34: DEFERRED-PHASE-2 | B34: =COUNTIF($C$5:$C$28,"DEFERRED-PHASE-2")
A35: ON-HOLD | B35: =COUNTIF($C$5:$C$28,"ON-HOLD")
A36: BLOCKED-OWNER-INPUT | B36: =COUNTIF($C$5:$C$28,"BLOCKED-OWNER-INPUT")

Sheet Bulk Product Upload
A1: Bulk product upload (Excel/CSV) with shop inventory update - sub-feature status
A2: Statuses: Not started / In progress / Done on Test / Done on Prod / Blocked. Design: docs/product-import-2026-10/README.md. Tests: docs/testing/bulk-product-upload-test-report.md.
A4: ID | B4: Sub-feature | C4: Status | D4: Date | E4: Notes | F4: Branch / PR
A5: BPU-01 | B5: Parser (Amazon template) | C5: Done on Prod | D5: 2026-10-15 | E5: Built and unit-tested locally: Template sheet chosen, headings found by content (labels, attribute keys, section headers), ABC123 example + notice rows skipped, key-first mapping with qualifiers stripped (audience kept), repeated #1-#5 columns to arrays, lossless raw cells. 309-column PUZZLES fixture parses in ~0.2 s. Generic: no product-type logic. Not yet on Test. Live on test.gokesari.com 15 Oct: PI-03 pass (PUZZLES.xlsm: 309 columns, rows 6-7 left out, macros not run). Released to gokesari.com 15 Oct 15:58 UTC (PR #179); signed-out prod checks pass. | F5: PR #173, #174, release #179
A6: BPU-02 | B6: Parser (GoKesari template + CSV) | C6: Done on Prod | D6: 2026-10-15 | E6: Simple template (Products + Instructions sheets, Barcode Type/Unit/Action dropdowns, EXAMPLE row never imported) and CSV (comma/semicolon/tab, BOM). Header aliases case-insensitive. Tested locally. Live on test.gokesari.com 15 Oct: PI-02 template download, PI-09 template import pass. Released to gokesari.com 15 Oct 15:58 UTC (PR #179); signed-out prod checks pass. | F6: PR #173, #174, release #179
A7: BPU-03 | B7: Field mapping | C7: Done on Prod | D7: 2026-10-15 | E7: All §2 fields mapped; Indian numbers, dd/mm/yyyy and Excel-serial dates, Y/N, units to cm/g. Unreadable values = warnings, raw kept. Decision: file MRP = listing MRP (shop_listing_details), never master. Live on test.gokesari.com 15 Oct: PI-03/PI-04/PI-09 pass. Released to gokesari.com 15 Oct 15:58 UTC (PR #179); signed-out prod checks pass. | F7: PR #173, #174, release #179
A8: BPU-04 | B8: Matching & master catalogue | C8: Done on Prod | D8: 2026-10-15 | E8: SKU (or P-code) → barcode → name+brand(+size/color) → new Pending product. Pending products visible to the existing duplicate check. Decision: fallback category = General (system 'uncategorised'). Live on test.gokesari.com 15 Oct: PI-05 re-import matched all 5 by SKU (5 updated); PI-11 Edit with no match skipped. Released to gokesari.com 15 Oct 15:58 UTC (PR #179); signed-out prod checks pass. | F8: PR #173, #174, release #179
A9: BPU-05 | B9: Inventory update + ledger | C9: Done on Prod | D9: 2026-10-15 | E9: Set / Add modes, blank / negative / non-numeric quantity rules, duplicate-SKU merge, inventory_movements with source=bulk_upload + import_job_id + user, row lock + atomic add (tested with concurrent orders). Online stock. Live on test.gokesari.com 15 Oct: PI-10 Set 11 then Add 4 = 15; PI-11 blank/negative unchanged; PI-13 Delete = stock 0. Released to gokesari.com 15 Oct 15:58 UTC (PR #179); signed-out prod checks pass. | F9: PR #173, #174, release #179
A10: BPU-06 | B10: Image import | C10: Done on Prod | D10: 2026-10-15 | E10: Async after commit; http/https only, SSRF guard at connect time, JPEG/PNG/WebP, 5 MB, 15 s, each URL once; existing photo pipeline + moderation; failures are row warnings. Live on test.gokesari.com 15 Oct: Fixture image URLs (example CDN) refused with row warnings, products still created. Real image URLs not tried on the site. Released to gokesari.com 15 Oct 15:58 UTC (PR #179); signed-out prod checks pass. | F10: PR #173, #174, release #179
A11: BPU-07 | B11: Web UI (shop owner) | C11: Done on Prod | D11: 2026-10-15 | E11: Inventory → Bulk upload (Excel/CSV) tile; /shop/product-import: drag-and-drop, template, help, background check with progress, preview (summary, paginated table, warnings filter, stock mode), import progress, result + report, history, duplicate-file prompt. Checked in a browser locally (screenshots in docs/product-import-2026-10/screenshots). Live on test.gokesari.com 15 Oct: PI-01..PI-15 pass (desktop + phone cards with the Android app agent). Released to gokesari.com 15 Oct 15:58 UTC (PR #179); signed-out prod checks pass. | F11: PR #173, #174, release #179
A12: BPU-08 | B12: Web UI (admin/operator) | C12: Done on Prod | D12: 2026-10-15 | E12: /admin/product-import with shop picker; tiles under admin Product master and operator Catalogue. Checked locally as admin and operator. Operators' prices go to the owner for approval (existing rule). Live on test.gokesari.com 15 Oct: Admin and operator PS-01..04 pass; operator prices go to the owner, admin prices apply. Released to gokesari.com 15 Oct 15:58 UTC (PR #179); signed-out prod checks pass. | F12: PR #173, #174, release #179
A13: BPU-09 | B13: API | C13: Done on Prod | D13: 2026-10-15 | E13: 8 endpoints under /api/v1 (+ shop picker). Owner = own shops only; operator/admin any shop; audit-logged. Route tests pass. Live on test.gokesari.com 15 Oct: PI-08/PI-09/PI-15 and the staff runs use /api/v1. Released to gokesari.com 15 Oct 15:58 UTC (PR #179); signed-out prod checks pass. | F13: PR #173, #174, release #179
A14: BPU-10 | B14: Android app | C14: In progress | D14: 2026-10-15 | E14: Version 1.1.0 / versionCode 2. The app shows the website: the upload uses Android's system document picker (Files, Drive, WhatsApp, e-mail attachments). APKs built by the PR's 'Android APK' workflow; Play Store AAB needs EAS (Expo account) - not run. Live on test.gokesari.com 15 Oct: APK run 19 (Android APK workflow) built 1.1.0/versionCode 2; phone-width app agent preview pass (PI-12). System file picker on a real phone not tried; AAB needs EAS. | F14: PR #173, #174, release #179
A15: BPU-11 | B15: iOS app | C15: Blocked | D15: 2026-10-15 | E15: Code is shared with Android (version 1.1.0 / buildNumber 2; iPhone Files picker). iPhone build/TestFlight runs on EAS and needs EXPO_TOKEN + Apple Developer account - not available to this session. | F15: PR #173, #174, release #179
... A21: BPU-17 | B21: Testing report | C21: Done on Prod | D21: 2026-10-15 | E21: Test report md + PDF: Test 23/23 (section 2.7), Prod signed-out 13/13 (section 2.8). | F21: PR #173, #174, release #179

Sheet Inventory & Accounting
A1: Inventory & Accounting for shop owners (NEW-067) - feature and sub-feature status
A2: Statuses: Not started / In progress / Done / Blocked (dropdown in column E). Done = built, tested and live on gokesari.com (released by #179). Design: docs/inventory-accounting-2026-10/README.md. Tests: docs/inventory-accounting-2026-10/TESTING_REPORT.md and INVENTORY_ACCOUNTING_TEST_REPORT_2026-10-15.xlsx.
A4: ID | B4: Part | C4: Feature / sub-feature | D4: What it does | E4: Status | F4: Where it runs | G4: Date | H4: Notes / blocked on | I4: PR(s)
A5: IA-001 | B5: 1 Inventory | C5: Product master per shop | D5: Listings linked to the gokesari.com master product (MRP, HSN, GST rate, unit, barcode/GTIN); shop-level HSN/GST/price stay per shop | E5: Done | F5: Production (gokesari.com) and test | G5: 2026-10-15 | H5: - | I5: #171, released #179
A6: IA-002 | B6: 1 Inventory | C6: Stock ledger | D6: inv_stock_ledger: every movement (opening, purchase, sale, sale return, damage/expiry write-off, adjustment, reversal) with date, source document, qty, cost/rate, user; current stock = sum of the ledger | E6: Done | F6: Production (gokesari.com) and test | G6: 2026-10-15 | H6: - | I6: #171, released #179
A7: IA-003 | B7: 1 Inventory | C7: Online orders reduce stock in real time | D7: DB triggers on shop_products / inventory_movements write the ledger row in the checkout / cancellation / subscription / catalogue transaction (event-driven, no cron, existing code unchanged) | E7: Done | F7: Production (gokesari.com) and test | G7: 2026-10-15 | H7: Verified on test.gokesari.com with a real customer order (stock 199 → 198, SALE row with the order id) and its cancellation; a cancellation is labelled SALE_RETURN since migration 0078 (found in staging testing) | I7: #171, #172 (0078), released #179
A8: IA-004 | B8: 1 Inventory | C8: Opening balance backfill | D8: Migration 0076 writes today's stock of every listing as OPENING so ledger = stock from day one; drift check on the stock page | E8: Done | F8: Production (gokesari.com) and test | G8: 2026-10-15 | H8: - | I8: #171, released #179
A9: IA-005 | B9: 1 Inventory | C9: Batch & expiry tracking | D9: Per listing (auto-on when a bill has batch numbers); FEFO batch balances; expiring-soon list with alert window setting | E9: Done | F9: Production (gokesari.com) and test | G9: 2026-10-15 | H9: - | I9: #171, released #179
A10: IA-006 | B10: 1 Inventory | C10: Low stock / reorder level | D10: Existing per-shop thresholds and stock alerts reused; purchases and write-offs re-evaluate alerts | E10: Done | F10: Production (gokesari.com) and test | G10: 2026-10-15 | H10: - | I10: #171, released #179
A11: IA-007 | B11: 1 Inventory | C11: Stock valuation FIFO / weighted average | D11: Selectable per shop; reversals take back exactly the reversed cost; uncosted opening stock valued at last purchase rate and reported | E11: Done | F11: Production (gokesari.com) and test | G11: 2026-10-15 | H11: - | I11: #171, released #179
A12: IA-008 | B12: 1 Inventory | C12: Loose goods & unit conversions | D12: kg/g/L/ml/piece/dozen, UQC codes, Hindi/Marathi unit words; owner-saved conversions (1 case = 24); fractional quantities exact in the ledger | E12: Done | F12: Production (gokesari.com) and test | G12: 2026-10-15 | H12: - | I12: #171, released #179
A13: IA-009 | B13: 1 Inventory | C13: Write-off and physical count | D13: Damage / expiry write-off at cost (P&L line); physical count posts the difference as an adjustment | E13: Done | F13: Production (gokesari.com) and test | G13: 2026-10-15 | H13: - | I13: #171, released #179
A14: IA-010 | B14: 2 Accounting | C14: Purchase register | D14: Confirmed bills, versions, cancellations; month filter | E14: Done | F14: Production (gokesari.com) and test | G14: 2026-10-15 | H14: - | I14: #171, released #179
A15: IA-011 | B15: 2 Accounting | C15: Sales register | D15: Own GST invoices plus GoKesari order tax invoices | E15: Done | F15: Production (gokesari.com) and test | G15: 2026-10-15 | H15: - | I15: #171, released #179
... A60: IA-056 | B60: 7 Data & security | C60: Encryption key on the servers | D60: INTEGRATION_ENCRYPTION_KEY (base64, 32 bytes) set on test.gokesari.com and gokesari.com — needed for GST portal linking and for encrypting stored bills | E60: Blocked | F60: Server settings (test and production) | G60: 2026-10-15 | H60: Owner added the variable on test and production (15 Oct), but the value is not base64 of 32 bytes: test.gokesari.com reports encryption not configured (/api/shops/{id}/integration → ready.encryption=false) and GST linking answers 500. Fix: set the value from `openssl rand -base64 32` (44 characters ending in '='), a different one per site, and redeploy. Nothing has been encrypted with the old values | I60: #171, released #179
A62: Count | B62: Done | C62: =COUNTIF($E$5:$E$60,B62)
B63: In progress | C63: =COUNTIF($E$5:$E$60,B63)
B64: Not started | C64: =COUNTIF($E$5:$E$60,B64)
B65: Blocked | C65: =COUNTIF($E$5:$E$60,B65)
B66: Total | C66: =SUM(C62:C65)

Sheet Feature Register
A1: # | B1: Section | C1: Feature ID | D1: Module / area | E1: Feature | F1: Functionality (what it does today) | G1: Process flow step(s) | H1: Priority | I1: Status (18 Oct 2026) | J1: Where it runs | K1: Switched on? | L1: Built in PR(s) | M1: Released to production in PR(s) | N1: Remaining scope / gap | O1: Blocked on / next step | P1: Status 16 Oct | Q1: Change since 16 Oct (PRs #185-#188) | R1: Evidence (code / docs)
A2: 1 | B2: Feature Master | C2: GS-001 | D2: Identity & Access | E2: Mobile/email/Gmail login | F2: Google, email magic link and a single mobile-or-email form; first-time /onboarding profile; My Profile with verified email change; checkout requires a mobile; admin can release a wrongly claimed number. Login rebuild now on main (was staging-only on 3 Oct). | G2: F1.1.1, F1.1.2, F1.1.3 | H2: P0 | I2: BLOCKED | J2: Production - partly live | K2: Live (email OTP); SMS OTP not available | L2: #10 (magic link); #23 (Phase A mobile OTP); #31 (login rebuild, onboarding, My Profile); #80 (same OTP reply); #121 (one consent box) | M2: #14; #23; #43; #81; #123 | N2: SMS delivery of the OTP so a mobile number is proven (OTP provider seam ready). | O2: D2 - SMS/OTP vendor with DLT registration | P2: BLOCKED | Q2: No change | R2: src/server/otp/providers.ts; src/app/onboarding; src/app/profile; drizzle/0038_login_profile.sql
A3: 2 | B3: Feature Master | C3: GS-002 | D3: Identity & Access | E3: Role-based access control | F3: SOCIETY_ADMIN role; society roles scoped per membership (ADMIN/OPERATOR/RESIDENT) | G3: F5.1.2, F12.2.1 | H3: P0 | I3: COMPLETED | J3: Production (gokesari.com) | K3: Live | L3: Baseline; #10 (SOCIETY_ADMIN); #11 (society roles) | M3: Baseline; #14; #19 | N3: - | O3: - | P3: COMPLETED | Q3: No change | R3: src/server/authz/permissions.ts; src/server/db/schema.ts (userRoleEnum)
A4: 3 | B4: Feature Master | C4: GS-003 | D4: Identity & Access | E4: Multi-role user account | F4: user_role_grants; active role switcher in the header; /api/me/roles; admin revoke; shop/rider/society flows grant roles; staff roles exclusive | G4: F12.2.1 | H4: P1 | I4: COMPLETED | J4: Production (gokesari.com) | K4: Live | L4: #18 | M4: #19 | N4: - | O4: - | P4: COMPLETED | Q4: No change | R4: src/server/services/roles.ts; src/app/api/me/roles/route.ts
A5: 4 | B5: Feature Master | C5: GS-004 | D5: Location | E5: PIN / address selection | F5: 'Deliver to' location: saved address, device position or PIN, remembered in a cookie. Phase B added Maps Places address search, a 'save this place' path, and recipient name / recipient mobile / Home-Work-Other on addresses | G5: F1.2.1 | H5: P0 | I5: COMPLETED | J5: Production (gokesari.com) | K5: Live | L5: Baseline (location capture); #10 (customer location); #23 (Phase B); #83 (Deliver-to pill) | M5: Baseline; #14; #23; #84 | N5: - | O5: - | P5: COMPLETED | Q5: No change | R5: src/lib/geo/provider.ts; src/components/location-bar.tsx; drizzle/0026
A6: 5 | B6: Feature Master | C6: GS-005 | D6: Location | E6: Society identification | F6: Society membership; address <-> society link; orders.society_id | G6: F1.2.2, F5.1.2 | H6: P0 | I6: COMPLETED | J6: Production (gokesari.com) | K6: Live | L6: #11 | M6: #19 | N6: - | O6: - | P6: COMPLETED | Q6: No change | R6: src/server/services/societies.ts
A7: 6 | B7: Feature Master | C7: GS-006 | D7: Shop Onboarding | E7: Shop registration | F7: Shop owner registers a shop (/shop/register): name, owner, address with map location, shop type and categories, at least one of PAN / Udyam / GST / Shop Act; duplicate-registration guard; resubmission after rejection; operations approve or reject. | G7: F8.1.1 | H7: P0 | I7: COMPLETED | J7: Production (gokesari.com) | K7: Live | L7: Baseline; #22 (duplicate guard); #45 (validation, GST field); #53 (documents) | M7: Baseline; #19; #47; #54 | N7: 6 Oct: GST field added at registration; at least one of PAN / Udyam / GST / Shop Act required (135f29a). | O7: - | P7: COMPLETED | Q7: No change | R7: -
A8: 7 | B8: Feature Master | C8: GS-007 | D8: Shop Onboarding | E8: Business KYC | F8: Seller verification Parts 1-4: PAN, GSTIN, Udyam, FSSAI and Shop Act per shop with document upload, vendor check (provider-agnostic, Gridlines adapter + mock), name matching, cross-document consistency score, per-document status, admin review queue (approve / reject with reason / re-check), daily re-check and expiry job, auto-suspend on lapse, DPDP retention/erasure. | G8: F8.2.1 | H8: P0 | I8: COMPLETED | J8: Production (gokesari.com) | K8: Live; vendor checks run on the MOCK vendor until Gridlines keys are set (KYC_PROVIDER) | L8: Baseline (GST/PAN self-service); #53 (seller verification) | M8: Baseline; #54 | N8: Real vendor: Gridlines sandbox then live keys and written confirmation of response fields, Shop Act coverage, prices, DPA. Since SM-002 (PR #58) an admin can approve a shop only once every mandatory document is verified (VERIFIED stage). | O8: - | P8: COMPLETED | Q8: No change | R8: src/server/services/seller-verification*.ts; src/server/kyc/; /shop/verification; /admin/seller-verification; drizzle/0040, 0041; docs/seller-verification/
A9: 8 | B9: Feature Master | C9: GS-008 | D9: Shop Onboarding | E9: Payment reference verification | F9: approveShop() now refuses unless fee_payment_status = PAID (derived from the shop_payments ledger), naming the amount outstanding; waived fee (zero snapshot) is written PAID at registration; approval queue shows each pending shop's fee state. Gate is on the transition only - shops already APPROVED untouched | G9: F8.2.3 | H9: P0 | I9: COMPLETED | J9: Production (gokesari.com) | K9: Live | L9: Baseline (registration fees); #29 (fee gate on approval) | M9: Baseline; #29 | N9: - | O9: - | P9: COMPLETED | Q9: No change | R9: src/server/services/shops.ts (approveShop); src/components/shop-approval-panel.tsx; tests/integration/registration-fees.test.ts
A10: 9 | B10: Feature Master | C10: GS-009 | D10: Shop Onboarding | E10: Shop categories | F10: Admin-configurable category master: shop_categories + shop_category_mapping (many per shop), seeded from the 44 shop types and backfilled; registration requires at least one category; owners edit their own on /shop; operators/admins manage the list at /admin/shop-categories and assign per shop; uncategorised shops flagged; categories feed search relevance | G10: F8.3.2 | H10: P0 | I10: COMPLETED | J10: Production (gokesari.com) | K10: Live | L10: #23 (shop categories); #30 (explicit Save) | M10: #23; #32 | N10: - | O10: - | P10: COMPLETED | Q10: No change | R10: src/server/services/shop-categories.ts; src/app/admin/shop-categories/page.tsx; drizzle/0035
A11: 10 | B11: Feature Master | C11: GS-010 | D11: Shop Onboarding | E11: Service radius / delivery zone | F11: shops.service_radius_km (1-50 km) editable by the shop; Phase B added extra delivery zones by PIN code (shops.delivery_pincodes), honoured by serviceability, checkout and discovery | G11: F8.3.3 | H11: P0 | I11: COMPLETED | J11: Production (gokesari.com) | K11: Live | L11: Baseline; #10 (delivery radius); #23 (Phase B PIN zones) | M11: Baseline; #14; #23 | N11: - | O11: - | P11: COMPLETED | Q11: No change | R11: src/server/services/serviceability.ts; src/server/db/schema.ts:691; drizzle/0019, 0026
A12: 11 | B12: Feature Master | C12: GS-011 | D12: Catalog | E12: Product master | F12: Central product catalogue (products) with brand, pack size, GTIN, HSN, GST rate and MRP; fed by the Product Master Data Platform (PMD) and the category master; shop-created products go through an approval queue. | G12: - | H12: P0 | I12: COMPLETED | J12: Production (gokesari.com) | K12: Live | L12: Baseline (product identity/MRP); #4 (Product Master platform); #38 (category master) | M12: Baseline; #8; #43 | N12: - | O12: - | P12: COMPLETED | Q12: No change | R12: -
A13: 12 | B13: Feature Master | C13: GS-012 | D13: Catalog | E13: Shop catalog mapping | F13: Each shop lists master products as its own listings (shop_products) with its own online and in-shop price, stock and availability; listings follow the shop's product categories. | G13: F9.2.2 | H13: P0 | I13: COMPLETED | J13: Production (gokesari.com) | K13: Live | L13: Baseline (shop-created products); #38 (category visibility); #45 (inventory fill) | M13: Baseline; #43; #47 | N13: - | O13: - | P13: COMPLETED | Q13: No change | R13: -
... A268: 267 | B268: Known gaps (not started) | C268: GAP-019 | D268: Checkout | E268: Wallet checkout takes 30-38 s on the test site | F268: Placing an order with the wallet took 30+ s (timed out once; the retry with the same request id was safe and charged once) and 37.8 s on the rerun. | G268: - | H268: - | I268: YET TO START | J268: Not started | K268: - | L268: - | M268: - | N268: Profile checkout on test; likely the far database (GAP-010) | O268: - | P268: YET TO START | Q268: No change | R268: docs/order-lifecycle-2026-10/TEST_RESULTS_STAGING_2026-10-14.md

Sheet Process Flow Tree
A1: GoKesari process flow trees - status of every step (16 Oct 2026)
A2: Level 1 = end-to-end flow, level 2 = stage, level 3 = step. Step status is set by hand (dropdown in column G); stage and flow status are formulas: COMPLETED only when every step is; BLOCKED if any step is blocked; YET TO START when no step has started; otherwise IN PROGRESS.
A4: Flow / step ID | B4: Level | C4: Process flow tree | D4: Actor | E4: Feature IDs | F4: Steps done | G4: Status | H4: Built in PR(s) | I4: Gap / note | J4: Batch status (18 Oct) | K4: Batch PR(s) | L4: Batch gap / note
A5: F1 | B5: 1 | C5: F1 Customer purchase journey | D5: Customer | F5: =COUNTIFS($B$6:$B$48,3,$G$6:$G$48,"COMPLETED")&" / "&COUNTIF($B$6:$B$48,3) | G5: =IF(COUNTIFS($B$6:$B$48,3,$G$6:$G$48,"COMPLETED")=COUNTIF($B$6:$B$48,3),"COMPLETED",IF(COUNTIFS($B$6:$B$48,3,$G$6:$G$48,"BLOCKED")>0,"BLOCKED",IF(COUNTIFS($B$6:$B$48,3,$G$6:$G$48,"YET TO START")=COUNTIF($B$6:$B$48,3),"YET TO START","IN PROGRESS"))) | J5: =(COUNTIFS($B$6:$B$48,3,$J$6:$J$48,"DONE")+COUNTIFS($B$6:$B$48,3,$J$6:$J$48,"DONE-SANDBOX"))&" / "&COUNTIFS($B$6:$B$48,3,$J$6:$J$48,"<>")&" batch steps done"
A6: F1.1 | B6: 2 | C6: F1.1 Sign in and profile | F6: =COUNTIFS($B$7:$B$9,3,$G$7:$G$9,"COMPLETED")&" / "&COUNTIF($B$7:$B$9,3) | G6: =IF(COUNTIFS($B$7:$B$9,3,$G$7:$G$9,"COMPLETED")=COUNTIF($B$7:$B$9,3),"COMPLETED",IF(COUNTIFS($B$7:$B$9,3,$G$7:$G$9,"BLOCKED")>0,"BLOCKED",IF(COUNTIFS($B$7:$B$9,3,$G$7:$G$9,"YET TO START")=COUNTIF($B$7:$B$9,3),"YET TO START","IN PROGRESS"))) | J6: =(COUNTIFS($B$7:$B$9,3,$J$7:$J$9,"DONE")+COUNTIFS($B$7:$B$9,3,$J$7:$J$9,"DONE-SANDBOX"))&" / "&COUNTIFS($B$7:$B$9,3,$J$7:$J$9,"<>")&" batch steps done"
A7: F1.1.1 | B7: 3 | C7: Sign in with Google, email magic link or a code sent to email (mobile or email form) | D7: Customer | E7: GS-001, NEW-018 | G7: COMPLETED | H7: #10; #23; #31; #80 | I7: -
A8: F1.1.2 | B8: 3 | C8: Prove the mobile number by SMS OTP | D8: Customer | E8: GS-001, GS-074 | G8: COMPLETED | H8: #190, #192, #194 | I8: DONE (18 Oct batch): Email channel live: OtpProvider routing, 6-digit codes, 5-minute expiry (verified on test.gokesari.com: emails now say 5 minutes), 5 attempts, resend cooldown, DB-backed limits per email/user/IP, hashed + audited, hourly purge. 'OTP sent to your email' wording. SMS = Phase-2 stub (vendor decision D2). | J8: DONE | K8: #190, #192, #194 | L8: Email channel live: OtpProvider routing, 6-digit codes, 5-minute expiry (verified on test.gokesari.com: emails now say 5 minutes), 5 attempts, resend cooldown, DB-backed limits per email/user/IP, hashed + audited, hourly purge. 'OTP sent to your email' wording. SMS = Phase-2 stub (vendor decision D2).
A9: F1.1.3 | B9: 3 | C9: First-time profile (/onboarding) and My Profile | D9: Customer | E9: GS-001 | G9: COMPLETED | H9: #31 | I9: -
A10: F1.2 | B10: 2 | C10: F1.2 Location and society | F10: =COUNTIFS($B$11:$B$12,3,$G$11:$G$12,"COMPLETED")&" / "&COUNTIF($B$11:$B$12,3) | G10: =IF(COUNTIFS($B$11:$B$12,3,$G$11:$G$12,"COMPLETED")=COUNTIF($B$11:$B$12,3),"COMPLETED",IF(COUNTIFS($B$11:$B$12,3,$G$11:$G$12,"BLOCKED")>0,"BLOCKED",IF(COUNTIFS($B$11:$B$12,3,$G$11:$G$12,"YET TO START")=COUNTIF($B$11:$B$12,3),"YET TO START","IN PROGRESS"))) | J10: =(COUNTIFS($B$11:$B$12,3,$J$11:$J$12,"DONE")+COUNTIFS($B$11:$B$12,3,$J$11:$J$12,"DONE-SANDBOX"))&" / "&COUNTIFS($B$11:$B$12,3,$J$11:$J$12,"<>")&" batch steps done"
A11: F1.2.1 | B11: 3 | C11: Choose where to deliver: saved address, device position, PIN or map pin | D11: Customer | E11: GS-004 | G11: COMPLETED | H11: #10; #23; #83 | I11: Map 'Confirm location' 500 on test: the server key is restricted by referrer (GAP-008, owner)
A12: F1.2.2 | B12: 3 | C12: Society recognised from the address | D12: Customer | E12: GS-005 | G12: COMPLETED | H12: #11 | I12: -
A13: F1.3 | B13: 2 | C13: F1.3 Discover shops and products | F13: =COUNTIFS($B$14:$B$17,3,$G$14:$G$17,"COMPLETED")&" / "&COUNTIF($B$14:$B$17,3) | G13: =IF(COUNTIFS($B$14:$B$17,3,$G$14:$G$17,"COMPLETED")=COUNTIF($B$14:$B$17,3),"COMPLETED",IF(COUNTIFS($B$14:$B$17,3,$G$14:$G$17,"BLOCKED")>0,"BLOCKED",IF(COUNTIFS($B$14:$B$17,3,$G$14:$G$17,"YET TO START")=COUNTIF($B$14:$B$17,3),"YET TO START","IN PROGRESS"))) | J13: =(COUNTIFS($B$14:$B$17,3,$J$14:$J$17,"DONE")+COUNTIFS($B$14:$B$17,3,$J$14:$J$17,"DONE-SANDBOX"))&" / "&COUNTIFS($B$14:$B$17,3,$J$14:$J$17,"<>")&" batch steps done"
A14: F1.3.1 | B14: 3 | C14: Shops that deliver here / Shops near you, with filters and sort | D14: Customer | E14: GS-019, NAV-001, NEW-019, NEW-051 | G14: COMPLETED | H14: #10; #83 | I14: -
A15: F1.3.2 | B15: 3 | C15: Product search limited to serviceable shops | D15: Customer | E15: GS-020 | G15: COMPLETED | H15: #10; #48; #83 | I15: -
A16: F1.3.3 | B16: 3 | C16: Every shop selling a product | D16: Customer | E16: GS-021 | G16: COMPLETED | H16: #10 | I16: -
A17: F1.3.4 | B17: 3 | C17: Shops near me from the phone's location: radius 1-10 km, list or map, Directions; PIN box if location is refused | D17: Customer | E17: NEW-057, NEW-059 | G17: COMPLETED | H17: #133; #136; #135 | I17: Live on gokesari.com
A18: F1.4 | B18: 2 | C18: F1.4 Compare prices | F18: =COUNTIFS($B$19:$B$21,3,$G$19:$G$21,"COMPLETED")&" / "&COUNTIF($B$19:$B$21,3) | G18: =IF(COUNTIFS($B$19:$B$21,3,$G$19:$G$21,"COMPLETED")=COUNTIF($B$19:$B$21,3),"COMPLETED",IF(COUNTIFS($B$19:$B$21,3,$G$19:$G$21,"BLOCKED")>0,"BLOCKED",IF(COUNTIFS($B$19:$B$21,3,$G$19:$G$21,"YET TO START")=COUNTIF($B$19:$B$21,3),"YET TO START","IN PROGRESS"))) | J18: =(COUNTIFS($B$19:$B$21,3,$J$19:$J$21,"DONE")+COUNTIFS($B$19:$B$21,3,$J$19:$J$21,"DONE-SANDBOX"))&" / "&COUNTIFS($B$19:$B$21,3,$J$19:$J$21,"<>")&" batch steps done"
A19: F1.4.1 | B19: 3 | C19: Local price comparison across shops | D19: Customer | E19: GS-022 | G19: COMPLETED | H19: #10; #72 | I19: -
A20: F1.4.2 | B20: 3 | C20: Home-page price comparison (F9) | D20: Customer | E20: NAV-001 | G20: COMPLETED | H20: #55 | I20: Off by default
A21: F1.4.3 | B21: 3 | C21: Online (e-commerce) reference prices shown to customers | D21: Customer | E21: GS-023 | G21: BLOCKED | H21: #23; #190, #194 | I21: DROPPED (18 Oct batch): Dropped by a code constant (not a setting): hidden on product pages and for shops, public API 404, admin menu entry removed, no scraping or external calls at runtime; PR #23 code kept and isolated; offline Open Prices CLI refuses to run. | J21: DROPPED | K21: #190, #194 | L21: Dropped by a code constant (not a setting): hidden on product pages and for shops, public API 404, admin menu entry removed, no scraping or external calls at runtime; PR #23 code kept and isolated; offline Open Prices CLI refuses to run.
A22: F1.5 | B22: 2 | C22: F1.5 Cart | F22: =COUNTIFS($B$23:$B$27,3,$G$23:$G$27,"COMPLETED")&" / "&COUNTIF($B$23:$B$27,3) | G22: =IF(COUNTIFS($B$23:$B$27,3,$G$23:$G$27,"COMPLETED")=COUNTIF($B$23:$B$27,3),"COMPLETED",IF(COUNTIFS($B$23:$B$27,3,$G$23:$G$27,"BLOCKED")>0,"BLOCKED",IF(COUNTIFS($B$23:$B$27,3,$G$23:$G$27,"YET TO START")=COUNTIF($B$23:$B$27,3),"YET TO START","IN PROGRESS"))) | J22: =(COUNTIFS($B$23:$B$27,3,$J$23:$J$27,"DONE")+COUNTIFS($B$23:$B$27,3,$J$23:$J$27,"DONE-SANDBOX"))&" / "&COUNTIFS($B$23:$B$27,3,$J$23:$J$27,"<>")&" batch steps done"
A23: F1.5.1 | B23: 3 | C23: Add to cart with quantity controls on the product card | D23: Customer | E23: GS-024, NEW-012 | G23: COMPLETED | H23: #48; #72 | I23: -
A24: F1.5.2 | B24: 3 | C24: Multi-shop cart | D24: Customer | E24: GS-025 | G24: COMPLETED | H24: Baseline; #10 | I24: -
A25: F1.5.3 | B25: 3 | C25: Cart re-validated against the location (serviceability, stock, minimum order, paused shops) | D25: Customer | E25: GS-026, NEW-005 | G25: COMPLETED | H25: #11; #23 | I25: -
A26: F1.5.4 | B26: 3 | C26: Coupons (F7) and shop offers (F8) | D26: Customer | E26: NAV-003, NAV-002 | G26: COMPLETED | H26: #55 | I26: Off by default
A27: F1.5.5 | B27: 3 | C27: Open-order prompt before paying (C3) | D27: Customer | E27: NEW-024 | G27: COMPLETED | H27: #85; #120 | I27: Live on gokesari.com since #120 (9 Oct)
A28: F1.6 | B28: 2 | C28: F1.6 Checkout | F28: =COUNTIFS($B$29:$B$31,3,$G$29:$G$31,"COMPLETED")&" / "&COUNTIF($B$29:$B$31,3) | G28: =IF(COUNTIFS($B$29:$B$31,3,$G$29:$G$31,"COMPLETED")=COUNTIF($B$29:$B$31,3),"COMPLETED",IF(COUNTIFS($B$29:$B$31,3,$G$29:$G$31,"BLOCKED")>0,"BLOCKED",IF(COUNTIFS($B$29:$B$31,3,$G$29:$G$31,"YET TO START")=COUNTIF($B$29:$B$31,3),"YET TO START","IN PROGRESS"))) | J28: =(COUNTIFS($B$29:$B$31,3,$J$29:$J$31,"DONE")+COUNTIFS($B$29:$B$31,3,$J$29:$J$31,"DONE-SANDBOX"))&" / "&COUNTIFS($B$29:$B$31,3,$J$29:$J$31,"<>")&" batch steps done"
A29: F1.6.1 | B29: 3 | C29: Mobile number and delivery address required | D29: Customer | E29: GS-026 | G29: COMPLETED | H29: #31 | I29: -
A30: F1.6.2 | B30: 3 | C30: Delivery window or a scheduled time slot with capacity | D30: Customer | E30: GS-027 | G30: COMPLETED | H30: Baseline; #55; #58 | I30: Slots off by default
A31: F1.6.3 | B31: 3 | C31: Order from a closed shop after confirmation | D31: Customer | E31: NEW-003 | G31: COMPLETED | H31: #24 | I31: -
A32: F1.7 | B32: 2 | C32: F1.7 Payment | F32: =COUNTIFS($B$33:$B$35,3,$G$33:$G$35,"COMPLETED")&" / "&COUNTIF($B$33:$B$35,3) | G32: =IF(COUNTIFS($B$33:$B$35,3,$G$33:$G$35,"COMPLETED")=COUNTIF($B$33:$B$35,3),"COMPLETED",IF(COUNTIFS($B$33:$B$35,3,$G$33:$G$35,"BLOCKED")>0,"BLOCKED",IF(COUNTIFS($B$33:$B$35,3,$G$33:$G$35,"YET TO START")=COUNTIF($B$33:$B$35,3),"YET TO START","IN PROGRESS"))) | J32: =(COUNTIFS($B$33:$B$35,3,$J$33:$J$35,"DONE")+COUNTIFS($B$33:$B$35,3,$J$33:$J$35,"DONE-SANDBOX"))&" / "&COUNTIFS($B$33:$B$35,3,$J$33:$J$35,"<>")&" batch steps done"
A33: F1.7.1 | B33: 3 | C33: Pay from wallet (topped up through Cashfree) | D33: Customer | E33: GS-029, GS-028 | G33: COMPLETED | H33: Baseline | I33: -
A34: F1.7.2 | B34: 3 | C34: Cash on delivery with limits | D34: Customer | E34: GS-030 | G34: COMPLETED | H34: #18 | I34: -
A35: F1.7.3 | B35: 3 | C35: Pay the order directly by UPI / card / netbanking | D35: Customer | E35: GS-028, NEW-007 | G35: COMPLETED | H35: #190, #192, #194 | I35: DONE-SANDBOX (18 Oct batch): PaymentGateway interface: sandbox (working on test.gokesari.com after #192), Cashfree adapter, Razorpay/PhonePe scaffolds; UPI/card/netbanking via hosted checkout only (no card data). Production flag onlinePayments OFF until gateway choice, merchant account, live keys and webhook secret (Owner inputs §1-2). | J35: DONE-SANDBOX | K35: #190, #192, #194 | L35: PaymentGateway interface: sandbox (working on test.gokesari.com after #192), Cashfree adapter, Razorpay/PhonePe scaffolds; UPI/card/netbanking via hosted checkout only (no card data). Production flag onlinePayments OFF until gateway choice, merchant account, live keys and webhook secret (Owner inputs §1-2).
A36: F1.8 | B36: 2 | C36: F1.8 Order engine | F36: =COUNTIFS($B$37:$B$41,3,$G$37:$G$41,"COMPLETED")&" / "&COUNTIF($B$37:$B$41,3) | G36: =IF(COUNTIFS($B$37:$B$41,3,$G$37:$G$41,"COMPLETED")=COUNTIF($B$37:$B$41,3),"COMPLETED",IF(COUNTIFS($B$37:$B$41,3,$G$37:$G$41,"BLOCKED")>0,"BLOCKED",IF(COUNTIFS($B$37:$B$41,3,$G$37:$G$41,"YET TO START")=COUNTIF($B$37:$B$41,3),"YET TO START","IN PROGRESS"))) | J36: =(COUNTIFS($B$37:$B$41,3,$J$37:$J$41,"DONE")+COUNTIFS($B$37:$B$41,3,$J$37:$J$41,"DONE-SANDBOX"))&" / "&COUNTIFS($B$37:$B$41,3,$J$37:$J$41,"<>")&" batch steps done"
A37: F1.8.1 | B37: 3 | C37: Validate stock and service area | D37: Customer | E37: GS-026, GS-016 | G37: COMPLETED | H37: #11; #23 | I37: -
A38: F1.8.2 | B38: 3 | C38: Split by shop; one parent GK- reference (F6) | D38: Customer | E38: GS-033 | G38: COMPLETED | H38: Baseline; #55 | I38: Parent reference off by default
A39: F1.8.3 | B39: 3 | C39: Confirm wallet / COD payment inside the order transaction | D39: Customer | E39: GS-032 | G39: COMPLETED | H39: Baseline; #10 | I39: -
A40: F1.8.4 | B40: 3 | C40: Gateway payment confirmation and payment state machine | D40: Customer | E40: SM-005, GS-073 | G40: COMPLETED | H40: #190, #192, #194 | I40: DONE-SANDBOX (18 Oct batch): Payment state machine CREATED>PENDING>AUTHORIZED>CAPTURED>(PARTIALLY_)REFUNDED + FAILED/EXPIRED; signed webhooks, idempotent by event id, reconciled with the gateway's order status; 5-minute reconciliation job; order idempotency key; order CONFIRMED only on CAPTURED. | J40: DONE-SANDBOX | K40: #190, #192, #194 | L40: Payment state machine CREATED>PENDING>AUTHORIZED>CAPTURED>(PARTIALLY_)REFUNDED + FAILED/EXPIRED; signed webhooks, idempotent by event id, reconciled with the gateway's order status; 5-minute reconciliation job; order idempotency key; order CONFIRMED only on CAPTURED.
A41: F1.8.5 | B41: 3 | C41: Create the shop order and notify the shop | D41: Customer | E41: GS-032, GS-055 | G41: COMPLETED | H41: #10; #23 | I41: -
A42: F1.9 | B42: 2 | C42: F1.9 Track and receive | F42: =COUNTIFS($B$43:$B$48,3,$G$43:$G$48,"COMPLETED")&" / "&COUNTIF($B$43:$B$48,3) | G42: =IF(COUNTIFS($B$43:$B$48,3,$G$43:$G$48,"COMPLETED")=COUNTIF($B$43:$B$48,3),"COMPLETED",IF(COUNTIFS($B$43:$B$48,3,$G$43:$G$48,"BLOCKED")>0,"BLOCKED",IF(COUNTIFS($B$43:$B$48,3,$G$43:$G$48,"YET TO START")=COUNTIF($B$43:$B$48,3),"YET TO START","IN PROGRESS"))) | J42: =(COUNTIFS($B$43:$B$48,3,$J$43:$J$48,"DONE")+COUNTIFS($B$43:$B$48,3,$J$43:$J$48,"DONE-SANDBOX"))&" / "&COUNTIFS($B$43:$B$48,3,$J$43:$J$48,"<>")&" batch steps done"
A43: F1.9.1 | B43: 3 | C43: Order status and live tracking on My Orders | D43: Customer | E43: NAV-004, GS-042 | G43: COMPLETED | H43: #29 | I43: -
A44: F1.9.2 | B44: 3 | C44: Real-time events and 5-second tracking | D44: Customer | E44: NEW-028, NEW-029 | G44: COMPLETED | H44: #89; #120 | I44: Live on gokesari.com since #120 (9 Oct)
A45: F1.9.3 | B45: 3 | C45: Delivery code (OTP) given to the rider at handover | D45: Customer | E45: GS-043 | G45: COMPLETED | H45: #10 | I45: -
A46: F1.9.4 | B46: 3 | C46: Delivery code hashed, emailed to the customer, resendable | D46: Customer | E46: NEW-035 | G46: COMPLETED | H46: #91; #120 | I46: Live on gokesari.com since #120 (9 Oct)
A47: F1.9.5 | B47: 3 | C47: Cancel from My Orders | D47: Customer | E47: GAP-007, NEW-020, NAV-004 | G47: COMPLETED | H47: #122; #123 (prod) | I47: Cancel order on My Orders before packing, with confirmation; follows rule cancellation
A48: F1.9.6 | B48: 3 | C48: Collect from the shop with a pickup code; see the delivery option, person and time on My Orders | D48: Customer | E48: NEW-039, GS-041 | G48: COMPLETED | H48: #102; #103; #120 | I48: On gokesari.com since #120 (9 Oct), switched off by default - switch on in Admin > Business rules
A49: F2 | B49: 1 | C49: F2 Shop order fulfilment | D49: Shop owner | F49: =COUNTIFS($B$50:$B$60,3,$G$50:$G$60,"COMPLETED")&" / "&COUNTIF($B$50:$B$60,3) | G49: =IF(COUNTIFS($B$50:$B$60,3,$G$50:$G$60,"COMPLETED")=COUNTIF($B$50:$B$60,3),"COMPLETED",IF(COUNTIFS($B$50:$B$60,3,$G$50:$G$60,"BLOCKED")>0,"BLOCKED",IF(COUNTIFS($B$50:$B$60,3,$G$50:$G$60,"YET TO START")=COUNTIF($B$50:$B$60,3),"YET TO START","IN PROGRESS"))) | J49: =(COUNTIFS($B$50:$B$60,3,$J$50:$J$60,"DONE")+COUNTIFS($B$50:$B$60,3,$J$50:$J$60,"DONE-SANDBOX"))&" / "&COUNTIFS($B$50:$B$60,3,$J$50:$J$60,"<>")&" batch steps done"
A50: F2.1 | B50: 2 | C50: F2.1 Receive and decide | F50: =COUNTIFS($B$51:$B$54,3,$G$51:$G$54,"COMPLETED")&" / "&COUNTIF($B$51:$B$54,3) | G50: =IF(COUNTIFS($B$51:$B$54,3,$G$51:$G$54,"COMPLETED")=COUNTIF($B$51:$B$54,3),"COMPLETED",IF(COUNTIFS($B$51:$B$54,3,$G$51:$G$54,"BLOCKED")>0,"BLOCKED",IF(COUNTIFS($B$51:$B$54,3,$G$51:$G$54,"YET TO START")=COUNTIF($B$51:$B$54,3),"YET TO START","IN PROGRESS"))) | J50: =(COUNTIFS($B$51:$B$54,3,$J$51:$J$54,"DONE")+COUNTIFS($B$51:$B$54,3,$J$51:$J$54,"DONE-SANDBOX"))&" / "&COUNTIFS($B$51:$B$54,3,$J$51:$J$54,"<>")&" batch steps done"
A51: F2.1.1 | B51: 3 | C51: Receive the order (in-app + email) | D51: Shop owner | E51: GS-055, NAV-008 | G51: COMPLETED | H51: #10; #23 | I51: SMS / WhatsApp waits on D2
A52: F2.1.2 | B52: 3 | C52: Accept or reject (reject = full refund + restock) | D52: Shop owner | E52: GS-034 | G52: COMPLETED | H52: #10 | I52: -
A53: F2.1.3 | B53: 3 | C53: Acceptance timeout: reminder, then auto-cancel with full refund | D53: Shop owner | E53: NEW-007 | G53: COMPLETED | H53: #58 | I53: Off by default
A54: F2.1.4 | B54: 3 | C54: Wallet minimum balance checked before accepting | D54: Shop owner | E54: NEW-033 | G54: COMPLETED | H54: #91; #98; #120 | I54: On gokesari.com since #120 (9 Oct), switched off by default - switch on in Admin > Business rules
A55: F2.2 | B55: 2 | C55: F2.2 Prepare | F55: =COUNTIFS($B$56:$B$60,3,$G$56:$G$60,"COMPLETED")&" / "&COUNTIF($B$56:$B$60,3) | G55: =IF(COUNTIFS($B$56:$B$60,3,$G$56:$G$60,"COMPLETED")=COUNTIF($B$56:$B$60,3),"COMPLETED",IF(COUNTIFS($B$56:$B$60,3,$G$56:$G$60,"BLOCKED")>0,"BLOCKED",IF(COUNTIFS($B$56:$B$60,3,$G$56:$G$60,"YET TO START")=COUNTIF($B$56:$B$60,3),"YET TO START","IN PROGRESS"))) | J55: =(COUNTIFS($B$56:$B$60,3,$J$56:$J$60,"DONE")+COUNTIFS($B$56:$B$60,3,$J$56:$J$60,"DONE-SANDBOX"))&" / "&COUNTIFS($B$56:$B$60,3,$J$56:$J$60,"<>")&" batch steps done"
A56: F2.2.1 | B56: 3 | C56: Substitution with customer approval | D56: Shop owner | E56: GS-035 | G56: COMPLETED | H56: #10 | I56: -
A57: F2.2.2 | B57: 3 | C57: Pick and pack per line | D57: Shop owner | E57: GS-036 | G57: COMPLETED | H57: #10 | I57: -
A58: F2.2.3 | B58: 3 | C58: Mark READY - starts the rider search | D58: Shop owner | E58: GA-006 | G58: COMPLETED | H58: #10 | I58: -
A59: F2.2.4 | B59: 3 | C59: Choose pickup / own delivery / GoKesari partner with a date and 1-hour slot; change it with a customer notice | D59: Shop owner | E59: NEW-039, GS-027 | G59: COMPLETED | H59: #102; #103; #120 | I59: On gokesari.com since #120 (9 Oct), switched off by default - switch on in Admin > Business rules
A60: F2.2.5 | B60: 3 | C60: Shop's own delivery staff: private delivery link, start delivery, customer's code to complete | D60: Shop owner | E60: NEW-039, NEW-035 | G60: COMPLETED | H60: #102; #120 | I60: On gokesari.com since #120 (9 Oct), switched off by default - switch on in Admin > Business rules
A61: F3 | B61: 1 | C61: F3 Rider (gig) assignment | D61: System | F61: =COUNTIFS($B$62:$B$71,3,$G$62:$G$71,"COMPLETED")&" / "&COUNTIF($B$62:$B$71,3) | G61: =IF(COUNTIFS($B$62:$B$71,3,$G$62:$G$71,"COMPLETED")=COUNTIF($B$62:$B$71,3),"COMPLETED",IF(COUNTIFS($B$62:$B$71,3,$G$62:$G$71,"BLOCKED")>0,"BLOCKED",IF(COUNTIFS($B$62:$B$71,3,$G$62:$G$71,"YET TO START")=COUNTIF($B$62:$B$71,3),"YET TO START","IN PROGRESS"))) | J61: =(COUNTIFS($B$62:$B$71,3,$J$62:$J$71,"DONE")+COUNTIFS($B$62:$B$71,3,$J$62:$J$71,"DONE-SANDBOX"))&" / "&COUNTIFS($B$62:$B$71,3,$J$62:$J$71,"<>")&" batch steps done"
A62: F3.1 | B62: 2 | C62: F3.1 Eligibility | F62: =COUNTIFS($B$63:$B$64,3,$G$63:$G$64,"COMPLETED")&" / "&COUNTIF($B$63:$B$64,3) | G62: =IF(COUNTIFS($B$63:$B$64,3,$G$63:$G$64,"COMPLETED")=COUNTIF($B$63:$B$64,3),"COMPLETED",IF(COUNTIFS($B$63:$B$64,3,$G$63:$G$64,"BLOCKED")>0,"BLOCKED",IF(COUNTIFS($B$63:$B$64,3,$G$63:$G$64,"YET TO START")=COUNTIF($B$63:$B$64,3),"YET TO START","IN PROGRESS"))) | J62: =(COUNTIFS($B$63:$B$64,3,$J$63:$J$64,"DONE")+COUNTIFS($B$63:$B$64,3,$J$63:$J$64,"DONE-SANDBOX"))&" / "&COUNTIFS($B$63:$B$64,3,$J$63:$J$64,"<>")&" batch steps done"
A63: F3.1.1 | B63: 3 | C63: Society authorisation (whitelist, exclusive or priority) | D63: System | E63: GA-001, GS-045 | G63: COMPLETED | H63: #11 | I63: -
A64: F3.1.2 | B64: 3 | C64: Availability and online status | D64: System | E64: GA-004, GS-038 | G64: COMPLETED | H64: Baseline; #21 | I64: -
A65: F3.2 | B65: 2 | C65: F3.2 Ranking | F65: =COUNTIFS($B$66:$B$68,3,$G$66:$G$68,"COMPLETED")&" / "&COUNTIF($B$66:$B$68,3) | G65: =IF(COUNTIFS($B$66:$B$68,3,$G$66:$G$68,"COMPLETED")=COUNTIF($B$66:$B$68,3),"COMPLETED",IF(COUNTIFS($B$66:$B$68,3,$G$66:$G$68,"BLOCKED")>0,"BLOCKED",IF(COUNTIFS($B$66:$B$68,3,$G$66:$G$68,"YET TO START")=COUNTIF($B$66:$B$68,3),"YET TO START","IN PROGRESS"))) | J65: =(COUNTIFS($B$66:$B$68,3,$J$66:$J$68,"DONE")+COUNTIFS($B$66:$B$68,3,$J$66:$J$68,"DONE-SANDBOX"))&" / "&COUNTIFS($B$66:$B$68,3,$J$66:$J$68,"<>")&" batch steps done"
A66: F3.2.1 | B66: 3 | C66: Preferred partner ranked higher | D66: System | E66: GA-002, GS-040 | G66: COMPLETED | H66: #11 | I66: -
A67: F3.2.2 | B67: 3 | C67: Distance, reliability and fairness | D67: System | E67: GA-003, GA-007, GA-008 | G67: COMPLETED | H67: Baseline; #11 | I67: -
A68: F3.2.3 | B68: 3 | C68: Road ETA (F4), busy riders as fallback (F3), batching | D68: System | E68: GS-072, GA-005 | G68: COMPLETED | H68: #55; #58 | I68: Off by default
A69: F3.3 | B69: 2 | C69: F3.3 Offer | F69: =COUNTIFS($B$70:$B$71,3,$G$70:$G$71,"COMPLETED")&" / "&COUNTIF($B$70:$B$71,3) | G69: =IF(COUNTIFS($B$70:$B$71,3,$G$70:$G$71,"COMPLETED")=COUNTIF($B$70:$B$71,3),"COMPLETED",IF(COUNTIFS($B$70:$B$71,3,$G$70:$G$71,"BLOCKED")>0,"BLOCKED",IF(COUNTIFS($B$70:$B$71,3,$G$70:$G$71,"YET TO START")=COUNTIF($B$70:$B$71,3),"YET TO START","IN PROGRESS"))) | J69: =(COUNTIFS($B$70:$B$71,3,$J$70:$J$71,"DONE")+COUNTIFS($B$70:$B$71,3,$J$70:$J$71,"DONE-SANDBOX"))&" / "&COUNTIFS($B$70:$B$71,3,$J$70:$J$71,"<>")&" batch steps done"
A70: F3.3.1 | B70: 3 | C70: Offer to the best rider with expiry, retries and operator override | D70: System | E70: GS-039, GA-009, RBAC-007 | G70: COMPLETED | H70: Baseline; #10; #23 | I70: -
A71: F3.3.2 | B71: 3 | C71: Broadcast offers / widen the radius | D71: System | E71: GAP-004 | G71: COMPLETED | H71: #190, #194 | I71: DONE (18 Oct batch): Rider side: broadcast after N s, radius 2>4>6 km, atomic first accept, 'Offer taken' (rule dispatchBroadcast, OFF until the owner switches it on). Owner request: admin/operator broadcasts (audience, city/PIN, schedule, expiry) + Notification Centre (bell + /notifications, read/unread) on web and app; push/email by opt-in. | J71: DONE | K71: #190, #194 | L71: Rider side: broadcast after N s, radius 2>4>6 km, atomic first accept, 'Offer taken' (rule dispatchBroadcast, OFF until the owner switches it on). Owner request: admin/operator broadcasts (audience, city/PIN, schedule, expiry) + Notification Centre (bell + /notifications, read/unread) on web and app; push/email by opt-in.
A72: F4 | B72: 1 | C72: F4 Delivery | D72: Rider | F72: =COUNTIFS($B$73:$B$84,3,$G$73:$G$84,"COMPLETED")&" / "&COUNTIF($B$73:$B$84,3) | G72: =IF(COUNTIFS($B$73:$B$84,3,$G$73:$G$84,"COMPLETED")=COUNTIF($B$73:$B$84,3),"COMPLETED",IF(COUNTIFS($B$73:$B$84,3,$G$73:$G$84,"BLOCKED")>0,"BLOCKED",IF(COUNTIFS($B$73:$B$84,3,$G$73:$G$84,"YET TO START")=COUNTIF($B$73:$B$84,3),"YET TO START","IN PROGRESS"))) | J72: =(COUNTIFS($B$73:$B$84,3,$J$73:$J$84,"DONE")+COUNTIFS($B$73:$B$84,3,$J$73:$J$84,"DONE-SANDBOX"))&" / "&COUNTIFS($B$73:$B$84,3,$J$73:$J$84,"<>")&" batch steps done"
A73: F4.1 | B73: 2 | C73: F4.1 Pickup | F73: =COUNTIFS($B$74:$B$76,3,$G$74:$G$76,"COMPLETED")&" / "&COUNTIF($B$74:$B$76,3) | G73: =IF(COUNTIFS($B$74:$B$76,3,$G$74:$G$76,"COMPLETED")=COUNTIF($B$74:$B$76,3),"COMPLETED",IF(COUNTIFS($B$74:$B$76,3,$G$74:$G$76,"BLOCKED")>0,"BLOCKED",IF(COUNTIFS($B$74:$B$76,3,$G$74:$G$76,"YET TO START")=COUNTIF($B$74:$B$76,3),"YET TO START","IN PROGRESS"))) | J73: =(COUNTIFS($B$74:$B$76,3,$J$74:$J$76,"DONE")+COUNTIFS($B$74:$B$76,3,$J$74:$J$76,"DONE-SANDBOX"))&" / "&COUNTIFS($B$74:$B$76,3,$J$74:$J$76,"<>")&" batch steps done"
A74: F4.1.1 | B74: 3 | C74: Accept the job (Jobs screen; ordered trip list when batched) | D74: Rider | E74: NAV-011 | G74: COMPLETED | H74: #21; #58 | I74: -
A75: F4.1.2 | B75: 3 | C75: Arrive at shop checkpoint and pickup code | D75: Rider | E75: NEW-004, GS-041 | G75: COMPLETED | H75: #10; #23 | I75: -
A76: F4.1.3 | B76: 3 | C76: Pickup by QR code | D76: Rider | E76: GAP-001 | G76: COMPLETED | H76: #190, #192, #194 | I76: DONE (18 Oct batch): Signed single-use QR (HMAC) on the shop screen and printable packing slip; camera scan in the rider app; PICKED_UP with time + GPS, customer told at once; typed-code fallback. Rule pickupQr OFF; on gokesari.com set PICKUP_QR_SECRET first. | J76: DONE | K76: #190, #192, #194 | L76: Signed single-use QR (HMAC) on the shop screen and printable packing slip; camera scan in the rider app; PICKED_UP with time + GPS, customer told at once; typed-code fallback. Rule pickupQr OFF; on gokesari.com set PICKUP_QR_SECRET first.
A77: F4.2 | B77: 2 | C77: F4.2 Drop | F77: =COUNTIFS($B$78:$B$84,3,$G$78:$G$84,"COMPLETED")&" / "&COUNTIF($B$78:$B$84,3) | G77: =IF(COUNTIFS($B$78:$B$84,3,$G$78:$G$84,"COMPLETED")=COUNTIF($B$78:$B$84,3),"COMPLETED",IF(COUNTIFS($B$78:$B$84,3,$G$78:$G$84,"BLOCKED")>0,"BLOCKED",IF(COUNTIFS($B$78:$B$84,3,$G$78:$G$84,"YET TO START")=COUNTIF($B$78:$B$84,3),"YET TO START","IN PROGRESS"))) | J77: =(COUNTIFS($B$78:$B$84,3,$J$78:$J$84,"DONE")+COUNTIFS($B$78:$B$84,3,$J$78:$J$84,"DONE-SANDBOX"))&" / "&COUNTIFS($B$78:$B$84,3,$J$78:$J$84,"<>")&" batch steps done"
A78: F4.2.1 | B78: 3 | C78: Navigate with a Google Maps deep link | D78: Rider | E78: GS-072 | G78: COMPLETED | H78: #23 | I78: -
A79: F4.2.2 | B79: 3 | C79: In-app turn-by-turn navigation | D79: Rider | E79: GAP-002 | G79: COMPLETED | H79: #190, #194 | I79: DONE-SANDBOX (18 Oct batch): RoutingProvider (mock / Google Routes / OSRM): route line, next manoeuvre, ETA, off-route re-route, voice prompts, Open-in-Google-Maps; keeps feeding live tracking. Mock router on test; real directions need a Google Routes key or own OSRM server. Rule riderNavigation OFF. | J79: DONE-SANDBOX | K79: #190, #194 | L79: RoutingProvider (mock / Google Routes / OSRM): route line, next manoeuvre, ETA, off-route re-route, voice prompts, Open-in-Google-Maps; keeps feeding live tracking. Mock router on test; real directions need a Google Routes key or own OSRM server. Rule riderNavigation OFF.
A80: F4.2.3 | B80: 3 | C80: Society gate access and instructions | D80: Rider | E80: GS-047 | G80: COMPLETED | H80: #11; #23 | I80: -
A81: F4.2.4 | B81: 3 | C81: Delivery code, arrival checkpoint and photo proof | D81: Rider | E81: GS-043, NEW-007 | G81: COMPLETED | H81: #10; #23; #58 | I81: Photo proof off by default
A82: F4.2.5 | B82: 3 | C82: Code lockout raises a ticket; shop cannot bypass the code | D82: Rider | E82: NEW-035 | G82: COMPLETED | H82: #91; #120 | I82: Live on gokesari.com since #120 (9 Oct)
A83: F4.2.6 | B83: 3 | C83: Signature capture | D83: Rider | E83: GAP-003 | G83: BLOCKED | H83: - | I83: DEFERRED-PHASE-2 (18 Oct batch): Signature capture deferred to Phase 2 by the owner; not built. | J83: DEFERRED-PHASE-2 | K83: - | L83: Signature capture deferred to Phase 2 by the owner; not built.
A84: F4.2.7 | B84: 3 | C84: Failed delivery / return to shop | D84: Rider | E84: SM-001, WF-005 | G84: COMPLETED | H84: #10 | I84: -
A85: F5 | B85: 1 | C85: F5 Society-authorised delivery | D85: Society admin | F85: =COUNTIFS($B$86:$B$95,3,$G$86:$G$95,"COMPLETED")&" / "&COUNTIF($B$86:$B$95,3) | G85: =IF(COUNTIFS($B$86:$B$95,3,$G$86:$G$95,"COMPLETED")=COUNTIF($B$86:$B$95,3),"COMPLETED",IF(COUNTIFS($B$86:$B$95,3,$G$86:$G$95,"BLOCKED")>0,"BLOCKED",IF(COUNTIFS($B$86:$B$95,3,$G$86:$G$95,"YET TO START")=COUNTIF($B$86:$B$95,3),"YET TO START","IN PROGRESS"))) | J85: =(COUNTIFS($B$86:$B$95,3,$J$86:$J$95,"DONE")+COUNTIFS($B$86:$B$95,3,$J$86:$J$95,"DONE-SANDBOX"))&" / "&COUNTIFS($B$86:$B$95,3,$J$86:$J$95,"<>")&" batch steps done"
A86: F5.1 | B86: 2 | C86: F5.1 Society set-up | F86: =COUNTIFS($B$87:$B$88,3,$G$87:$G$88,"COMPLETED")&" / "&COUNTIF($B$87:$B$88,3) | G86: =IF(COUNTIFS($B$87:$B$88,3,$G$87:$G$88,"COMPLETED")=COUNTIF($B$87:$B$88,3),"COMPLETED",IF(COUNTIFS($B$87:$B$88,3,$G$87:$G$88,"BLOCKED")>0,"BLOCKED",IF(COUNTIFS($B$87:$B$88,3,$G$87:$G$88,"YET TO START")=COUNTIF($B$87:$B$88,3),"YET TO START","IN PROGRESS"))) | J86: =(COUNTIFS($B$87:$B$88,3,$J$87:$J$88,"DONE")+COUNTIFS($B$87:$B$88,3,$J$87:$J$88,"DONE-SANDBOX"))&" / "&COUNTIFS($B$87:$B$88,3,$J$87:$J$88,"<>")&" batch steps done"
A87: F5.1.1 | B87: 3 | C87: Register the society; operations verify it | D87: Society admin | E87: GS-044 | G87: COMPLETED | H87: #11 | I87: -
A88: F5.1.2 | B88: 3 | C88: Members: admin, operator, resident | D88: Society admin | E88: GS-005, GS-002 | G88: COMPLETED | H88: #11 | I88: -
A89: F5.2 | B89: 2 | C89: F5.2 Rider control | F89: =COUNTIFS($B$90:$B$92,3,$G$90:$G$92,"COMPLETED")&" / "&COUNTIF($B$90:$B$92,3) | G89: =IF(COUNTIFS($B$90:$B$92,3,$G$90:$G$92,"COMPLETED")=COUNTIF($B$90:$B$92,3),"COMPLETED",IF(COUNTIFS($B$90:$B$92,3,$G$90:$G$92,"BLOCKED")>0,"BLOCKED",IF(COUNTIFS($B$90:$B$92,3,$G$90:$G$92,"YET TO START")=COUNTIF($B$90:$B$92,3),"YET TO START","IN PROGRESS"))) | J89: =(COUNTIFS($B$90:$B$92,3,$J$90:$J$92,"DONE")+COUNTIFS($B$90:$B$92,3,$J$90:$J$92,"DONE-SANDBOX"))&" / "&COUNTIFS($B$90:$B$92,3,$J$90:$J$92,"<>")&" batch steps done"
A90: F5.2.1 | B90: 3 | C90: Whitelist or revoke riders | D90: Society admin | E90: GS-045, RBAC-009 | G90: COMPLETED | H90: #11 | I90: -
A91: F5.2.2 | B91: 3 | C91: Only verified societies may add riders (C2) | D91: Society admin | E91: NEW-023 | G91: COMPLETED | H91: #85; #120 | I91: Live on gokesari.com since #120 (9 Oct)
A92: F5.2.3 | B92: 3 | C92: Rider photo and ID on the society dashboard (C5) | D92: Society admin | E92: NEW-026 | G92: COMPLETED | H92: #85; #120 | I92: Live on gokesari.com since #120 (9 Oct)
A93: F5.3 | B93: 2 | C93: F5.3 Gate | F93: =COUNTIFS($B$94:$B$95,3,$G$94:$G$95,"COMPLETED")&" / "&COUNTIF($B$94:$B$95,3) | G93: =IF(COUNTIFS($B$94:$B$95,3,$G$94:$G$95,"COMPLETED")=COUNTIF($B$94:$B$95,3),"COMPLETED",IF(COUNTIFS($B$94:$B$95,3,$G$94:$G$95,"BLOCKED")>0,"BLOCKED",IF(COUNTIFS($B$94:$B$95,3,$G$94:$G$95,"YET TO START")=COUNTIF($B$94:$B$95,3),"YET TO START","IN PROGRESS"))) | J93: =(COUNTIFS($B$94:$B$95,3,$J$94:$J$95,"DONE")+COUNTIFS($B$94:$B$95,3,$J$94:$J$95,"DONE-SANDBOX"))&" / "&COUNTIFS($B$94:$B$95,3,$J$94:$J$95,"<>")&" batch steps done"
A94: F5.3.1 | B94: 3 | C94: Delivery instructions for the assigned rider | D94: Society admin | E94: GS-047 | G94: COMPLETED | H94: #11 | I94: -
A95: F5.3.2 | B95: 3 | C95: Security notified of the assigned rider | D95: Society admin | E95: GS-046 | G95: COMPLETED | H95: #11 | I95: -
A96: F6 | B96: 1 | C96: F6 After the order: returns, refunds, disputes, ratings | D96: Customer / Operator | F96: =COUNTIFS($B$97:$B$110,3,$G$97:$G$110,"COMPLETED")&" / "&COUNTIF($B$97:$B$110,3) | G96: =IF(COUNTIFS($B$97:$B$110,3,$G$97:$G$110,"COMPLETED")=COUNTIF($B$97:$B$110,3),"COMPLETED",IF(COUNTIFS($B$97:$B$110,3,$G$97:$G$110,"BLOCKED")>0,"BLOCKED",IF(COUNTIFS($B$97:$B$110,3,$G$97:$G$110,"YET TO START")=COUNTIF($B$97:$B$110,3),"YET TO START","IN PROGRESS"))) | J96: =(COUNTIFS($B$97:$B$110,3,$J$97:$J$110,"DONE")+COUNTIFS($B$97:$B$110,3,$J$97:$J$110,"DONE-SANDBOX"))&" / "&COUNTIFS($B$97:$B$110,3,$J$97:$J$110,"<>")&" batch steps done"
A97: F6.1 | B97: 2 | C97: F6.1 Cancellation | F97: =COUNTIFS($B$98:$B$100,3,$G$98:$G$100,"COMPLETED")&" / "&COUNTIF($B$98:$B$100,3) | G97: =IF(COUNTIFS($B$98:$B$100,3,$G$98:$G$100,"COMPLETED")=COUNTIF($B$98:$B$100,3),"COMPLETED",IF(COUNTIFS($B$98:$B$100,3,$G$98:$G$100,"BLOCKED")>0,"BLOCKED",IF(COUNTIFS($B$98:$B$100,3,$G$98:$G$100,"YET TO START")=COUNTIF($B$98:$B$100,3),"YET TO START","IN PROGRESS"))) | J97: =(COUNTIFS($B$98:$B$100,3,$J$98:$J$100,"DONE")+COUNTIFS($B$98:$B$100,3,$J$98:$J$100,"DONE-SANDBOX"))&" / "&COUNTIFS($B$98:$B$100,3,$J$98:$J$100,"<>")&" batch steps done"
A98: F6.1.1 | B98: 3 | C98: Cancel before packing: full refund incl. delivery fee | D98: Customer / Operator | E98: NEW-006 | G98: COMPLETED | H98: #10; #23 | I98: -
A99: F6.1.2 | B99: 3 | C99: Customer may cancel until packing (rule) | D99: Customer / Operator | E99: NEW-020 | G99: COMPLETED | H99: #85; #120 | I99: On gokesari.com since #120 (9 Oct), switched off by default - switch on in Admin > Business rules
A100: F6.1.3 | B100: 3 | C100: After-packing treatments (D10) signed off | D100: Customer / Operator | E100: NEW-006 | G100: COMPLETED | H100: #190, #194 | I100: DONE (18 Oct batch): Before packing: full refund incl. delivery (unchanged). After packing: per-shop fee (amount or %, cap, on/off) within admin limits, shown before confirming, written to the order ledger. Rule afterPackingCancellation OFF until the refund policy text is updated. | J100: DONE | K100: #190, #194 | L100: Before packing: full refund incl. delivery (unchanged). After packing: per-shop fee (amount or %, cap, on/off) within admin limits, shown before confirming, written to the order ledger. Rule afterPackingCancellation OFF until the refund policy text is updated.
A101: F6.2 | B101: 2 | C101: F6.2 Returns and refunds | F101: =COUNTIFS($B$102:$B$104,3,$G$102:$G$104,"COMPLETED")&" / "&COUNTIF($B$102:$B$104,3) | G101: =IF(COUNTIFS($B$102:$B$104,3,$G$102:$G$104,"COMPLETED")=COUNTIF($B$102:$B$104,3),"COMPLETED",IF(COUNTIFS($B$102:$B$104,3,$G$102:$G$104,"BLOCKED")>0,"BLOCKED",IF(COUNTIFS($B$102:$B$104,3,$G$102:$G$104,"YET TO START")=COUNTIF($B$102:$B$104,3),"YET TO START","IN PROGRESS"))) | J101: =(COUNTIFS($B$102:$B$104,3,$J$102:$J$104,"DONE")+COUNTIFS($B$102:$B$104,3,$J$102:$J$104,"DONE-SANDBOX"))&" / "&COUNTIFS($B$102:$B$104,3,$J$102:$J$104,"<>")&" batch steps done"
...

Sheet PR Register
A1: PR # | B1: Title | C1: Type | D1: Branch (head -> base) | E1: Target | F1: State | G1: Created | H1: Merged / closed | I1: Features built / extended | J1: Features released to production | K1: Released to production via | L1: Notes
A2: 1 | B2: Add the Product Master Data Platform (pilot) | C2: Feature | D2: feature/product-master-platform -> main | E2: Production (main -> gokesari.com) | F2: Closed - not merged | G2: 2026-09-20 | H2: 2026-09-21 | I2: PMD-001 | J2: - | K2: - | L2: Superseded by #4 (closed unmerged).
A3: 2 | B3: Add GS1 India and manufacturer-catalogue connectors (Excel, mapping templates) | C3: Feature | D3: feature/pmd-gs1-manufacturer-feeds -> feature/product-master-platform | E3: Stacked on feature/product-master-platform | F3: Closed - not merged | G3: 2026-09-20 | H3: 2026-09-21 | I3: PMD-002 | J3: - | K3: - | L3: Stacked on #1; superseded by #4.
A4: 3 | B4: PMD: loader rework for scale (bulk path, workers, dashboard/index fixes) | C4: Feature | D4: feature/pmd-loader-rework -> feature/product-master-platform | E4: Stacked on feature/product-master-platform | F4: Closed - not merged | G4: 2026-09-20 | H4: 2026-09-21 | I4: PMD-003 | J4: - | K4: - | L4: Stacked on #1; superseded by #4.
A5: 4 | B5: Product Master: platform, feeds, loader rework and shop-catalogue promotion (into staging) | C5: Feature | D5: release/pmd-to-staging -> staging | E5: Test site (staging -> test.gokesari.com) | F5: Merged | G5: 2026-09-20 | H5: 2026-09-20 | I5: GS-011, PMD-001, PMD-002, PMD-003, PMD-004 | J5: - | K5: #8 | L5: Released by #8.
A6: 5 | B6: Product Master: one-command copy of the pilot data into a target database | C6: Feature | D6: feature/pmd-copy-script -> staging | E6: Test site (staging -> test.gokesari.com) | F6: Merged | G6: 2026-09-20 | H6: 2026-09-21 | I6: PMD-004 | J6: - | K6: #8 | L6: Released by #8.
A7: 6 | B7: Product Master: fix duplicate brand on concurrent promotion; parallel promotion option | C7: Feature | D7: feature/pmd-promote-concurrency -> staging | E7: Test site (staging -> test.gokesari.com) | F7: Merged | G7: 2026-09-21 | H7: 2026-09-21 | I7: PMD-004 | J7: - | K7: #8 | L7: Released by #8.
A8: 7 | B8: CI: checkout and setup-node v5 (Node 24) | C8: DevOps / repo | D8: chore/ci-node24-actions -> staging | E8: Test site (staging -> test.gokesari.com) | F8: Merged | G8: 2026-09-21 | H8: 2026-09-21 | I8: PLT-003 | J8: - | K8: #8 | L8: Released by #8.
A9: 8 | B9: Promote staging to main: Product Master platform (deploys live) | C9: Release (staging -> main) | D9: staging -> main | E9: Production (main -> gokesari.com) | F9: Merged | G9: 2026-09-21 | H9: 2026-09-21 | I9: - | J9: GS-011, PMD-001, PMD-002, PMD-003, PMD-004, PLT-003 | K9: Itself (merged to main)
A10: 9 | B10: Product Master: script to apply duplicate-review decisions | C10: Feature | D10: feature/pmd-review-decide -> staging | E10: Test site (staging -> test.gokesari.com) | F10: Merged | G10: 2026-09-21 | H10: 2026-09-21 | I10: PMD-005 | J10: - | K10: #12 | L10: Released by #12.
A11: 10 | B11: Phase 1 go-live development (for QA on staging) | C11: Feature | D11: dev/phase1-go-live -> staging | E11: Test site (staging -> test.gokesari.com) | F11: Merged | G11: 2026-09-24 | H11: 2026-09-28 | I11: GS-001, GS-002, GS-004, GS-010, GS-019, GS-020, GS-021, GS-022, GS-025, GS-031, GS-032, GS-034, GS-035, GS-036, GS-039, GS-041, GS-043, GS-055, GS-057, GS-061, GS-062, GS-064, GS-067, GS-070, GS-071, WF-001, WF-002, WF-003, WF-005, WF-007, WF-010, RBAC-002, RBAC-007, RBAC-011, RBAC-012, RBAC-015, SM-001, GA-006, GA-009, NAV-008, NAV-010, NEW-006 | J11: - | K11: #14 | L11: Squash-merged into staging; released by #14.
A12: 11 | B12: Phase 2: society, ratings, subscription expansion (for QA on staging) | C12: Feature | D12: dev/phase2-society -> staging | E12: Test site (staging -> test.gokesari.com) | F12: Merged | G12: 2026-09-25 | H12: 2026-09-28 | I12: GS-002, GS-005, GS-026, GS-040, GS-044, GS-045, GS-046, GS-047, GS-049, GS-051, GS-056, GS-059, GS-060, WF-001, WF-003, WF-004, WF-006, RBAC-009, SM-004, SM-006, GA-001, GA-002, GA-007, GA-008, NAV-002, NAV-014 | J12: - | K12: #19
A13: 12 | B13: Promote staging to main: Phase 1 + Phase 2 (deploys live) | C13: Release (staging -> main) | D13: staging -> main | E13: Production (main -> gokesari.com) | F13: Merged | G13: 2026-09-25 | H13: 2026-09-28 | I13: - | J13: PMD-005 | K13: Itself (merged to main) | L13: Squash release of #9 to main.
A14: 13 | B14: Hotfix: log the root cause of failed database queries | C14: Fix / hotfix | D14: hotfix/log-db-error-cause -> staging | E14: Test site (staging -> test.gokesari.com) | F14: Merged | G14: 2026-09-25 | H14: 2026-09-28 | I14: PLT-002 | J14: - | K14: #19
A15: 14 | B15: Staging | C15: Release (staging -> main) | D15: staging -> main | E15: Production (main -> gokesari.com) | F15: Merged | G15: 2026-09-28 | H15: 2026-09-28 | I15: - | J15: GS-001, GS-002, GS-004, GS-010, GS-019, GS-020, GS-021, GS-022, GS-025, GS-031, GS-032, GS-034, GS-035, GS-036, GS-039, GS-041, GS-043, GS-055, GS-057, GS-061, GS-062, GS-064, GS-067, GS-070, GS-071, WF-001, WF-002, WF-003, WF-005, WF-007, WF-010, RBAC-002, RBAC-007, RBAC-011, RBAC-012, RBAC-015, SM-001, GA-006, GA-009, NAV-008, NAV-010, NEW-006 | K15: Itself (merged to main) | L15: Squash release of Phase 1 (#10) to main.
A16: 15 | B16: fix: patch Node.js security vulnerabilities | C16: Security / dependencies | D16: fix/patch-vulnerabilities-07273736-1790597348 -> staging | E16: Test site (staging -> test.gokesari.com) | F16: Closed - not merged | G16: 2026-09-28 | H16: 2026-09-28 | I16: PLT-004 | J16: - | K16: - | L16: Superseded by the Next.js 16.3.6 bump released in #19.
A17: 16 | B17: Pin Node 20, bump Next.js to 16.3.6, log DB error causes | C17: Security / dependencies | D17: claude/turbopack-css-crash-2y3or2 -> main | E17: Production (main -> gokesari.com) | F17: Closed - not merged | G17: 2026-09-28 | H17: 2026-09-28 | I17: PLT-002, PLT-004 | J17: - | K17: - | L17: Closed; its DB-error logging landed via #13.
A18: 17 | B18: Hotfix: build with webpack so Hostinger deploys succeed | C18: Fix / hotfix | D18: hotfix/hostinger-webpack-build -> staging | E18: Test site (staging -> test.gokesari.com) | F18: Merged | G18: 2026-09-28 | H18: 2026-09-28 | I18: PLT-001 | J18: - | K18: #19 | L18: Squash-merged into staging; released by #19.
A19: 18 | B19: Phase 3: multi-role grants, COD, shop marketing, risk rules, KPI analytics | C19: Feature | D19: dev/phase3-growth -> staging | E19: Test site (staging -> test.gokesari.com) | F19: Merged | G19: 2026-09-28 | H19: 2026-09-28 | I19: GS-003, GS-030, GS-052, GS-053, GS-068, GS-069, WF-009, RBAC-013, NAV-009, NAV-018, NAV-019, KPI-001, KPI-002, KPI-003, KPI-004, KPI-005, KPI-006, KPI-007, KPI-008, KPI-009, KPI-010, KPI-011, KPI-012, KPI-013, KPI-014, KPI-015 | J19: - | K19: #19
A20: 19 | B20: Staging | C20: Release (staging -> main) | D20: staging -> main | E20: Production (main -> gokesari.com) | F20: Merged | G20: 2026-09-28 | H20: 2026-09-30 | I20: PLT-004 | J20: GS-002, GS-003, GS-005, GS-006, GS-026, GS-030, GS-034, GS-038, GS-040, GS-042, GS-044, GS-045, GS-046, GS-047, GS-049, GS-051, GS-052, GS-053, GS-056, GS-059, GS-060, GS-065, GS-066, GS-068, GS-069, WF-001, WF-003, WF-004, WF-006, WF-008, WF-009, RBAC-009, RBAC-010, RBAC-013, SM-004, SM-006, GA-001, GA-002, GA-007, GA-008, NAV-002, NAV-009, NAV-011, NAV-012, NAV-013, NAV-014, NAV-015, NAV-016, NAV-017, NAV-018, NAV-019, KPI-001, KPI-002, KPI-003, KPI-004, KPI-005, KPI-006, KPI-007, KPI-008, KPI-009, KPI-010, KPI-011, KPI-012, KPI-013, KPI-014, KPI-015, PLT-001, PLT-002, PLT-004 | K20: Itself (merged to main) | L20: Release of Phases 2-4 (#11, #18, #21), #13, #17, #20, #22 to main.
A21: 20 | B21: Hotfix: resolve @/ imports in Hostinger webpack builds | C21: Fix / hotfix | D21: hotfix/webpack-src-alias -> staging | E21: Test site (staging -> test.gokesari.com) | F21: Merged | G21: 2026-09-28 | H21: 2026-09-28 | I21: PLT-001 | J21: - | K21: #19
A22: 21 | B22: Phase 4: operations, exceptions, fraud, and tracking hardening | C22: Feature | D22: dev/phase4-operations -> staging | E22: Test site (staging -> test.gokesari.com) | F22: Merged | G22: 2026-09-29 | H22: 2026-09-30 | I22: GS-034, GS-038, GS-042, GS-065, GS-066, GS-068, RBAC-010, NAV-011, NAV-012, NAV-013, NAV-015, NAV-016, NAV-017 | J22: - | K22: #19 | L22: Rebased onto staging; released by #19.
A23: 22 | B23: Stop the same shop being registered twice | C23: Feature | D23: fix/shop-duplicate-registration -> staging | E23: Test site (staging -> test.gokesari.com) | F23: Merged | G23: 2026-09-29 | H23: 2026-09-30 | I23: GS-006, WF-008 | J23: - | K23: #19 | L23: Merged into staging by hand; released by #19.
A24: 23 | B24: Release: Phases A–J, shop categories, migrations 0025–0035 | C24: Release + direct commits (Phases A-J) | D24: staging -> main | E24: Production (main -> gokesari.com) | F24: Merged | G24: 2026-10-01 | H24: 2026-10-01 | I24: GS-001, GS-004, GS-009, GS-010, GS-014, GS-015, GS-017, GS-018, GS-023, GS-026, GS-039, GS-043, GS-047, GS-055, GS-057, GS-063, GS-065, GS-072, GS-074, WF-001, WF-003, WF-005, WF-007, RBAC-007, RBAC-014, SM-002, SM-003, GA-009, NAV-001, NAV-003, NAV-006, NAV-012, NAV-017, NEW-001, NEW-002, NEW-004, NEW-005, NEW-006, NEW-007 | J24: GS-001, GS-004, GS-009, GS-010, GS-014, GS-015, GS-017, GS-018, GS-023, GS-026, GS-039, GS-043, GS-047, GS-055, GS-057, GS-063, GS-065, GS-072, GS-074, WF-001, WF-003, WF-005, WF-007, RBAC-007, RBAC-014, SM-002, SM-003, GA-009, NAV-001, NAV-003, NAV-006, NAV-012, NAV-017, NEW-001, NEW-002, NEW-004, NEW-005, NEW-006, NEW-007 | K24: Itself (merged to main) | L24: Phases A-J, the settings screen and shop categories were committed straight to staging, so this release PR is their only PR.
A25: 24 | B25: Release: closed-shop ordering with confirmation and alerts; IST opening hours | C25: Feature | D25: staging -> main | E25: Production (main -> gokesari.com) | F25: Merged | G25: 2026-10-01 | H25: 2026-10-01 | I25: WF-001, WF-002, NAV-002, NEW-003 | J25: WF-001, WF-002, NAV-002, NEW-003 | K25: Itself (merged to main) | L25: Closed-shop ordering was committed straight to staging; this release PR is its only PR.
A26: 25 | B26: Point CNAME and domain examples at gokesari.com | C26: DevOps / repo | D26: claude/charming-edison-ofoncf -> staging | E26: Test site (staging -> test.gokesari.com) | F26: Merged | G26: 2026-10-02 | H26: 2026-10-02 | I26: PLT-005 | J26: - | K26: #32
A27: 26 | B27: Port GoKesari from PostgreSQL to MySQL | C27: Platform port | D27: claude/awesome-dijkstra-fmccpl -> main | E27: Production (main -> gokesari.com) | F27: Closed - not merged | G27: 2026-10-02 | H27: 2026-10-07 | I27: - | J27: - | K27: - | L27: Closed without merging - the app stays on PostgreSQL.
A28: 27 | B28: Point this repo's deployment docs at GoKesari, not bkesari | C28: DevOps / repo | D28: claude/amazing-cannon-5n3fro -> main | E28: Production (main -> gokesari.com) | F28: Closed - not merged | G28: 2026-10-02 | H28: 2026-10-03 | I28: PLT-005 | J28: - | K28: - | L28: Closed; superseded by #25 and #33.
A29: 28 | B29: Re-audit the feature status workbook against the code on main | C29: Docs / reports | D29: claude/confident-albattani-dqw1dk -> main | E29: Production (main -> gokesari.com) | F29: Merged | G29: 2026-10-02 | H29: 2026-10-02 | I29: - | J29: - | K29: Itself (merged to main)
A30: 29 | B30: Mount the live tracking screen and enforce the registration-fee gate | C30: Feature | D30: claude/confident-albattani-dqw1dk -> main | E30: Production (main -> gokesari.com) | F30: Merged | G30: 2026-10-02 | H30: 2026-10-03 | I30: GS-008, GS-042, WF-005, WF-008, NAV-004, NAV-016 | J30: GS-008, GS-042, WF-005, WF-008, NAV-004, NAV-016 | K30: Itself (merged to main)
A31: 30 | B31: Explicit Save flow on three admin screens | C31: Feature | D31: claude/eloquent-darwin-n8yblq -> main | E31: Production (main -> gokesari.com) | F31: Merged | G31: 2026-10-02 | H31: 2026-10-03 | I31: GS-009, RBAC-013, NEW-009 | J31: - | K31: #32 | L31: Also merged into staging by hand; released by #32.
A32: 31 | B32: Login by mobile or email, first-time profile and My Profile | C32: Feature | D32: claude/tender-cannon-vmecpj -> staging | E32: Test site (staging -> test.gokesari.com) | F32: Merged | G32: 2026-10-03 | H32: 2026-10-03 | I32: GS-001, GS-026, WF-001, NAV-003 | J32: - | K32: #43
A33: 32 | B33: Release: explicit Save flow on admin screens; gokesari.com domain corrections | C33: Release (staging -> main) | D33: staging -> main | E33: Production (main -> gokesari.com) | F33: Merged | G33: 2026-10-03 | H33: 2026-10-03 | I33: - | J33: GS-009, RBAC-013, NEW-009, PLT-005 | K33: Itself (merged to main)
A34: 33 | B34: Delete DEPLOY_NOW.md, a runbook for the other brand's domain | C34: DevOps / repo | D34: claude/charming-edison-ofoncf -> staging | E34: Test site (staging -> test.gokesari.com) | F34: Merged | G34: 2026-10-03 | H34: 2026-10-03 | I34: PLT-005 | J34: - | K34: #36
A35: 34 | B35: Add the operations consent view (NAV-019) | C35: Feature | D35: claude/confident-albattani-dqw1dk -> main | E35: Production (main -> gokesari.com) | F35: Merged | G35: 2026-10-03 | H35: 2026-10-03 | I35: GS-070, NAV-019 | J35: GS-070, NAV-019 | K35: Itself (merged to main)
A36: 35 | B36: Make `npm run dev` start again under Next 16 | C36: Fix / hotfix | D36: claude/confident-albattani-dqw1dk -> main | E36: Production (main -> gokesari.com) | F36: Merged | G36: 2026-10-03 | H36: 2026-10-03 | I36: PLT-001 | J36: PLT-001 | K36: Itself (merged to main)
A37: 36 | B37: Promote staging: delete DEPLOY_NOW.md | C37: Release (staging -> main) | D37: staging -> main | E37: Production (main -> gokesari.com) | F37: Merged | G37: 2026-10-03 | H37: 2026-10-03 | I37: - | J37: PLT-005 | K37: Itself (merged to main)
A38: 37 | B38: Add a GoKesari deploy runbook | C38: Docs / reports | D38: claude/confident-albattani-dqw1dk -> main | E38: Production (main -> gokesari.com) | F38: Merged | G38: 2026-10-03 | H38: 2026-10-03 | I38: PLT-006 | J38: PLT-006 | K38: Itself (merged to main)
A39: 38 | B39: Product Master: category management (category master, shop categories, one-time categorisation) | C39: Feature | D39: claude/wizardly-goldberg-cb4pqg -> staging | E39: Test site (staging -> test.gokesari.com) | F39: Merged | G39: 2026-10-03 | H39: 2026-10-03 | I39: GS-011, GS-012, GS-013, RBAC-004, NAV-007, NEW-008 | J39: - | K39: #43
A40: 39 | B40: Categorisation script: --fallback category and --from-json reports | C40: Feature | D40: claude/wizardly-goldberg-cb4pqg -> staging | E40: Test site (staging -> test.gokesari.com) | F40: Merged | G40: 2026-10-03 | H40: 2026-10-03 | I40: NEW-008 | J40: - | K40: #43
A41: 40 | B41: GS-058: dispute case lifecycle | C41: Feature | D41: claude/confident-albattani-dqw1dk -> main | E41: Production (main -> gokesari.com) | F41: Merged | G41: 2026-10-03 | H41: 2026-10-03 | I41: GS-058, SM-006 | J41: GS-058, SM-006 | K41: Itself (merged to main)
A42: 41 | B42: Limit this project's Claude chats to GoKesari | C42: DevOps / repo | D42: claude/wizardly-goldberg-cb4pqg -> staging | E42: Test site (staging -> test.gokesari.com) | F42: Merged | G42: 2026-10-03 | H42: 2026-10-03 | I42: PLT-005 | J42: - | K42: #43
A43: 42 | B43: Merge main into staging: fix the migration 0037 clash; feature status report 3 Oct | C43: Docs / reports | D43: claude/pensive-cray-ccof2w -> staging | E43: Test site (staging -> test.gokesari.com) | F43: Merged | G43: 2026-10-03 | H43: 2026-10-03 | I43: - | J43: - | K43: #43
A44: 43 | B44: Release: staging → main (product category management, login/profile, GoKesari-only chat rule) | C44: Release (staging -> main) | D44: staging -> main | E44: Production (main -> gokesari.com) | F44: Merged | G44: 2026-10-03 | H44: 2026-10-03 | I44: - | J44: GS-001, GS-011, GS-012, GS-013, GS-026, WF-001, RBAC-004, NAV-003, NAV-007, NEW-008, PLT-005 | K44: Itself (merged to main)
A45: 44 | B45: Merge main into staging: renumber dispute migration to 0039 | C45: Docs / reports | D45: claude/wizardly-goldberg-cb4pqg -> staging | E45: Test site (staging -> test.gokesari.com) | F45: Closed - not merged | G45: 2026-10-03 | H45: 2026-10-03 | I45: - | J45: - | K45: - | L45: Closed; superseded by #42 (migration renumbering).
A46: 45 | B46: Shop owner fixes: registration validation, inventory fill, per-shop prices, owner name, Sign out | C46: Feature | D46: claude/magical-hamilton-kbhqm0 -> staging | E46: Test site (staging -> test.gokesari.com) | F46: Merged | G46: 2026-10-03 | H46: 2026-10-03 | I46: GS-006, GS-012, GS-015, WF-008, NAV-006, NAV-007, NEW-010 | J46: - | K46: #47
A47: 46 | B47: Add open features summary spreadsheet (3 Oct 2026) | C47: Docs / reports | D47: claude/focused-ptolemy-55j95o -> main | E47: Production (main -> gokesari.com) | F47: Merged | G47: 2026-10-03 | H47: 2026-10-05 | I47: - | J47: - | K47: Itself (merged to main)
A48: 47 | B48: Release: shop owner fixes (staging → main) | C48: Release (staging -> main) | D48: staging -> main | E48: Production (main -> gokesari.com) | F48: Merged | G48: 2026-10-03 | H48: 2026-10-03 | I48: - | J48: GS-006, GS-012, GS-015, WF-008, NAV-006, NAV-007, NEW-010 | K48: Itself (merged to main)
A49: 48 | B49: Add cart and checkout flow enhancements | C49: Feature | D49: claude/brave-mendel-615f3y -> staging | E49: Test site (staging -> test.gokesari.com) | F49: Merged | G49: 2026-10-03 | H49: 2026-10-07 | I49: GS-020, GS-024, NAV-003, NEW-012 | J49: - | K49: #71
A50: 49 | B50: Fix ENOENT race when the Excel import skips a sheet | C50: Fix / hotfix | D50: claude/magical-hamilton-kbhqm0 -> staging | E50: Test site (staging -> test.gokesari.com) | F50: Merged | G50: 2026-10-03 | H50: 2026-10-04 | I50: PMD-001 | J50: - | K50: #50
A51: 50 | B51: Release: fix Excel import ENOENT race (staging → main) | C51: Release (staging -> main) | D51: staging -> main | E51: Production (main -> gokesari.com) | F51: Merged | G51: 2026-10-04 | H51: 2026-10-04 | I51: - | J51: PMD-001 | K51: Itself (merged to main)
A52: 51 | B52: Add comprehensive test execution framework for 791 test cases | C52: QA / tests | D52: claude/excel-test-cases-xk1gjq -> staging | E52: Test site (staging -> test.gokesari.com) | F52: Merged | G52: 2026-10-04 | H52: 2026-10-07 | I52: QA-001, QA-002 | J52: - | K52: #70
A53: 52 | B53: Update e2e acceptance tests to current sign-in and wallet flows | C53: QA / tests | D53: claude/magical-hamilton-kbhqm0 -> staging | E53: Test site (staging -> test.gokesari.com) | F53: Merged | G53: 2026-10-04 | H53: 2026-10-04 | I53: QA-001 | J53: - | K53: #54
A54: 53 | B54: Seller verification: KYC core, document rules, seller/admin screens, daily job, compliance controls | C54: Feature | D54: claude/gracious-hypatia-t6lkul -> staging | E54: Test site (staging -> test.gokesari.com) | F54: Merged | G54: 2026-10-05 | H54: 2026-10-05 | I54: GS-006, GS-007, WF-008 | J54: - | K54: #54
A55: 54 | B55: Release: seller document verification to production | C55: Release (staging -> main) | D55: staging -> main | E55: Production (main -> gokesari.com) | F55: Merged | G55: 2026-10-05 | H55: 2026-10-05 | I55: - | J55: GS-006, GS-007, WF-008, QA-001 | K55: Itself (merged to main)
A56: 55 | B56: Marketplace features F1–F11 (behind business rules, off by default) | C56: Feature | D56: claude/gracious-hypatia-t6lkul -> staging | E56: Test site (staging -> test.gokesari.com) | F56: Merged | G56: 2026-10-05 | H56: 2026-10-05 | I56: GS-014, GS-022, GS-027, GS-033, GS-054, GS-072, WF-001, WF-003, SM-002, SM-003, SM-004, GA-005, NAV-001, NAV-002, NAV-003, NAV-009, NAV-013 | J56: - | K56: #57
A57: 56 | B57: Fix referral link redirect pointing at the internal host | C57: Fix / hotfix | D57: claude/gracious-hypatia-t6lkul -> staging | E57: Test site (staging -> test.gokesari.com) | F57: Merged | G57: 2026-10-06 | H57: 2026-10-06 | I57: GS-054 | J57: - | K57: #57
... A85: 84 | B85: Promote staging to main: home and Shops redesign | C85: Release (staging -> main) | D85: staging -> main | E85: Production (main -> gokesari.com) | F85: Merged | G85: 2026-10-07 | H85: 2026-10-07 | I85: - | J85: GS-004, GS-019, GS-020, GS-051, NAV-001, NAV-005, NEW-017, NEW-019 | K85: Itself (merged to main)
A86: 85 | B86: Decisions A–E: cancellation refunds, admin settings, data exposure, 6 Oct features (test only) | C86: Feature | D86: claude/hopeful-meitner-ia1fxd -> staging | E86: Test site (staging -> test.gokesari.com) | F86: Merged | G86: 2026-10-07 | H86: 2026-10-08 | I86: NEW-020, NEW-021, NEW-022, NEW-023, NEW-024, NEW-025, NEW-026, NEW-027, PLT-007, QA-001 | J86: - | K86: #86 - reverted by #87 | L86: Merged to staging only; production release #86 was reverted by #87.
A87: 86 | B87: Release to production: decisions A–E + optional build-time migration | C87: Release (staging -> main) | D87: staging -> main | E87: Production (main -> gokesari.com) | F87: Merged | G87: 2026-10-08 | H87: 2026-10-08 | I87: - | J87: Reverted by #87 - NEW-020, NEW-021, NEW-022, NEW-023, NEW-024, NEW-026, PLT-007 | K87: Itself (merged to main) | L87: Reverted by #87 the same day: production DB lacked migrations 0056/0057, shop pages returned 500.
A88: 87 | B88: Revert release #86: shop pages fail without migrations 0056/0057 | C88: Revert | D88: claude/gifted-allen-rh2ta2 -> main | E88: Production (main -> gokesari.com) | F88: Merged | G88: 2026-10-08 | H88: 2026-10-08 | I88: - | J88: - | K88: Itself (merged to main) | L88: Re-release A-E after production has 0056/0057 by reverting this commit (a plain staging -> main merge will not bring them back).
A89: 88 | B89: Runbook: stop the row-count checks going stale every release | C89: Docs / reports | D89: claude/confident-albattani-dqw1dk -> main | E89: Production (main -> gokesari.com) | F89: Merged | G89: 2026-10-08 | H89: 2026-10-08 | I89: PLT-006 | J89: PLT-006 | K89: Itself (merged to main)
A90: 89 | B90: Event layer: real-time workflows, cron only as a safety net (test site) | C90: Feature | D90: claude/affectionate-albattani-texk4z -> staging | E90: Test site (staging -> test.gokesari.com) | F90: Merged | G90: 2026-10-08 | H90: 2026-10-08 | I90: NEW-028, NEW-029, NEW-030, NEW-031, NEW-032 | J90: - | K90: Not yet (test site only)
A91: 90 | B91: Automate test-database work: "Test database" workflow + shared migration lock | C91: DevOps / repo | D91: claude/affectionate-albattani-texk4z -> staging | E91: Test site (staging -> test.gokesari.com) | F91: Merged | G91: 2026-10-08 | H91: 2026-10-08 | I91: PLT-007, PLT-008 | J91: - | K91: Not yet (test site only)
A92: 91 | B92: Shop prepaid wallet + OTP-confirmed delivery (test site) | C92: Feature | D92: claude/compassionate-ritchie-d4zal1 -> staging | E92: Test site (staging -> test.gokesari.com) | F92: Merged | G92: 2026-10-08 | H92: 2026-10-08 | I92: NEW-033, NEW-035 | J92: - | K92: #120
A93: 92 | B93: Three modules: shop product media, accounting integration & GST, shop self-registration (test site) | C93: Feature | D93: claude/laughing-mendel-ftwcgo -> staging | E93: Test site (staging -> test.gokesari.com) | F93: Merged | G93: 2026-10-08 | H93: 2026-10-09 | I93: NEW-036, NEW-037, NEW-038 | J93: NEW-036, NEW-037, NEW-038 | K93: #120 | L93: Merged into staging 9 Oct 08:34 UTC; released to production in #120.
A94: 93 | B94: Production database workflow: by hand, from main, typed confirmation | C94: DevOps / repo | D94: claude/affectionate-albattani-texk4z -> staging | E94: Test site (staging -> test.gokesari.com) | F94: Merged | G94: 2026-10-08 | H94: 2026-10-08 | I94: PLT-009 | J94: - | K94: #118 (workflow onto main) and #120 | L94: On main since #118 (9 Oct); not runnable until the repository secrets are set.
A95: 94 | B95: Test database: switch the shop wallet on (1% commission) via the workflow | C95: Test data / settings | D95: claude/compassionate-ritchie-d4zal1 -> staging | E95: Test site (staging -> test.gokesari.com) | F95: Merged | G95: 2026-10-08 | H95: 2026-10-08 | I95: NEW-033, PLT-008 | J95: - | K95: Test site only
A96: 95 | B96: Test database: credit Kesari Dairy Farm ₹500 and Asmy Exports ₹1,000 | C96: Test data / settings | D96: claude/compassionate-ritchie-d4zal1 -> staging | E96: Test site (staging -> test.gokesari.com) | F96: Merged | G96: 2026-10-08 | H96: 2026-10-08 | I96: PLT-008 | J96: - | K96: Test site only
A97: 96 | B97: Test wallet credits: Asmy Exports ₹1,000 and QA Test Bakery A ₹500 | C97: Test data / settings | D97: claude/compassionate-ritchie-d4zal1 -> staging | E97: Test site (staging -> test.gokesari.com) | F97: Merged | G97: 2026-10-08 | H97: 2026-10-08 | I97: PLT-008 | J97: - | K97: Test site only
A98: 97 | B98: Test wallet credits: QA Test Bakery B ₹500 | C98: Test data / settings | D98: claude/compassionate-ritchie-d4zal1 -> staging | E98: Test site (staging -> test.gokesari.com) | F98: Merged | G98: 2026-10-08 | H98: 2026-10-08 | I98: PLT-008 | J98: - | K98: Test site only
A99: 98 | B99: Shop wallet: ₹5/km delivery charge, no checkout below the minimum, commission back on refunds | C99: Feature | D99: claude/compassionate-ritchie-d4zal1 -> staging | E99: Test site (staging -> test.gokesari.com) | F99: Merged | G99: 2026-10-08 | H99: 2026-10-08 | I99: NEW-034 | J99: - | K99: #120
A100: 99 | B100: Test wallet credits: ₹5,000 to every shop onboarded by 8 Oct 2026 17:55 UTC | C100: Test data / settings | D100: claude/compassionate-ritchie-d4zal1 -> staging | E100: Test site (staging -> test.gokesari.com) | F100: Merged | G100: 2026-10-08 | H100: 2026-10-08 | I100: PLT-008 | J100: - | K100: Test site only | L100: Merged 8 Oct 18:09 UTC: Rs 5,000 test-wallet credit to every shop approved by 8 Oct 17:55 UTC (test site only).
A101: 100 | B101: Android and iPhone app for gokesari.com (mobile/) | C101: Feature | D101: claude/fervent-carson-mra5my -> main | E101: Production (main -> gokesari.com) | F101: Merged | G101: 2026-10-08 | H101: 2026-10-09 | I101: NEW-043, NEW-044, NEW-045, PLT-010 | J101: NEW-044, NEW-045 | K101: Itself (merged to main) | L101: Merged 9 Oct 04:19 UTC. Website parts live on gokesari.com; the app itself is not in any store yet (Android APK test builds only).
A102: 101 | B102: Feature, process-flow and PR status workbook (8 Oct 2026) | C102: Docs / reports | D102: claude/sweet-volta-ryv75e -> main | E102: Production (main -> gokesari.com) | F102: Merged | G102: 2026-10-08 | H102: 2026-10-08 | I102: - | J102: - | K102: Itself (merged to main) | L102: The 8 Oct version of this workbook.
A103: 102 | B103: Four features: delivery options & scheduling, legal documents, bank accounts with Rs 1 verification, mandatory referral code | C103: Feature | D103: claude/busy-euler-5ipjns -> staging | E103: Test site (staging -> test.gokesari.com) | F103: Merged | G103: 2026-10-08 | H103: 2026-10-08 | I103: NEW-039, NEW-040, NEW-041, NEW-042, PLT-011 | J103: NEW-039, NEW-040, NEW-041, NEW-042 (switched off) | K103: #120 | L103: Migrations 0061-0064 (renumbered after staging's 0060); each feature a rule, off by default, on for test.
A104: 103 | B104: Four features: fixes from the staging run, sandbox payment tooling, test results | C104: Fix / hotfix | D104: claude/busy-euler-5ipjns -> staging | E104: Test site (staging -> test.gokesari.com) | F104: Merged | G104: 2026-10-08 | H104: 2026-10-08 | I104: NEW-039, NEW-040, NEW-041, NEW-042, PLT-011, QA-004 | J104: NEW-039, NEW-040, NEW-041, NEW-042 (switched off) | K104: #120 | L104: Fixes S-1 (repeat-safe mark ready / handovers), S-2 (Rs 1 refund status), S-3 (wording); TEST_RESULTS.md.
A105: 104 | B105: Four features: re-check of the follow-up fixes on test, email sending limit (docs) | C105: Docs / reports | D105: claude/busy-euler-5ipjns -> staging | E105: Test site (staging -> test.gokesari.com) | F105: Merged | G105: 2026-10-08 | H105: 2026-10-08 | I105: QA-004, GAP-009 | J105: - | K105: Not yet (test site only) | L105: Docs only. Note: CI on the staging merge commit (76e2cc5) failed in 'Unit and integration tests' although the same tests passed on the PR head - to investigate / re-run.
A106: 105 | B106: Feature, process-flow and PR status workbook (9 Oct 2026) | C106: Docs / reports | D106: claude/peaceful-pascal-jai8w2 -> main | E106: Production (main -> gokesari.com) | F106: Merged | G106: 2026-10-09 | H106: 2026-10-09 | I106: - | J106: - | K106: Itself (merged to main) | L106: The morning version of this workbook.
A107: 106 | B107: Owner's decisions: pickup refunds the delivery fee, refunds to bank, referral code at customer registration | C107: Feature | D107: claude/busy-euler-5ipjns -> staging | E107: Test site (staging -> test.gokesari.com) | F107: Merged | G107: 2026-10-09 | H107: 2026-10-09 | I107: NEW-039, NEW-048, NEW-049 | J107: NEW-048, NEW-049 (switched off) | K107: #120 | L107: Behind business rules, off by default.
A108: 107 | B108: CLAUDE.md: standard folders for GoKesari reports and test results | C108: Docs / reports | D108: claude/peaceful-pascal-jai8w2 -> main | E108: Production (main -> gokesari.com) | F108: Merged | G108: 2026-10-09 | H108: 2026-10-09 | I108: - | J108: - | K108: Itself (merged to main)
A109: 108 | B109: Four features: test results for the owner's decisions (docs) | C109: Docs / reports | D109: claude/busy-euler-5ipjns -> staging | E109: Test site (staging -> test.gokesari.com) | F109: Merged | G109: 2026-10-09 | H109: 2026-10-09 | I109: QA-004 | J109: - | K109: #120 | L109: Docs only.
A110: 109 | B110: Four features: owner's second-round decisions (blocked shops show as paused, mandatory customer referral code) | C110: Feature | D110: claude/busy-euler-5ipjns -> staging | E110: Test site (staging -> test.gokesari.com) | F110: Merged | G110: 2026-10-09 | H110: 2026-10-09 | I110: NEW-040, NEW-048 | J110: NEW-040, NEW-048 (switched off) | K110: #120 | L110: Decisions O-4, O-5; migration 0072.
A111: 110 | B111: Staging-run fixes: repeated customer code request; paused shops read 'Not taking new orders' | C111: Fix / hotfix | D111: claude/busy-euler-5ipjns -> staging | E111: Test site (staging -> test.gokesari.com) | F111: Merged | G111: 2026-10-09 | H111: 2026-10-09 | I111: NEW-040, NEW-048 | J111: NEW-040, NEW-048 (switched off) | K111: #120 | L111: Fixes S-6, S-7.
A112: 111 | B112: Four features: second-round test results; approved refunds-to-bank wording (O-8) | C112: Improvement | D112: claude/busy-euler-5ipjns -> staging | E112: Test site (staging -> test.gokesari.com) | F112: Merged | G112: 2026-10-09 | H112: 2026-10-09 | I112: NEW-049, QA-004 | J112: NEW-049 (switched off) | K112: #120
A113: 112 | B113: Tile Board home screens for customer, shop owner, admin and operator | C113: Feature | D113: claude/serene-gates-7cymxj -> staging | E113: Test site (staging -> test.gokesari.com) | F113: Merged | G113: 2026-10-09 | H113: 2026-10-09 | I113: NEW-046, NEW-047, NAV-001, NAV-006, NAV-017 | J113: NEW-046, NEW-047 | K113: #120 | L113: Approved design 'Theme 1 Tile Board'; 29 new unit tests; no migrations.
A114: 113 | B114: Cashfree sandbox test data for staging payment tests (CLAUDE.md + docs) | C114: Docs / reports | D114: claude/busy-euler-5ipjns -> staging | E114: Test site (staging -> test.gokesari.com) | F114: Merged | G114: 2026-10-09 | H114: 2026-10-09 | I114: - | J114: - | K114: #120 | L114: Docs only.
A115: 114 | B115: Tile Board: fit the app's shorter screen; test-site results | C115: Improvement | D115: claude/serene-gates-7cymxj -> staging | E115: Test site (staging -> test.gokesari.com) | F115: Merged | G115: 2026-10-09 | H115: 2026-10-09 | I115: NEW-046 | J115: NEW-046 | K115: #120 | L115: Phone screens under 760px tall (the app's WebView).
A116: 115 | B116: O-7: bank check with Cashfree's Verification Suite; staging vs main report | C116: Feature | D116: claude/busy-euler-5ipjns -> staging | E116: Test site (staging -> test.gokesari.com) | F116: Merged | G116: 2026-10-09 | H116: 2026-10-09 | I116: NEW-050 | J116: NEW-050 (switched off) | K116: #120 | L116: Migration 0073.
A117: 116 | B117: Merge main into staging (mobile app work), keeping release #86 | C117: DevOps / repo | D117: claude/serene-gates-7cymxj -> staging | E117: Test site (staging -> test.gokesari.com) | F117: Merged | G117: 2026-10-09 | H117: 2026-10-09 | I117: NEW-043, NEW-044, NEW-045, NEW-046 | J117: - | K117: #120 | L117: Undid the #86 revert (e16dd6d) before merging main, so staging kept every feature; removed the 10 staging->main conflicts. Also added /delivery/ and /disputes to the app's link list.
A118: 117 | B118: O-7: accept Cashfree's own key names; staging check results | C118: Fix / hotfix | D118: claude/busy-euler-5ipjns -> staging | E118: Test site (staging -> test.gokesari.com) | F118: Merged | G118: 2026-10-09 | H118: 2026-10-09 | I118: NEW-050 | J118: NEW-050 (switched off) | K118: #120
A119: 118 | B119: Production database workflow onto main (no application change) | C119: DevOps / repo | D119: claude/serene-gates-7cymxj -> main | E119: Production (main -> gokesari.com) | F119: Merged | G119: 2026-10-09 | H119: 2026-10-09 | I119: PLT-009 | J119: PLT-009 | K119: Itself (merged to main) | L119: Workflow, scripts and runbook only; gokesari.com redeployed with unchanged code.
A120: 119 | B120: Production database workflow on main (tooling only) | C120: DevOps / repo | D120: claude/busy-euler-5ipjns -> main | E120: Production (main -> gokesari.com) | F120: Closed - not merged | G120: 2026-10-09 | H120: 2026-10-09 | I120: PLT-009 | J120: - | K120: - | L120: Duplicate of #118; closed.
A121: 120 | B121: Release: staging -> main (gokesari.com), migrations 0056-0073 via MIGRATE_ON_BUILD | C121: Release (staging -> main) | D121: staging -> main | E121: Production (main -> gokesari.com) | F121: Merged | G121: 2026-10-09 | H121: 2026-10-09 | I121: - | J121: Everything on staging (PRs #85-#117) | K121: Itself (merged to main) | L121: Merged 14:06 UTC. Production migrated by MIGRATE_ON_BUILD during the deploy; Neon snapshot taken first. Verified 14:55 UTC: pages 200, new build live.
A122: 121 | B122: Sign-in: one Terms & Privacy box instead of three; 9 Oct status report (end of day) | C122: Improvement | D122: claude/serene-gates-7cymxj -> staging | E122: Test site (staging -> test.gokesari.com) | F122: Merged | G122: 2026-10-09 | H122: 2026-10-09 | I122: NEW-056; GS-001 | J122: NEW-056 | K122: #123 | L122: Also carried the 9 Oct end-of-day status report.
A123: 122 | B123: Tile Board everywhere: one-screen role homes, one path to every function | C123: Feature | D123: claude/bold-volta-vxs1yf -> staging | E123: Test site (staging -> test.gokesari.com) | F123: Merged | G123: 2026-10-09 | H123: 2026-10-09 | I123: NEW-046; NEW-047; NEW-051 to NEW-055; GAP-007; NAV-001, NAV-002, NAV-004 to NAV-008, NAV-017 | J123: Same | K123: #123 | L123: UI layer only - no database, API or payment change. Merged 18:04 UTC (the last CI run before GitHub Actions stopped).
A124: 123 | B124: Release: staging -> main (gokesari.com) - Tile Board everywhere (#122) and single sign-in consent (#121) | C124: Release (staging -> main) | D124: staging -> main | E124: Production (main -> gokesari.com) | F124: Merged | G124: 2026-10-09 | H124: 2026-10-09 | I124: - | J124: Everything in #121, #122 | K124: Itself (merged to main) | L124: Merged 19:28 UTC. No migration.
A125: 124 | B125: Performance and second UI pass: fewer database reads per page; one screen per view on the longest pages | C125: Improvement | D125: claude/bold-volta-vxs1yf -> staging | E125: Test site (staging -> test.gokesari.com) | F125: Merged | G125: 2026-10-09 | H125: 2026-10-09 | I125: PLT-012; PLT-013; NEW-021; NEW-052; NEW-054; NAV-002, NAV-006, NAV-007, NAV-017; QA-005 | J125: Same | K125: #126 | L125: Merged 21:25 UTC without CI on the owner's instruction (GitHub Actions billing); local tsc, eslint, next build, Vitest 1,662 passed. Includes the UI pass test report and issue register.
A126: 125 | B126: PMD rollback script: drop the stray phpMyAdmin mention | C126: Fix / hotfix | D126: claude/focused-carson-4pa1e2 -> staging | E126: Test site (staging -> test.gokesari.com) | F126: Merged | G126: 2026-10-09 | H126: 2026-10-10 | I126: PMD-001 | J126: PMD-001 (comment only) | K126: #131 | L126: Comment-only change to a manual rollback script; merged without CI.
A127: 126 | B127: Release: staging -> main (gokesari.com) - performance and second UI pass (#124) | C127: Release (staging -> main) | D127: staging -> main | E127: Production (main -> gokesari.com) | F127: Merged | G127: 2026-10-09 | H127: 2026-10-09 | I127: - | J127: Everything in #124 | K127: Itself (merged to main) | L127: Merged 21:41 UTC without CI (owner's instruction). Production checks 21:44 UTC: pages 200, signed-in pages redirect to sign-in, Lighthouse mobile home 93/100/100/100.
...

Sheet Blockers & Decisions
A1: # | B1: Type | C1: Item | D1: What is needed | E1: Unblocks (feature IDs) | F1: Who | G1: Status | H1: Source
A2: 1 | B2: Release blocker | C2: Production database is behind (0055) - next release cannot ship | D2: Resolved 9 Oct: the owner set MIGRATE_ON_BUILD=true for gokesari.com and the #120 deploy applied migrations 0056-0073 before the new code went live (Neon snapshot taken first). | E2: NEW-020-026, NEW-028-042, PLT-007 | F2: Owner | G2: Resolved | H2: PR #86, #87; ITEMS_A_E_2026-10-07.md section 3a
A3: 2 | B3: Release blocker | C3: 'Production database' workflow is only on staging | D3: Resolved 9 Oct: #118 put the workflow on main. Running it still needs repository secrets - see #32. | E3: PLT-009 (and the release blocker above) | F3: Owner / dev | G3: Resolved | H3: PR #93; docs/event-driven-2026-10/PROD_DB.md
A4: 3 | B4: Go-live blocker | C4: No recorded browser / QA sign-off | D4: Execute the 791-case plan (smoke, P0, P1, P2) on test.gokesari.com and record results. Progress 9 Oct: the first recorded browser run (four features + regression, 8-9 Oct, TEST_RESULTS.md) - the 791-case plan itself is still not run. 10 Oct: second recorded run - Tile Board UI pass, 1,026 of 1,038 checks PASS (QA-005). | E4: QA-003; QA-005; go-live | F4: QA / owner | G4: Open | H4: 6 Oct report; TEST_SUMMARY_AND_STATUS.md
A5: 4 | B5: Go-live blocker | C5: Production cron jobs | D5: Schedule seller-verification, dispute-escalation, shop-acceptance, delivery-dispatch and notifications on gokesari.com; add timeout-sweep and notification-retry when the event layer ships. Not confirmed since 6 Oct. The daily seller-verification job now also starts legal-document grace periods and sends expiry reminders (NEW-040). | E5: GS-007, GS-058, NEW-007, NEW-028 | F5: Owner | G5: Open | H5: DEPLOY_RUNBOOK.md; ITEMS_A_E section 3a.7
A6: 5 | B6: Decision | C6: Per-order online payment (GS-028 / NEW-007) | D6: Approve building per-order Cashfree payment, or launch with wallet + COD only. | E6: GS-028, GS-073, SM-005, WF-001, NAV-003, NEW-007 | F6: Owner | G6: Pending | H6: 6 Oct report
A7: 6 | B7: Vendor | C7: D2 - SMS / OTP vendor (DLT) and WhatsApp provider | D7: Pick a DLT-registered SMS provider and a WhatsApp BSP (or Meta Cloud API). Also blocks testing paid self-registration on test (SMS_PROVIDER=none, N-2). | E7: GS-001, GS-074, NEW-035 (SMS code), NEW-038 | F7: Owner | G7: Pending | H7: 6 Oct report; three-modules PLAN.md P2
A8: 7 | B8: Decision | C8: D7 - licensed external price source | D8: Approve a lawful / licensed source for customer-visible reference prices (then one rule flip). | E8: GS-023 | F8: Owner | G8: Pending | H8: 6 Oct report
A9: 8 | B9: Decision | C9: D10 - cancellation after packing | D9: Confirm READY/ASSIGNED (customer refused) and PICKED_UP/OUT_FOR_DELIVERY (goods-only refund, delivery fee kept). | E9: NEW-006 sign-off, NEW-020 | F9: Owner | G9: Pending | H9: ITEMS_A_E section 1-A
A10: 9 | B10: Decision | C10: D6 - delivery fee kept on cancellation; platform invoicing of its own fees | D10: Decide how the kept delivery fee is shared/reported and how GoKesari invoices its fees (SAC). | E10: GAP-006 | F10: Owner / CA | G10: Pending | H10: 3 Oct open features; ITEMS_A_E section 5
A11: 10 | B11: Decision | C11: RBAC-003 - operator 'Limited' shop management | D11: Define what an operator may change on a shop. | E11: RBAC-003 | F11: Owner | G11: Pending | H11: 6 Oct report
A12: 11 | B12: Decision | C12: SM-006 scope | D12: Accept the dispute lifecycle as the issue state machine, or add its states to grievances. | E12: SM-006 | F12: Owner | G12: Pending | H12: ITEMS_A_E section 5
A13: 12 | B13: Decision | C13: Which off-by-default features to switch on in production | D13: Choose which of the now-released off-by-default features to switch on in production: F3-F11 and #58 rules, plus fulfilmentOptions, legalDocuments, bankAccounts, bankRefunds, bankAccountCheck, shopReferral, customerSignupReferral, shopWallet, selfRegistration, cancellation PREPARING (all off on gokesari.com after #120). | E13: GS-014, GS-027, GS-033, GS-054, GS-072, GA-005, NAV-001, NAV-002, NAV-003, NEW-007 | F13: Owner | G13: Pending | H13: 6 Oct report
... A57: 56 | B57: Dev | C57: Flaky test: PMD parallel loader | D57: Resolved 16 Oct: #184 (each parallel worker scores only its own committed batch; shared products rescored at the end; reproduced 1 in 3 before, 15/15 after) released to gokesari.com by #185. | E57: PMD-001 | F57: Dev | G57: Resolved | H57: docs/inventory-accounting-2026-10/TESTING_REPORT.md
