Workbook

Sheet Summary
A1: Inventory & Accounting — testing report (2026-10-15)
A3: Environment | B3: PASS | C3: FAIL | D3: BLOCKED | E3: SKIPPED | F3: N/A | G3: Total
A4: Local (Postgres 16, CI-equivalent) | B4: =COUNTIFS('Test cases'!$C$2:$C$2000,$A4,'Test cases'!$F$2:$F$2000,"PASS") | C4: =COUNTIFS('Test cases'!$C$2:$C$2000,$A4,'Test cases'!$F$2:$F$2000,"FAIL") | D4: =COUNTIFS('Test cases'!$C$2:$C$2000,$A4,'Test cases'!$F$2:$F$2000,"BLOCKED") | E4: =COUNTIFS('Test cases'!$C$2:$C$2000,$A4,'Test cases'!$F$2:$F$2000,"SKIPPED") | F4: =COUNTIFS('Test cases'!$C$2:$C$2000,$A4,'Test cases'!$F$2:$F$2000,"N/A") | G4: =SUM(B4:F4)
A5: Local production build (next start) | B5: =COUNTIFS('Test cases'!$C$2:$C$2000,$A5,'Test cases'!$F$2:$F$2000,"PASS") | C5: =COUNTIFS('Test cases'!$C$2:$C$2000,$A5,'Test cases'!$F$2:$F$2000,"FAIL") | D5: =COUNTIFS('Test cases'!$C$2:$C$2000,$A5,'Test cases'!$F$2:$F$2000,"BLOCKED") | E5: =COUNTIFS('Test cases'!$C$2:$C$2000,$A5,'Test cases'!$F$2:$F$2000,"SKIPPED") | F5: =COUNTIFS('Test cases'!$C$2:$C$2000,$A5,'Test cases'!$F$2:$F$2000,"N/A") | G5: =SUM(B5:F5)
A6: test.gokesari.com | B6: =COUNTIFS('Test cases'!$C$2:$C$2000,$A6,'Test cases'!$F$2:$F$2000,"PASS") | C6: =COUNTIFS('Test cases'!$C$2:$C$2000,$A6,'Test cases'!$F$2:$F$2000,"FAIL") | D6: =COUNTIFS('Test cases'!$C$2:$C$2000,$A6,'Test cases'!$F$2:$F$2000,"BLOCKED") | E6: =COUNTIFS('Test cases'!$C$2:$C$2000,$A6,'Test cases'!$F$2:$F$2000,"SKIPPED") | F6: =COUNTIFS('Test cases'!$C$2:$C$2000,$A6,'Test cases'!$F$2:$F$2000,"N/A") | G6: =SUM(B6:F6)
A7: test.gokesari.com (phone) | B7: =COUNTIFS('Test cases'!$C$2:$C$2000,$A7,'Test cases'!$F$2:$F$2000,"PASS") | C7: =COUNTIFS('Test cases'!$C$2:$C$2000,$A7,'Test cases'!$F$2:$F$2000,"FAIL") | D7: =COUNTIFS('Test cases'!$C$2:$C$2000,$A7,'Test cases'!$F$2:$F$2000,"BLOCKED") | E7: =COUNTIFS('Test cases'!$C$2:$C$2000,$A7,'Test cases'!$F$2:$F$2000,"SKIPPED") | F7: =COUNTIFS('Test cases'!$C$2:$C$2000,$A7,'Test cases'!$F$2:$F$2000,"N/A") | G7: =SUM(B7:F7)
A8: test.gokesari.com (Android app WebView) | B8: =COUNTIFS('Test cases'!$C$2:$C$2000,$A8,'Test cases'!$F$2:$F$2000,"PASS") | C8: =COUNTIFS('Test cases'!$C$2:$C$2000,$A8,'Test cases'!$F$2:$F$2000,"FAIL") | D8: =COUNTIFS('Test cases'!$C$2:$C$2000,$A8,'Test cases'!$F$2:$F$2000,"BLOCKED") | E8: =COUNTIFS('Test cases'!$C$2:$C$2000,$A8,'Test cases'!$F$2:$F$2000,"SKIPPED") | F8: =COUNTIFS('Test cases'!$C$2:$C$2000,$A8,'Test cases'!$F$2:$F$2000,"N/A") | G8: =SUM(B8:F8)
A9: gokesari.com | B9: =COUNTIFS('Test cases'!$C$2:$C$2000,$A9,'Test cases'!$F$2:$F$2000,"PASS") | C9: =COUNTIFS('Test cases'!$C$2:$C$2000,$A9,'Test cases'!$F$2:$F$2000,"FAIL") | D9: =COUNTIFS('Test cases'!$C$2:$C$2000,$A9,'Test cases'!$F$2:$F$2000,"BLOCKED") | E9: =COUNTIFS('Test cases'!$C$2:$C$2000,$A9,'Test cases'!$F$2:$F$2000,"SKIPPED") | F9: =COUNTIFS('Test cases'!$C$2:$C$2000,$A9,'Test cases'!$F$2:$F$2000,"N/A") | G9: =SUM(B9:F9)
A10: GitHub Actions | B10: =COUNTIFS('Test cases'!$C$2:$C$2000,$A10,'Test cases'!$F$2:$F$2000,"PASS") | C10: =COUNTIFS('Test cases'!$C$2:$C$2000,$A10,'Test cases'!$F$2:$F$2000,"FAIL") | D10: =COUNTIFS('Test cases'!$C$2:$C$2000,$A10,'Test cases'!$F$2:$F$2000,"BLOCKED") | E10: =COUNTIFS('Test cases'!$C$2:$C$2000,$A10,'Test cases'!$F$2:$F$2000,"SKIPPED") | F10: =COUNTIFS('Test cases'!$C$2:$C$2000,$A10,'Test cases'!$F$2:$F$2000,"N/A") | G10: =SUM(B10:F10)

Sheet Test cases
A1: ID | B1: Level | C1: Environment | D1: Test case | E1: Covers | F1: Result | G1: Detail / evidence
A2: IT-BILL-CAPTURE-01 | B2: Integration | C2: Local (Postgres 16, CI-equivalent) | D2: soft copy: e-invoice JSON › reads, matches by barcode and name, validates, and touches stock only on confirm | E2: Parts 4-7 | F2: PASS | G2: tests/integration/bill-capture.test.ts (1116 ms)
A3: IT-BILL-CAPTURE-02 | B3: Integration | C3: Local (Postgres 16, CI-equivalent) | D3: soft copy: e-invoice JSON › the original file is stored and readable only by its shop | E3: Parts 4-7 | F3: PASS | G3: tests/integration/bill-capture.test.ts (1050 ms)
A4: IT-BILL-CAPTURE-03 | B4: Integration | C4: Local (Postgres 16, CI-equivalent) | D4: review & correction screen › flags wrong totals and a bad GSTIN; owner edits fix them; corrections are remembered for the supplier | E4: Parts 4-7 | F4: PASS | G4: tests/integration/bill-capture.test.ts (1416 ms)
A5: IT-BILL-CAPTURE-04 | B5: Integration | C5: Local (Postgres 16, CI-equivalent) | D5: review & correction screen › a blank bill can be typed in by hand | E5: Parts 4-7 | F5: PASS | G5: tests/integration/bill-capture.test.ts (1359 ms)
A6: IT-BILL-CAPTURE-05 | B6: Integration | C6: Local (Postgres 16, CI-equivalent) | D6: soft copy: Excel bill › finds the item table and maps the lines | E6: Parts 4-7 | F6: PASS | G6: tests/integration/bill-capture.test.ts (1370 ms)
A7: IT-BILL-CAPTURE-06 | B7: Integration | C7: Local (Postgres 16, CI-equivalent) | D7: hard copy: photo with a signed e-invoice QR › takes supplier GSTIN, number, date and total from the QR and reads the rest by OCR | E7: Parts 4-7 | F7: PASS | G7: tests/integration/bill-capture.test.ts (3716 ms)
A8: IT-BILL-CAPTURE-07 | B8: Integration | C8: Local (Postgres 16, CI-equivalent) | D8: queue and forwarding › the dispatcher reads waiting bills once; an unreadable file fails cleanly | E8: Parts 4-7 | F8: PASS | G8: tests/integration/bill-capture.test.ts (1296 ms)
A9: IT-BILL-CAPTURE-08 | B9: Integration | C9: Local (Postgres 16, CI-equivalent) | D9: queue and forwarding › a bill emailed to the shop's private address becomes a capture | E9: Parts 4-7 | F9: PASS | G9: tests/integration/bill-capture.test.ts (1082 ms)
A10: IT-INVENTORY-ACCO-01 | B10: Integration | C10: Local (Postgres 16, CI-equivalent) | D10: stock ledger follows every stock change (triggers) › records opening stock of a new listing and keeps ledger = listing count | E10: Parts 1-3,6,7 | F10: PASS | G10: tests/integration/inventory-accounting.test.ts (1050 ms)
A11: IT-INVENTORY-ACCO-02 | B11: Integration | C11: Local (Postgres 16, CI-equivalent) | D11: stock ledger follows every stock change (triggers) › an online order reduces the ledger in the same transaction, a cancellation puts it back | E11: Parts 1-3,6,7 | F11: PASS | G11: tests/integration/inventory-accounting.test.ts (1577 ms)
A12: IT-INVENTORY-ACCO-03 | B12: Integration | C12: Local (Postgres 16, CI-equivalent) | D12: stock ledger follows every stock change (triggers) › a manual stock edit on the catalogue screen is an adjustment | E12: Parts 1-3,6,7 | F12: PASS | G12: tests/integration/inventory-accounting.test.ts (1509 ms)
... A221: CI-MIGRATE | B221: CI | C221: GitHub Actions | D221: migrate-on-build rewind through rollback-0078 → 0077 → 0076 (proves the rollback scripts) | E221: All parts | F221: PASS | G221: tests/integration/migrate-on-build.test.ts, local and CI

Sheet Defects & fixes
A1: # | B1: Found in | C1: Defect | D1: Fix | E1: Status
A2: 1 | B2: Integration (local) | C2: Mock GST provider never produced an amount mismatch for a shop with 3 bills, so reconciliation's mismatch path was untested end to end | D2: Mock now adds ₹10 to every second reported bill (i % 2 === 1) | E2: Fixed
A3: 2 | B3: Unit (local) | C3: Bill text parser read the word 'Invoice' as the invoice number on 'TAX INVOICE / Invoice No:' headers | D3: Number must follow no / number / # or a colon, and contain a digit | E3: Fixed
A4: 3 | B4: Unit (local) | C4: Amounts such as 9072.00 were read as 2.00 (comma-group regex matched the tail) | D4: Number regex requires at least one comma group in the Indian-grouping branch | E4: Fixed
A5: 4 | B5: Integration (local) | C5: 'Create new product' on a bill line created a duplicate master product when the barcode already existed in the master catalogue | D5: Line creation reuses the master product by barcode; test updated | E5: Fixed
A6: 5 | B6: Typecheck | C6: mrpSource 'SHOP_OWNER' is not a valid enum value for new listings created from a bill | D6: Uses SELLER_SUBMITTED | E6: Fixed
A7: 6 | B7: Lint | C7: Review screen set state inside an effect (cascading render) when the bill status changed | D7: Effect removed; the page keys the review component by status + updatedAt | E7: Fixed
A8: 7 | B8: E2E (local, phone) | C8: The accounts board reused the data-tile-board marker, which hides Seller Central's top bar and padding on phones | D8: Marker renamed to data-accounts-board | E8: Fixed
A9: 8 | B9: E2E (local) | C9: Content-Security-Policy sandbox on the file route blocked the browser's PDF viewer for uploaded PDF bills | D9: Sandbox CSP applied to images only | E9: Fixed
A10: 9 | B10: Integration (local, full suite) | C10: migrate-on-build rewind test failed because the 0076 tables blocked rolling back earlier migrations | D10: 0076 added to the rollback list (also proves scripts/rollback-0076.sql) | E10: Fixed
A11: 10 | B11: E2E (local) | C11: GST import test clicked a button label that the panel no longer used | D11: Selector 'Import file' | E11: Fixed
A12: 11 | B12: Merge with staging | C12: Staging added a multi-shop switcher; accounts pages picked the newest shop instead of the chosen one | D12: Module uses activeShop() like the rest of Seller Central | E12: Fixed
A13: 12 | B13: Staging test tooling | C13: Sign-in script pressed Enter before the page hydrated, so the consent tick did not register and no code was sent | D13: Script waits for 'Get code' to enable before clicking | E13: Fixed
... A16: 15 | B16: Staging · TS-STOCK-CANCEL (real customer order) | C16: A cancelled online order's restock was written to the stock ledger as ADJUSTMENT without the order id (stock and totals were correct) — the existing restock code records no order id | D16: Migration 0078: the ledger trigger links the cancellation to its order (SALE_RETURN) and relabels rows written since 0076; existing order code unchanged; rollback-0078.sql; integration test asserts it (PR #172) | E16: Fixed
